Workbook
Name DEPT: #REF!
Name DEPT: #REF!
Name DEPT: #REF!
Name DEPT: #REF!
Name DEPT: #REF!
Name DEPT: #REF!
Name DEPT: #REF!
Name DEPT: #REF!
Name DEPT: #REF!
Name DEPT: #REF!
Name trial: #REF!
Name trial: #REF!
Name trial: #REF!
Name trial: #REF!
Name trial: #REF!
Name trial: #REF!
Name trial: #REF!
Name trial: #REF!
Name trial: #REF!
Name trial: #REF!
Name trial: #REF!
Name trial: #REF!
Name trial: #REF!
Name trial: #REF!
Name TRIALBAL: #REF!
Name TRIALBAL: #REF!
Name TRIALBAL: #REF!
Name TRIALBAL: #REF!
Name TRIALBAL: #REF!
Name TRIALBAL: #REF!
Name TRIALBAL: #REF!
Name TRIALBAL: #REF!
Name TRIALBAL: #REF!
Name TRIALBAL: #REF!
Name TRIALBAL: #REF!
Name TRIALBAL: #REF!
Name TRIALBAL: #REF!
Name TRIALBAL: #REF!
Name TRIALBAL: #REF!

Sheet Cover Page
A1: Financial Reports F01 - F39
A2: Company Accounts
A3: S/No | B3: Old | C3: New | D3: Report Name | F3: Format | H3: User/Comment
A4: 1 | B4: F101 | C4: F21 | D4: P&L Account against Budget | E4: Normal | F4: A4 P | G4: 000s | H4: P&L against budget for Coy, Div, Dept, Sec & Units
A5: =A4+1 -> 2 | B5: F101S | C5: F21S | D5: P&L Account against Budget | E5: Normal | F5: A4 P | G5: 000s | H5: Convert to S$
A6: =A5+1 -> 3 | C6: F21R | D6: P&L Account against Budget (Raw) | E6: Normal | F6: A4 P | G6: Actual | H6: In Actual Data for easy checking of entries.
A7: =A6+1 -> 4 | B7: F102 | C7: F22 | D7: P&L Account by Month | E7: Brief | F7: A4 L | G7: 000s | H7: P&L Statement Actual by Month for Coy, Div, Dept, Sec & Units
A8: =A7+1 -> 5 | B8: F102S | C8: F22S | D8: P&L Account by Month | E8: Brief | F8: A4 L | G8: 000s | H8: Convert to S$
A9: =A8+1 -> 6 | B9: F103 | C9: F23 | D9: P&L Account by Div/Dept/Sec/Units | E9: Normal (9) | F9: A4 P | G9: 000s | H9: P&L Statement Actual for all Div/Dept/Sec/Units
A10: =A9+1 -> 7 | B10: F121 | C10: F24 | D10: Manufacturing Account against Budget | E10: Normal (9) | F10: A4 P | G10: 000s | H10: Manufacturing Account against budget for Coy, Div, Dept, Sec & Units
A11: =A10+1 -> 8 | B11: F122 | C11: F25 | D11: Manufacturing Account by Div/Dept/Sec/Units | E11: Normal (9) | F11: A4 P | G11: 000s | H11: Manufacturing Account for all Div/Dept/Sec/Units
A12: =A11+1 -> 9 | C12: F26M | D12: ASU Manufacturing Account by Products by Month | F12: A4 P | G12: 000s
A13: =A12+1 -> 10 | C13: F26Y | D13: ASU Manufacturing Account by Products Year To Date | F13: A4 P | G13: 000s
A14: =A13+1 -> 11 | B14: F131 | C14: F30 | D14: Balance Sheet | F14: A4 P | G14: 000s
A15: =A14+1 -> 12 | C15: F30R | D15: Balance Sheet (Raw) | F15: A4 P | G15: Actual | H15: In Actual Data for easy checking of entries.
A16: =A15+1 -> 13 | B16: F141 | C16: F31 | D16: Detailed P&L Account | F16: A4 L | G16: 000s
A17: =A16+1 -> 14 | B17: F142 | C17: F32 | D17: Detailed Manufacturing Account | F17: A4 L | G17: 000s
A18: =A17+1 -> 15 | B18: F151 | C18: F33 | D18: Detailed Balance Sheet | F18: A4 P | G18: 000s
A19: =A18+1 -> 16 | B19: New | C19: F38 | D19: TNSC Reporting Package
A20: =A19+1 -> 17 | B20: New | C20: F39 | D20: SAF Report

Sheet F21
A1: LEEDEN NATIONAL OXYGEN LTD | D1: AS OF: 11-Oct-2017 | H1: FOR THE MONTH OF: Sep -17
A2: DIVISION: | D2: DEPT: | H2: SECTION:
A3: F21 PROFIT & LOSS ACCOUNT | D3: CURRENCY: 000s | H3: FX: 0.00
D4: CURRENT MONTH | H4: YEAR TO DATE
D5: Aug-17 | E5: Sep-17 | F5: Budget | G5: Variance | H5: Actual | I5: Budget | J5: Variance | K5: Last Year | L5: Variance
A6: 1 | B6: External Sales | C6: 5001 to 5029, 5051 to 5099
A7: =A6+1 -> 2 | B7: Interco Sales | C7: 5031 to 5049
A8: =A7+1 -> 3 | B8: Total Sales | C8: =SUM(C6:C7)
A9: =A8+1 -> 4 | B9: Cost of External Sales | C9: 5101 to 5119, 5141 to 5499, 6000 to 6999
A10: =A9+1 -> 5 | B10: Cost of Interco Sales | C10: 5121 to 5139
A11: =A10+1 -> 6 | B11: Total Cost of Sales | C11: =SUM(C9:C10)
A12: =A11+1 -> 7 | B12: Gross Profit | C12: =C8+C11
A13: =A12+1 -> 8 | B13: Commission/Mgt Income | C13: 5501 to 5509
A14: =A13+1 -> 9 | B14: Gain/(Loss) Disposal of FA | C14: 9101
A15: =A14+1 -> 10 | B15: Other Op Income | C15: 5511 to 5599, 9001 to 9019, 9041Credit, 9102 to 9109Credit
A16: =A15+1 -> 11 | B16: Other Op Expense | C16: 5601 to 5999, 9041Debit, 9102 to 9109Debit, 9111 to 9115, 9117 to 9199
A17: =A16+1 -> 12 | B17: Total Oth Op Income/ (Exp) | C17: =SUM(C13:C16)
A18: =A17+1 -> 13 | B18: Personnel Related Cost | C18: 7000 to 7099
... A60: =A59+1 -> 55 | B60: Dividend Declared | C60: 4902
B61: Performance Indicators | D61: Aug-17 | E61: Sep-17 | F61: Budget | G61: Variance | H61: Actual | I61: Budget | J61: Variance | K61: Last Year | L61: Variance
A62: =A61+1 -> 1 | B62: Gross Profits Margin % | C62: Gross Profits/Total Sales
A63: =A62+1 -> 2 | B63: - External Sales GP % | C63: (External Sales - Cost of External Sales)/External Sales
A64: 3 | B64: - Interco Sales GP % | C64: (Interco Sales - Cost of Interco Sales)/Interco Sales
A65: 4 | B65: Selling & Dist Margin % | C65: -Total S&D Exps/Total Sales
A66: 5 | B66: A&G Margin Direct % | C66: -Total Direct A&G Exps/Total Sales
A67: 6 | B67: A&G Margin Total % | C67: -Total A&G Exps/Total Sales
A68: 7 | B68: Operating Profit Margin % | C68: Profits from Operations/Total Sales
A69: 8 | B69: Profits Before Taxation % | C69: Profits Before Taxation/Total Sales
A70: 9 | B70: Profit After Taxation % | C70: Profits after Taxation/Total Sales

Sheet F21S
A1: LEEDEN NATIONAL OXYGEN LTD | D1: ='F21'!D1:G1 -> AS OF: 11-Oct-2017 | H1: ='F21'!H1:L1 -> FOR THE MONTH OF: Sep -17
A2: DIVISION: COMPANY | D2: DEPT: | H2: SECTION:
A3: F21S PROFIT & LOSS ACCOUNT | D3: CURRENCY: SGD 000s | H3: FX: 0.00
D4: CURRENT MONTH | H4: YEAR TO DATE
D5: Aug-17 | E5: Sep-17 | F5: Budget | G5: Variance | H5: Actual | I5: Budget | J5: Variance | K5: Last Year | L5: Variance
A6: 1 | B6: ='F21'!B6 -> External Sales | C6: ='F21'!C6 -> 5001 to 5029, 5051 to 5099
A7: =A6+1 -> 2 | B7: ='F21'!B7 -> Interco Sales | C7: ='F21'!C7 -> 5031 to 5049
A8: =A7+1 -> 3 | B8: ='F21'!B8 -> Total Sales | C8: ='F21'!C8 -> =SUM(C6:C7)
A9: =A8+1 -> 4 | B9: ='F21'!B9 -> Cost of External Sales | C9: ='F21'!C9 -> 5101 to 5119, 5141 to 5499, 6000 to 6999
A10: =A9+1 -> 5 | B10: ='F21'!B10 -> Cost of Interco Sales | C10: ='F21'!C10 -> 5121 to 5139
A11: =A10+1 -> 6 | B11: ='F21'!B11 -> Total Cost of Sales | C11: ='F21'!C11 -> =SUM(C9:C10)
A12: =A11+1 -> 7 | B12: ='F21'!B12 -> Gross Profit | C12: ='F21'!C12 -> =C8+C11
A13: =A12+1 -> 8 | B13: ='F21'!B13 -> Commission/Mgt Income | C13: ='F21'!C13 -> 5501 to 5509
A14: =A13+1 -> 9 | B14: ='F21'!B14 -> Gain/(Loss) Disposal of FA | C14: ='F21'!C14 -> 9101
A15: =A14+1 -> 10 | B15: ='F21'!B15 -> Other Op Income | C15: ='F21'!C15 -> 5511 to 5599, 9001 to 9019, 9041Credit, 9102 to 9109Credit
A16: =A15+1 -> 11 | B16: ='F21'!B16 -> Other Op Expense | C16: ='F21'!C16 -> 5601 to 5999, 9041Debit, 9102 to 9109Debit, 9111 to 9115, 9117 to 9199
A17: =A16+1 -> 12 | B17: ='F21'!B17 -> Total Oth Op Income/ (Exp) | C17: ='F21'!C17 -> =SUM(C13:C16)
A18: =A17+1 -> 13 | B18: ='F21'!B18 -> Personnel Related Cost | C18: ='F21'!C18 -> 7000 to 7099
... A60: =A59+1 -> 55 | B60: ='F21'!B60 -> Dividend Declared | C60: ='F21'!C60 -> 4902
B61: ='F21'!B61 -> Performance Indicators | D61: Aug-17 | E61: Sep-17 | F61: Budget | G61: Variance | H61: Actual | I61: Budget | J61: Variance | K61: Last Year | L61: Variance
A62: =A61+1 -> 1 | B62: ='F21'!B62 -> Gross Profits Margin % | C62: ='F21'!C62 -> Gross Profits/Total Sales
A63: =A62+1 -> 2 | B63: ='F21'!B63 -> - External Sales GP % | C63: ='F21'!C63 -> (External Sales - Cost of External Sales)/External Sales
A64: 3 | B64: ='F21'!B64 -> - Interco Sales GP % | C64: ='F21'!C64 -> (Interco Sales - Cost of Interco Sales)/Interco Sales
A65: 4 | B65: ='F21'!B65 -> Selling & Dist Margin % | C65: ='F21'!C65 -> -Total S&D Exps/Total Sales
A66: 5 | B66: ='F21'!B66 -> A&G Margin Direct % | C66: ='F21'!C66 -> -Total Direct A&G Exps/Total Sales
A67: 6 | B67: ='F21'!B67 -> A&G Margin Total % | C67: ='F21'!C67 -> -Total A&G Exps/Total Sales
A68: 7 | B68: ='F21'!B68 -> Operating Profit Margin % | C68: ='F21'!C68 -> Profits from Operations/Total Sales
A69: 8 | B69: ='F21'!B69 -> Profits Before Taxation % | C69: ='F21'!C69 -> Profits Before Taxation/Total Sales
A70: 9 | B70: ='F21'!B70 -> Profit After Taxation % | C70: ='F21'!C70 -> Profits after Taxation/Total Sales

Sheet F21R
A1: LEEDEN NATIONAL OXYGEN LTD | D1: =F21S!D1 -> AS OF: 11-Oct-2017 | H1: =F21S!H1 -> FOR THE MONTH OF: Sep -17
A2: DIVISION: COMPANY | D2: DEPT: | H2: SECTION:
A3: F21R PROFIT & LOSS ACCOUNT (RAW) | D3: CURRENCY: | H3: FX: 0.00
D4: CURRENT MONTH | H4: YEAR TO DATE
D5: Aug-17 | E5: Sep-17 | F5: Budget | G5: Variance | H5: Actual | I5: Budget | J5: Variance | K5: Last Year | L5: Variance
A6: 1 | B6: =F21S!B6 -> External Sales | C6: =F21S!C6 -> 5001 to 5029, 5051 to 5099
A7: =A6+1 -> 2 | B7: =F21S!B7 -> Interco Sales | C7: =F21S!C7 -> 5031 to 5049
A8: =A7+1 -> 3 | B8: =F21S!B8 -> Total Sales | C8: =F21S!C8 -> =SUM(C6:C7)
A9: =A8+1 -> 4 | B9: =F21S!B9 -> Cost of External Sales | C9: =F21S!C9 -> 5101 to 5119, 5141 to 5499, 6000 to 6999
A10: =A9+1 -> 5 | B10: =F21S!B10 -> Cost of Interco Sales | C10: =F21S!C10 -> 5121 to 5139
A11: =A10+1 -> 6 | B11: =F21S!B11 -> Total Cost of Sales | C11: =F21S!C11 -> =SUM(C9:C10)
A12: =A11+1 -> 7 | B12: =F21S!B12 -> Gross Profit | C12: =F21S!C12 -> =C8+C11
A13: =A12+1 -> 8 | B13: =F21S!B13 -> Commission/Mgt Income | C13: =F21S!C13 -> 5501 to 5509
A14: =A13+1 -> 9 | B14: =F21S!B14 -> Gain/(Loss) Disposal of FA | C14: =F21S!C14 -> 9101
A15: =A14+1 -> 10 | B15: =F21S!B15 -> Other Op Income | C15: =F21S!C15 -> 5511 to 5599, 9001 to 9019, 9041Credit, 9102 to 9109Credit
A16: =A15+1 -> 11 | B16: =F21S!B16 -> Other Op Expense | C16: =F21S!C16 -> 5601 to 5999, 9041Debit, 9102 to 9109Debit, 9111 to 9115, 9117 to 9199
A17: =A16+1 -> 12 | B17: =F21S!B17 -> Total Oth Op Income/ (Exp) | C17: =F21S!C17 -> =SUM(C13:C16)
A18: =A17+1 -> 13 | B18: =F21S!B18 -> Personnel Related Cost | C18: =F21S!C18 -> 7000 to 7099
... A60: =A59+1 -> 55 | B60: =F21S!B60 -> Dividend Declared | C60: =F21S!C60 -> 4902
B61: =F21S!B61 -> Performance Indicators | D61: Aug-17 | E61: Sep-17 | F61: Budget | G61: Variance | H61: Actual | I61: Budget | J61: Variance | K61: Last Year | L61: Variance
A62: =A61+1 -> 1 | B62: =F21S!B62 -> Gross Profits Margin % | C62: =F21S!C62 -> Gross Profits/Total Sales
A63: =A62+1 -> 2 | B63: =F21S!B63 -> - External Sales GP % | C63: =F21S!C63 -> (External Sales - Cost of External Sales)/External Sales
A64: 3 | B64: =F21S!B64 -> - Interco Sales GP % | C64: =F21S!C64 -> (Interco Sales - Cost of Interco Sales)/Interco Sales
A65: 4 | B65: =F21S!B65 -> Selling & Dist Margin % | C65: =F21S!C65 -> -Total S&D Exps/Total Sales
A66: 5 | B66: =F21S!B66 -> A&G Margin Direct % | C66: =F21S!C66 -> -Total Direct A&G Exps/Total Sales
A67: 6 | B67: =F21S!B67 -> A&G Margin Total % | C67: =F21S!C67 -> -Total A&G Exps/Total Sales
A68: 7 | B68: =F21S!B68 -> Operating Profit Margin % | C68: =F21S!C68 -> Profits from Operations/Total Sales
A69: 8 | B69: =F21S!B69 -> Profits Before Taxation % | C69: =F21S!C69 -> Profits Before Taxation/Total Sales
A70: 9 | B70: =F21S!B70 -> Profit After Taxation % | C70: =F21S!C70 -> Profits after Taxation/Total Sales

Sheet F22
A1: LEEDEN NATIONAL OXYGEN LTD | D1: =F21S!D1 -> AS OF: 11-Oct-2017 | O1: FOR THE YEAR OF: 2018
A2: DIVISION: | D2: DEPT: | O2: SECTION:
A3: F22 P&L ACCOUNT BY MONTH | D3: CURRENCY: 000s | O3: FX: 0.00
D4: 42826 | E4: 42856 | F4: 42887 | G4: 42917 | H4: 42948 | I4: 42979 | J4: 43009 | K4: 43040 | L4: 43070 | M4: 43101 | N4: 43132 | O4: 43160 | P4: Total | Q4: FY 2017 | R4: Variance %
A5: 1 | B5: =F21R!B6 -> External Sales | C5: =F21R!C6 -> 5001 to 5029, 5051 to 5099
A6: =A5+1 -> 2 | B6: =F21R!B7 -> Interco Sales | C6: =F21R!C7 -> 5031 to 5049
A7: =A6+1 -> 3 | B7: =F21R!B8 -> Total Sales | C7: =SUM(C5:C6)
A8: =A7+1 -> 4 | B8: =F21R!B9 -> Cost of External Sales | C8: =F21R!C9 -> 5101 to 5119, 5141 to 5499, 6000 to 6999
A9: =A8+1 -> 5 | B9: =F21R!B10 -> Cost of Interco Sales | C9: =F21R!C10 -> 5121 to 5139
A10: =A9+1 -> 6 | B10: =F21R!B11 -> Total Cost of Sales | C10: =SUM(C8:C9)
A11: =A10+1 -> 7 | B11: =F21R!B12 -> Gross Profit | C11: =C7+C10
A12: =A11+1 -> 8 | B12: =F21R!B13 -> Commission/Mgt Income | C12: =F21R!C13 -> 5501 to 5509
A13: =A12+1 -> 9 | B13: =F21R!B14 -> Gain/(Loss) Disposal of FA | C13: =F21R!C14 -> 9101
A14: =A13+1 -> 10 | B14: =F21R!B15 -> Other Op Income | C14: =F21R!C15 -> 5511 to 5599, 9001 to 9019, 9041Credit, 9102 to 9109Credit
A15: =A14+1 -> 11 | B15: =F21R!B16 -> Other Op Expense | C15: =F21R!C16 -> 5601 to 5999, 9041Debit, 9102 to 9109Debit, 9111 to 9115, 9117 to 9199
A16: =A15+1 -> 12 | B16: =F21R!B17 -> Total Oth Op Income/ (Exp) | C16: =SUM(C12:C15)
A17: =A16+1 -> 13 | B17: Selling & Distribution | C17: 7000 to 7999
A18: =A17+1 -> 14 | B18: A&G Direct Expenses | C18: 8000 to 8699
A19: =A18+1 -> 15 | B19: A&G Other Expenses | C19: 8700 to 8799
A20: =A19+1 -> 16 | B20: =F21R!B49 -> Profit from Operations | C20: =C11+C16+SUM(C17:C19)
A21: =A20+1 -> 17 | B21: =F21R!B50 -> Interest Income | C21: =F21R!C50 -> 9023
A22: =A21+1 -> 18 | B22: =F21R!B51 -> Interest (Expense) | C22: =F21R!C51 -> 8801 to 8809
A23: =A22+1 -> 19 | B23: =F21R!B52 -> Derivatives Gain/(Loss) | C23: =F21R!C52 -> 8821 to 8822
A24: =A23+1 -> 20 | B24: =F21R!B53 -> Forex Gain/(Loss) | C24: =F21R!C53 -> 8831 to 8832
A25: =A24+1 -> 21 | B25: =F21R!B54 -> Dividend Income | C25: =F21R!C54 -> 9021
A26: =A25+1 -> 22 | B26: =F21R!B55 -> Other Non-Op Income/(Exp) | C26: =F21R!C55 -> 9031, 9116, 9200 to 9211
A27: =A26+1 -> 23 | B27: =F21R!B56 -> Total Non-Op Income/(Exp) | C27: =F21R!C56 -> =SUM(C50:C55)
A28: =A27+1 -> 24 | B28: =F21R!B57 -> Profit Before Taxation | C28: =F21R!C57 -> =C49+C56
A29: =A28+1 -> 25 | B29: =F21R!B58 -> Less: Taxation | C29: =F21R!C58 -> 9400 to 9999
A30: =A29+1 -> 26 | B30: =F21R!B59 -> Profits After Taxation | C30: =F21R!C59 -> =C57+C58
A31: =A30+1 -> 27 | B31: =F21R!B60 -> Dividend Declared | C31: =F21R!C60 -> 4902
B32: Performance Indicators | D32: 42826 | E32: 42856 | F32: 42887 | G32: 42917 | H32: 42948 | I32: 42979 | J32: 43009 | K32: 43040 | L32: 43070 | M32: 43101 | N32: 43132 | O32: 43160 | P32: Total | Q32: FY 2017 | R32: Variance %
A33: =A32+1 -> 1 | B33: Gross Profits Margin % | C33: =F21R!C62 -> Gross Profits/Total Sales
A34: =A33+1 -> 2 | B34: - External Sales GP % | C34: =F21R!C63 -> (External Sales - Cost of External Sales)/External Sales
A35: =A34+1 -> 3 | B35: - Interco Sales GP % | C35: =F21R!C64 -> (Interco Sales - Cost of Interco Sales)/Interco Sales
A36: =A35+1 -> 4 | B36: Selling & Dist Margin % | C36: =F21R!C65 -> -Total S&D Exps/Total Sales
A37: =A36+1 -> 5 | B37: A&G Margin Direct % | C37: =F21R!C66 -> -Total Direct A&G Exps/Total Sales
A38: =A37+1 -> 6 | B38: A&G Margin Total % | C38: =F21R!C67 -> -Total A&G Exps/Total Sales
A39: =A38+1 -> 7 | B39: Operating Profits Margin % | C39: =F21R!C68 -> Profits from Operations/Total Sales
A40: =A39+1 -> 8 | B40: Profits Before Taxation % | C40: =F21R!C69 -> Profits Before Taxation/Total Sales
A41: =A40+1 -> 9 | B41: Profit After Taxation % | C41: =F21R!C70 -> Profits after Taxation/Total Sales

Sheet F22S
A1: LEEDEN NATIONAL OXYGEN LTD | D1: ='F22'!D1:N1 -> AS OF: 11-Oct-2017 | O1: ='F22'!O1 -> FOR THE YEAR OF: 2018
A2: DIVISION: HO CORPORATE | D2: DEPT: ADMIN | O2: SECTION:
A3: F22S P&L ACCOUNT BY MONTH | D3: CURRENCY: SGD 000s | O3: FX: 0.00
D4: 42826 | E4: 42856 | F4: 42887 | G4: 42917 | H4: 42948 | I4: 42979 | J4: 43009 | K4: 43040 | L4: 43070 | M4: 43101 | N4: 43132 | O4: 43160 | P4: Total | Q4: FY 2017 | R4: Variance %
A5: 1 | B5: ='F22'!B5 -> External Sales | C5: ='F22'!C5 -> 5001 to 5029, 5051 to 5099
A6: =A5+1 -> 2 | B6: ='F22'!B6 -> Interco Sales | C6: ='F22'!C6 -> 5031 to 5049
A7: =A6+1 -> 3 | B7: ='F22'!B7 -> Total Sales | C7: ='F22'!C7 -> =SUM(C5:C6)
A8: =A7+1 -> 4 | B8: ='F22'!B8 -> Cost of External Sales | C8: ='F22'!C8 -> 5101 to 5119, 5141 to 5499, 6000 to 6999
A9: =A8+1 -> 5 | B9: ='F22'!B9 -> Cost of Interco Sales | C9: ='F22'!C9 -> 5121 to 5139
A10: =A9+1 -> 6 | B10: ='F22'!B10 -> Total Cost of Sales | C10: ='F22'!C10 -> =SUM(C8:C9)
A11: =A10+1 -> 7 | B11: ='F22'!B11 -> Gross Profit | C11: ='F22'!C11 -> =C7+C10
A12: =A11+1 -> 8 | B12: ='F22'!B12 -> Commission/Mgt Income | C12: ='F22'!C12 -> 5501 to 5509
A13: =A12+1 -> 9 | B13: ='F22'!B13 -> Gain/(Loss) Disposal of FA | C13: ='F22'!C13 -> 9101
A14: =A13+1 -> 10 | B14: ='F22'!B14 -> Other Op Income | C14: ='F22'!C14 -> 5511 to 5599, 9001 to 9019, 9041Credit, 9102 to 9109Credit
A15: =A14+1 -> 11 | B15: ='F22'!B15 -> Other Op Expense | C15: ='F22'!C15 -> 5601 to 5999, 9041Debit, 9102 to 9109Debit, 9111 to 9115, 9117 to 9199
A16: =A15+1 -> 12 | B16: ='F22'!B16 -> Total Oth Op Income/ (Exp) | C16: ='F22'!C16 -> =SUM(C12:C15)
A17: =A16+1 -> 13 | B17: ='F22'!B17 -> Selling & Distribution | C17: ='F22'!C17 -> 7000 to 7999
... A31: =A30+1 -> 27 | B31: ='F22'!B31 -> Dividend Declared | C31: ='F22'!C31 -> 4902
B32: ='F22'!B32 -> Performance Indicators | D32: 42826 | E32: 42856 | F32: 42887 | G32: 42917 | H32: 42948 | I32: 42979 | J32: 43009 | K32: 43040 | L32: 43070 | M32: 43101 | N32: 43132 | O32: 43160 | P32: Total | Q32: FY 2017 | R32: Variance %
A33: 1 | B33: ='F22'!B33 -> Gross Profits Margin % | C33: ='F22'!C33 -> Gross Profits/Total Sales
A34: =A33+1 -> 2 | B34: ='F22'!B34 -> - External Sales GP % | C34: ='F22'!C34 -> (External Sales - Cost of External Sales)/External Sales
A35: =A34+1 -> 3 | B35: ='F22'!B35 -> - Interco Sales GP % | C35: ='F22'!C35 -> (Interco Sales - Cost of Interco Sales)/Interco Sales
A36: =A35+1 -> 4 | B36: ='F22'!B36 -> Selling & Dist Margin % | C36: ='F22'!C36 -> -Total S&D Exps/Total Sales
A37: =A36+1 -> 5 | B37: ='F22'!B37 -> A&G Margin Direct % | C37: ='F22'!C37 -> -Total Direct A&G Exps/Total Sales
A38: =A37+1 -> 6 | B38: ='F22'!B38 -> A&G Margin Total % | C38: ='F22'!C38 -> -Total A&G Exps/Total Sales
A39: =A38+1 -> 7 | B39: ='F22'!B39 -> Operating Profits Margin % | C39: ='F22'!C39 -> Profits from Operations/Total Sales
A40: =A39+1 -> 8 | B40: ='F22'!B40 -> Profits Before Taxation % | C40: ='F22'!C40 -> Profits Before Taxation/Total Sales
A41: =A40+1 -> 9 | B41: ='F22'!B41 -> Profit After Taxation % | C41: ='F22'!C41 -> Profits after Taxation/Total Sales

Sheet F23-Div
A1: LEEDEN NATIONAL OXYGEN LTD | D1: =F22S!D1 -> AS OF: 11-Oct-2017 | I1: =F21S!H1 -> FOR THE MONTH OF: Sep -17
A2: DIVISION: | D2: DEPT: | I2: SECTION:
A3: F23 P&L ACCOUNT BY DIV/DEPT/SEC/UNITS | D3: CURRENCY: SGD 000s | I3: FX: 0.00
D4: DIV 1 | E4: DIV 2 | F4: DIV 3 | G4: DIV 4 | H4: DIV 5 | I4: DIV 6 | J4: DIV 7 | K4: DIV 8 | L4: DIV 9 | M4: TOTAL
A5: 1 | B5: =F21R!B6 -> External Sales | C5: =F21R!C6 -> 5001 to 5029, 5051 to 5099
A6: =A5+1 -> 2 | B6: =F21R!B7 -> Interco Sales | C6: =F21R!C7 -> 5031 to 5049
A7: =A6+1 -> 3 | B7: =F21R!B8 -> Total Sales | C7: =SUM(C5:C6)
A8: =A7+1 -> 4 | B8: =F21R!B9 -> Cost of External Sales | C8: =F21R!C9 -> 5101 to 5119, 5141 to 5499, 6000 to 6999
A9: =A8+1 -> 5 | B9: =F21R!B10 -> Cost of Interco Sales | C9: =F21R!C10 -> 5121 to 5139
A10: =A9+1 -> 6 | B10: =F21R!B11 -> Total Cost of Sales | C10: =SUM(C8:C9)
A11: =A10+1 -> 7 | B11: =F21R!B12 -> Gross Profit | C11: =C7+C10
A12: =A11+1 -> 8 | B12: =F21R!B13 -> Commission/Mgt Income | C12: =F21R!C13 -> 5501 to 5509
A13: =A12+1 -> 9 | B13: =F21R!B14 -> Gain/(Loss) Disposal of FA | C13: =F21R!C14 -> 9101
A14: =A13+1 -> 10 | B14: =F21R!B15 -> Other Op Income | C14: =F21R!C15 -> 5511 to 5599, 9001 to 9019, 9041Credit, 9102 to 9109Credit
A15: =A14+1 -> 11 | B15: =F21R!B16 -> Other Op Expense | C15: =F21R!C16 -> 5601 to 5999, 9041Debit, 9102 to 9109Debit, 9111 to 9115, 9117 to 9199
A16: =A15+1 -> 12 | B16: =F21R!B17 -> Total Oth Op Income/ (Exp) | C16: =SUM(C12:C15)
A17: =A16+1 -> 13 | B17: =F21R!B18 -> Personnel Related Cost | C17: =F21R!C18 -> 7000 to 7099
A18: =A17+1 -> 14 | B18: =F21R!B19 -> Carriage/Transportation | C18: =F21R!C19 -> 7100 to 7199
A19: =A18+1 -> 15 | B19: =F21R!B20 -> Advertising/Promotion | C19: =F21R!C20 -> 7200 to 7299
A20: =A19+1 -> 16 | B20: =F21R!B21 -> Overseas Travelling | C20: =F21R!C21 -> 7301
A21: =A20+1 -> 17 | B21: =F21R!B22 -> Entertainment | C21: =F21R!C22 -> 7302 to 7399
A22: =A21+1 -> 18 | B22: =F21R!B23 -> Equipment Expenses | C22: =F21R!C23 -> 7400 to 7499
A23: =A22+1 -> 19 | B23: =F21R!B24 -> Rental/Property Related | C23: =F21R!C24 -> 7500 to 7599
A24: =A23+1 -> 20 | B24: =F21R!B25 -> Depn of Fixed Assets | C24: =F21R!C25 -> 7600 to 7699
A25: =A24+1 -> 21 | B25: =F21R!B26 -> Stationery/Printing/Telephone | C25: =F21R!C26 -> 7701 to 7705
A26: =A25+1 -> 22 | B26: =F21R!B27 -> HO/Interco and Other S&D | C26: =F21R!C27 -> 7706 to 7999
A27: =A26+1 -> 23 | B27: =F21R!B28 -> Total S&D Expenses | C27: =SUM(C17:C26)
A28: =A27+1 -> 24 | B28: =F21R!B29 -> Personnel Related Cost | C28: =F21R!C29 -> 8000 to 8099
A29: =A28+1 -> 25 | B29: =F21R!B30 -> Overseas Travelling | C29: =F21R!C30 -> 8101
A30: =A29+1 -> 26 | B30: =F21R!B31 -> Transportation | C30: =F21R!C31 -> 8102 to 8149
A31: =A30+1 -> 27 | B31: =F21R!B32 -> Entertainment & Donations | C31: =F21R!C32 -> 8150 to 8199
A32: =A31+1 -> 28 | B32: =F21R!B33 -> Equipment Expenses | C32: =F21R!C33 -> 8200 to 8299
A33: =A32+1 -> 29 | B33: =F21R!B34 -> Rental/Property Related | C33: =F21R!C34 -> 8300 to 8399
A34: =A33+1 -> 30 | B34: =F21R!B35 -> Depn of Fixed Assets | C34: =F21R!C35 -> 8400 to 8499
A35: =A34+1 -> 31 | B35: =F21R!B36 -> Stationery/Printing/Telephone | C35: =F21R!C36 -> 8500 to 8599
A36: =A35+1 -> 32 | B36: =F21R!B37 -> Legal/Prof Fees/Ins/Safety | C36: =F21R!C37 -> 8600 to 8649
A37: =A36+1 -> 33 | B37: =F21R!B38 -> IT System Exps | C37: =F21R!C38 -> 8651
A38: =A37+1 -> 34 | B38: =F21R!B39 -> Purchasing Exps | C38: =F21R!C39 -> 8653
A39: =A38+1 -> 35 | B39: =F21R!B40 -> A&G Direct Expenses | C39: =SUM(C28:C38)
A40: =A39+1 -> 36 | B40: =F21R!B41 -> Prov for Stock Obso/Pilferage | C40: =F21R!C41 -> 8701 to 8702
A41: =A40+1 -> 37 | B41: =F21R!B42 -> Prov for Doubtful Debts | C41: =F21R!C42 -> 8703
A42: =A41+1 -> 38 | B42: =F21R!B43 -> Bad Debts Recovered | C42: =F21R!C43 -> 8704
A43: =A42+1 -> 39 | B43: =F21R!B44 -> Stocks Written Down/Written Off | C43: =F21R!C44 -> 8705
A44: =A43+1 -> 40 | B44: =F21R!B45 -> GST/VAT Expense | C44: =F21R!C45 -> 8711 to 8712
A45: =A44+1 -> 41 | B45: =F21R!B46 -> HO/Interco Alloc | C45: =F21R!C46 -> 8798 to 8799
A46: =A45+1 -> 42 | B46: =F21R!B47 -> Other A&G Expenses | C46: =SUM(C40:C45)
A47: =A46+1 -> 43 | B47: =F21R!B48 -> Total A&G Expenses | C47: =C39+C46
A48: =A47+1 -> 44 | B48: =F21R!B49 -> Profit from Operations | C48: =C11+C16+C27+C47
A49: =A48+1 -> 45 | B49: =F21R!B50 -> Interest Income | C49: =F21R!C50 -> 9023
A50: =A49+1 -> 46 | B50: =F21R!B51 -> Interest (Expense) | C50: =F21R!C51 -> 8801 to 8809
A51: =A50+1 -> 47 | B51: =F21R!B52 -> Derivatives Gain/(Loss) | C51: =F21R!C52 -> 8821 to 8822
A52: =A51+1 -> 48 | B52: =F21R!B53 -> Forex Gain/(Loss) | C52: =F21R!C53 -> 8831 to 8832
A53: =A52+1 -> 49 | B53: =F21R!B54 -> Dividend Income | C53: =F21R!C54 -> 9021
A54: =A53+1 -> 50 | B54: =F21R!B55 -> Other Non-Op Income/(Exp) | C54: =F21R!C55 -> 9031, 9116, 9200 to 9211
A55: =A54+1 -> 51 | B55: =F21R!B56 -> Total Non-Op Income/(Exp) | C55: =SUM(C49:C54)
A56: =A55+1 -> 52 | B56: =F21R!B57 -> Profit Before Taxation | C56: =C48+C55
A57: =A56+1 -> 53 | B57: =F21R!B58 -> Less: Taxation | C57: =F21R!C58 -> 9400 to 9999
A58: =A57+1 -> 54 | B58: =F21R!B59 -> Profits After Taxation | C58: =C56+C57
A59: =A58+1 -> 55 | B59: =F21R!B60 -> Dividend Declared | C59: =F21R!C60 -> 4902
B60: Performance Indicators | D60: DIV 1 | E60: DIV 2 | F60: DIV 3 | G60: DIV 4 | H60: DIV 5 | I60: DIV 6 | J60: DIV 7 | K60: DIV 8 | L60: DIV 9 | M60: TOTAL
A61: =A60+1 -> 1 | B61: Gross Profits Margin % | C61: =F21R!C62 -> Gross Profits/Total Sales
A62: =A61+1 -> 2 | B62: - External Sales GP % | C62: =F21R!C63 -> (External Sales - Cost of External Sales)/External Sales
A63: 3 | B63: - Interco Sales GP % | C63: =F21R!C64 -> (Interco Sales - Cost of Interco Sales)/Interco Sales
A64: 4 | B64: Selling & Dist Margin % | C64: =F21R!C65 -> -Total S&D Exps/Total Sales
A65: 5 | B65: A&G Margin Direct % | C65: =F21R!C66 -> -Total Direct A&G Exps/Total Sales
A66: 6 | B66: A&G Margin Total % | C66: =F21R!C67 -> -Total A&G Exps/Total Sales
A67: 7 | B67: Operating Profit Margin % | C67: =F21R!C68 -> Profits from Operations/Total Sales
A68: 8 | B68: Profit Before Taxation % | C68: =F21R!C69 -> Profits Before Taxation/Total Sales
A69: 9 | B69: Profit After Taxation % | C69: =F21R!C70 -> Profits after Taxation/Total Sales

Sheet F23-Dep
A1: LEEDEN NATIONAL OXYGEN LTD | D1: AS OF: 11-Oct-2017 | I1: FOR THE MONTH OF: Sep -17
A2: DIVISION: WELDING & SAFETY | D2: DEPT: | I2: SECTION:
A3: ='F23-Div'!A3:B3 -> F23 P&L ACCOUNT BY DIV/DEPT/SEC/UNITS | D3: CURRENCY: SGD 000s | I3: FX: 0.00
D4: DEPT 1 | E4: DEPT 2 | F4: DEPT 3 | G4: DEPT 4 | H4: DEPT 5 | I4: DEPT 6 | J4: DEPT 7 | K4: DEPT 8 | L4: DEPT 9 | M4: TOTAL
A5: 1 | B5: ='F23-Div'!B5 -> External Sales | C5: ='F23-Div'!C5 -> 5001 to 5029, 5051 to 5099
A6: =A5+1 -> 2 | B6: ='F23-Div'!B6 -> Interco Sales | C6: ='F23-Div'!C6 -> 5031 to 5049
A7: =A6+1 -> 3 | B7: ='F23-Div'!B7 -> Total Sales | C7: ='F23-Div'!C7 -> =SUM(C5:C6)
A8: =A7+1 -> 4 | B8: ='F23-Div'!B8 -> Cost of External Sales | C8: ='F23-Div'!C8 -> 5101 to 5119, 5141 to 5499, 6000 to 6999
A9: =A8+1 -> 5 | B9: ='F23-Div'!B9 -> Cost of Interco Sales | C9: ='F23-Div'!C9 -> 5121 to 5139
A10: =A9+1 -> 6 | B10: ='F23-Div'!B10 -> Total Cost of Sales | C10: ='F23-Div'!C10 -> =SUM(C8:C9)
A11: =A10+1 -> 7 | B11: ='F23-Div'!B11 -> Gross Profit | C11: ='F23-Div'!C11 -> =C7+C10
A12: =A11+1 -> 8 | B12: ='F23-Div'!B12 -> Commission/Mgt Income | C12: ='F23-Div'!C12 -> 5501 to 5509
A13: =A12+1 -> 9 | B13: ='F23-Div'!B13 -> Gain/(Loss) Disposal of FA | C13: ='F23-Div'!C13 -> 9101
A14: =A13+1 -> 10 | B14: ='F23-Div'!B14 -> Other Op Income | C14: ='F23-Div'!C14 -> 5511 to 5599, 9001 to 9019, 9041Credit, 9102 to 9109Credit
A15: =A14+1 -> 11 | B15: ='F23-Div'!B15 -> Other Op Expense | C15: ='F23-Div'!C15 -> 5601 to 5999, 9041Debit, 9102 to 9109Debit, 9111 to 9115, 9117 to 9199
A16: =A15+1 -> 12 | B16: ='F23-Div'!B16 -> Total Oth Op Income/ (Exp) | C16: ='F23-Div'!C16 -> =SUM(C12:C15)
A17: =A16+1 -> 13 | B17: ='F23-Div'!B17 -> Personnel Related Cost | C17: ='F23-Div'!C17 -> 7000 to 7099
... A59: =A58+1 -> 55 | B59: ='F23-Div'!B59 -> Dividend Declared | C59: ='F23-Div'!C59 -> 4902
B60: ='F23-Div'!B60 -> Performance Indicators | D60: DEPT 1 | E60: DEPT 2 | F60: DEPT 3 | G60: DEPT 4 | H60: DEPT 5 | I60: DEPT 6 | J60: DEPT 7 | K60: DEPT 8 | L60: DEPT 9 | M60: TOTAL
A61: =A60+1 -> 1 | B61: ='F23-Div'!B61 -> Gross Profits Margin % | C61: ='F23-Div'!C61 -> Gross Profits/Total Sales
A62: =A61+1 -> 2 | B62: ='F23-Div'!B62 -> - External Sales GP % | C62: ='F23-Div'!C62 -> (External Sales - Cost of External Sales)/External Sales
A63: 3 | B63: ='F23-Div'!B63 -> - Interco Sales GP % | C63: ='F23-Div'!C63 -> (Interco Sales - Cost of Interco Sales)/Interco Sales
A64: 4 | B64: ='F23-Div'!B64 -> Selling & Dist Margin % | C64: ='F23-Div'!C64 -> -Total S&D Exps/Total Sales
A65: 5 | B65: ='F23-Div'!B65 -> A&G Margin Direct % | C65: ='F23-Div'!C65 -> -Total Direct A&G Exps/Total Sales
A66: 6 | B66: ='F23-Div'!B66 -> A&G Margin Total % | C66: ='F23-Div'!C66 -> -Total A&G Exps/Total Sales
A67: 7 | B67: ='F23-Div'!B67 -> Operating Profit Margin % | C67: ='F23-Div'!C67 -> Profits from Operations/Total Sales
A68: 8 | B68: ='F23-Div'!B68 -> Profit Before Taxation % | C68: ='F23-Div'!C68 -> Profits Before Taxation/Total Sales
A69: 9 | B69: ='F23-Div'!B69 -> Profit After Taxation % | C69: ='F23-Div'!C69 -> Profits after Taxation/Total Sales

Sheet F23-Sec
A1: LEEDEN NATIONAL OXYGEN LTD | D1: ='F23-Dep'!D1:H1 -> AS OF: 11-Oct-2017 | I1: ='F23-Dep'!I1:M1 -> FOR THE MONTH OF: Sep -17
A2: DIVISION: WELDING & SAFETY | D2: DEPT: WELDING SALES/PRODUCTS | I2: SECTION:
A3: ='F23-Dep'!A3:B3 -> F23 P&L ACCOUNT BY DIV/DEPT/SEC/UNITS | D3: CURRENCY: SGD 000s | I3: FX: 0.00
D4: SECT 1 | E4: SECT 2 | F4: SECT 3 | G4: SECT 4 | H4: SECT 5 | I4: SECT 6 | J4: SECT 7 | K4: SECT 8 | L4: SECT 9 | M4: TOTAL
A5: 1 | B5: ='F23-Dep'!B5 -> External Sales | C5: ='F23-Dep'!C5 -> 5001 to 5029, 5051 to 5099
A6: =A5+1 -> 2 | B6: ='F23-Dep'!B6 -> Interco Sales | C6: ='F23-Dep'!C6 -> 5031 to 5049
A7: =A6+1 -> 3 | B7: ='F23-Dep'!B7 -> Total Sales | C7: ='F23-Dep'!C7 -> =SUM(C5:C6)
A8: =A7+1 -> 4 | B8: ='F23-Dep'!B8 -> Cost of External Sales | C8: ='F23-Dep'!C8 -> 5101 to 5119, 5141 to 5499, 6000 to 6999
A9: =A8+1 -> 5 | B9: ='F23-Dep'!B9 -> Cost of Interco Sales | C9: ='F23-Dep'!C9 -> 5121 to 5139
A10: =A9+1 -> 6 | B10: ='F23-Dep'!B10 -> Total Cost of Sales | C10: ='F23-Dep'!C10 -> =SUM(C8:C9)
A11: =A10+1 -> 7 | B11: ='F23-Dep'!B11 -> Gross Profit | C11: ='F23-Dep'!C11 -> =C7+C10
A12: =A11+1 -> 8 | B12: ='F23-Dep'!B12 -> Commission/Mgt Income | C12: ='F23-Dep'!C12 -> 5501 to 5509
A13: =A12+1 -> 9 | B13: ='F23-Dep'!B13 -> Gain/(Loss) Disposal of FA | C13: ='F23-Dep'!C13 -> 9101
A14: =A13+1 -> 10 | B14: ='F23-Dep'!B14 -> Other Op Income | C14: ='F23-Dep'!C14 -> 5511 to 5599, 9001 to 9019, 9041Credit, 9102 to 9109Credit
A15: =A14+1 -> 11 | B15: ='F23-Dep'!B15 -> Other Op Expense | C15: ='F23-Dep'!C15 -> 5601 to 5999, 9041Debit, 9102 to 9109Debit, 9111 to 9115, 9117 to 9199
A16: =A15+1 -> 12 | B16: ='F23-Dep'!B16 -> Total Oth Op Income/ (Exp) | C16: ='F23-Dep'!C16 -> =SUM(C12:C15)
A17: =A16+1 -> 13 | B17: ='F23-Dep'!B17 -> Personnel Related Cost | C17: ='F23-Dep'!C17 -> 7000 to 7099
... A59: =A58+1 -> 55 | B59: ='F23-Dep'!B59 -> Dividend Declared | C59: ='F23-Dep'!C59 -> 4902
B60: ='F23-Dep'!B60 -> Performance Indicators | D60: SECT 1 | E60: SECT 2 | F60: SECT 3 | G60: SECT 4 | H60: SECT 5 | I60: SECT 6 | J60: SECT 7 | K60: SECT 8 | L60: SECT 9 | M60: TOTAL
A61: =A60+1 -> 1 | B61: ='F23-Dep'!B61 -> Gross Profits Margin % | C61: ='F23-Dep'!C61 -> Gross Profits/Total Sales
A62: =A61+1 -> 2 | B62: ='F23-Dep'!B62 -> - External Sales GP % | C62: ='F23-Dep'!C62 -> (External Sales - Cost of External Sales)/External Sales
A63: 3 | B63: ='F23-Dep'!B63 -> - Interco Sales GP % | C63: ='F23-Dep'!C63 -> (Interco Sales - Cost of Interco Sales)/Interco Sales
A64: 4 | B64: ='F23-Dep'!B64 -> Selling & Dist Margin % | C64: ='F23-Dep'!C64 -> -Total S&D Exps/Total Sales
A65: 5 | B65: ='F23-Dep'!B65 -> A&G Margin Direct % | C65: ='F23-Dep'!C65 -> -Total Direct A&G Exps/Total Sales
A66: 6 | B66: ='F23-Dep'!B66 -> A&G Margin Total % | C66: ='F23-Dep'!C66 -> -Total A&G Exps/Total Sales
A67: 7 | B67: ='F23-Dep'!B67 -> Operating Profit Margin % | C67: ='F23-Dep'!C67 -> Profits from Operations/Total Sales
A68: 8 | B68: ='F23-Dep'!B68 -> Profit Before Taxation % | C68: ='F23-Dep'!C68 -> Profits Before Taxation/Total Sales
A69: 9 | B69: ='F23-Dep'!B69 -> Profit After Taxation % | C69: ='F23-Dep'!C69 -> Profits after Taxation/Total Sales

Sheet F23-Units
A1: LEEDEN NATIONAL OXYGEN LTD | D1: ='F23-Dep'!D1:H1 -> AS OF: 11-Oct-2017 | I1: ='F23-Dep'!I1:M1 -> FOR THE MONTH OF: Sep -17
A2: DIVISION: GAS | D2: DEPT: PACKAGED GAS PRODUCTION | I2: SECTION: | J2: REFILLING
A3: ='F23-Dep'!A3:B3 -> F23 P&L ACCOUNT BY DIV/DEPT/SEC/UNITS | D3: CURRENCY: SGD 000s | I3: FX: 0.00
D4: UNIT 1 | E4: UNIT 2 | F4: UNIT 3 | G4: UNIT 4 | H4: UNIT 5 | I4: UNIT 6 | J4: UNIT 7 | K4: UNIT 8 | L4: UNIT 9 | M4: TOTAL
A5: 1 | B5: ='F23-Sec'!B5 -> External Sales | C5: ='F23-Sec'!C5 -> 5001 to 5029, 5051 to 5099
A6: =A5+1 -> 2 | B6: ='F23-Sec'!B6 -> Interco Sales | C6: ='F23-Sec'!C6 -> 5031 to 5049
A7: =A6+1 -> 3 | B7: ='F23-Sec'!B7 -> Total Sales | C7: ='F23-Sec'!C7 -> =SUM(C5:C6)
A8: =A7+1 -> 4 | B8: ='F23-Sec'!B8 -> Cost of External Sales | C8: ='F23-Sec'!C8 -> 5101 to 5119, 5141 to 5499, 6000 to 6999
A9: =A8+1 -> 5 | B9: ='F23-Sec'!B9 -> Cost of Interco Sales | C9: ='F23-Sec'!C9 -> 5121 to 5139
A10: =A9+1 -> 6 | B10: ='F23-Sec'!B10 -> Total Cost of Sales | C10: ='F23-Sec'!C10 -> =SUM(C8:C9)
A11: =A10+1 -> 7 | B11: ='F23-Sec'!B11 -> Gross Profit | C11: ='F23-Sec'!C11 -> =C7+C10
A12: =A11+1 -> 8 | B12: ='F23-Sec'!B12 -> Commission/Mgt Income | C12: ='F23-Sec'!C12 -> 5501 to 5509
A13: =A12+1 -> 9 | B13: ='F23-Sec'!B13 -> Gain/(Loss) Disposal of FA | C13: ='F23-Sec'!C13 -> 9101
A14: =A13+1 -> 10 | B14: ='F23-Sec'!B14 -> Other Op Income | C14: ='F23-Sec'!C14 -> 5511 to 5599, 9001 to 9019, 9041Credit, 9102 to 9109Credit
A15: =A14+1 -> 11 | B15: ='F23-Sec'!B15 -> Other Op Expense | C15: ='F23-Sec'!C15 -> 5601 to 5999, 9041Debit, 9102 to 9109Debit, 9111 to 9115, 9117 to 9199
A16: =A15+1 -> 12 | B16: ='F23-Sec'!B16 -> Total Oth Op Income/ (Exp) | C16: ='F23-Sec'!C16 -> =SUM(C12:C15)
A17: =A16+1 -> 13 | B17: ='F23-Sec'!B17 -> Personnel Related Cost | C17: ='F23-Sec'!C17 -> 7000 to 7099
... A59: =A58+1 -> 55 | B59: ='F23-Sec'!B59 -> Dividend Declared | C59: ='F23-Sec'!C59 -> 4902
B60: ='F23-Sec'!B60 -> Performance Indicators | D60: UNIT 1 | E60: UNIT 2 | F60: UNIT 3 | G60: UNIT 4 | H60: UNIT 5 | I60: UNIT 6 | J60: UNIT 7 | K60: UNIT 8 | L60: UNIT 9 | M60: TOTAL
A61: =A60+1 -> 1 | B61: ='F23-Sec'!B61 -> Gross Profits Margin % | C61: ='F23-Sec'!C61 -> Gross Profits/Total Sales
A62: =A61+1 -> 2 | B62: ='F23-Sec'!B62 -> - External Sales GP % | C62: ='F23-Sec'!C62 -> (External Sales - Cost of External Sales)/External Sales
A63: 3 | B63: ='F23-Sec'!B63 -> - Interco Sales GP % | C63: ='F23-Sec'!C63 -> (Interco Sales - Cost of Interco Sales)/Interco Sales
A64: 4 | B64: ='F23-Sec'!B64 -> Selling & Dist Margin % | C64: ='F23-Sec'!C64 -> -Total S&D Exps/Total Sales
A65: 5 | B65: ='F23-Sec'!B65 -> A&G Margin Direct % | C65: ='F23-Sec'!C65 -> -Total Direct A&G Exps/Total Sales
A66: 6 | B66: ='F23-Sec'!B66 -> A&G Margin Total % | C66: ='F23-Sec'!C66 -> -Total A&G Exps/Total Sales
A67: 7 | B67: ='F23-Sec'!B67 -> Operating Profit Margin % | C67: ='F23-Sec'!C67 -> Profits from Operations/Total Sales
A68: 8 | B68: ='F23-Sec'!B68 -> Profit Before Taxation % | C68: ='F23-Sec'!C68 -> Profits Before Taxation/Total Sales
A69: 9 | B69: ='F23-Sec'!B69 -> Profit After Taxation % | C69: ='F23-Sec'!C69 -> Profits after Taxation/Total Sales

Sheet F24
A1: LEEDEN NATIONAL OXYGEN LTD | D1: AS OF: 11-Oct-2017 | H1: FOR THE MONTH OF: Sep -17
A2: DIVISION: GAS | D2: DEPT: | H2: SECTION:
A3: F24 MANUFACTURING ACCOUNT | D3: CURRENCY: SGD 000s | H3: FX: 0.00
D4: CURRENT MONTH | H4: YEAR TO DATE
D5: Aug-17 | E5: Sep-17 | F5: Budget | G5: Variance | H5: Actual | I5: Budget | J5: Variance | K5: Last Year | L5: Variance
A6: 1 | B6: Manufacturing Costs
A7: =A6+1 -> 2 | B7: DM–Raw Materials | C7: 6101
A8: =A7+1 -> 3 | B8: DM–Parts & Access | C8: 6102
A9: =A8+1 -> 4 | B9: DM–Packing & Label Materials | C9: 6103 to 6104
A10: =A9+1 -> 5 | B10: DM–Others | C10: 6105 to 6199
A11: =A10+1 -> 6 | B11: Direct Material | C11: =SUM(C7:C10)
A12: =A11+1 -> 7 | B12: Salary & Leave | C12: 6201 to 6202
A13: =A12+1 -> 8 | B13: Bonus | C13: 6203 to 6204
A14: =A13+1 -> 9 | B14: Foreign Workers/Casual/Temp | C14: 6206, 6208
A15: =A14+1 -> 10 | B15: Overtime | C15: 6209 to 6210
A16: =A15+1 -> 11 | B16: Shift Allowance & Incentive | C16: 6205, 6211 to 6212
A17: =A16+1 -> 12 | B17: Staff Transport/Vehicle Rental | C17: 6213
A18: =A17+1 -> 13 | B18: Social Security Contribution | C18: 6214
A19: =A18+1 -> 14 | B19: Workers' Levy | C19: 6215
A20: =A19+1 -> 15 | B20: Others Direct Labor Costs | C20: 6207, 6216 to 6229
... A34: =A33+1 -> 29 | B34: Other Indirect Labor Costs | C34: 6315, 6323 to 6349
A35: =A34+1 -> 30 | B35: QA Allocated Cost
A36: =A35+1 -> 31 | B36: PM Allocated Cost
A37: =A36+1 -> 32 | B37: Indirect Labor | C37: =SUM(C25:C36)
A38: =A37+1 -> 33 | B38: Utilities - Elec, Water, Gas | C38: 6401 to 6410
A39: =A38+1 -> 34 | B39: Product Development/Testing | C39: 6421 to 6430
A40: =A39+1 -> 35 | B40: Carriage/Transport/Storage | C40: 6411 to 6420
A41: =A40+1 -> 36 | B41: Manufacturing Loss/Wastage | C41: 6431, 6432
A42: =A41+1 -> 37 | B42: Rejects/Reworks/Scrap | C42: 6433 to 6435
A43: =A42+1 -> 38 | B43: Disposal of Sludge/Others | C43: 6436 to 6499
A44: =A43+1 -> 39 | B44: QA Allocated Cost
A45: =A44+1 -> 40 | B45: PM Allocated Cost
A46: =A45+1 -> 41 | B46: Other Variable Overhead | C46: =SUM(C38:C45)
A47: =A46+1 -> 42 | B47: Total Variable Overhead | C47: =C24+C37+C46
A48: =A47+1 -> 43 | B48: Factory Rental/Upkeep | C48: 6501 to 6502, 6506
A49: =A48+1 -> 44 | B49: Property Tax for Factory | C49: 6503
A50: =A49+1 -> 45 | B50: Repair & Maintainance/Upkeep | C50: 6601 to 6620
A51: =A50+1 -> 46 | B51: Leasing of Mac&Equip/Vehicles/Cyl | C51: 6621 to 6623
A52: =A51+1 -> 47 | B52: Depreciation | C52: 6701 to 6749
A53: =A52+1 -> 48 | B53: Licenses & Insurance | C53: 6504, 6751 to 6759
A54: =A53+1 -> 49 | B54: Non Capitalised Purchases | C54: 6761 to 6769
A55: =A54+1 -> 50 | B55: Others Fixed Overhead | C55: 6505, 6771 to 6799
A56: =A55+1 -> 51 | B56: QA Allocated Cost
A57: =A56+1 -> 52 | B57: PM Allocated Cost
A58: =A57+1 -> 53 | B58: Fixed Overhead | C58: =SUM(C48:C57)
A59: =A58+1 -> 54 | B59: Cost of Goods Manufactured | C59: =C23+C47+C58

Sheet F25-Div
A1: LEEDEN NATIONAL OXYGEN LTD | D1: ='F24'!D1:G1 -> AS OF: 11-Oct-2017 | I1: FOR THE MONTH OF: Sep -17
A2: DIVISION: | D2: DEPT: | I2: SECTION:
A3: F25 MANUFACTURING ACCOUNT | D3: CURRENCY: SGD 000s | I3: FX: 0.00
A4: BY DIV/DEPT/SEC/UNITS | D4: DIV 1 | E4: DIV 2 | F4: DIV 3 | G4: DIV 4 | H4: DIV 5 | I4: DIV 6 | J4: DIV 7 | K4: DIV 8 | L4: TOTAL
A5: 1 | B5: ='F24'!B6 -> Manufacturing Costs
A6: =A5+1 -> 2 | B6: ='F24'!B7 -> DM–Raw Materials | C6: ='F24'!C7 -> 6101
A7: =A6+1 -> 3 | B7: ='F24'!B8 -> DM–Parts & Access | C7: ='F24'!C8 -> 6102
A8: =A7+1 -> 4 | B8: ='F24'!B9 -> DM–Packing & Label Materials | C8: ='F24'!C9 -> 6103 to 6104
A9: =A8+1 -> 5 | B9: ='F24'!B10 -> DM–Others | C9: ='F24'!C10 -> 6105 to 6199
A10: =A9+1 -> 6 | B10: ='F24'!B11 -> Direct Material | C10: =SUM(C6:C9)
A11: =A10+1 -> 7 | B11: ='F24'!B12 -> Salary & Leave | C11: ='F24'!C12 -> 6201 to 6202
A12: =A11+1 -> 8 | B12: ='F24'!B13 -> Bonus | C12: ='F24'!C13 -> 6203 to 6204
A13: =A12+1 -> 9 | B13: ='F24'!B14 -> Foreign Workers/Casual/Temp | C13: ='F24'!C14 -> 6206, 6208
A14: =A13+1 -> 10 | B14: ='F24'!B15 -> Overtime | C14: ='F24'!C15 -> 6209 to 6210
A15: =A14+1 -> 11 | B15: ='F24'!B16 -> Shift Allowance & Incentive | C15: ='F24'!C16 -> 6205, 6211 to 6212
A16: =A15+1 -> 12 | B16: ='F24'!B17 -> Staff Transport/Vehicle Rental | C16: ='F24'!C17 -> 6213
A17: =A16+1 -> 13 | B17: ='F24'!B18 -> Social Security Contribution | C17: ='F24'!C18 -> 6214
A18: =A17+1 -> 14 | B18: ='F24'!B19 -> Workers' Levy | C18: ='F24'!C19 -> 6215
A19: =A18+1 -> 15 | B19: ='F24'!B20 -> Others Direct Labor Costs | C19: ='F24'!C20 -> 6207, 6216 to 6229
A20: =A19+1 -> 16 | B20: ='F24'!B21 -> Direct Labor | C20: =SUM(C11:C19)
A21: =A20+1 -> 17 | B21: ='F24'!B22 -> Direct Expenses | C21: ='F24'!C22 -> 6251 to 6299
A22: =A21+1 -> 18 | B22: ='F24'!B23 -> Prime Cost | C22: =C10+C20+C21
A23: =A22+1 -> 19 | B23: ='F24'!B24 -> Indirect Material | C23: ='F24'!C24 -> 6301 to 6310
A24: =A23+1 -> 20 | B24: ='F24'!B25 -> Salary & Leave | C24: ='F24'!C25 -> 6311
A25: =A24+1 -> 21 | B25: ='F24'!B26 -> Bonus | C25: ='F24'!C26 -> 6312
A26: =A25+1 -> 22 | B26: ='F24'!B27 -> Foreign Workers/Casual/Temp | C26: ='F24'!C27 -> 6314, 6316
A27: =A26+1 -> 23 | B27: ='F24'!B28 -> Overtime | C27: ='F24'!C28 -> 6317
A28: =A27+1 -> 24 | B28: ='F24'!B29 -> Shift Allowance & Incentive | C28: ='F24'!C29 -> 6313, 6318 to 6319
A29: =A28+1 -> 25 | B29: ='F24'!B30 -> Staff Transport/Vehicle Rental | C29: ='F24'!C30 -> 6320
A30: =A29+1 -> 26 | B30: ='F24'!B31 -> Social Security Contribution | C30: ='F24'!C31 -> 6321
A31: =A30+1 -> 27 | B31: ='F24'!B32 -> Workers' Levy | C31: ='F24'!C32 -> 6322
A32: =A31+1 -> 28 | B32: ='F24'!B33 -> Expats' Expenses | C32: ='F24'!C33 -> 6351 to 6399
A33: =A32+1 -> 29 | B33: ='F24'!B34 -> Other Indirect Labor Costs | C33: ='F24'!C34 -> 6315, 6323 to 6349
A34: =A33+1 -> 30 | B34: ='F24'!B35 -> QA Allocated Cost
A35: =A34+1 -> 31 | B35: ='F24'!B36 -> PM Allocated Cost
A36: =A35+1 -> 32 | B36: ='F24'!B37 -> Indirect Labor | C36: =SUM(C24:C35)
A37: =A36+1 -> 33 | B37: ='F24'!B38 -> Utilities - Elec, Water, Gas | C37: ='F24'!C38 -> 6401 to 6410
A38: =A37+1 -> 34 | B38: ='F24'!B39 -> Product Development/Testing | C38: ='F24'!C39 -> 6421 to 6430
A39: =A38+1 -> 35 | B39: ='F24'!B40 -> Carriage/Transport/Storage | C39: ='F24'!C40 -> 6411 to 6420
A40: =A39+1 -> 36 | B40: ='F24'!B41 -> Manufacturing Loss/Wastage | C40: ='F24'!C41 -> 6431, 6432
A41: =A40+1 -> 37 | B41: ='F24'!B42 -> Rejects/Reworks/Scrap | C41: ='F24'!C42 -> 6433 to 6435
A42: =A41+1 -> 38 | B42: ='F24'!B43 -> Disposal of Sludge/Others | C42: ='F24'!C43 -> 6436 to 6499
A43: =A42+1 -> 39 | B43: ='F24'!B44 -> QA Allocated Cost
A44: =A43+1 -> 40 | B44: ='F24'!B45 -> PM Allocated Cost
A45: =A44+1 -> 41 | B45: ='F24'!B46 -> Other Variable Overhead | C45: =SUM(C37:C44)
A46: =A45+1 -> 42 | B46: ='F24'!B47 -> Total Variable Overhead | C46: =C23+C36+c45
A47: =A46+1 -> 43 | B47: ='F24'!B48 -> Factory Rental/Upkeep | C47: ='F24'!C48 -> 6501 to 6502, 6506
A48: =A47+1 -> 44 | B48: ='F24'!B49 -> Property Tax for Factory | C48: ='F24'!C49 -> 6503
A49: =A48+1 -> 45 | B49: ='F24'!B50 -> Repair & Maintainance/Upkeep | C49: ='F24'!C50 -> 6601 to 6620
A50: =A49+1 -> 46 | B50: ='F24'!B51 -> Leasing of Mac&Equip/Vehicles/Cyl | C50: ='F24'!C51 -> 6621 to 6623
A51: =A50+1 -> 47 | B51: ='F24'!B52 -> Depreciation | C51: ='F24'!C52 -> 6701 to 6749
A52: =A51+1 -> 48 | B52: ='F24'!B53 -> Licenses & Insurance | C52: ='F24'!C53 -> 6504, 6751 to 6759
A53: =A52+1 -> 49 | B53: ='F24'!B54 -> Non Capitalised Purchases | C53: ='F24'!C54 -> 6761 to 6769
A54: =A53+1 -> 50 | B54: ='F24'!B55 -> Others Fixed Overhead | C54: ='F24'!C55 -> 6505, 6771 to 6799
A55: =A54+1 -> 51 | B55: ='F24'!B56 -> QA Allocated Cost
A56: =A55+1 -> 52 | B56: ='F24'!B57 -> PM Allocated Cost
A57: =A56+1 -> 53 | B57: ='F24'!B58 -> Fixed Overhead | C57: =SUM(C47:C56)
A58: =A57+1 -> 54 | B58: ='F24'!B59 -> Cost of Goods Manufactured | C58: =C22+C46+C57

Sheet F25-Dep
A1: LEEDEN NATIONAL OXYGEN LTD | D1: ='F24'!D1:G1 -> AS OF: 11-Oct-2017 | I1: FOR THE MONTH OF: Sep -17
A2: DIVISION: GAS | D2: DEPT: | I2: SECTION:
A3: ='F25-Div'!A3:B3 -> F25 MANUFACTURING ACCOUNT | D3: CURRENCY: SGD 000s | I3: FX: 0.00
A4: ='F25-Div'!A4:B4 -> BY DIV/DEPT/SEC/UNITS | D4: DEPT 1 | E4: DEPT 2 | F4: DEPT 3 | G4: DEPT 4 | H4: DEPT 5 | I4: DEPT 6 | J4: DEPT 7 | K4: DEPT 8 | L4: TOTAL
A5: 1 | B5: ='F25-Div'!B5 -> Manufacturing Costs
A6: =A5+1 -> 2 | B6: ='F25-Div'!B6 -> DM–Raw Materials | C6: ='F25-Div'!C6 -> 6101
A7: =A6+1 -> 3 | B7: ='F25-Div'!B7 -> DM–Parts & Access | C7: ='F25-Div'!C7 -> 6102
A8: =A7+1 -> 4 | B8: ='F25-Div'!B8 -> DM–Packing & Label Materials | C8: ='F25-Div'!C8 -> 6103 to 6104
A9: =A8+1 -> 5 | B9: ='F25-Div'!B9 -> DM–Others | C9: ='F25-Div'!C9 -> 6105 to 6199
A10: =A9+1 -> 6 | B10: ='F25-Div'!B10 -> Direct Material | C10: ='F25-Div'!C10 -> =SUM(C6:C9)
A11: =A10+1 -> 7 | B11: ='F25-Div'!B11 -> Salary & Leave | C11: ='F25-Div'!C11 -> 6201 to 6202
A12: =A11+1 -> 8 | B12: ='F25-Div'!B12 -> Bonus | C12: ='F25-Div'!C12 -> 6203 to 6204
A13: =A12+1 -> 9 | B13: ='F25-Div'!B13 -> Foreign Workers/Casual/Temp | C13: ='F25-Div'!C13 -> 6206, 6208
A14: =A13+1 -> 10 | B14: ='F25-Div'!B14 -> Overtime | C14: ='F25-Div'!C14 -> 6209 to 6210
A15: =A14+1 -> 11 | B15: ='F25-Div'!B15 -> Shift Allowance & Incentive | C15: ='F25-Div'!C15 -> 6205, 6211 to 6212
A16: =A15+1 -> 12 | B16: ='F25-Div'!B16 -> Staff Transport/Vehicle Rental | C16: ='F25-Div'!C16 -> 6213
A17: =A16+1 -> 13 | B17: ='F25-Div'!B17 -> Social Security Contribution | C17: ='F25-Div'!C17 -> 6214
... A33: =A32+1 -> 29 | B33: ='F25-Div'!B33 -> Other Indirect Labor Costs | C33: ='F25-Div'!C33 -> 6315, 6323 to 6349
A34: =A33+1 -> 30 | B34: ='F25-Div'!B34 -> QA Allocated Cost
A35: =A34+1 -> 31 | B35: ='F25-Div'!B35 -> PM Allocated Cost
A36: =A35+1 -> 32 | B36: ='F25-Div'!B36 -> Indirect Labor | C36: ='F25-Div'!C36 -> =SUM(C24:C35)
A37: =A36+1 -> 33 | B37: ='F25-Div'!B37 -> Utilities - Elec, Water, Gas | C37: ='F25-Div'!C37 -> 6401 to 6410
A38: =A37+1 -> 34 | B38: ='F25-Div'!B38 -> Product Development/Testing | C38: ='F25-Div'!C38 -> 6421 to 6430
A39: =A38+1 -> 35 | B39: ='F25-Div'!B39 -> Carriage/Transport/Storage | C39: ='F25-Div'!C39 -> 6411 to 6420
A40: =A39+1 -> 36 | B40: ='F25-Div'!B40 -> Manufacturing Loss/Wastage | C40: ='F25-Div'!C40 -> 6431, 6432
A41: =A40+1 -> 37 | B41: ='F25-Div'!B41 -> Rejects/Reworks/Scrap | C41: ='F25-Div'!C41 -> 6433 to 6435
A42: =A41+1 -> 38 | B42: ='F25-Div'!B42 -> Disposal of Sludge/Others | C42: ='F25-Div'!C42 -> 6436 to 6499
A43: =A42+1 -> 39 | B43: ='F25-Div'!B43 -> QA Allocated Cost
A44: =A43+1 -> 40 | B44: ='F25-Div'!B44 -> PM Allocated Cost
A45: =A44+1 -> 41 | B45: ='F25-Div'!B45 -> Other Variable Overhead | C45: =SUM(C37:C44)
A46: =A45+1 -> 42 | B46: ='F25-Div'!B46 -> Total Variable Overhead | C46: ='F25-Div'!C46 -> =C23+C36+c45
A47: =A46+1 -> 43 | B47: ='F25-Div'!B47 -> Factory Rental/Upkeep | C47: ='F25-Div'!C47 -> 6501 to 6502, 6506
A48: =A47+1 -> 44 | B48: ='F25-Div'!B48 -> Property Tax for Factory | C48: ='F25-Div'!C48 -> 6503
A49: =A48+1 -> 45 | B49: ='F25-Div'!B49 -> Repair & Maintainance/Upkeep | C49: ='F25-Div'!C49 -> 6601 to 6620
A50: =A49+1 -> 46 | B50: ='F25-Div'!B50 -> Leasing of Mac&Equip/Vehicles/Cyl | C50: ='F25-Div'!C50 -> 6621 to 6623
A51: =A50+1 -> 47 | B51: ='F25-Div'!B51 -> Depreciation | C51: ='F25-Div'!C51 -> 6701 to 6749
A52: =A51+1 -> 48 | B52: ='F25-Div'!B52 -> Licenses & Insurance | C52: ='F25-Div'!C52 -> 6504, 6751 to 6759
A53: =A52+1 -> 49 | B53: ='F25-Div'!B53 -> Non Capitalised Purchases | C53: ='F25-Div'!C53 -> 6761 to 6769
A54: =A53+1 -> 50 | B54: ='F25-Div'!B54 -> Others Fixed Overhead | C54: ='F25-Div'!C54 -> 6505, 6771 to 6799
A55: =A54+1 -> 51 | B55: ='F25-Div'!B55 -> QA Allocated Cost
A56: =A55+1 -> 52 | B56: ='F25-Div'!B56 -> PM Allocated Cost
A57: =A56+1 -> 53 | B57: ='F25-Div'!B57 -> Fixed Overhead | C57: ='F25-Div'!C57 -> =SUM(C47:C56)
A58: =A57+1 -> 54 | B58: ='F25-Div'!B58 -> Cost of Goods Manufactured | C58: ='F25-Div'!C58 -> =C22+C46+C57

Sheet F25-Sec
A1: LEEDEN NATIONAL OXYGEN LTD | D1: ='F25-Div'!D1:H1 -> AS OF: 11-Oct-2017 | I1: ='F25-Div'!I1:L1 -> FOR THE MONTH OF: Sep -17
A2: ='F25-Dep'!A2 -> DIVISION: GAS | D2: DEPT: | E2: PACKAGED GAS PRODUCTION | I2: SECTION:
A3: ='F25-Dep'!A3:B3 -> F25 MANUFACTURING ACCOUNT | D3: CURRENCY: SGD 000s | I3: FX: 0.00
A4: ='F25-Div'!A4:B4 -> BY DIV/DEPT/SEC/UNITS | D4: SECT 1 | E4: SECT 2 | F4: SECT 3 | G4: SECT 4 | H4: SECT 5 | I4: SECT 6 | J4: SECT 7 | K4: SECT 8 | L4: TOTAL
A5: 1 | B5: ='F25-Dep'!B5 -> Manufacturing Costs
A6: =A5+1 -> 2 | B6: ='F25-Dep'!B6 -> DM–Raw Materials | C6: ='F25-Dep'!C6 -> 6101
A7: =A6+1 -> 3 | B7: ='F25-Dep'!B7 -> DM–Parts & Access | C7: ='F25-Dep'!C7 -> 6102
A8: =A7+1 -> 4 | B8: ='F25-Dep'!B8 -> DM–Packing & Label Materials | C8: ='F25-Dep'!C8 -> 6103 to 6104
A9: =A8+1 -> 5 | B9: ='F25-Dep'!B9 -> DM–Others | C9: ='F25-Dep'!C9 -> 6105 to 6199
A10: =A9+1 -> 6 | B10: ='F25-Dep'!B10 -> Direct Material | C10: ='F25-Dep'!C10 -> =SUM(C6:C9)
A11: =A10+1 -> 7 | B11: ='F25-Dep'!B11 -> Salary & Leave | C11: ='F25-Dep'!C11 -> 6201 to 6202
A12: =A11+1 -> 8 | B12: ='F25-Dep'!B12 -> Bonus | C12: ='F25-Dep'!C12 -> 6203 to 6204
A13: =A12+1 -> 9 | B13: ='F25-Dep'!B13 -> Foreign Workers/Casual/Temp | C13: ='F25-Dep'!C13 -> 6206, 6208
A14: =A13+1 -> 10 | B14: ='F25-Dep'!B14 -> Overtime | C14: ='F25-Dep'!C14 -> 6209 to 6210
A15: =A14+1 -> 11 | B15: ='F25-Dep'!B15 -> Shift Allowance & Incentive | C15: ='F25-Dep'!C15 -> 6205, 6211 to 6212
A16: =A15+1 -> 12 | B16: ='F25-Dep'!B16 -> Staff Transport/Vehicle Rental | C16: ='F25-Dep'!C16 -> 6213
A17: =A16+1 -> 13 | B17: ='F25-Dep'!B17 -> Social Security Contribution | C17: ='F25-Dep'!C17 -> 6214
... A33: =A32+1 -> 29 | B33: ='F25-Dep'!B33 -> Other Indirect Labor Costs | C33: ='F25-Dep'!C33 -> 6315, 6323 to 6349
A34: =A33+1 -> 30 | B34: ='F25-Dep'!B34 -> QA Allocated Cost
A35: =A34+1 -> 31 | B35: ='F25-Dep'!B35 -> PM Allocated Cost
A36: =A35+1 -> 32 | B36: ='F25-Dep'!B36 -> Indirect Labor | C36: ='F25-Dep'!C36 -> =SUM(C24:C35)
A37: =A36+1 -> 33 | B37: ='F25-Dep'!B37 -> Utilities - Elec, Water, Gas | C37: ='F25-Dep'!C37 -> 6401 to 6410
A38: =A37+1 -> 34 | B38: ='F25-Dep'!B38 -> Product Development/Testing | C38: ='F25-Dep'!C38 -> 6421 to 6430
A39: =A38+1 -> 35 | B39: ='F25-Dep'!B39 -> Carriage/Transport/Storage | C39: ='F25-Dep'!C39 -> 6411 to 6420
A40: =A39+1 -> 36 | B40: ='F25-Dep'!B40 -> Manufacturing Loss/Wastage | C40: ='F25-Dep'!C40 -> 6431, 6432
A41: =A40+1 -> 37 | B41: ='F25-Dep'!B41 -> Rejects/Reworks/Scrap | C41: ='F25-Dep'!C41 -> 6433 to 6435
A42: =A41+1 -> 38 | B42: ='F25-Dep'!B42 -> Disposal of Sludge/Others | C42: ='F25-Dep'!C42 -> 6436 to 6499
A43: =A42+1 -> 39 | B43: ='F25-Dep'!B43 -> QA Allocated Cost
A44: =A43+1 -> 40 | B44: ='F25-Dep'!B44 -> PM Allocated Cost
A45: =A44+1 -> 41 | B45: ='F25-Dep'!B45 -> Other Variable Overhead | C45: =SUM(C37:C44)
A46: =A45+1 -> 42 | B46: ='F25-Dep'!B46 -> Total Variable Overhead | C46: ='F25-Dep'!C46 -> =C23+C36+c45
A47: =A46+1 -> 43 | B47: ='F25-Dep'!B47 -> Factory Rental/Upkeep | C47: ='F25-Dep'!C47 -> 6501 to 6502, 6506
A48: =A47+1 -> 44 | B48: ='F25-Dep'!B48 -> Property Tax for Factory | C48: ='F25-Dep'!C48 -> 6503
A49: =A48+1 -> 45 | B49: ='F25-Dep'!B49 -> Repair & Maintainance/Upkeep | C49: ='F25-Dep'!C49 -> 6601 to 6620
A50: =A49+1 -> 46 | B50: ='F25-Dep'!B50 -> Leasing of Mac&Equip/Vehicles/Cyl | C50: ='F25-Dep'!C50 -> 6621 to 6623
A51: =A50+1 -> 47 | B51: ='F25-Dep'!B51 -> Depreciation | C51: ='F25-Dep'!C51 -> 6701 to 6749
A52: =A51+1 -> 48 | B52: ='F25-Dep'!B52 -> Licenses & Insurance | C52: ='F25-Dep'!C52 -> 6504, 6751 to 6759
A53: =A52+1 -> 49 | B53: ='F25-Dep'!B53 -> Non Capitalised Purchases | C53: ='F25-Dep'!C53 -> 6761 to 6769
A54: =A53+1 -> 50 | B54: ='F25-Dep'!B54 -> Others Fixed Overhead | C54: ='F25-Dep'!C54 -> 6505, 6771 to 6799
A55: =A54+1 -> 51 | B55: ='F25-Dep'!B55 -> QA Allocated Cost
A56: =A55+1 -> 52 | B56: ='F25-Dep'!B56 -> PM Allocated Cost
A57: =A56+1 -> 53 | B57: ='F25-Dep'!B57 -> Fixed Overhead | C57: ='F25-Dep'!C57 -> =SUM(C47:C56)
A58: =A57+1 -> 54 | B58: ='F25-Dep'!B58 -> Cost of Goods Manufactured | C58: ='F25-Dep'!C58 -> =C22+C46+C57

Sheet F25-Units
A1: LEEDEN NATIONAL OXYGEN LTD | D1: ='F25-Div'!D1:H1 -> AS OF: 11-Oct-2017 | I1: ='F25-Div'!I1:L1 -> FOR THE MONTH OF: Sep -17
A2: ='F25-Sec'!A2 -> DIVISION: GAS | D2: DEPT: | E2: PACKAGED GAS PRODUCTION | I2: SECTION: REFILLING
A3: ='F25-Sec'!A3:B3 -> F25 MANUFACTURING ACCOUNT | D3: CURRENCY: SGD 000s | I3: FX: 0.00
A4: ='F25-Div'!A4:B4 -> BY DIV/DEPT/SEC/UNITS | D4: UNIT 1 | E4: UNIT 2 | F4: UNIT 3 | G4: UNIT 4 | H4: UNIT 5 | I4: UNIT 6 | J4: UNIT 7 | K4: UNIT 8 | L4: TOTAL
A5: 1 | B5: ='F25-Sec'!B5 -> Manufacturing Costs
A6: =A5+1 -> 2 | B6: ='F25-Sec'!B6 -> DM–Raw Materials | C6: ='F25-Sec'!C6 -> 6101
A7: =A6+1 -> 3 | B7: ='F25-Sec'!B7 -> DM–Parts & Access | C7: ='F25-Sec'!C7 -> 6102
A8: =A7+1 -> 4 | B8: ='F25-Sec'!B8 -> DM–Packing & Label Materials | C8: ='F25-Sec'!C8 -> 6103 to 6104
A9: =A8+1 -> 5 | B9: ='F25-Sec'!B9 -> DM–Others | C9: ='F25-Sec'!C9 -> 6105 to 6199
A10: =A9+1 -> 6 | B10: ='F25-Sec'!B10 -> Direct Material | C10: ='F25-Sec'!C10 -> =SUM(C6:C9)
A11: =A10+1 -> 7 | B11: ='F25-Sec'!B11 -> Salary & Leave | C11: ='F25-Sec'!C11 -> 6201 to 6202
A12: =A11+1 -> 8 | B12: ='F25-Sec'!B12 -> Bonus | C12: ='F25-Sec'!C12 -> 6203 to 6204
A13: =A12+1 -> 9 | B13: ='F25-Sec'!B13 -> Foreign Workers/Casual/Temp | C13: ='F25-Sec'!C13 -> 6206, 6208
A14: =A13+1 -> 10 | B14: ='F25-Sec'!B14 -> Overtime | C14: ='F25-Sec'!C14 -> 6209 to 6210
A15: =A14+1 -> 11 | B15: ='F25-Sec'!B15 -> Shift Allowance & Incentive | C15: ='F25-Sec'!C15 -> 6205, 6211 to 6212
A16: =A15+1 -> 12 | B16: ='F25-Sec'!B16 -> Staff Transport/Vehicle Rental | C16: ='F25-Sec'!C16 -> 6213
A17: =A16+1 -> 13 | B17: ='F25-Sec'!B17 -> Social Security Contribution | C17: ='F25-Sec'!C17 -> 6214
... A33: =A32+1 -> 29 | B33: ='F25-Sec'!B33 -> Other Indirect Labor Costs | C33: ='F25-Sec'!C33 -> 6315, 6323 to 6349
A34: =A33+1 -> 30 | B34: ='F25-Sec'!B34 -> QA Allocated Cost
A35: =A34+1 -> 31 | B35: ='F25-Sec'!B35 -> PM Allocated Cost
A36: =A35+1 -> 32 | B36: ='F25-Sec'!B36 -> Indirect Labor | C36: ='F25-Sec'!C36 -> =SUM(C24:C35)
A37: =A36+1 -> 33 | B37: ='F25-Sec'!B37 -> Utilities - Elec, Water, Gas | C37: ='F25-Sec'!C37 -> 6401 to 6410
A38: =A37+1 -> 34 | B38: ='F25-Sec'!B38 -> Product Development/Testing | C38: ='F25-Sec'!C38 -> 6421 to 6430
A39: =A38+1 -> 35 | B39: ='F25-Sec'!B39 -> Carriage/Transport/Storage | C39: ='F25-Sec'!C39 -> 6411 to 6420
A40: =A39+1 -> 36 | B40: ='F25-Sec'!B40 -> Manufacturing Loss/Wastage | C40: ='F25-Sec'!C40 -> 6431, 6432
A41: =A40+1 -> 37 | B41: ='F25-Sec'!B41 -> Rejects/Reworks/Scrap | C41: ='F25-Sec'!C41 -> 6433 to 6435
A42: =A41+1 -> 38 | B42: ='F25-Sec'!B42 -> Disposal of Sludge/Others | C42: ='F25-Sec'!C42 -> 6436 to 6499
A43: =A42+1 -> 39 | B43: ='F25-Sec'!B43 -> QA Allocated Cost
A44: =A43+1 -> 40 | B44: ='F25-Sec'!B44 -> PM Allocated Cost
A45: =A44+1 -> 41 | B45: ='F25-Sec'!B45 -> Other Variable Overhead | C45: =SUM(C37:C44)
A46: =A45+1 -> 42 | B46: ='F25-Sec'!B46 -> Total Variable Overhead | C46: ='F25-Sec'!C46 -> =C23+C36+c45
A47: =A46+1 -> 43 | B47: ='F25-Sec'!B47 -> Factory Rental/Upkeep | C47: ='F25-Sec'!C47 -> 6501 to 6502, 6506
A48: =A47+1 -> 44 | B48: ='F25-Sec'!B48 -> Property Tax for Factory | C48: ='F25-Sec'!C48 -> 6503
A49: =A48+1 -> 45 | B49: ='F25-Sec'!B49 -> Repair & Maintainance/Upkeep | C49: ='F25-Sec'!C49 -> 6601 to 6620
A50: =A49+1 -> 46 | B50: ='F25-Sec'!B50 -> Leasing of Mac&Equip/Vehicles/Cyl | C50: ='F25-Sec'!C50 -> 6621 to 6623
A51: =A50+1 -> 47 | B51: ='F25-Sec'!B51 -> Depreciation | C51: ='F25-Sec'!C51 -> 6701 to 6749
A52: =A51+1 -> 48 | B52: ='F25-Sec'!B52 -> Licenses & Insurance | C52: ='F25-Sec'!C52 -> 6504, 6751 to 6759
A53: =A52+1 -> 49 | B53: ='F25-Sec'!B53 -> Non Capitalised Purchases | C53: ='F25-Sec'!C53 -> 6761 to 6769
A54: =A53+1 -> 50 | B54: ='F25-Sec'!B54 -> Others Fixed Overhead | C54: ='F25-Sec'!C54 -> 6505, 6771 to 6799
A55: =A54+1 -> 51 | B55: ='F25-Sec'!B55 -> QA Allocated Cost
A56: =A55+1 -> 52 | B56: ='F25-Sec'!B56 -> PM Allocated Cost
A57: =A56+1 -> 53 | B57: ='F25-Sec'!B57 -> Fixed Overhead | C57: ='F25-Sec'!C57 -> =SUM(C47:C56)
A58: =A57+1 -> 54 | B58: ='F25-Sec'!B58 -> Cost of Goods Manufactured | C58: ='F25-Sec'!C58 -> =C22+C46+C57

Sheet F26M
A1: LEEDEN NATIONAL OXYGEN LTD | D1: ='F25-Div'!D1:H1 -> AS OF: 11-Oct-2017 | I1: ='F25-Div'!I1:L1 -> FOR THE MONTH OF: Sep -17
A2: DEPT: IGP | D2: SECTION: ASPs | I2: UNIT: ASP2
A3: F26M ASU MANUFACTURING ACCOUNT | D3: CURRENCY: SGD 000s | I3: FX: 0.00
A4: BY PRODUCTS BY MONTH | D4: GO | E4: LO | F4: GN | G4: LN | H4: LAR | L4: TOTAL
A5: 1 | B5: Budget Production (M3 / KG)
A6: =A5+1 -> 2 | B6: Actual Production (M3 / KG)
A7: =A6+1 -> 3 | B7: Variance (M3 / KG)
A9: 4 | B9: Allocation Factors
A11: ACTUAL | B11: Budget
D12: GO | E12: LO | F12: GN | G12: LN | H12: LAR | L12: TOTAL
A13: 1 | B13: Direct Expenses -Electricity
A14: =A13+1 -> 2 | B14: Direct Labor
A15: =A14+1 -> 3 | B15: Prime Cost
A16: =A15+1 -> 4 | B16: Indirect Labor
A17: =A16+1 -> 5 | B17: Other Variable Overhead
A18: =A17+1 -> 6 | B18: Total Variable Overhead
A19: =A18+1 -> 7 | B19: Fixed Overhead
A20: =A19+1 -> 8 | B20: Cost of Goods Manufactured
B21: Cost Indicators :
A22: 1 | B22: Direct Exps (m3 / Kg) | C22: Direct Expenses/Actual Production Volume
A23: =A22+1 -> 2 | B23: Direct Labour (m3 / Kg) | C23: Direct Labour/Actual Production Volume
A24: =A23+1 -> 3 | B24: Indirect Labour (m3 / Kg) | C24: Indirect Labour/Actual Production Volume
A25: =A24+1 -> 4 | B25: Variable Overhead (m3 / Kg) | C25: Variable Overhead/Actual Production Volume
A26: =A25+1 -> 5 | B26: Total Variable (m3 / Kg) | C26: Total Variable/Actual Production Volume
A27: =A26+1 -> 6 | B27: Fixed Overhead (m3 / Kg) | C27: Fixed Overhead/Actual Production Volume
A28: =A27+1 -> 7 | B28: Manufacturing Costs (m3/ Kg) | C28: Manufacturing Costs/Actual Production Volume
A30: BUDGET | B30: Budget
D31: GO | E31: LO | F31: GN | G31: LN | H31: LAR | L31: TOTAL
A32: 1 | B32: Direct Expenses -Electricity
A33: =A32+1 -> 2 | B33: Direct Labor
A34: =A33+1 -> 3 | B34: Prime Cost
A35: =A34+1 -> 4 | B35: Indirect Labor
A36: =A35+1 -> 5 | B36: Other Variable Overhead
A37: =A36+1 -> 6 | B37: Total Variable Overhead
A38: =A37+1 -> 7 | B38: Fixed Overhead
A39: =A38+1 -> 8 | B39: Cost of Goods Manufactured
B40: Cost Indicators :
A41: 1 | B41: Direct Exps (m3 / Kg) | C41: =C22 -> Direct Expenses/Actual Production Volume
A42: =A41+1 -> 2 | B42: Direct Labour (m3 / Kg) | C42: =C23 -> Direct Labour/Actual Production Volume
A43: =A42+1 -> 3 | B43: Indirect Labour (m3 / Kg) | C43: =C24 -> Indirect Labour/Actual Production Volume
A44: =A43+1 -> 4 | B44: Variable Overhead (m3 / Kg) | C44: =C25 -> Variable Overhead/Actual Production Volume
A45: =A44+1 -> 5 | B45: Total Variable (m3 / Kg) | C45: =C26 -> Total Variable/Actual Production Volume
A46: =A45+1 -> 6 | B46: Fixed Overhead (m3 / Kg) | C46: =C27 -> Fixed Overhead/Actual Production Volume
A47: =A46+1 -> 7 | B47: Manufacturing Costs (m3/ Kg) | C47: =C28 -> Manufacturing Costs/Actual Production Volume
A49: VARIANCES | B49: Variances
D50: GO | E50: LO | F50: GN | G50: LN | H50: LAR | L50: TOTAL
A51: 1 | B51: Direct Expenses -Electricity
A52: =A51+1 -> 2 | B52: Direct Labor
A53: =A52+1 -> 3 | B53: Prime Cost
A54: =A53+1 -> 4 | B54: Indirect Labor
A55: =A54+1 -> 5 | B55: Other Variable Overhead
A56: =A55+1 -> 6 | B56: Total Variable Overhead
A57: =A56+1 -> 7 | B57: Fixed Overhead
A58: =A57+1 -> 8 | B58: Cost of Goods Manufactured
B59: Cost Indicators :
A60: 1 | B60: Direct Exps (m3 / Kg) | C60: =C41 -> Direct Expenses/Actual Production Volume
A61: =A60+1 -> 2 | B61: Direct Labour (m3 / Kg) | C61: =C42 -> Direct Labour/Actual Production Volume
A62: =A61+1 -> 3 | B62: Indirect Labour (m3 / Kg) | C62: =C43 -> Indirect Labour/Actual Production Volume
A63: =A62+1 -> 4 | B63: Variable Overhead (m3 / Kg) | C63: =C44 -> Variable Overhead/Actual Production Volume
A64: =A63+1 -> 5 | B64: Total Variable (m3 / Kg) | C64: =C45 -> Total Variable/Actual Production Volume
A65: =A64+1 -> 6 | B65: Fixed Overhead (m3 / Kg) | C65: =C46 -> Fixed Overhead/Actual Production Volume
A66: =A65+1 -> 7 | B66: Manufacturing Costs (m3/ Kg) | C66: =C47 -> Manufacturing Costs/Actual Production Volume

Sheet F26Y
A1: LEEDEN NATIONAL OXYGEN LTD | D1: ='F25-Div'!D1:H1 -> AS OF: 11-Oct-2017 | I1: ='F25-Div'!I1:L1 -> FOR THE MONTH OF: Sep -17
A2: DEPT: IGP | D2: SECTION: ASPs | I2: UNIT: ASP2
A3: F26Y ASU MANUFACTURING ACCOUNT | D3: CURRENCY: SGD 000s | I3: FX: 0.00
A4: BY PRODUCTS YEAR TO DATE | D4: GO | E4: LO | F4: GN | G4: LN | H4: LAR | L4: TOTAL
A5: 1 | B5: Budget Production (M3 / KG)
A6: =A5+1 -> 2 | B6: Actual Production (M3 / KG)
A7: =A6+1 -> 3 | B7: Variance (M3 / KG)
A9: 4 | B9: Allocation Factors
A11: ACTUAL | B11: Budget
D12: GO | E12: LO | F12: GN | G12: LN | H12: LAR | L12: TOTAL
A13: 1 | B13: Direct Expenses -Electricity
A14: =A13+1 -> 2 | B14: Direct Labor
A15: =A14+1 -> 3 | B15: Prime Cost
A16: =A15+1 -> 4 | B16: Indirect Labor
A17: =A16+1 -> 5 | B17: Other Variable Overhead
A18: =A17+1 -> 6 | B18: Total Variable Overhead
A19: =A18+1 -> 7 | B19: Fixed Overhead
A20: =A19+1 -> 8 | B20: Cost of Goods Manufactured
B21: Cost Indicators :
A22: 1 | B22: Direct Exps (m3 / Kg) | C22: =F26M!C22 -> Direct Expenses/Actual Production Volume
A23: =A22+1 -> 2 | B23: Direct Labour (m3 / Kg) | C23: =F26M!C23 -> Direct Labour/Actual Production Volume
A24: =A23+1 -> 3 | B24: Indirect Labour (m3 / Kg) | C24: =F26M!C24 -> Indirect Labour/Actual Production Volume
A25: =A24+1 -> 4 | B25: Variable Overhead (m3 / Kg) | C25: =F26M!C25 -> Variable Overhead/Actual Production Volume
A26: =A25+1 -> 5 | B26: Total Variable (m3 / Kg) | C26: =F26M!C26 -> Total Variable/Actual Production Volume
A27: =A26+1 -> 6 | B27: Fixed Overhead (m3 / Kg) | C27: =F26M!C27 -> Fixed Overhead/Actual Production Volume
A28: =A27+1 -> 7 | B28: Manufacturing Costs (m3/ Kg) | C28: =F26M!C28 -> Manufacturing Costs/Actual Production Volume
A30: BUDGET | B30: Budget
D31: GO | E31: LO | F31: GN | G31: LN | H31: LAR | L31: TOTAL
A32: 1 | B32: Direct Expenses -Electricity
A33: =A32+1 -> 2 | B33: Direct Labor
A34: =A33+1 -> 3 | B34: Prime Cost
A35: =A34+1 -> 4 | B35: Indirect Labor
A36: =A35+1 -> 5 | B36: Other Variable Overhead
A37: =A36+1 -> 6 | B37: Total Variable Overhead
A38: =A37+1 -> 7 | B38: Fixed Overhead
A39: =A38+1 -> 8 | B39: Cost of Goods Manufactured
B40: Cost Indicators :
A41: 1 | B41: Direct Exps (m3 / Kg) | C41: =F26M!C41 -> Direct Expenses/Actual Production Volume
A42: =A41+1 -> 2 | B42: Direct Labour (m3 / Kg) | C42: =F26M!C42 -> Direct Labour/Actual Production Volume
A43: =A42+1 -> 3 | B43: Indirect Labour (m3 / Kg) | C43: =F26M!C43 -> Indirect Labour/Actual Production Volume
A44: =A43+1 -> 4 | B44: Variable Overhead (m3 / Kg) | C44: =F26M!C44 -> Variable Overhead/Actual Production Volume
A45: =A44+1 -> 5 | B45: Total Variable (m3 / Kg) | C45: =F26M!C45 -> Total Variable/Actual Production Volume
A46: =A45+1 -> 6 | B46: Fixed Overhead (m3 / Kg) | C46: =F26M!C46 -> Fixed Overhead/Actual Production Volume
A47: =A46+1 -> 7 | B47: Manufacturing Costs (m3/ Kg) | C47: =F26M!C47 -> Manufacturing Costs/Actual Production Volume
A49: VARIANCES | B49: Variances
D50: GO | E50: LO | F50: GN | G50: LN | H50: LAR | L50: TOTAL
A51: 1 | B51: Direct Expenses -Electricity
A52: =A51+1 -> 2 | B52: Direct Labor
A53: =A52+1 -> 3 | B53: Prime Cost
A54: =A53+1 -> 4 | B54: Indirect Labor
A55: =A54+1 -> 5 | B55: Other Variable Overhead
A56: =A55+1 -> 6 | B56: Total Variable Overhead
A57: =A56+1 -> 7 | B57: Fixed Overhead
A58: =A57+1 -> 8 | B58: Cost of Goods Manufactured
B59: Cost Indicators :
A60: 1 | B60: Direct Exps (m3 / Kg) | C60: =F26M!C60 -> Direct Expenses/Actual Production Volume
A61: =A60+1 -> 2 | B61: Direct Labour (m3 / Kg) | C61: =F26M!C61 -> Direct Labour/Actual Production Volume
A62: =A61+1 -> 3 | B62: Indirect Labour (m3 / Kg) | C62: =F26M!C62 -> Indirect Labour/Actual Production Volume
A63: =A62+1 -> 4 | B63: Variable Overhead (m3 / Kg) | C63: =F26M!C63 -> Variable Overhead/Actual Production Volume
A64: =A63+1 -> 5 | B64: Total Variable (m3 / Kg) | C64: =F26M!C64 -> Total Variable/Actual Production Volume
A65: =A64+1 -> 6 | B65: Fixed Overhead (m3 / Kg) | C65: =F26M!C65 -> Fixed Overhead/Actual Production Volume
A66: =A65+1 -> 7 | B66: Manufacturing Costs (m3/ Kg) | C66: =F26M!C66 -> Manufacturing Costs/Actual Production Volume

Sheet F30
A1: LEEDEN NATIONAL OXYGEN LTD | D1: ='F24'!D1:G1 -> AS OF: 11-Oct-2017 | H1: MONTH: | I1: =H4 -> 42979
A2: F30 BALANCE SHEET | D2: CURRENCY: 000s | H2: FX RATE: | I2: 1
D3: Audited | E3: Audited | F3: S$ | G3: S$ | H3: S$ | I3: S$
D4: 42430 | E4: 42795 | F4: 42917 | G4: 42948 | H4: 42979 | I4: =H4 -> 42979
A5: 1 | B5: Cash and Bank Balances | C5: 1000 to 1099Debit, 3000 to 3099Debit
A6: =A5+1 -> 2 | B6: Fixed Deposits | C6: 1100 to 1199
A7: =A6+1 -> 3 | B7: Stocks | C7: 1200 to 1299
A8: =A7+1 -> 4 | B8: Trade Debtors | C8: 1300 to 1399, 1499
A9: =A8+1 -> 5 | B9: Due From Assoc/JV/Related | C9: 1411 to 1433
A10: =A9+1 -> 6 | B10: Due From Interco | C10: 1401 to 1404
A11: =A10+1 -> 7 | B11: Short-Term Investment | C11: 1501 to 1699 Except 1502
A12: =A11+1 -> 8 | B12: Other Debtors/Deposits/Prepayment | C12: 1700, 1800 to 1999
A13: =A12+1 -> 9 | B13: TOTAL CURRENT ASSETS | C13: =SUM(C5:C12)
A14: =A13+1 -> 10 | B14: Freehold Land | C14: 2001 (Exclude A-Z)
A15: =A14+1 -> 11 | B15: Leasehold Properties | C15: 2002 to 2019 (Exclude A-Z)
A16: =A15+1 -> 12 | B16: Construction in Progress | C16: 2021 (Exclude A-Z)
A17: =A16+1 -> 13 | B17: Renovations | C17: 2022 (Exclude A-Z)
... A64: =A63+1 -> 60 | B64: TOTAL LIAB & EQUITY | C64: =C56+C63
B65: Performance Indicators | D65: =D4 -> 42430 | E65: =E4 -> 42795 | F65: =F4 -> 42917 | G65: =G4 -> 42948 | H65: =H4 -> 42979 | I65: =I4 -> 42979
A66: 1 | B66: Debtors Turnover (Days) | C66: (Trade debtors + provision for debts)/ (External sales + External sales other) x No. of days to date
A67: =A66+1 -> 2 | B67: Stocks Turnover (Days) | C67: (Stock + Provision for stock obsolescence)/ -(Total Cost of sales) x No. of days to date
A68: =A67+1 -> 3 | B68: Creditors Turnover (Days) | C68: Account Payable/Cost of Goods Sold x No. of days to date
A69: =A68+1 -> 4 | B69: Liabilities to Equity (Leverage) | C69: Total Liabilities / Total Equity
A70: =A69+1 -> 5 | B70: Debt to Equity | C70: Total Borrowings / Total Equity. Total Borrowings refers to summation of OD or factoring or revolving credit, Trust receipts or ST loans, current portion of Term Loans, Current HP creditors, Long Term Loans and HP Creditors.
A71: =A70+1 -> 6 | B71: Provision for Doubtful Debts | C71: 1301Z
A72: =A71+1 -> 7 | B72: Provision for Stock Obso/Pilferage | C72: 1201Z, 1221Z, 1241Z, 1242Z, 1241L
A73: =A72+1 -> 8 | B73: Provision for Plant Maintenance | C73: 3993

Sheet F30R
A1: LEEDEN NATIONAL OXYGEN LTD | D1: ='F24'!D1:G1 -> AS OF: 11-Oct-2017 | H1: MONTH: | I1: =H4 -> 42979
A2: F30R BALANCE SHEET (RAW) | D2: CURRENCY: | H2: FX RATE: | I2: 1
D3: Audited | E3: Audited | F3: S$ | G3: S$ | H3: S$ | I3: S$
D4: 42430 | E4: 42795 | F4: 42917 | G4: 42948 | H4: 42979 | I4: =H4 -> 42979
A5: 1 | B5: Cash and Bank Balances | C5: ='F30'!C5 -> 1000 to 1099Debit, 3000 to 3099Debit
A6: =A5+1 -> 2 | B6: Fixed Deposits | C6: ='F30'!C6 -> 1100 to 1199
A7: =A6+1 -> 3 | B7: Stocks | C7: ='F30'!C7 -> 1200 to 1299
A8: =A7+1 -> 4 | B8: Trade Debtors | C8: ='F30'!C8 -> 1300 to 1399, 1499
A9: =A8+1 -> 5 | B9: Due From Assoc/JV/Related | C9: ='F30'!C9 -> 1411 to 1433
A10: =A9+1 -> 6 | B10: Due From Interco | C10: ='F30'!C10 -> 1401 to 1404
A11: =A10+1 -> 7 | B11: Short-Term Investment | C11: ='F30'!C11 -> 1501 to 1699 Except 1502
A12: =A11+1 -> 8 | B12: Other Debtors/Deposits/Prepayment | C12: ='F30'!C12 -> 1700, 1800 to 1999
A13: =A12+1 -> 9 | B13: TOTAL CURRENT ASSETS | C13: ='F30'!C13 -> =SUM(C5:C12)
A14: =A13+1 -> 10 | B14: Freehold Land | C14: ='F30'!C14 -> 2001 (Exclude A-Z)
A15: =A14+1 -> 11 | B15: Leasehold Properties | C15: ='F30'!C15 -> 2002 to 2019 (Exclude A-Z)
A16: =A15+1 -> 12 | B16: Construction in Progress | C16: ='F30'!C16 -> 2021 (Exclude A-Z)
A17: =A16+1 -> 13 | B17: Renovations | C17: ='F30'!C17 -> 2022 (Exclude A-Z)
... A64: =A63+1 -> 60 | B64: TOTAL LIAB & EQUITY | C64: ='F30'!C64 -> =C56+C63
B65: Performance Indicators | D65: =D4 -> 42430 | E65: =E4 -> 42795 | F65: =F4 -> 42917 | G65: =G4 -> 42948 | H65: =H4 -> 42979 | I65: =I4 -> 42979
A66: 1 | B66: Debtors Turnover (Days) | C66: ='F30'!C66 -> (Trade debtors + provision for debts)/ (External sales + External sales other) x No. of days to date
A67: =A66+1 -> 2 | B67: Stocks Turnover (Days) | C67: ='F30'!C67 -> (Stock + Provision for stock obsolescence)/ -(Total Cost of sales) x No. of days to date
A68: =A67+1 -> 3 | B68: Creditors Turnover (Days) | C68: ='F30'!C68 -> Account Payable/Cost of Goods Sold x No. of days to date
A69: =A68+1 -> 4 | B69: Liabilities to Equity (Leverage) | C69: ='F30'!C69 -> Total Liabilities / Total Equity
A70: =A69+1 -> 5 | B70: Debt to Equity | C70: ='F30'!C70 -> Total Borrowings / Total Equity. Total Borrowings refers to summation of OD or factoring or revolving credit, Trust receipts or ST loans, current portion of Term Loans, Current HP creditors, Long Term Loans and HP Creditors.
A71: =A70+1 -> 6 | B71: Provision for Doubtful Debts | C71: ='F30'!C71 -> 1301Z
A72: =A71+1 -> 7 | B72: Provision for Stock Obso/Pilferage | C72: ='F30'!C72 -> 1201Z, 1221Z, 1241Z, 1242Z, 1241L
A73: =A72+1 -> 8 | B73: Provision for Plant Maintenance | C73: ='F30'!C73 -> 3993

Sheet F31
A1: LEEDEN NATIONAL OXYGEN LTD | D1: ='F22'!D1:N1 -> AS OF: 11-Oct-2017 | N1: ='F22'!O1 -> FOR THE YEAR OF: 2018
A2: F31 DETAILED P&L ACCOUNT | D2: CURRENCY: S$
D3: 42826 | E3: 42856 | F3: 42887 | G3: 42917 | H3: 42948 | I3: 42979 | J3: 43009 | K3: 43040 | L3: 43070 | M3: 43101 | N3: 43132 | O3: 43160 | P3: Total | Q3: FY 2017 | R3: Variance %
A4: 1 | B4: External Sales–Goods | C4: 5001
A5: =A4+1 -> 2 | B5: External Sales–Project Sales | C5: 5002
A6: =A5+1 -> 3 | B6: External Sales–Cylinder Rental | C6: 5003
A7: =A6+1 -> 4 | B7: External Sales–Equip Rental | C7: 5004
A8: =A7+1 -> 5 | B8: External Sales–Repair & Service | C8: 5005
A9: =A8+1 -> 6 | B9: External Sales–Delivery Charges | C9: 5006
A10: =A9+1 -> 7 | B10: External Sales–Other Charges | C10: 5007
A11: =A10+1 -> 8 | B11: External Sales–Mgmt Fee | C11: 5021
A12: =A11+1 -> 9 | B12: Enternal Sales–Property Rental | C12: 5022
A13: =A12+1 -> 10 | B13: External Sales | C13: =SUM(C4:C12)
A14: =A13+1 -> 11 | B14: Interco Sales–Goods | C14: 5031
A15: =A14+1 -> 12 | B15: Interco Sales–Cylinder Rental | C15: 5032
A16: =A15+1 -> 13 | B16: Interco Sales–Equip Rental | C16: 5033
... A71: =A70+1 -> 68 | B71: Gross Profit | C71: =C34+C70
A72: =A71+1 -> 69 | B72: Add Other Operating Income
A73: =A72+1 -> 70 | B73: Commission Income | C73: 5501
A74: =A73+1 -> 71 | B74: Property Rental Income | C74: 5502
A75: =A74+1 -> 72 | B75: Admin/Management Income | C75: 5503
A76: =A75+1 -> 73 | B76: Gain/(Loss) Disposal of FA | C76: 9101
A77: =A76+1 -> 74 | B77: Income on Disposal of Scrap | C77: 5511
A78: =A77+1 -> 75 | B78: Insurance Claim | C78: 5512, 9011
A79: =A78+1 -> 76 | B79: Logistic Service Income | C79: 5513
A80: =A79+1 -> 77 | B80: Other Misc Income | C80: 5519
A81: =A80+1 -> 78 | B81: Government Grant | C81: 9001
A82: =A81+1 -> 79 | B82: Share of Assoc/JV’s P&L | C82: 9041Credit
A83: =A82+1 -> 80 | B83: Gain on Disposal of Investment | C83: 9102Credit
A84: =A83+1 -> 81 | B84: Gain on Asset Held for Sales | C84: 9103Credit
A85: =A84+1 -> 82 | B85: Other Operating Income | C85: =SUM(C73:C84)
A86: =A85+1 -> 83 | B86: Less Other Operating Expenses
A87: =A86+1 -> 84 | B87: Other Misc Expenses | C87: 5629
A88: =A87+1 -> 85 | B88: Other Non-Operating Exps | C88: 9199
A89: =A88+1 -> 86 | B89: Share of Assoc/JV’s P&L | C89: 9041Debit
A90: =A89+1 -> 87 | B90: Loss on Disposal of Investment | C90: 9102Debit
A91: =A90+1 -> 88 | B91: Loss on Asset Held for Sales | C91: 9103Debit
A92: =A91+1 -> 89 | B92: Impairm Loss on Subsidiaries | C92: 9111
A93: =A92+1 -> 90 | B93: Impairm Loss on Assoc/JV/Rel Co | C93: 9112
A94: =A93+1 -> 91 | B94: Impairm Loss–Property | C94: 9113
A95: =A94+1 -> 92 | B95: Impairm Loss–Plant & Equip | C95: 9114
A96: =A95+1 -> 93 | B96: Impairm Loss–Investment | C96: 9115
A97: =A96+1 -> 94 | B97: Impairm Loss–Others | C97: 9117
A98: =A97+1 -> 95 | B98: Real Property Gain Tax | C98: 9121
A99: =A98+1 -> 96 | B99: Foreign Withholding Tax | C99: 9122
A100: =A99+1 -> 97 | B100: Amortisation–Product License | C100: 9131
A101: =A100+1 -> 98 | B101: Amortisation–Club Membership | C101: 9132
A102: =A101+1 -> 99 | B102: Amortisation–Trademark & Patent | C102: 9133
A103: =A102+1 -> 100 | B103: Other Operating Expenses | C103: =SUM(C87:C102)
A104: =A103+1 -> 101 | B104: Total Other Op Income/(Exp) | C104: =C85+C103
A105: =A104+1 -> 102 | B105: Salary & Leave | C105: 7001
A106: =A105+1 -> 103 | B106: Provision for Bonus | C106: 7002
A107: =A106+1 -> 104 | B107: Comms & Incentives | C107: 7003
A108: =A107+1 -> 105 | B108: Foreign Workers | C108: 7004
A109: =A108+1 -> 106 | B109: Casual/Temp Staff | C109: 7005
A110: =A109+1 -> 107 | B110: Overtime | C110: 7006
A111: =A110+1 -> 108 | B111: Staff Allow & Incentive | C111: 7007
A112: =A111+1 -> 109 | B112: Shift Allowance | C112: 7008
A113: =A112+1 -> 110 | B113: Staff Transport | C113: 7009
A114: =A113+1 -> 111 | B114: Staff Vehicle Expenses | C114: 7010
... A159: =A158+1 -> 156 | B159: Insurance of Vehicles | C159: 7410
A160: =A159+1 -> 157 | B160: Upkeep-Machinery | C160: 7411
A161: =A160+1 -> 158 | B161: Upkeep-Equipment | C161: 7412
A162: =A161+1 -> 159 | B162: Upkeep-Furniture & Fitting | C162: 7413
A163: =A162+1 -> 160 | B163: Upkeep-Office Equip | C163: 7414
A164: =A163+1 -> 161 | B164: Upkeep-Computers | C164: 7415
A165: =A164+1 -> 162 | B165: S&D Equipment Expenses | C165: =SUM(C150:C164)
A166: =A165+1 -> 163 | B166: Rental | C166: 7501
A167: =A166+1 -> 164 | B167: Upkeep of Premises | C167: 7502
A168: =A167+1 -> 165 | B168: Waste Disposal | C168: 7503
A169: =A168+1 -> 166 | B169: Electricity Charges | C169: 7504
A170: =A169+1 -> 167 | B170: Water Charges | C170: 7505
A171: =A170+1 -> 168 | B171: Gas Charges | C171: 7506
A172: =A171+1 -> 169 | B172: Property Tax | C172: 7507
A173: =A172+1 -> 170 | B173: Licenses Fees | C173: 7508
A174: =A173+1 -> 171 | B174: Insurance–General | C174: 7509
A175: =A174+1 -> 172 | B175: S&D Rental/Property Related | C175: =SUM(C166:C174)
A176: =A175+1 -> 173 | B176: Dep–Leasehold Land | C176: 7601
... A253: =A252+1 -> 250 | B253: R&M–Motor Vehicles | C253: 8207
A254: =A253+1 -> 251 | B254: Upkeep-Equipment | C254: 8208
A255: =A254+1 -> 252 | B255: Upkeep-Office Equip | C255: 8209
A256: =A255+1 -> 253 | B256: A&G Equipment Expenses | C256: =SUM(C247:C255)
A257: =A256+1 -> 254 | B257: Rental of Premises | C257: 8301
A258: =A257+1 -> 255 | B258: Upkeep of Premises | C258: 8302
A259: =A258+1 -> 256 | B259: Waste Disposal | C259: 8303
A260: =A259+1 -> 257 | B260: Electricity Charges | C260: 8304
A261: =A260+1 -> 258 | B261: Water Charges | C261: 8305
A262: =A261+1 -> 259 | B262: Gas Charges | C262: 8306
A263: =A262+1 -> 260 | B263: Property Tax | C263: 8307
A264: =A263+1 -> 261 | B264: Assessment Fee | C264: 8308
A265: =A264+1 -> 262 | B265: Stamp Duty | C265: 8309
A266: =A265+1 -> 263 | B266: Licenses Fees | C266: 8310
A267: =A266+1 -> 264 | B267: A&G Rental/Property Related | C267: =SUM(C257:C266)
... A334: =A333+1 -> 331 | B334: Net Profit Before Taxation | C334: =C311+C333
A335: =A334+1 -> 332 | B335: Less: Taxation
A336: =A335+1 -> 333 | B336: Taxation–Current Year | C336: 9401
A337: =A336+1 -> 334 | B337: Taxation–Prior Year | C337: 9402
A338: =A337+1 -> 335 | B338: Deferred Tax–Current Year | C338: 9403
A339: =A338+1 -> 336 | B339: Deferred Tax–Prior Year | C339: 9404
A340: =A339+1 -> 337 | B340: Taxation | C340: =SUM(C336:C339)
...

Sheet F32
A1: LEEDEN NATIONAL OXYGEN LTD | D1: ='F31'!D1:M1 -> AS OF: 11-Oct-2017 | M1: FOR THE YEAR OF: 2018
A2: DIVISION: | D2: DEPT: | I2: SECTION: | N2: Poducts:
A3: F32 DETAILED MANUFACTURING A/C | I3: CURRENCY: SGD 000s | O3: FX: 0.00
D4: 42826 | E4: 42856 | F4: 42887 | G4: 42917 | H4: 42948 | I4: 42979 | J4: 43009 | K4: 43040 | L4: 43070 | M4: 43101 | N4: 43132 | O4: 43160 | P4: Total
B5: Direct Material
A6: 1 | B6: DM–Raw Materials | C6: 6101
A7: =A6+1 -> 2 | B7: DM–Parts & Access | C7: 6102
A8: =A7+1 -> 3 | B8: DM–Packaging Materials | C8: 6103
A9: =A8+1 -> 4 | B9: DM–Labelling Materials | C9: 6104
A10: =A9+1 -> 5 | B10: DM–Refill Materials | C10: 6105
A11: =A10+1 -> 6 | B11: DM–Others | C11: 6106 to 6198
A12: =A11+1 -> 7 | B12: DM–Control A/C | C12: 6199
A13: =A12+1 -> 8 | B13: Total Direct Material | C13: =SUM(C6:C12) | D13: =SUM(D6:D12) -> 0 | E13: =SUM(E6:E12) -> 0 | F13: =SUM(F6:F12) -> 0 | G13: =SUM(G6:G12) -> 0 | H13: =SUM(H6:H12) -> 0 | I13: =SUM(I6:I12) -> 0 | J13: =SUM(J6:J12) -> 0 | K13: =SUM(K6:K12) -> 0 | ... P13: =SUM(P6:P12) -> 0
B14: Direct Labour
A15: =A13+1 -> 9 | B15: DL–Salary & Leave | C15: 6201
A16: =A15+1 -> 10 | B16: DL-Salary Foreign Workers | C16: 6202
A17: =A16+1 -> 11 | B17: DL–Bonus | C17: 6203
A18: =A17+1 -> 12 | B18: DL–Bonus Foreign Workers | C18: 6204
A19: =A18+1 -> 13 | B19: DL–Coms & Incentive | C19: 6205
A20: =A19+1 -> 14 | B20: DL–Foreign Workers | C20: 6206
A21: =A20+1 -> 15 | B21: DL–Contractors | C21: 6207
A22: =A21+1 -> 16 | B22: DL–Casual/Temp Staff | C22: 6208
A23: =A22+1 -> 17 | B23: DL–Overtime | C23: 6209
A24: =A23+1 -> 18 | B24: DL–OT Foreign Workers | C24: 6210
A25: =A24+1 -> 19 | B25: DL–Shift Allow & Incentive | C25: 6211
A26: =A25+1 -> 20 | B26: DL–Worker Allowance | C26: 6212
A27: =A26+1 -> 21 | B27: DL–Worker Transport | C27: 6213
... A38: =A37+1 -> 32 | B38: DL–Control A/C | C38: 6229
A39: =A38+1 -> 33 | B39: Total Direct Labour | C39: =SUM(C15:C38) | D39: =SUM(D15:D38) -> 0 | E39: =SUM(E15:E38) -> 0 | F39: =SUM(F15:F38) -> 0 | G39: =SUM(G15:G38) -> 0 | H39: =SUM(H15:H38) -> 0 | I39: =SUM(I15:I38) -> 0 | J39: =SUM(J15:J38) -> 0 | K39: =SUM(K15:K38) -> 0 | ... P39: =SUM(P15:P38) -> 0
A40: =A39+1 -> 34 | B40: Direct Exps-Electricity | C40: 6251
A41: =A40+1 -> 35 | B41: Direct Exps–LPG | C41: 6252
A42: =A41+1 -> 36 | B42: Direct Exps–Welding Gases | C42: 6253
A43: =A42+1 -> 37 | B43: Direct Exps–Others | C43: 6254
A44: =A43+1 -> 38 | B44: Prime Cost | C44: =C13+C39+C40:C43 | D44: =SUM(D13,D39,D40:D42) -> 0 | E44: =SUM(E13,E39,E40:E42) -> 0 | F44: =SUM(F13,F39,F40:F42) -> 0 | G44: =SUM(G13,G39,G40:G42) -> 0 | H44: =SUM(H13,H39,H40:H42) -> 0 | I44: =SUM(I13,I39,I40:I42) -> 0 | J44: =SUM(J13,J39,J40:J42) -> 0 | K44: =SUM(K13,K39,K40:K42) -> 0 | ... P44: =SUM(P13,P39,P40:P42) -> 0
A45: =A44+1 -> 39 | B45: Indirect Material | C45: 6301 to 6310
B46: Indirect labour
A47: =A45+1 -> 40 | B47: IL–Salary & Leave | C47: 6311
A48: =A47+1 -> 41 | B48: IL–Bonus | C48: 6312
A49: =A48+1 -> 42 | B49: IL–Coms & Incentive | C49: 6313
A50: =A49+1 -> 43 | B50: IL–Foreign Workers | C50: 6314
A51: =A50+1 -> 44 | B51: IL–Contractors | C51: 6315
A52: =A51+1 -> 45 | B52: IL–Casual/ Temp Staff | C52: 6316
A53: =A52+1 -> 46 | B53: IL–Overtime | C53: 6317
A54: =A53+1 -> 47 | B54: IL–Shift Allow & Incentive | C54: 6318
A55: =A54+1 -> 48 | B55: IL–Worker Allowance | C55: 6319
A56: =A55+1 -> 49 | B56: IL–Staff Transport | C56: 6320
A57: =A56+1 -> 50 | B57: IL–Social Securities | C57: 6321
A58: =A57+1 -> 51 | B58: IL–Worker’s Levy | C58: 6322
A59: =A58+1 -> 52 | B59: IL–Staff Recruitment | C59: 6323
... A72: =A71+1 -> 65 | B72: Expats’ Other Expenses | C72: 6356
A73: =A72+1 -> 66 | B73: QA Allocated Cost
A74: =A73+1 -> 67 | B74: PM Allocated Cost
A75: =A74+1 -> 68 | B75: Total Indirect Labour | C75: =SUM(C47:C74) | D75: =SUM(D47:D72) -> 0 | E75: =SUM(E47:E72) -> 0 | F75: =SUM(F47:F72) -> 0 | G75: =SUM(G47:G72) -> 0 | H75: =SUM(H47:H72) -> 0 | I75: =SUM(I47:I72) -> 0 | J75: =SUM(J47:J72) -> 0 | K75: =SUM(K47:K72) -> 0 | ... P75: =SUM(P47:P72) -> 0
A76: =A75+1 -> 69 | B76: Electricity Charges | C76: 6401
A77: =A76+1 -> 70 | B77: Water Charges | C77: 6402
A78: =A77+1 -> 71 | B78: Gas Charges | C78: 6403
A79: =A78+1 -> 72 | B79: Carriage Inwards | C79: 6411
A80: =A79+1 -> 73 | B80: Import/Custom Duties | C80: 6412
A81: =A80+1 -> 74 | B81: Handling Charges | C81: 6413
A82: =A81+1 -> 75 | B82: Storage Charges | C82: 6414
A83: =A82+1 -> 76 | B83: Overseas Traveling | C83: 6415
A84: =A83+1 -> 77 | B84: Research & Development | C84: 6421
A85: =A84+1 -> 78 | B85: Product Certification | C85: 6422
A86: =A85+1 -> 79 | B86: Product Testing | C86: 6423
A87: =A86+1 -> 80 | B87: QC Testing | C87: 6424
... A93: =A92+1 -> 86 | B93: Disposal of Sludge | C93: 6436
A94: =A93+1 -> 87 | B94: QA Allocated Cost
A95: =A94+1 -> 88 | B95: PM Allocated Cost
A96: =A95+1 -> 89 | B96: Other Variable Overhead | C96: =SUM(C76:C95)
A97: =A96+1 -> 90 | B97: Total Variable Overhead | C97: =C45+C75+C96 | D97: =SUM(D75:D93) -> 0 | E97: =SUM(E75:E93) -> 0 | F97: =SUM(F75:F93) -> 0 | G97: =SUM(G75:G93) -> 0 | H97: =SUM(H75:H93) -> 0 | I97: =SUM(I75:I93) -> 0 | J97: =SUM(J75:J93) -> 0 | K97: =SUM(K75:K93) -> 0 | ... P97: =SUM(P75:P93) -> 0
A98: =A97+1 -> 91 | B98: Factory Rental | C98: 6501
A99: =A98+1 -> 92 | B99: Upkeep of Factory | C99: 6502
A100: =A99+1 -> 93 | B100: Property Tax | C100: 6503
A101: =A100+1 -> 94 | B101: Licenses | C101: 6504
A102: =A101+1 -> 95 | B102: Waste Disposal | C102: 6505
A103: =A102+1 -> 96 | B103: R&M–Factory | C103: 6506
A104: =A103+1 -> 97 | B104: R&M–Plant | C104: 6601
A105: =A104+1 -> 98 | B105: R&M–Machinery | C105: 6602
A106: =A105+1 -> 99 | B106: R&M–Equipment | C106: 6603
A107: =A106+1 -> 100 | B107: R&M– Pipelines | C107: 6604
A108: =A107+1 -> 101 | B108: R&M–Storage Tanks | C108: 6605
A109: =A108+1 -> 102 | B109: R&M–ISO Tanks | C109: 6606
... A116: =A115+1 -> 109 | B116: R&M–Vehicles | C116: 6613
A117: =A116+1 -> 110 | B117: Upkeep-Plant | C117: 6614
A118: =A117+1 -> 111 | B118: Upkeep-Machinery | C118: 6615
A119: =A118+1 -> 112 | B119: Upkeep-Equipment | C119: 6616
A120: =A119+1 -> 113 | B120: Upkeep-Racks & Cylinders | C120: 6617
A121: =A120+1 -> 114 | B121: Upkeep-Furniture & Fitting | C121: 6618
A122: =A121+1 -> 115 | B122: Upkeep-Office Equip | C122: 6619
A123: =A122+1 -> 116 | B123: Upkeep-Computers | C123: 6620
A124: =A123+1 -> 117 | B124: Leasing of Machinery & Equip | C124: 6621
A125: =A124+1 -> 118 | B125: Leasing of Vehicles | C125: 6622
A126: =A125+1 -> 119 | B126: Rental of Cylinders | C126: 6623
A127: =A126+1 -> 120 | B127: Dep–Leasehold Land | C127: 6701
A128: =A127+1 -> 121 | B128: Dep–Land Rights Use | C128: 6702
A129: =A128+1 -> 122 | B129: Dep–Buildings | C129: 6703
A130: =A129+1 -> 123 | B130: Dep–Renovations | C130: 6704
A131: =A130+1 -> 124 | B131: Dep–Plant | C131: 6705
A132: =A131+1 -> 125 | B132: Dep–Machinery | C132: 6706
A133: =A132+1 -> 126 | B133: Dep–Equipment | C133: 6707
...

Sheet F33
A1: LEEDEN NATIONAL OXYGEN LTD | D1: ='F32'!D1:I1 -> AS OF: 11-Oct-2017 | N1: FOR THE YEAR OF: 2018
A2: F33 DETAILED BALANCE SHEET | D2: CURRENCY: S$
D3: 42826 | E3: 42856 | F3: 42887 | G3: 42917 | H3: 42948 | I3: 42979 | J3: 43009 | K3: 43040 | L3: 43070 | M3: 43101 | N3: 43132 | O3: 43160 | P3: FY 2017
A4: 1 | B4: Cash and Bank Balances | C4: 1000 to 1099Debit, 3000 to 3099Debit
A5: =A4+1 -> 2 | B5: Fixed Deposit | C5: 1100 to 1199
A6: =A5+1 -> 3 | B6: Raw Materials | C6: 1201
A7: =A6+1 -> 4 | B7: Prov for Raw Materials | C7: 1201Z
A8: =A7+1 -> 5 | B8: Semi-Finished Goods | C8: 1211
A9: =A8+1 -> 6 | B9: Work in Progress | C9: 1212
A10: =A9+1 -> 7 | B10: Packing & Labelling Materials | C10: 1221
A11: =A10+1 -> 8 | B11: Prov for Packing & Label Material | C11: 1221Z
A12: =A11+1 -> 9 | B12: Consumables | C12: 1222
A13: =A12+1 -> 10 | B13: Stocks In Transit | C13: 1231
A14: =A13+1 -> 11 | B14: Finished Goods | C14: 1241
A15: =A14+1 -> 12 | B15: Prov for Finished Goods | C15: 1241Z
A16: =A15+1 -> 13 | B16: Trading Stocks | C16: 1242
... A253: =A252+1 -> 250 | B253: TOTAL LIAB & EQUITY | C253: =C233+C252

Sheet Formula
A1: Profit & Loss Account
A2: 1 | B2: Gross Profits Margin % | C2: Gross Profits / Total Sales
A3: 2 | B3: External Sales GP % | C3: (External Sales - Cost of External Sales) / External Sales
A4: 3 | B4: Interco Sales GP % | C4: (Interco Sales - Cost of Interco Sales) / Interco Sales
A5: 4 | B5: S&D Margin % | C5: Total S&D Expenses / Total Sales
A6: 5 | B6: A&G Margin Direct % | C6: Total Direct A&G Expenses / Total Sales
A7: 6 | B7: A&G Margin Total % | C7: Total A&G Expenses / Total Sales
A8: 7 | B8: Operating Profit Margin % | C8: Profits from Operations / Total Sales
A9: 8 | B9: Profit After Taxation % | C9: Profits after Taxation / Total Sales
A11: Manufacturing Account
A12: 1 | B12: Direct Material (m3 / Kg) | C12: Direct Material / Actual Production Volume
A13: 2 | B13: Direct Labour (m3 / Kg) | C13: Direct Labour / Actual Production Volume
A14: 3 | B14: Direct Exps (m3 / Kg) | C14: Direct Expenses / Actual Production Volume
A15: 4 | B15: Indirect Material (m3 / Kg) | C15: Indirect Material / Actual Production Volume
A16: 5 | B16: Indirect Labour (m3 / Kg) | C16: Indirect Labour / Actual Production Volume
A17: 6 | B17: Variable Overhead (m3 / Kg) | C17: Variable Overhead / Actual Production Volume
A18: 7 | B18: Total Variable (m3 / Kg) | C18: Total Variable / Actual Production Volume
A19: 8 | B19: Fixed Overhead (m3 / Kg) | C19: Fixed Overhead / Actual Production Volume
A20: 9 | B20: Manufacturing Costs (m3/ Kg) | C20: Manufacturing Costs / Actual Production Volume
A22: Balance Sheet
A23: 1 | B23: Debtors Turnover (Days) | C23: (Trade debtors + provision for debts)/ (External sales + External sales other) x No. of days to date
A24: 2 | B24: Stocks Turnover (Days) | C24: (Stock + Provision for stock obsolescence)/ -(Total Cost of sales) x No. of days to date
A25: 3 | B25: Creditors Turnover (Days) | C25: Account Payable/Cost of Goods Sold x No. of days to date
A26: 4 | B26: Liabilities to Equity (Leverage) | C26: Total Liabilities / Total Equity
A27: 5 | B27: Debt to Equity | C27: Total Borrowings / Total Equity. Total Borrowings refers to summation of OD or factoring or revolving credit, Trust receipts or ST loans, current portion of Term Loans, Current HP creditors, Long Term Loans and HP Creditors.
A28: 6 | B28: Provision for Doubtful Debts | C28: 1301Z
A29: 7 | B29: Provision for Stock Obso/Pilferage | C29: 1201Z, 1221Z, 1241Z, 1242Z, 1241L
A30: 8 | B30: Provision for Plant Maintenance | C30: 2101Z

Sheet Sheet1
J2: Monthly Sales | AF2: Monthly Operating Income
B10: Sep'17 | F10: Oct'17 | J10: Nov'17 | N10: Dec'17 | R10: Jan'18 | V10: Feb'18 | Z10: Sep'17 | AD10: Oct'17 | AH10: Nov'17 | AL10: Dec'17 | AP10: Jan'18 | AT10: Feb'18
C12: Current Month | K12: Budget | Q12: Last Year | AA12: Current Month | AI12: Budget | AO12: Last Year
I15: Year-To-Date Sales | AD15: Year-To-Date Operating Income
B23: Sep'17 | F23: Oct'17 | J23: Nov'17 | N23: Dec'17 | R23: Jan'18 | V23: Feb'18 | Z23: Sep'17 | AD23: Oct'17 | AH23: Nov'17 | AL23: Dec'17 | AP23: Jan'18 | AT23: Feb'18
C25: Current Month | K25: Budget | Q25: Last Year | AA25: Current Month | AI25: Budget | AO25: Last Year
