Workbook

Sheet Reference
A1: New
A2: Rename
A3: Remove
A4: New
A5: Combine

Sheet F101 F21 PNL-Debug
A1: DELETE FROM tbFinanceItemSeq where Report = 'PNL'
A3: select s.* , i.ItemName from tbFinanceItemSeq s
A4: LEFT JOIN tbFinanceItem i on s.ItemID = i.ItemID
A5: where s.Report = 'PNL'
A6: order by s.ItemSeqID
A8: Select * from tbFinanceItem where ItemName like '%(PNL)%'
A11: SELECT TOP 10 * FROM tbReport where ReportID = 426;
A12: -- F101 Profit & Loss Account.rpt
A15: Update tbReport
A16: set FileName = 'F101 Profit & Loss Account.rpt' ,
A17: Description = '[COA2016] F21 Profit & Loss Account'
A18: where ReportID = 426;
... A23: where ReportID = 427;

Sheet F101 F21 PNL-Origin
A1: INSERT INTO tbFinanceItemSeq(Report,ItemSeqID,ItemSN,ItemID) VALUES('PNL',1,1,1081)
A2: INSERT INTO tbFinanceItemSeq(Report,ItemSeqID,ItemSN,ItemID) VALUES('PNL',2,2,1082)
A3: INSERT INTO tbFinanceItemSeq(Report,ItemSeqID,ItemSN,ItemID) VALUES('PNL',3,3,1083)
A4: INSERT INTO tbFinanceItemSeq(Report,ItemSeqID,ItemSN,ItemID) VALUES('PNL',4,4,1084)
A5: INSERT INTO tbFinanceItemSeq(Report,ItemSeqID,ItemSN,ItemID) VALUES('PNL',5,5,1085)
A6: INSERT INTO tbFinanceItemSeq(Report,ItemSeqID,ItemSN,ItemID) VALUES('PNL',6,6,1086)
A7: INSERT INTO tbFinanceItemSeq(Report,ItemSeqID,ItemSN,ItemID) VALUES('PNL',7,7,1087)
A8: INSERT INTO tbFinanceItemSeq(Report,ItemSeqID,ItemSN,ItemID) VALUES('PNL',8,8,1088)
A9: INSERT INTO tbFinanceItemSeq(Report,ItemSeqID,ItemSN,ItemID) VALUES('PNL',9,9,1089)
A10: INSERT INTO tbFinanceItemSeq(Report,ItemSeqID,ItemSN,ItemID) VALUES('PNL',10,10,1090)
A11: INSERT INTO tbFinanceItemSeq(Report,ItemSeqID,ItemSN,ItemID) VALUES('PNL',11,11,1091)
A12: INSERT INTO tbFinanceItemSeq(Report,ItemSeqID,ItemSN,ItemID) VALUES('PNL',12,12,1092)
... A65: INSERT INTO tbFinanceItemSeq(Report,ItemSeqID,ItemSN,ItemID) VALUES('PNL',65,9,1140)

Sheet F101 F21 PNL-New
A1: Status | B1: Report | C1: New - ItemSeqID | D1: ItemSeqID | E1: New - ItemSN | F1: ItemSN | G1: ItemID | H1: ItemName | I1: Insert Script
A2: Exist | B2: PNL | C2: =D2 -> 1 | D2: 1 | E2: =F2 -> 1 | F2: 1 | G2: 1081 | H2: (PNL)External Sales | I2: =IF(A2<>"Remove",CONCATENATE("INSERT INTO tbFinanceItemSeq(Report,ItemSeqID,ItemSN,ItemID) VALUES('",B2,"',",C2,",",E2,",",G2,")"),"") -> INSERT INTO tbFinanceItemSeq(Report,ItemSeqID,ItemSN,ItemID) VALUES('PNL',1,1,1081)
A3: Exist | B3: PNL | C3: =D3 -> 2 | D3: 2 | E3: =F3 -> 2 | F3: 2 | G3: 1082 | H3: (PNL)Interco Sales | I3: =IF(A3<>"Remove",CONCATENATE("INSERT INTO tbFinanceItemSeq(Report,ItemSeqID,ItemSN,ItemID) VALUES('",B3,"',",C3,",",E3,",",G3,")"),"") -> INSERT INTO tbFinanceItemSeq(Report,ItemSeqID,ItemSN,ItemID) VALUES('PNL',2,2,1082)
A4: Exist | B4: PNL | C4: =D4 -> 3 | D4: 3 | E4: =F4 -> 3 | F4: 3 | G4: 1083 | H4: (PNL)Total Sales | I4: =IF(A4<>"Remove",CONCATENATE("INSERT INTO tbFinanceItemSeq(Report,ItemSeqID,ItemSN,ItemID) VALUES('",B4,"',",C4,",",E4,",",G4,")"),"") -> INSERT INTO tbFinanceItemSeq(Report,ItemSeqID,ItemSN,ItemID) VALUES('PNL',3,3,1083)
A5: Exist | B5: PNL | C5: =D5 -> 4 | D5: 4 | E5: =F5 -> 4 | F5: 4 | G5: 1084 | H5: (PNL)Cost of External Sales | I5: =IF(A5<>"Remove",CONCATENATE("INSERT INTO tbFinanceItemSeq(Report,ItemSeqID,ItemSN,ItemID) VALUES('",B5,"',",C5,",",E5,",",G5,")"),"") -> INSERT INTO tbFinanceItemSeq(Report,ItemSeqID,ItemSN,ItemID) VALUES('PNL',4,4,1084)
A6: Exist | B6: PNL | C6: =D6 -> 5 | D6: 5 | E6: =F6 -> 5 | F6: 5 | G6: 1085 | H6: (PNL)Cost of Interco Sales | I6: =IF(A6<>"Remove",CONCATENATE("INSERT INTO tbFinanceItemSeq(Report,ItemSeqID,ItemSN,ItemID) VALUES('",B6,"',",C6,",",E6,",",G6,")"),"") -> INSERT INTO tbFinanceItemSeq(Report,ItemSeqID,ItemSN,ItemID) VALUES('PNL',5,5,1085)
A7: Exist | B7: PNL | C7: =D7 -> 6 | D7: 6 | E7: =F7 -> 6 | F7: 6 | G7: 1086 | H7: (PNL)Total Cost of Sales | I7: =IF(A7<>"Remove",CONCATENATE("INSERT INTO tbFinanceItemSeq(Report,ItemSeqID,ItemSN,ItemID) VALUES('",B7,"',",C7,",",E7,",",G7,")"),"") -> INSERT INTO tbFinanceItemSeq(Report,ItemSeqID,ItemSN,ItemID) VALUES('PNL',6,6,1086)
A8: Exist | B8: PNL | C8: =D8 -> 7 | D8: 7 | E8: =F8 -> 7 | F8: 7 | G8: 1087 | H8: (PNL)Gross Profit | I8: =IF(A8<>"Remove",CONCATENATE("INSERT INTO tbFinanceItemSeq(Report,ItemSeqID,ItemSN,ItemID) VALUES('",B8,"',",C8,",",E8,",",G8,")"),"") -> INSERT INTO tbFinanceItemSeq(Report,ItemSeqID,ItemSN,ItemID) VALUES('PNL',7,7,1087)
A9: Exist | B9: PNL | C9: =D9 -> 8 | D9: 8 | E9: =F9 -> 8 | F9: 8 | G9: 1088 | H9: (PNL)Commission Income/Mgt Income | I9: =IF(A9<>"Remove",CONCATENATE("INSERT INTO tbFinanceItemSeq(Report,ItemSeqID,ItemSN,ItemID) VALUES('",B9,"',",C9,",",E9,",",G9,")"),"") -> INSERT INTO tbFinanceItemSeq(Report,ItemSeqID,ItemSN,ItemID) VALUES('PNL',8,8,1088)
A10: New | B10: PNL | C10: 9 | E10: 9 | G10: 1126 | H10: (PNL)Gain/(Loss) Disposal of FA | I10: =IF(A10<>"Remove",CONCATENATE("INSERT INTO tbFinanceItemSeq(Report,ItemSeqID,ItemSN,ItemID) VALUES('",B10,"',",C10,",",E10,",",G10,")"),"") -> INSERT INTO tbFinanceItemSeq(Report,ItemSeqID,ItemSN,ItemID) VALUES('PNL',9,9,1126)
A11: Exist | B11: PNL | C11: =SUM(D11,1) -> 10 | D11: 9 | E11: =SUM(F11,1) -> 10 | F11: 9 | G11: 1089 | H11: (PNL)Other Op Income | I11: =IF(A11<>"Remove",CONCATENATE("INSERT INTO tbFinanceItemSeq(Report,ItemSeqID,ItemSN,ItemID) VALUES('",B11,"',",C11,",",E11,",",G11,")"),"") -> INSERT INTO tbFinanceItemSeq(Report,ItemSeqID,ItemSN,ItemID) VALUES('PNL',10,10,1089)
A12: Exist | B12: PNL | C12: =SUM(D12,1) -> 11 | D12: 10 | E12: =SUM(F12,1) -> 11 | F12: 10 | G12: 1090 | H12: (PNL)Other Op Expense | I12: =IF(A12<>"Remove",CONCATENATE("INSERT INTO tbFinanceItemSeq(Report,ItemSeqID,ItemSN,ItemID) VALUES('",B12,"',",C12,",",E12,",",G12,")"),"") -> INSERT INTO tbFinanceItemSeq(Report,ItemSeqID,ItemSN,ItemID) VALUES('PNL',11,11,1090)
A13: Exist | B13: PNL | C13: =SUM(D13,1) -> 12 | D13: 11 | E13: =SUM(F13,1) -> 12 | F13: 11 | G13: 1091 | H13: (PNL)Total Other Op Income/ (Exp) | I13: =IF(A13<>"Remove",CONCATENATE("INSERT INTO tbFinanceItemSeq(Report,ItemSeqID,ItemSN,ItemID) VALUES('",B13,"',",C13,",",E13,",",G13,")"),"") -> INSERT INTO tbFinanceItemSeq(Report,ItemSeqID,ItemSN,ItemID) VALUES('PNL',12,12,1091)
A14: Exist | B14: PNL | C14: =SUM(D14,1) -> 13 | D14: 12 | E14: =SUM(F14,1) -> 13 | F14: 12 | G14: 1092 | H14: (PNL)S&D Personnel Related Cost | I14: =IF(A14<>"Remove",CONCATENATE("INSERT INTO tbFinanceItemSeq(Report,ItemSeqID,ItemSN,ItemID) VALUES('",B14,"',",C14,",",E14,",",G14,")"),"") -> INSERT INTO tbFinanceItemSeq(Report,ItemSeqID,ItemSN,ItemID) VALUES('PNL',13,13,1092)
A15: Exist | B15: PNL | C15: =SUM(D15,1) -> 14 | D15: 13 | E15: =SUM(F15,1) -> 14 | F15: 13 | G15: 1093 | H15: (PNL)S&D Carriage/Transportation | I15: =IF(A15<>"Remove",CONCATENATE("INSERT INTO tbFinanceItemSeq(Report,ItemSeqID,ItemSN,ItemID) VALUES('",B15,"',",C15,",",E15,",",G15,")"),"") -> INSERT INTO tbFinanceItemSeq(Report,ItemSeqID,ItemSN,ItemID) VALUES('PNL',14,14,1093)
A16: Exist | B16: PNL | C16: =SUM(D16,1) -> 15 | D16: 14 | E16: =SUM(F16,1) -> 15 | F16: 14 | G16: 1094 | H16: (PNL)S&D Advertising/Promotion | I16: =IF(A16<>"Remove",CONCATENATE("INSERT INTO tbFinanceItemSeq(Report,ItemSeqID,ItemSN,ItemID) VALUES('",B16,"',",C16,",",E16,",",G16,")"),"") -> INSERT INTO tbFinanceItemSeq(Report,ItemSeqID,ItemSN,ItemID) VALUES('PNL',15,15,1094)
A17: Exist | B17: PNL | C17: =SUM(D17,1) -> 16 | D17: 15 | E17: =SUM(F17,1) -> 16 | F17: 15 | G17: 1095 | H17: (PNL)S&D Overseas Travelling | I17: =IF(A17<>"Remove",CONCATENATE("INSERT INTO tbFinanceItemSeq(Report,ItemSeqID,ItemSN,ItemID) VALUES('",B17,"',",C17,",",E17,",",G17,")"),"") -> INSERT INTO tbFinanceItemSeq(Report,ItemSeqID,ItemSN,ItemID) VALUES('PNL',16,16,1095)
A18: Exist | B18: PNL | C18: =SUM(D18,1) -> 17 | D18: 16 | E18: =SUM(F18,1) -> 17 | F18: 16 | G18: 1096 | H18: (PNL)S&D Entertainment | I18: =IF(A18<>"Remove",CONCATENATE("INSERT INTO tbFinanceItemSeq(Report,ItemSeqID,ItemSN,ItemID) VALUES('",B18,"',",C18,",",E18,",",G18,")"),"") -> INSERT INTO tbFinanceItemSeq(Report,ItemSeqID,ItemSN,ItemID) VALUES('PNL',17,17,1096)
A19: Exist | B19: PNL | C19: =SUM(D19,1) -> 18 | D19: 17 | E19: =SUM(F19,1) -> 18 | F19: 17 | G19: 1097 | H19: (PNL)S&D Equipment Expenses | I19: =IF(A19<>"Remove",CONCATENATE("INSERT INTO tbFinanceItemSeq(Report,ItemSeqID,ItemSN,ItemID) VALUES('",B19,"',",C19,",",E19,",",G19,")"),"") -> INSERT INTO tbFinanceItemSeq(Report,ItemSeqID,ItemSN,ItemID) VALUES('PNL',18,18,1097)
A20: Exist | B20: PNL | C20: =SUM(D20,1) -> 19 | D20: 18 | E20: =SUM(F20,1) -> 19 | F20: 18 | G20: 1098 | H20: (PNL)S&D Rental/Property Related | I20: =IF(A20<>"Remove",CONCATENATE("INSERT INTO tbFinanceItemSeq(Report,ItemSeqID,ItemSN,ItemID) VALUES('",B20,"',",C20,",",E20,",",G20,")"),"") -> INSERT INTO tbFinanceItemSeq(Report,ItemSeqID,ItemSN,ItemID) VALUES('PNL',19,19,1098)
A21: Exist | B21: PNL | C21: =SUM(D21,1) -> 20 | D21: 19 | E21: =SUM(F21,1) -> 20 | F21: 19 | G21: 1099 | H21: (PNL)S&D Depn of Fixed Assets | I21: =IF(A21<>"Remove",CONCATENATE("INSERT INTO tbFinanceItemSeq(Report,ItemSeqID,ItemSN,ItemID) VALUES('",B21,"',",C21,",",E21,",",G21,")"),"") -> INSERT INTO tbFinanceItemSeq(Report,ItemSeqID,ItemSN,ItemID) VALUES('PNL',20,20,1099)
A22: Exist | B22: PNL | C22: =SUM(D22,1) -> 21 | D22: 20 | E22: =SUM(F22,1) -> 21 | F22: 20 | G22: 1100 | H22: (PNL)S&D Stationery/Printing/Telephone | I22: =IF(A22<>"Remove",CONCATENATE("INSERT INTO tbFinanceItemSeq(Report,ItemSeqID,ItemSN,ItemID) VALUES('",B22,"',",C22,",",E22,",",G22,")"),"") -> INSERT INTO tbFinanceItemSeq(Report,ItemSeqID,ItemSN,ItemID) VALUES('PNL',21,21,1100)
A23: Remove | B23: PNL | D23: 21 | F23: 21 | G23: 1101 | H23: (PNL)Other S&D Expenses | I23: =IF(A23<>"Remove",CONCATENATE("INSERT INTO tbFinanceItemSeq(Report,ItemSeqID,ItemSN,ItemID) VALUES('",B23,"',",C23,",",E23,",",G23,")"),"")
A24: New | B24: PNL | C24: 22 | E24: 22 | G24: 1101 | H24: (PNL)HO/Interco and Other S&D | I24: =IF(A24<>"Remove",CONCATENATE("INSERT INTO tbFinanceItemSeq(Report,ItemSeqID,ItemSN,ItemID) VALUES('",B24,"',",C24,",",E24,",",G24,")"),"") -> INSERT INTO tbFinanceItemSeq(Report,ItemSeqID,ItemSN,ItemID) VALUES('PNL',22,22,1101)
A25: Exist | B25: PNL | C25: =SUM(D25,1) -> 23 | D25: 22 | E25: =SUM(F25,1) -> 23 | F25: 22 | G25: 1102 | H25: (PNL)Total S&D Expenses | I25: =IF(A25<>"Remove",CONCATENATE("INSERT INTO tbFinanceItemSeq(Report,ItemSeqID,ItemSN,ItemID) VALUES('",B25,"',",C25,",",E25,",",G25,")"),"") -> INSERT INTO tbFinanceItemSeq(Report,ItemSeqID,ItemSN,ItemID) VALUES('PNL',23,23,1102)
A26: Exist | B26: PNL | C26: =SUM(D26,1) -> 24 | D26: 23 | E26: =SUM(F26,1) -> 24 | F26: 23 | G26: 1103 | H26: (PNL)A&G Personnel Related Cost | I26: =IF(A26<>"Remove",CONCATENATE("INSERT INTO tbFinanceItemSeq(Report,ItemSeqID,ItemSN,ItemID) VALUES('",B26,"',",C26,",",E26,",",G26,")"),"") -> INSERT INTO tbFinanceItemSeq(Report,ItemSeqID,ItemSN,ItemID) VALUES('PNL',24,24,1103)
A27: Exist | B27: PNL | C27: =SUM(D27,1) -> 25 | D27: 24 | E27: =SUM(F27,1) -> 25 | F27: 24 | G27: 1104 | H27: (PNL)A&G Overseas Travelling | I27: =IF(A27<>"Remove",CONCATENATE("INSERT INTO tbFinanceItemSeq(Report,ItemSeqID,ItemSN,ItemID) VALUES('",B27,"',",C27,",",E27,",",G27,")"),"") -> INSERT INTO tbFinanceItemSeq(Report,ItemSeqID,ItemSN,ItemID) VALUES('PNL',25,25,1104)
A28: Exist | B28: PNL | C28: =SUM(D28,1) -> 26 | D28: 25 | E28: =SUM(F28,1) -> 26 | F28: 25 | G28: 1105 | H28: (PNL)A&G Transportation | I28: =IF(A28<>"Remove",CONCATENATE("INSERT INTO tbFinanceItemSeq(Report,ItemSeqID,ItemSN,ItemID) VALUES('",B28,"',",C28,",",E28,",",G28,")"),"") -> INSERT INTO tbFinanceItemSeq(Report,ItemSeqID,ItemSN,ItemID) VALUES('PNL',26,26,1105)
A29: Remove | B29: PNL | D29: 26 | F29: 26 | G29: 1106 | H29: (PNL)A&G Entertainment | I29: =IF(A29<>"Remove",CONCATENATE("INSERT INTO tbFinanceItemSeq(Report,ItemSeqID,ItemSN,ItemID) VALUES('",B29,"',",C29,",",E29,",",G29,")"),"")
A30: New | B30: PNL | C30: 27 | E30: 27 | G30: 1106 | H30: (PNL)A&G Entertainment & Donation | I30: =IF(A30<>"Remove",CONCATENATE("INSERT INTO tbFinanceItemSeq(Report,ItemSeqID,ItemSN,ItemID) VALUES('",B30,"',",C30,",",E30,",",G30,")"),"") -> INSERT INTO tbFinanceItemSeq(Report,ItemSeqID,ItemSN,ItemID) VALUES('PNL',27,27,1106)
A31: Exist | B31: PNL | C31: =SUM(D31,1) -> 28 | D31: 27 | E31: =SUM(F31,1) -> 28 | F31: 27 | G31: 1107 | H31: (PNL)A&G Equipment Expenses | I31: =IF(A31<>"Remove",CONCATENATE("INSERT INTO tbFinanceItemSeq(Report,ItemSeqID,ItemSN,ItemID) VALUES('",B31,"',",C31,",",E31,",",G31,")"),"") -> INSERT INTO tbFinanceItemSeq(Report,ItemSeqID,ItemSN,ItemID) VALUES('PNL',28,28,1107)
A32: Exist | B32: PNL | C32: =SUM(D32,1) -> 29 | D32: 28 | E32: =SUM(F32,1) -> 29 | F32: 28 | G32: 1108 | H32: (PNL)A&G Rental/Property Related | I32: =IF(A32<>"Remove",CONCATENATE("INSERT INTO tbFinanceItemSeq(Report,ItemSeqID,ItemSN,ItemID) VALUES('",B32,"',",C32,",",E32,",",G32,")"),"") -> INSERT INTO tbFinanceItemSeq(Report,ItemSeqID,ItemSN,ItemID) VALUES('PNL',29,29,1108)
A33: Exist | B33: PNL | C33: =SUM(D33,1) -> 30 | D33: 29 | E33: =SUM(F33,1) -> 30 | F33: 29 | G33: 1109 | H33: (PNL)A&G Depn of Fixed Assets | I33: =IF(A33<>"Remove",CONCATENATE("INSERT INTO tbFinanceItemSeq(Report,ItemSeqID,ItemSN,ItemID) VALUES('",B33,"',",C33,",",E33,",",G33,")"),"") -> INSERT INTO tbFinanceItemSeq(Report,ItemSeqID,ItemSN,ItemID) VALUES('PNL',30,30,1109)
A34: Exist | B34: PNL | C34: =SUM(D34,1) -> 31 | D34: 30 | E34: =SUM(F34,1) -> 31 | F34: 30 | G34: 1110 | H34: (PNL)A&G Stationery/Printing/Telephone | I34: =IF(A34<>"Remove",CONCATENATE("INSERT INTO tbFinanceItemSeq(Report,ItemSeqID,ItemSN,ItemID) VALUES('",B34,"',",C34,",",E34,",",G34,")"),"") -> INSERT INTO tbFinanceItemSeq(Report,ItemSeqID,ItemSN,ItemID) VALUES('PNL',31,31,1110)
A35: Exist | B35: PNL | C35: =SUM(D35,1) -> 32 | D35: 31 | E35: =SUM(F35,1) -> 32 | F35: 31 | G35: 1111 | H35: (PNL)A&G Legal/Prof Fees/Ins/Safety | I35: =IF(A35<>"Remove",CONCATENATE("INSERT INTO tbFinanceItemSeq(Report,ItemSeqID,ItemSN,ItemID) VALUES('",B35,"',",C35,",",E35,",",G35,")"),"") -> INSERT INTO tbFinanceItemSeq(Report,ItemSeqID,ItemSN,ItemID) VALUES('PNL',32,32,1111)
A36: Exist | B36: PNL | C36: =SUM(D36,1) -> 33 | D36: 32 | E36: =SUM(F36,1) -> 33 | F36: 32 | G36: 1376 | H36: (PNL)A&G IT System Exps | I36: =IF(A36<>"Remove",CONCATENATE("INSERT INTO tbFinanceItemSeq(Report,ItemSeqID,ItemSN,ItemID) VALUES('",B36,"',",C36,",",E36,",",G36,")"),"") -> INSERT INTO tbFinanceItemSeq(Report,ItemSeqID,ItemSN,ItemID) VALUES('PNL',33,33,1376)
A37: Exist | B37: PNL | C37: =SUM(D37,1) -> 34 | D37: 33 | E37: =SUM(F37,1) -> 34 | F37: 33 | G37: 1377 | H37: (PNL)A&G Purchasing Exps | I37: =IF(A37<>"Remove",CONCATENATE("INSERT INTO tbFinanceItemSeq(Report,ItemSeqID,ItemSN,ItemID) VALUES('",B37,"',",C37,",",E37,",",G37,")"),"") -> INSERT INTO tbFinanceItemSeq(Report,ItemSeqID,ItemSN,ItemID) VALUES('PNL',34,34,1377)
A38: Exist | B38: PNL | C38: =SUM(D38,1) -> 35 | D38: 34 | E38: =SUM(F38,1) -> 35 | F38: 34 | G38: 1112 | H38: (PNL)A&G Direct Expenses | I38: =IF(A38<>"Remove",CONCATENATE("INSERT INTO tbFinanceItemSeq(Report,ItemSeqID,ItemSN,ItemID) VALUES('",B38,"',",C38,",",E38,",",G38,")"),"") -> INSERT INTO tbFinanceItemSeq(Report,ItemSeqID,ItemSN,ItemID) VALUES('PNL',35,35,1112)
A39: Exist | B39: PNL | C39: =SUM(D39,1) -> 36 | D39: 35 | E39: =SUM(F39,1) -> 36 | F39: 35 | G39: 1113 | H39: (PNL)Prov for Stock Obso/Pilferage | I39: =IF(A39<>"Remove",CONCATENATE("INSERT INTO tbFinanceItemSeq(Report,ItemSeqID,ItemSN,ItemID) VALUES('",B39,"',",C39,",",E39,",",G39,")"),"") -> INSERT INTO tbFinanceItemSeq(Report,ItemSeqID,ItemSN,ItemID) VALUES('PNL',36,36,1113)
A40: Exist | B40: PNL | C40: =SUM(D40,1) -> 37 | D40: 36 | E40: =SUM(F40,1) -> 37 | F40: 36 | G40: 1114 | H40: (PNL)Prov for Doubtful Debts | I40: =IF(A40<>"Remove",CONCATENATE("INSERT INTO tbFinanceItemSeq(Report,ItemSeqID,ItemSN,ItemID) VALUES('",B40,"',",C40,",",E40,",",G40,")"),"") -> INSERT INTO tbFinanceItemSeq(Report,ItemSeqID,ItemSN,ItemID) VALUES('PNL',37,37,1114)
A41: Exist | B41: PNL | C41: =SUM(D41,1) -> 38 | D41: 37 | E41: =SUM(F41,1) -> 38 | F41: 37 | G41: 1115 | H41: (PNL)Bad Debts Recovered | I41: =IF(A41<>"Remove",CONCATENATE("INSERT INTO tbFinanceItemSeq(Report,ItemSeqID,ItemSN,ItemID) VALUES('",B41,"',",C41,",",E41,",",G41,")"),"") -> INSERT INTO tbFinanceItemSeq(Report,ItemSeqID,ItemSN,ItemID) VALUES('PNL',38,38,1115)
A42: Exist | B42: PNL | C42: =SUM(D42,1) -> 39 | D42: 38 | E42: =SUM(F42,1) -> 39 | F42: 38 | G42: 1585 | H42: (PNL)Stocks Written Down/Written Off | I42: =IF(A42<>"Remove",CONCATENATE("INSERT INTO tbFinanceItemSeq(Report,ItemSeqID,ItemSN,ItemID) VALUES('",B42,"',",C42,",",E42,",",G42,")"),"") -> INSERT INTO tbFinanceItemSeq(Report,ItemSeqID,ItemSN,ItemID) VALUES('PNL',39,39,1585)
... A44: Remove | B44: PNL | C44: =SUM(D44,1) -> 41 | D44: 40 | E44: =SUM(F44,1) -> 41 | F44: 40 | G44: 1117 | H44: (PNL)HO / Interco Allocation | I44: =IF(A44<>"Remove",CONCATENATE("INSERT INTO tbFinanceItemSeq(Report,ItemSeqID,ItemSN,ItemID) VALUES('",B44,"',",C44,",",E44,",",G44,")"),"")
A45: New | B45: PNL | C45: 41 | E45: 41 | G45: 1117 | H45: (PNL)HO/Interco Alloc | I45: =IF(A45<>"Remove",CONCATENATE("INSERT INTO tbFinanceItemSeq(Report,ItemSeqID,ItemSN,ItemID) VALUES('",B45,"',",C45,",",E45,",",G45,")"),"") -> INSERT INTO tbFinanceItemSeq(Report,ItemSeqID,ItemSN,ItemID) VALUES('PNL',41,41,1117)
A46: Remove | B46: PNL | D46: 41 | F46: 41 | G46: 1118 | H46: (PNL)A&G Other Expenses | I46: =IF(A46<>"Remove",CONCATENATE("INSERT INTO tbFinanceItemSeq(Report,ItemSeqID,ItemSN,ItemID) VALUES('",B46,"',",C46,",",E46,",",G46,")"),"")
A47: New | B47: PNL | C47: 42 | E47: 42 | G47: 1118 | H47: (PNL) Other A&G Expenses | I47: =IF(A47<>"Remove",CONCATENATE("INSERT INTO tbFinanceItemSeq(Report,ItemSeqID,ItemSN,ItemID) VALUES('",B47,"',",C47,",",E47,",",G47,")"),"") -> INSERT INTO tbFinanceItemSeq(Report,ItemSeqID,ItemSN,ItemID) VALUES('PNL',42,42,1118)
A48: Exist | B48: PNL | C48: =SUM(D48,1) -> 43 | D48: 42 | E48: =SUM(F48,1) -> 43 | F48: 42 | G48: 1119 | H48: (PNL)Total A&G Expenses | I48: =IF(A48<>"Remove",CONCATENATE("INSERT INTO tbFinanceItemSeq(Report,ItemSeqID,ItemSN,ItemID) VALUES('",B48,"',",C48,",",E48,",",G48,")"),"") -> INSERT INTO tbFinanceItemSeq(Report,ItemSeqID,ItemSN,ItemID) VALUES('PNL',43,43,1119)
A49: Exist | B49: PNL | C49: =SUM(D49,1) -> 44 | D49: 43 | E49: =SUM(F49,1) -> 44 | F49: 43 | G49: 1120 | H49: (PNL)Profit from Operations | I49: =IF(A49<>"Remove",CONCATENATE("INSERT INTO tbFinanceItemSeq(Report,ItemSeqID,ItemSN,ItemID) VALUES('",B49,"',",C49,",",E49,",",G49,")"),"") -> INSERT INTO tbFinanceItemSeq(Report,ItemSeqID,ItemSN,ItemID) VALUES('PNL',44,44,1120)
A50: Exist | B50: PNL | C50: =SUM(D50,1) -> 45 | D50: 44 | E50: =SUM(F50,1) -> 45 | F50: 44 | G50: 1121 | H50: (PNL)Interest Income | I50: =IF(A50<>"Remove",CONCATENATE("INSERT INTO tbFinanceItemSeq(Report,ItemSeqID,ItemSN,ItemID) VALUES('",B50,"',",C50,",",E50,",",G50,")"),"") -> INSERT INTO tbFinanceItemSeq(Report,ItemSeqID,ItemSN,ItemID) VALUES('PNL',45,45,1121)
A51: Exist | B51: PNL | C51: =SUM(D51,1) -> 46 | D51: 45 | E51: =SUM(F51,1) -> 46 | F51: 45 | G51: 1122 | H51: (PNL)Interest Expense | I51: =IF(A51<>"Remove",CONCATENATE("INSERT INTO tbFinanceItemSeq(Report,ItemSeqID,ItemSN,ItemID) VALUES('",B51,"',",C51,",",E51,",",G51,")"),"") -> INSERT INTO tbFinanceItemSeq(Report,ItemSeqID,ItemSN,ItemID) VALUES('PNL',46,46,1122)
A52: New | B52: PNL | C52: 47 | E52: 47 | G52: =CONCATENATE("(SELECT TOP 1 ItemID FROM tbFinanceItem where ItemName = '",H52,"')") -> (SELECT TOP 1 ItemID FROM tbFinanceItem where ItemName = '(PNL)Derivatives Gain/(Loss)') | H52: (PNL)Derivatives Gain/(Loss) | I52: =IF(A52<>"Remove",CONCATENATE("INSERT INTO tbFinanceItemSeq(Report,ItemSeqID,ItemSN,ItemID) VALUES('",B52,"',",C52,",",E52,",",G52,")"),"") -> INSERT INTO tbFinanceItemSeq(Report,ItemSeqID,ItemSN,ItemID) VALUES('PNL',47,47,(SELECT TOP 1 ItemID FROM tbFinanceItem where ItemName = '(PNL)Derivatives Gain/(Loss)'))
A53: Remove | B53: PNL | C53: =SUM(D53,1) -> 47 | D53: 46 | E53: =SUM(F53,1) -> 47 | F53: 46 | G53: 1123 | H53: (PNL)Realised Forex Gain/(Loss) | I53: =IF(A53<>"Remove",CONCATENATE("INSERT INTO tbFinanceItemSeq(Report,ItemSeqID,ItemSN,ItemID) VALUES('",B53,"',",C53,",",E53,",",G53,")"),"")
A54: Remove | B54: PNL | C54: =SUM(D54,1) -> 48 | D54: 47 | E54: =SUM(F54,1) -> 48 | F54: 47 | G54: 1124 | H54: (PNL)Unrealised Forex Gain/(Loss) | I54: =IF(A54<>"Remove",CONCATENATE("INSERT INTO tbFinanceItemSeq(Report,ItemSeqID,ItemSN,ItemID) VALUES('",B54,"',",C54,",",E54,",",G54,")"),"")
A55: New | B55: PNL | C55: 48 | E55: 48 | G55: =CONCATENATE("(SELECT TOP 1 ItemID FROM tbFinanceItem where ItemName = '",H55,"')") -> (SELECT TOP 1 ItemID FROM tbFinanceItem where ItemName = '(PNL)Forex Gain/(Loss)') | H55: (PNL)Forex Gain/(Loss) | I55: =IF(A55<>"Remove",CONCATENATE("INSERT INTO tbFinanceItemSeq(Report,ItemSeqID,ItemSN,ItemID) VALUES('",B55,"',",C55,",",E55,",",G55,")"),"") -> INSERT INTO tbFinanceItemSeq(Report,ItemSeqID,ItemSN,ItemID) VALUES('PNL',48,48,(SELECT TOP 1 ItemID FROM tbFinanceItem where ItemName = '(PNL)Forex Gain/(Loss)'))
A56: Exist | B56: PNL | C56: =SUM(D56,1) -> 49 | D56: 48 | E56: =SUM(F56,1) -> 49 | F56: 48 | G56: 1125 | H56: (PNL)Dividend Income | I56: =IF(A56<>"Remove",CONCATENATE("INSERT INTO tbFinanceItemSeq(Report,ItemSeqID,ItemSN,ItemID) VALUES('",B56,"',",C56,",",E56,",",G56,")"),"") -> INSERT INTO tbFinanceItemSeq(Report,ItemSeqID,ItemSN,ItemID) VALUES('PNL',49,49,1125)
A57: Remove | B57: PNL | C57: =SUM(D57,1) -> 50 | D57: 49 | E57: =SUM(F57,1) -> 50 | F57: 49 | G57: 1126 | H57: (PNL)Gain/(Loss) Disposal of FA | I57: =IF(A57<>"Remove",CONCATENATE("INSERT INTO tbFinanceItemSeq(Report,ItemSeqID,ItemSN,ItemID) VALUES('",B57,"',",C57,",",E57,",",G57,")"),"")
A58: Exist | B58: PNL | C58: =(D58) -> 50 | D58: 50 | E58: =SUM(F58) -> 50 | F58: 50 | G58: 1127 | H58: (PNL)Other Non-Op Income/(Exp) | I58: =IF(A58<>"Remove",CONCATENATE("INSERT INTO tbFinanceItemSeq(Report,ItemSeqID,ItemSN,ItemID) VALUES('",B58,"',",C58,",",E58,",",G58,")"),"") -> INSERT INTO tbFinanceItemSeq(Report,ItemSeqID,ItemSN,ItemID) VALUES('PNL',50,50,1127)
A59: Exist | B59: PNL | C59: =(D59) -> 51 | D59: 51 | E59: =SUM(F59) -> 51 | F59: 51 | G59: 1128 | H59: (PNL)Total Non-Op Income/(Exp) | I59: =IF(A59<>"Remove",CONCATENATE("INSERT INTO tbFinanceItemSeq(Report,ItemSeqID,ItemSN,ItemID) VALUES('",B59,"',",C59,",",E59,",",G59,")"),"") -> INSERT INTO tbFinanceItemSeq(Report,ItemSeqID,ItemSN,ItemID) VALUES('PNL',51,51,1128)
A60: Exist | B60: PNL | C60: =(D60) -> 52 | D60: 52 | E60: =SUM(F60) -> 52 | F60: 52 | G60: 1129 | H60: (PNL)Profit Before Taxation | I60: =IF(A60<>"Remove",CONCATENATE("INSERT INTO tbFinanceItemSeq(Report,ItemSeqID,ItemSN,ItemID) VALUES('",B60,"',",C60,",",E60,",",G60,")"),"") -> INSERT INTO tbFinanceItemSeq(Report,ItemSeqID,ItemSN,ItemID) VALUES('PNL',52,52,1129)
A61: Exist | B61: PNL | C61: =(D61) -> 53 | D61: 53 | E61: =SUM(F61) -> 53 | F61: 53 | G61: 1130 | H61: (PNL)Less: Taxation | I61: =IF(A61<>"Remove",CONCATENATE("INSERT INTO tbFinanceItemSeq(Report,ItemSeqID,ItemSN,ItemID) VALUES('",B61,"',",C61,",",E61,",",G61,")"),"") -> INSERT INTO tbFinanceItemSeq(Report,ItemSeqID,ItemSN,ItemID) VALUES('PNL',53,53,1130)
A62: Exist | B62: PNL | C62: =(D62) -> 54 | D62: 54 | E62: =SUM(F62) -> 54 | F62: 54 | G62: 1131 | H62: (PNL)Profit After Taxation | I62: =IF(A62<>"Remove",CONCATENATE("INSERT INTO tbFinanceItemSeq(Report,ItemSeqID,ItemSN,ItemID) VALUES('",B62,"',",C62,",",E62,",",G62,")"),"") -> INSERT INTO tbFinanceItemSeq(Report,ItemSeqID,ItemSN,ItemID) VALUES('PNL',54,54,1131)
A63: Exist | B63: PNL | C63: =(D63) -> 55 | D63: 55 | E63: =SUM(F63) -> 55 | F63: 55 | G63: 1474 | H63: (PNL)Dividend Expenses | I63: =IF(A63<>"Remove",CONCATENATE("INSERT INTO tbFinanceItemSeq(Report,ItemSeqID,ItemSN,ItemID) VALUES('",B63,"',",C63,",",E63,",",G63,")"),"") -> INSERT INTO tbFinanceItemSeq(Report,ItemSeqID,ItemSN,ItemID) VALUES('PNL',55,55,1474)
A64: Exist | B64: PNL | C64: =(D64) -> 56 | D64: 56 | E64: =SUM(F64) -> 0 | F64: 0 | G64: 46 | H64: Performance Indicators | I64: =IF(A64<>"Remove",CONCATENATE("INSERT INTO tbFinanceItemSeq(Report,ItemSeqID,ItemSN,ItemID) VALUES('",B64,"',",C64,",",E64,",",G64,")"),"") -> INSERT INTO tbFinanceItemSeq(Report,ItemSeqID,ItemSN,ItemID) VALUES('PNL',56,0,46)
A65: Exist | B65: PNL | C65: =(D65) -> 57 | D65: 57 | E65: =SUM(F65) -> 1 | F65: 1 | G65: 1135 | H65: Gross Profits Margin % | I65: =IF(A65<>"Remove",CONCATENATE("INSERT INTO tbFinanceItemSeq(Report,ItemSeqID,ItemSN,ItemID) VALUES('",B65,"',",C65,",",E65,",",G65,")"),"") -> INSERT INTO tbFinanceItemSeq(Report,ItemSeqID,ItemSN,ItemID) VALUES('PNL',57,1,1135)
A66: Exist | B66: PNL | C66: =(D66) -> 58 | D66: 58 | E66: =SUM(F66) -> 2 | F66: 2 | G66: 1136 | H66: - External Sales GP % | I66: =IF(A66<>"Remove",CONCATENATE("INSERT INTO tbFinanceItemSeq(Report,ItemSeqID,ItemSN,ItemID) VALUES('",B66,"',",C66,",",E66,",",G66,")"),"") -> INSERT INTO tbFinanceItemSeq(Report,ItemSeqID,ItemSN,ItemID) VALUES('PNL',58,2,1136)
A67: Exist | B67: PNL | C67: =(D67) -> 59 | D67: 59 | E67: =SUM(F67) -> 3 | F67: 3 | G67: 1137 | H67: - Interco Sales GP % | I67: =IF(A67<>"Remove",CONCATENATE("INSERT INTO tbFinanceItemSeq(Report,ItemSeqID,ItemSN,ItemID) VALUES('",B67,"',",C67,",",E67,",",G67,")"),"") -> INSERT INTO tbFinanceItemSeq(Report,ItemSeqID,ItemSN,ItemID) VALUES('PNL',59,3,1137)
A68: Exist | B68: PNL | C68: =(D68) -> 60 | D68: 60 | E68: =SUM(F68) -> 4 | F68: 4 | G68: 50 | H68: Selling & Dist Margin % | I68: =IF(A68<>"Remove",CONCATENATE("INSERT INTO tbFinanceItemSeq(Report,ItemSeqID,ItemSN,ItemID) VALUES('",B68,"',",C68,",",E68,",",G68,")"),"") -> INSERT INTO tbFinanceItemSeq(Report,ItemSeqID,ItemSN,ItemID) VALUES('PNL',60,4,50)
A69: Remove | B69: PNL | C69: =(D69) -> 61 | D69: 61 | E69: =SUM(F69) -> 5 | F69: 5 | G69: 1138 | H69: A&G Margin Direct % | I69: =IF(A69<>"Remove",CONCATENATE("INSERT INTO tbFinanceItemSeq(Report,ItemSeqID,ItemSN,ItemID) VALUES('",B69,"',",C69,",",E69,",",G69,")"),"")
A70: Exist | B70: PNL | C70: 61 | D70: 62 | E70: 5 | F70: 6 | G70: 1139 | H70: A&G Margin Total % | I70: =IF(A70<>"Remove",CONCATENATE("INSERT INTO tbFinanceItemSeq(Report,ItemSeqID,ItemSN,ItemID) VALUES('",B70,"',",C70,",",E70,",",G70,")"),"") -> INSERT INTO tbFinanceItemSeq(Report,ItemSeqID,ItemSN,ItemID) VALUES('PNL',61,5,1139)
A71: Exist | B71: PNL | C71: 62 | D71: 63 | E71: 6 | F71: 7 | G71: 53 | H71: Operating Profit Margin % | I71: =IF(A71<>"Remove",CONCATENATE("INSERT INTO tbFinanceItemSeq(Report,ItemSeqID,ItemSN,ItemID) VALUES('",B71,"',",C71,",",E71,",",G71,")"),"") -> INSERT INTO tbFinanceItemSeq(Report,ItemSeqID,ItemSN,ItemID) VALUES('PNL',62,6,53)
A72: Exist | B72: PNL | C72: 63 | D72: 64 | E72: 7 | F72: 8 | G72: 52 | H72: Profit Before Taxation % | I72: =IF(A72<>"Remove",CONCATENATE("INSERT INTO tbFinanceItemSeq(Report,ItemSeqID,ItemSN,ItemID) VALUES('",B72,"',",C72,",",E72,",",G72,")"),"") -> INSERT INTO tbFinanceItemSeq(Report,ItemSeqID,ItemSN,ItemID) VALUES('PNL',63,7,52)
A73: Exist | B73: PNL | C73: 64 | D73: 65 | E73: 8 | F73: 9 | G73: 1140 | H73: Profit After Taxation % | I73: =IF(A73<>"Remove",CONCATENATE("INSERT INTO tbFinanceItemSeq(Report,ItemSeqID,ItemSN,ItemID) VALUES('",B73,"',",C73,",",E73,",",G73,")"),"") -> INSERT INTO tbFinanceItemSeq(Report,ItemSeqID,ItemSN,ItemID) VALUES('PNL',64,8,1140)

Sheet F21R PNLR-Script
A1: INSERT INTO
A2: tbReport
A3: (ReportCategoryID,Description,FileName,StoredProcName,CreatedBy,CreatedDate,ModifiedBy,ModifiedDate,IsActive,IsExternalReport)
A4: VALUES
A5: (1,'[COA2016] F21R Profit & loss Account (Raw)','F21R Profit & Loss Account (Raw).rpt',null,1,CURRENT_TIMESTAMP,Null,Null,1,0);

Sheet F21R PNLR-New
A1: Status | B1: Report | C1: New ItemSeqID | D1: New ItemSNNO | E1: ItemID | F1: PNL Item Name | G1: PNLR - Item Name | H1: Insert Script
A2: ='F101 F21 PNL-New'!A2 -> Exist | B2: PNLR | C2: ='F101 F21 PNL-New'!C2 -> 1 | D2: ='F101 F21 PNL-New'!E2 -> 1 | E2: =CONCATENATE("(SELECT ItemID FROM tbFinanceItem where ItemName = '",G2,"')") -> (SELECT ItemID FROM tbFinanceItem where ItemName = '(PNLR)External Sales') | F2: ='F101 F21 PNL-New'!H2 -> (PNL)External Sales | G2: =REPLACE(F2,2,3,B2) -> (PNLR)External Sales | H2: =IF(A2<>"Remove",CONCATENATE("INSERT INTO tbFinanceItemSeq(Report,ItemSeqID,ItemSN,ItemID) VALUES('",B2,"',",C2,",",D2,",",E2,")"),"") -> INSERT INTO tbFinanceItemSeq(Report,ItemSeqID,ItemSN,ItemID) VALUES('PNLR',1,1,(SELECT ItemID FROM tbFinanceItem where ItemName = '(PNLR)External Sales'))
A3: ='F101 F21 PNL-New'!A3 -> Exist | B3: PNLR | C3: ='F101 F21 PNL-New'!C3 -> 2 | D3: ='F101 F21 PNL-New'!E3 -> 2 | E3: =CONCATENATE("(SELECT ItemID FROM tbFinanceItem where ItemName = '",G3,"')") -> (SELECT ItemID FROM tbFinanceItem where ItemName = '(PNLR)Interco Sales') | F3: ='F101 F21 PNL-New'!H3 -> (PNL)Interco Sales | G3: =REPLACE(F3,2,3,B3) -> (PNLR)Interco Sales | H3: =IF(A3<>"Remove",CONCATENATE("INSERT INTO tbFinanceItemSeq(Report,ItemSeqID,ItemSN,ItemID) VALUES('",B3,"',",C3,",",D3,",",E3,")"),"") -> INSERT INTO tbFinanceItemSeq(Report,ItemSeqID,ItemSN,ItemID) VALUES('PNLR',2,2,(SELECT ItemID FROM tbFinanceItem where ItemName = '(PNLR)Interco Sales'))
A4: ='F101 F21 PNL-New'!A4 -> Exist | B4: PNLR | C4: ='F101 F21 PNL-New'!C4 -> 3 | D4: ='F101 F21 PNL-New'!E4 -> 3 | E4: =CONCATENATE("(SELECT ItemID FROM tbFinanceItem where ItemName = '",G4,"')") -> (SELECT ItemID FROM tbFinanceItem where ItemName = '(PNLR)Total Sales') | F4: ='F101 F21 PNL-New'!H4 -> (PNL)Total Sales | G4: =REPLACE(F4,2,3,B4) -> (PNLR)Total Sales | H4: =IF(A4<>"Remove",CONCATENATE("INSERT INTO tbFinanceItemSeq(Report,ItemSeqID,ItemSN,ItemID) VALUES('",B4,"',",C4,",",D4,",",E4,")"),"") -> INSERT INTO tbFinanceItemSeq(Report,ItemSeqID,ItemSN,ItemID) VALUES('PNLR',3,3,(SELECT ItemID FROM tbFinanceItem where ItemName = '(PNLR)Total Sales'))
A5: ='F101 F21 PNL-New'!A5 -> Exist | B5: PNLR | C5: ='F101 F21 PNL-New'!C5 -> 4 | D5: ='F101 F21 PNL-New'!E5 -> 4 | E5: =CONCATENATE("(SELECT ItemID FROM tbFinanceItem where ItemName = '",G5,"')") -> (SELECT ItemID FROM tbFinanceItem where ItemName = '(PNLR)Cost of External Sales') | F5: ='F101 F21 PNL-New'!H5 -> (PNL)Cost of External Sales | G5: =REPLACE(F5,2,3,B5) -> (PNLR)Cost of External Sales | H5: =IF(A5<>"Remove",CONCATENATE("INSERT INTO tbFinanceItemSeq(Report,ItemSeqID,ItemSN,ItemID) VALUES('",B5,"',",C5,",",D5,",",E5,")"),"") -> INSERT INTO tbFinanceItemSeq(Report,ItemSeqID,ItemSN,ItemID) VALUES('PNLR',4,4,(SELECT ItemID FROM tbFinanceItem where ItemName = '(PNLR)Cost of External Sales'))
A6: ='F101 F21 PNL-New'!A6 -> Exist | B6: PNLR | C6: ='F101 F21 PNL-New'!C6 -> 5 | D6: ='F101 F21 PNL-New'!E6 -> 5 | E6: =CONCATENATE("(SELECT ItemID FROM tbFinanceItem where ItemName = '",G6,"')") -> (SELECT ItemID FROM tbFinanceItem where ItemName = '(PNLR)Cost of Interco Sales') | F6: ='F101 F21 PNL-New'!H6 -> (PNL)Cost of Interco Sales | G6: =REPLACE(F6,2,3,B6) -> (PNLR)Cost of Interco Sales | H6: =IF(A6<>"Remove",CONCATENATE("INSERT INTO tbFinanceItemSeq(Report,ItemSeqID,ItemSN,ItemID) VALUES('",B6,"',",C6,",",D6,",",E6,")"),"") -> INSERT INTO tbFinanceItemSeq(Report,ItemSeqID,ItemSN,ItemID) VALUES('PNLR',5,5,(SELECT ItemID FROM tbFinanceItem where ItemName = '(PNLR)Cost of Interco Sales'))
A7: ='F101 F21 PNL-New'!A7 -> Exist | B7: PNLR | C7: ='F101 F21 PNL-New'!C7 -> 6 | D7: ='F101 F21 PNL-New'!E7 -> 6 | E7: =CONCATENATE("(SELECT ItemID FROM tbFinanceItem where ItemName = '",G7,"')") -> (SELECT ItemID FROM tbFinanceItem where ItemName = '(PNLR)Total Cost of Sales') | F7: ='F101 F21 PNL-New'!H7 -> (PNL)Total Cost of Sales | G7: =REPLACE(F7,2,3,B7) -> (PNLR)Total Cost of Sales | H7: =IF(A7<>"Remove",CONCATENATE("INSERT INTO tbFinanceItemSeq(Report,ItemSeqID,ItemSN,ItemID) VALUES('",B7,"',",C7,",",D7,",",E7,")"),"") -> INSERT INTO tbFinanceItemSeq(Report,ItemSeqID,ItemSN,ItemID) VALUES('PNLR',6,6,(SELECT ItemID FROM tbFinanceItem where ItemName = '(PNLR)Total Cost of Sales'))
A8: ='F101 F21 PNL-New'!A8 -> Exist | B8: PNLR | C8: ='F101 F21 PNL-New'!C8 -> 7 | D8: ='F101 F21 PNL-New'!E8 -> 7 | E8: =CONCATENATE("(SELECT ItemID FROM tbFinanceItem where ItemName = '",G8,"')") -> (SELECT ItemID FROM tbFinanceItem where ItemName = '(PNLR)Gross Profit') | F8: ='F101 F21 PNL-New'!H8 -> (PNL)Gross Profit | G8: =REPLACE(F8,2,3,B8) -> (PNLR)Gross Profit | H8: =IF(A8<>"Remove",CONCATENATE("INSERT INTO tbFinanceItemSeq(Report,ItemSeqID,ItemSN,ItemID) VALUES('",B8,"',",C8,",",D8,",",E8,")"),"") -> INSERT INTO tbFinanceItemSeq(Report,ItemSeqID,ItemSN,ItemID) VALUES('PNLR',7,7,(SELECT ItemID FROM tbFinanceItem where ItemName = '(PNLR)Gross Profit'))
A9: ='F101 F21 PNL-New'!A9 -> Exist | B9: PNLR | C9: ='F101 F21 PNL-New'!C9 -> 8 | D9: ='F101 F21 PNL-New'!E9 -> 8 | E9: =CONCATENATE("(SELECT ItemID FROM tbFinanceItem where ItemName = '",G9,"')") -> (SELECT ItemID FROM tbFinanceItem where ItemName = '(PNLR)Commission Income/Mgt Income') | F9: ='F101 F21 PNL-New'!H9 -> (PNL)Commission Income/Mgt Income | G9: =REPLACE(F9,2,3,B9) -> (PNLR)Commission Income/Mgt Income | H9: =IF(A9<>"Remove",CONCATENATE("INSERT INTO tbFinanceItemSeq(Report,ItemSeqID,ItemSN,ItemID) VALUES('",B9,"',",C9,",",D9,",",E9,")"),"") -> INSERT INTO tbFinanceItemSeq(Report,ItemSeqID,ItemSN,ItemID) VALUES('PNLR',8,8,(SELECT ItemID FROM tbFinanceItem where ItemName = '(PNLR)Commission Income/Mgt Income'))
A10: ='F101 F21 PNL-New'!A10 -> New | B10: PNLR | C10: ='F101 F21 PNL-New'!C10 -> 9 | D10: ='F101 F21 PNL-New'!E10 -> 9 | E10: =CONCATENATE("(SELECT ItemID FROM tbFinanceItem where ItemName = '",G10,"')") -> (SELECT ItemID FROM tbFinanceItem where ItemName = '(PNLR)Gain/(Loss) Disposal of FA') | F10: ='F101 F21 PNL-New'!H10 -> (PNL)Gain/(Loss) Disposal of FA | G10: =REPLACE(F10,2,3,B10) -> (PNLR)Gain/(Loss) Disposal of FA | H10: =IF(A10<>"Remove",CONCATENATE("INSERT INTO tbFinanceItemSeq(Report,ItemSeqID,ItemSN,ItemID) VALUES('",B10,"',",C10,",",D10,",",E10,")"),"") -> INSERT INTO tbFinanceItemSeq(Report,ItemSeqID,ItemSN,ItemID) VALUES('PNLR',9,9,(SELECT ItemID FROM tbFinanceItem where ItemName = '(PNLR)Gain/(Loss) Disposal of FA'))
A11: ='F101 F21 PNL-New'!A11 -> Exist | B11: PNLR | C11: ='F101 F21 PNL-New'!C11 -> 10 | D11: ='F101 F21 PNL-New'!E11 -> 10 | E11: =CONCATENATE("(SELECT ItemID FROM tbFinanceItem where ItemName = '",G11,"')") -> (SELECT ItemID FROM tbFinanceItem where ItemName = '(PNLR)Other Op Income') | F11: ='F101 F21 PNL-New'!H11 -> (PNL)Other Op Income | G11: =REPLACE(F11,2,3,B11) -> (PNLR)Other Op Income | H11: =IF(A11<>"Remove",CONCATENATE("INSERT INTO tbFinanceItemSeq(Report,ItemSeqID,ItemSN,ItemID) VALUES('",B11,"',",C11,",",D11,",",E11,")"),"") -> INSERT INTO tbFinanceItemSeq(Report,ItemSeqID,ItemSN,ItemID) VALUES('PNLR',10,10,(SELECT ItemID FROM tbFinanceItem where ItemName = '(PNLR)Other Op Income'))
A12: ='F101 F21 PNL-New'!A12 -> Exist | B12: PNLR | C12: ='F101 F21 PNL-New'!C12 -> 11 | D12: ='F101 F21 PNL-New'!E12 -> 11 | E12: =CONCATENATE("(SELECT ItemID FROM tbFinanceItem where ItemName = '",G12,"')") -> (SELECT ItemID FROM tbFinanceItem where ItemName = '(PNLR)Other Op Expense') | F12: ='F101 F21 PNL-New'!H12 -> (PNL)Other Op Expense | G12: =REPLACE(F12,2,3,B12) -> (PNLR)Other Op Expense | H12: =IF(A12<>"Remove",CONCATENATE("INSERT INTO tbFinanceItemSeq(Report,ItemSeqID,ItemSN,ItemID) VALUES('",B12,"',",C12,",",D12,",",E12,")"),"") -> INSERT INTO tbFinanceItemSeq(Report,ItemSeqID,ItemSN,ItemID) VALUES('PNLR',11,11,(SELECT ItemID FROM tbFinanceItem where ItemName = '(PNLR)Other Op Expense'))
A13: ='F101 F21 PNL-New'!A13 -> Exist | B13: PNLR | C13: ='F101 F21 PNL-New'!C13 -> 12 | D13: ='F101 F21 PNL-New'!E13 -> 12 | E13: =CONCATENATE("(SELECT ItemID FROM tbFinanceItem where ItemName = '",G13,"')") -> (SELECT ItemID FROM tbFinanceItem where ItemName = '(PNLR)Total Other Op Income/ (Exp)') | F13: ='F101 F21 PNL-New'!H13 -> (PNL)Total Other Op Income/ (Exp) | G13: =REPLACE(F13,2,3,B13) -> (PNLR)Total Other Op Income/ (Exp) | H13: =IF(A13<>"Remove",CONCATENATE("INSERT INTO tbFinanceItemSeq(Report,ItemSeqID,ItemSN,ItemID) VALUES('",B13,"',",C13,",",D13,",",E13,")"),"") -> INSERT INTO tbFinanceItemSeq(Report,ItemSeqID,ItemSN,ItemID) VALUES('PNLR',12,12,(SELECT ItemID FROM tbFinanceItem where ItemName = '(PNLR)Total Other Op Income/ (Exp)'))
... A73: ='F101 F21 PNL-New'!A73 -> Exist | B73: PNLR | C73: ='F101 F21 PNL-New'!C73 -> 64 | D73: ='F101 F21 PNL-New'!E73 -> 8 | E73: =CONCATENATE("(SELECT ItemID FROM tbFinanceItem where ItemName = '",G73,"')") -> (SELECT ItemID FROM tbFinanceItem where ItemName = 'PPNLRit After Taxation %') | F73: ='F101 F21 PNL-New'!H73 -> Profit After Taxation % | G73: =REPLACE(F73,2,3,B73) -> PPNLRit After Taxation % | H73: =IF(A73<>"Remove",CONCATENATE("INSERT INTO tbFinanceItemSeq(Report,ItemSeqID,ItemSN,ItemID) VALUES('",B73,"',",C73,",",D73,",",E73,")"),"") -> INSERT INTO tbFinanceItemSeq(Report,ItemSeqID,ItemSN,ItemID) VALUES('PNLR',64,8,(SELECT ItemID FROM tbFinanceItem where ItemName = 'PPNLRit After Taxation %'))

Sheet F102 F22 PNLS-Debug
A1: DELETE FROM tbFinanceItemSeq where Report = 'PNLS'
A3: SELECT TOP 10 * FROM tbReport where ReportID = 428;
A4: F102 Profit & Loss Account By Month.rpt
A5: procReportFinancePNLByMonth
A8: select s.* , i.ItemName from tbFinanceItemSeq s
A9: LEFT JOIN tbFinanceItem i on s.ItemID = i.ItemID
A10: where s.Report = 'PNLS'
A11: order by s.ItemSeqID
A13: SELECT TOP 10 * FROM tbReport where ReportID = 426;
A14: -- F101S Profit & Loss Account.rpt
A18: Update tbReport
A19: set FileName = 'F102 Profit & Loss Account By Month.rpt' ,
... A21: where ReportID = 428;

Sheet F102 F22 PNLS-Origin
A1: Report | B1: ItemSeqID | C1: ItemSN | D1: ItemID | E1: ItemName | F1: Insert Script
A2: PNLS | B2: 1 | C2: 1 | D2: 1081 | E2: (PNL)External Sales | F2: =CONCATENATE("INSERT INTO tbFinanceItemSeq(Report,ItemSeqID,ItemSN,ItemID) VALUES('",A2,"',",B2,",",C2,",",D2,")") -> INSERT INTO tbFinanceItemSeq(Report,ItemSeqID,ItemSN,ItemID) VALUES('PNLS',1,1,1081)
A3: PNLS | B3: 2 | C3: 2 | D3: 1082 | E3: (PNL)Interco Sales | F3: =CONCATENATE("INSERT INTO tbFinanceItemSeq(Report,ItemSeqID,ItemSN,ItemID) VALUES('",A3,"',",B3,",",C3,",",D3,")") -> INSERT INTO tbFinanceItemSeq(Report,ItemSeqID,ItemSN,ItemID) VALUES('PNLS',2,2,1082)
A4: PNLS | B4: 3 | C4: 3 | D4: 1083 | E4: (PNL)Total Sales | F4: =CONCATENATE("INSERT INTO tbFinanceItemSeq(Report,ItemSeqID,ItemSN,ItemID) VALUES('",A4,"',",B4,",",C4,",",D4,")") -> INSERT INTO tbFinanceItemSeq(Report,ItemSeqID,ItemSN,ItemID) VALUES('PNLS',3,3,1083)
A5: PNLS | B5: 4 | C5: 4 | D5: 1084 | E5: (PNL)Cost of External Sales | F5: =CONCATENATE("INSERT INTO tbFinanceItemSeq(Report,ItemSeqID,ItemSN,ItemID) VALUES('",A5,"',",B5,",",C5,",",D5,")") -> INSERT INTO tbFinanceItemSeq(Report,ItemSeqID,ItemSN,ItemID) VALUES('PNLS',4,4,1084)
A6: PNLS | B6: 5 | C6: 5 | D6: 1085 | E6: (PNL)Cost of Interco Sales | F6: =CONCATENATE("INSERT INTO tbFinanceItemSeq(Report,ItemSeqID,ItemSN,ItemID) VALUES('",A6,"',",B6,",",C6,",",D6,")") -> INSERT INTO tbFinanceItemSeq(Report,ItemSeqID,ItemSN,ItemID) VALUES('PNLS',5,5,1085)
A7: PNLS | B7: 6 | C7: 6 | D7: 1086 | E7: (PNL)Total Cost of Sales | F7: =CONCATENATE("INSERT INTO tbFinanceItemSeq(Report,ItemSeqID,ItemSN,ItemID) VALUES('",A7,"',",B7,",",C7,",",D7,")") -> INSERT INTO tbFinanceItemSeq(Report,ItemSeqID,ItemSN,ItemID) VALUES('PNLS',6,6,1086)
A8: PNLS | B8: 7 | C8: 7 | D8: 1087 | E8: (PNL)Gross Profit | F8: =CONCATENATE("INSERT INTO tbFinanceItemSeq(Report,ItemSeqID,ItemSN,ItemID) VALUES('",A8,"',",B8,",",C8,",",D8,")") -> INSERT INTO tbFinanceItemSeq(Report,ItemSeqID,ItemSN,ItemID) VALUES('PNLS',7,7,1087)
A9: PNLS | B9: 8 | C9: 8 | D9: 1088 | E9: (PNL)Commission Income/Mgt Income | F9: =CONCATENATE("INSERT INTO tbFinanceItemSeq(Report,ItemSeqID,ItemSN,ItemID) VALUES('",A9,"',",B9,",",C9,",",D9,")") -> INSERT INTO tbFinanceItemSeq(Report,ItemSeqID,ItemSN,ItemID) VALUES('PNLS',8,8,1088)
A10: PNLS | B10: 9 | C10: 9 | D10: 1089 | E10: (PNL)Other Op Income | F10: =CONCATENATE("INSERT INTO tbFinanceItemSeq(Report,ItemSeqID,ItemSN,ItemID) VALUES('",A10,"',",B10,",",C10,",",D10,")") -> INSERT INTO tbFinanceItemSeq(Report,ItemSeqID,ItemSN,ItemID) VALUES('PNLS',9,9,1089)
A11: PNLS | B11: 10 | C11: 10 | D11: 1090 | E11: (PNL)Other Op Expense | F11: =CONCATENATE("INSERT INTO tbFinanceItemSeq(Report,ItemSeqID,ItemSN,ItemID) VALUES('",A11,"',",B11,",",C11,",",D11,")") -> INSERT INTO tbFinanceItemSeq(Report,ItemSeqID,ItemSN,ItemID) VALUES('PNLS',10,10,1090)
A12: PNLS | B12: 11 | C12: 11 | D12: 1091 | E12: (PNL)Total Other Op Income/ (Exp) | F12: =CONCATENATE("INSERT INTO tbFinanceItemSeq(Report,ItemSeqID,ItemSN,ItemID) VALUES('",A12,"',",B12,",",C12,",",D12,")") -> INSERT INTO tbFinanceItemSeq(Report,ItemSeqID,ItemSN,ItemID) VALUES('PNLS',11,11,1091)
A13: PNLS | B13: 12 | C13: 12 | D13: 1102 | E13: (PNL)Total S&D Expenses | F13: =CONCATENATE("INSERT INTO tbFinanceItemSeq(Report,ItemSeqID,ItemSN,ItemID) VALUES('",A13,"',",B13,",",C13,",",D13,")") -> INSERT INTO tbFinanceItemSeq(Report,ItemSeqID,ItemSN,ItemID) VALUES('PNLS',12,12,1102)
... A30: PNLS | B30: 29 | C30: 1 | D30: 1135 | E30: Gross Profits Margin % | F30: =CONCATENATE("INSERT INTO tbFinanceItemSeq(Report,ItemSeqID,ItemSN,ItemID) VALUES('",A30,"',",B30,",",C30,",",D30,")") -> INSERT INTO tbFinanceItemSeq(Report,ItemSeqID,ItemSN,ItemID) VALUES('PNLS',29,1,1135)
A31: PNLS | B31: 30 | C31: 2 | D31: 1136 | E31: =- External Sales GP % -> #NAME? | F31: =CONCATENATE("INSERT INTO tbFinanceItemSeq(Report,ItemSeqID,ItemSN,ItemID) VALUES('",A31,"',",B31,",",C31,",",D31,")") -> INSERT INTO tbFinanceItemSeq(Report,ItemSeqID,ItemSN,ItemID) VALUES('PNLS',30,2,1136)
A32: PNLS | B32: 31 | C32: 3 | D32: 1137 | E32: =- Interco Sales GP % -> #NAME? | F32: =CONCATENATE("INSERT INTO tbFinanceItemSeq(Report,ItemSeqID,ItemSN,ItemID) VALUES('",A32,"',",B32,",",C32,",",D32,")") -> INSERT INTO tbFinanceItemSeq(Report,ItemSeqID,ItemSN,ItemID) VALUES('PNLS',31,3,1137)
A33: PNLS | B33: 32 | C33: 4 | D33: 50 | E33: Selling & Dist Margin % | F33: =CONCATENATE("INSERT INTO tbFinanceItemSeq(Report,ItemSeqID,ItemSN,ItemID) VALUES('",A33,"',",B33,",",C33,",",D33,")") -> INSERT INTO tbFinanceItemSeq(Report,ItemSeqID,ItemSN,ItemID) VALUES('PNLS',32,4,50)
A34: PNLS | B34: 33 | C34: 5 | D34: 1138 | E34: A&G Margin Direct % | F34: =CONCATENATE("INSERT INTO tbFinanceItemSeq(Report,ItemSeqID,ItemSN,ItemID) VALUES('",A34,"',",B34,",",C34,",",D34,")") -> INSERT INTO tbFinanceItemSeq(Report,ItemSeqID,ItemSN,ItemID) VALUES('PNLS',33,5,1138)
A35: PNLS | B35: 34 | C35: 6 | D35: 1139 | E35: A&G Margin Total % | F35: =CONCATENATE("INSERT INTO tbFinanceItemSeq(Report,ItemSeqID,ItemSN,ItemID) VALUES('",A35,"',",B35,",",C35,",",D35,")") -> INSERT INTO tbFinanceItemSeq(Report,ItemSeqID,ItemSN,ItemID) VALUES('PNLS',34,6,1139)
A36: PNLS | B36: 35 | C36: 7 | D36: 53 | E36: Operating Profit Margin % | F36: =CONCATENATE("INSERT INTO tbFinanceItemSeq(Report,ItemSeqID,ItemSN,ItemID) VALUES('",A36,"',",B36,",",C36,",",D36,")") -> INSERT INTO tbFinanceItemSeq(Report,ItemSeqID,ItemSN,ItemID) VALUES('PNLS',35,7,53)
A37: PNLS | B37: 36 | C37: 8 | D37: 52 | E37: Profit Before Taxation % | F37: =CONCATENATE("INSERT INTO tbFinanceItemSeq(Report,ItemSeqID,ItemSN,ItemID) VALUES('",A37,"',",B37,",",C37,",",D37,")") -> INSERT INTO tbFinanceItemSeq(Report,ItemSeqID,ItemSN,ItemID) VALUES('PNLS',36,8,52)
A38: PNLS | B38: 37 | C38: 9 | D38: 1140 | E38: Profit After Taxation % | F38: =CONCATENATE("INSERT INTO tbFinanceItemSeq(Report,ItemSeqID,ItemSN,ItemID) VALUES('",A38,"',",B38,",",C38,",",D38,")") -> INSERT INTO tbFinanceItemSeq(Report,ItemSeqID,ItemSN,ItemID) VALUES('PNLS',37,9,1140)

Sheet F102 F22 PNLS-NEW
A1: Status | B1: Report | C1: New - ItemSeqID | D1: ItemSeqID | E1: New - ItemSN | F1: ItemSN | G1: ItemID | H1: ItemName | I1: Insert Script
A2: Exist | B2: PNLS | C2: =D2 -> 1 | D2: 1 | E2: =F2 -> 1 | F2: 1 | G2: 1081 | H2: (PNL)External Sales | I2: =IF(A2<>"Remove",CONCATENATE("INSERT INTO tbFinanceItemSeq(Report,ItemSeqID,ItemSN,ItemID) VALUES('",B2,"',",C2,",",E2,",",G2,")"),"") -> INSERT INTO tbFinanceItemSeq(Report,ItemSeqID,ItemSN,ItemID) VALUES('PNLS',1,1,1081)
A3: Exist | B3: PNLS | C3: =D3 -> 2 | D3: 2 | E3: =F3 -> 2 | F3: 2 | G3: 1082 | H3: (PNL)Interco Sales | I3: =IF(A3<>"Remove",CONCATENATE("INSERT INTO tbFinanceItemSeq(Report,ItemSeqID,ItemSN,ItemID) VALUES('",B3,"',",C3,",",E3,",",G3,")"),"") -> INSERT INTO tbFinanceItemSeq(Report,ItemSeqID,ItemSN,ItemID) VALUES('PNLS',2,2,1082)
A4: Exist | B4: PNLS | C4: =D4 -> 3 | D4: 3 | E4: =F4 -> 3 | F4: 3 | G4: 1083 | H4: (PNL)Total Sales | I4: =IF(A4<>"Remove",CONCATENATE("INSERT INTO tbFinanceItemSeq(Report,ItemSeqID,ItemSN,ItemID) VALUES('",B4,"',",C4,",",E4,",",G4,")"),"") -> INSERT INTO tbFinanceItemSeq(Report,ItemSeqID,ItemSN,ItemID) VALUES('PNLS',3,3,1083)
A5: Exist | B5: PNLS | C5: =D5 -> 4 | D5: 4 | E5: =F5 -> 4 | F5: 4 | G5: 1084 | H5: (PNL)Cost of External Sales | I5: =IF(A5<>"Remove",CONCATENATE("INSERT INTO tbFinanceItemSeq(Report,ItemSeqID,ItemSN,ItemID) VALUES('",B5,"',",C5,",",E5,",",G5,")"),"") -> INSERT INTO tbFinanceItemSeq(Report,ItemSeqID,ItemSN,ItemID) VALUES('PNLS',4,4,1084)
A6: Exist | B6: PNLS | C6: =D6 -> 5 | D6: 5 | E6: =F6 -> 5 | F6: 5 | G6: 1085 | H6: (PNL)Cost of Interco Sales | I6: =IF(A6<>"Remove",CONCATENATE("INSERT INTO tbFinanceItemSeq(Report,ItemSeqID,ItemSN,ItemID) VALUES('",B6,"',",C6,",",E6,",",G6,")"),"") -> INSERT INTO tbFinanceItemSeq(Report,ItemSeqID,ItemSN,ItemID) VALUES('PNLS',5,5,1085)
A7: Exist | B7: PNLS | C7: =D7 -> 6 | D7: 6 | E7: =F7 -> 6 | F7: 6 | G7: 1086 | H7: (PNL)Total Cost of Sales | I7: =IF(A7<>"Remove",CONCATENATE("INSERT INTO tbFinanceItemSeq(Report,ItemSeqID,ItemSN,ItemID) VALUES('",B7,"',",C7,",",E7,",",G7,")"),"") -> INSERT INTO tbFinanceItemSeq(Report,ItemSeqID,ItemSN,ItemID) VALUES('PNLS',6,6,1086)
A8: Exist | B8: PNLS | C8: =D8 -> 7 | D8: 7 | E8: =F8 -> 7 | F8: 7 | G8: 1087 | H8: (PNL)Gross Profit | I8: =IF(A8<>"Remove",CONCATENATE("INSERT INTO tbFinanceItemSeq(Report,ItemSeqID,ItemSN,ItemID) VALUES('",B8,"',",C8,",",E8,",",G8,")"),"") -> INSERT INTO tbFinanceItemSeq(Report,ItemSeqID,ItemSN,ItemID) VALUES('PNLS',7,7,1087)
A9: Exist | B9: PNLS | C9: =D9 -> 8 | D9: 8 | E9: =F9 -> 8 | F9: 8 | G9: 1088 | H9: (PNL)Commission Income/Mgt Income | I9: =IF(A9<>"Remove",CONCATENATE("INSERT INTO tbFinanceItemSeq(Report,ItemSeqID,ItemSN,ItemID) VALUES('",B9,"',",C9,",",E9,",",G9,")"),"") -> INSERT INTO tbFinanceItemSeq(Report,ItemSeqID,ItemSN,ItemID) VALUES('PNLS',8,8,1088)
A10: New | B10: PNLS | C10: 9 | E10: 9 | G10: 1126 | H10: (PNL)Gain/(Loss) Disposal of FA | I10: =IF(A10<>"Remove",CONCATENATE("INSERT INTO tbFinanceItemSeq(Report,ItemSeqID,ItemSN,ItemID) VALUES('",B10,"',",C10,",",E10,",",G10,")"),"") -> INSERT INTO tbFinanceItemSeq(Report,ItemSeqID,ItemSN,ItemID) VALUES('PNLS',9,9,1126)
A11: Exist | B11: PNLS | C11: =D11+1 -> 10 | D11: 9 | E11: =F11+1 -> 10 | F11: 9 | G11: 1089 | H11: (PNL)Other Op Income | I11: =IF(A11<>"Remove",CONCATENATE("INSERT INTO tbFinanceItemSeq(Report,ItemSeqID,ItemSN,ItemID) VALUES('",B11,"',",C11,",",E11,",",G11,")"),"") -> INSERT INTO tbFinanceItemSeq(Report,ItemSeqID,ItemSN,ItemID) VALUES('PNLS',10,10,1089)
A12: Exist | B12: PNLS | C12: =D12+1 -> 11 | D12: 10 | E12: =F12+1 -> 11 | F12: 10 | G12: 1090 | H12: (PNL)Other Op Expense | I12: =IF(A12<>"Remove",CONCATENATE("INSERT INTO tbFinanceItemSeq(Report,ItemSeqID,ItemSN,ItemID) VALUES('",B12,"',",C12,",",E12,",",G12,")"),"") -> INSERT INTO tbFinanceItemSeq(Report,ItemSeqID,ItemSN,ItemID) VALUES('PNLS',11,11,1090)
A13: Exist | B13: PNLS | C13: =D13+1 -> 12 | D13: 11 | E13: =F13+1 -> 12 | F13: 11 | G13: 1091 | H13: (PNL)Total Other Op Income/ (Exp) | I13: =IF(A13<>"Remove",CONCATENATE("INSERT INTO tbFinanceItemSeq(Report,ItemSeqID,ItemSN,ItemID) VALUES('",B13,"',",C13,",",E13,",",G13,")"),"") -> INSERT INTO tbFinanceItemSeq(Report,ItemSeqID,ItemSN,ItemID) VALUES('PNLS',12,12,1091)
A14: New | B14: PNLS | C14: 13 | E14: 13 | G14: =CONCATENATE("(SELECT TOP 1 ItemID FROM tbFinanceItem where ItemName = '",H14,"')") -> (SELECT TOP 1 ItemID FROM tbFinanceItem where ItemName = '(PNL)Selling & Distribution') | H14: (PNL)Selling & Distribution | I14: =IF(A14<>"Remove",CONCATENATE("INSERT INTO tbFinanceItemSeq(Report,ItemSeqID,ItemSN,ItemID) VALUES('",B14,"',",C14,",",E14,",",G14,")"),"") -> INSERT INTO tbFinanceItemSeq(Report,ItemSeqID,ItemSN,ItemID) VALUES('PNLS',13,13,(SELECT TOP 1 ItemID FROM tbFinanceItem where ItemName = '(PNL)Selling & Distribution'))
A15: Remove | B15: PNLS | C15: =D15+1 -> 13 | D15: 12 | E15: =F15+1 -> 13 | F15: 12 | G15: 1102 | H15: (PNL)Total S&D Expenses | I15: =IF(A15<>"Remove",CONCATENATE("INSERT INTO tbFinanceItemSeq(Report,ItemSeqID,ItemSN,ItemID) VALUES('",B15,"',",C15,",",E15,",",G15,")"),"")
A16: Exist | B16: PNLS | C16: =D16+1 -> 14 | D16: 13 | E16: =F16+1 -> 14 | F16: 13 | G16: 1112 | H16: (PNL)A&G Direct Expenses | I16: =IF(A16<>"Remove",CONCATENATE("INSERT INTO tbFinanceItemSeq(Report,ItemSeqID,ItemSN,ItemID) VALUES('",B16,"',",C16,",",E16,",",G16,")"),"") -> INSERT INTO tbFinanceItemSeq(Report,ItemSeqID,ItemSN,ItemID) VALUES('PNLS',14,14,1112)
A17: Exist | B17: PNLS | C17: =D17+1 -> 15 | D17: 14 | E17: =F17+1 -> 15 | F17: 14 | G17: 1118 | H17: (PNL)A&G Other Expenses | I17: =IF(A17<>"Remove",CONCATENATE("INSERT INTO tbFinanceItemSeq(Report,ItemSeqID,ItemSN,ItemID) VALUES('",B17,"',",C17,",",E17,",",G17,")"),"") -> INSERT INTO tbFinanceItemSeq(Report,ItemSeqID,ItemSN,ItemID) VALUES('PNLS',15,15,1118)
A18: Exist | B18: PNLS | C18: =D18+1 -> 16 | D18: 15 | E18: =F18+1 -> 16 | F18: 15 | G18: 1120 | H18: (PNL)Profit from Operations | I18: =IF(A18<>"Remove",CONCATENATE("INSERT INTO tbFinanceItemSeq(Report,ItemSeqID,ItemSN,ItemID) VALUES('",B18,"',",C18,",",E18,",",G18,")"),"") -> INSERT INTO tbFinanceItemSeq(Report,ItemSeqID,ItemSN,ItemID) VALUES('PNLS',16,16,1120)
A19: Exist | B19: PNLS | C19: =D19+1 -> 17 | D19: 16 | E19: =F19+1 -> 17 | F19: 16 | G19: 1121 | H19: (PNL)Interest Income | I19: =IF(A19<>"Remove",CONCATENATE("INSERT INTO tbFinanceItemSeq(Report,ItemSeqID,ItemSN,ItemID) VALUES('",B19,"',",C19,",",E19,",",G19,")"),"") -> INSERT INTO tbFinanceItemSeq(Report,ItemSeqID,ItemSN,ItemID) VALUES('PNLS',17,17,1121)
A20: Exist | B20: PNLS | C20: =D20+1 -> 18 | D20: 17 | E20: =F20+1 -> 18 | F20: 17 | G20: 1122 | H20: (PNL)Interest Expense | I20: =IF(A20<>"Remove",CONCATENATE("INSERT INTO tbFinanceItemSeq(Report,ItemSeqID,ItemSN,ItemID) VALUES('",B20,"',",C20,",",E20,",",G20,")"),"") -> INSERT INTO tbFinanceItemSeq(Report,ItemSeqID,ItemSN,ItemID) VALUES('PNLS',18,18,1122)
A21: New | B21: PNLS | C21: 19 | E21: 19 | G21: =CONCATENATE("(SELECT ItemID FROM tbFinanceItem where ItemName = '",H21,"')") -> (SELECT ItemID FROM tbFinanceItem where ItemName = '(PNL)Derivatives Gain/(Loss)') | H21: (PNL)Derivatives Gain/(Loss) | I21: =IF(A21<>"Remove",CONCATENATE("INSERT INTO tbFinanceItemSeq(Report,ItemSeqID,ItemSN,ItemID) VALUES('",B21,"',",C21,",",E21,",",G21,")"),"") -> INSERT INTO tbFinanceItemSeq(Report,ItemSeqID,ItemSN,ItemID) VALUES('PNLS',19,19,(SELECT ItemID FROM tbFinanceItem where ItemName = '(PNL)Derivatives Gain/(Loss)'))
A22: New | B22: PNLS | C22: 20 | E22: 20 | G22: =CONCATENATE("(SELECT ItemID FROM tbFinanceItem where ItemName = '",H22,"')") -> (SELECT ItemID FROM tbFinanceItem where ItemName = '(PNL)Forex Gain/(Loss)') | H22: (PNL)Forex Gain/(Loss) | I22: =IF(A22<>"Remove",CONCATENATE("INSERT INTO tbFinanceItemSeq(Report,ItemSeqID,ItemSN,ItemID) VALUES('",B22,"',",C22,",",E22,",",G22,")"),"") -> INSERT INTO tbFinanceItemSeq(Report,ItemSeqID,ItemSN,ItemID) VALUES('PNLS',20,20,(SELECT ItemID FROM tbFinanceItem where ItemName = '(PNL)Forex Gain/(Loss)'))
A23: Remove | B23: PNLS | C23: =D23+1 -> 19 | D23: 18 | E23: =F23+1 -> 19 | F23: 18 | G23: 1123 | H23: (PNL)Realised Forex Gain/(Loss) | I23: =IF(A23<>"Remove",CONCATENATE("INSERT INTO tbFinanceItemSeq(Report,ItemSeqID,ItemSN,ItemID) VALUES('",B23,"',",C23,",",E23,",",G23,")"),"")
A24: Remove | B24: PNLS | C24: =D24+1 -> 20 | D24: 19 | E24: =F24+1 -> 20 | F24: 19 | G24: 1124 | H24: (PNL)Unrealised Forex Gain/(Loss) | I24: =IF(A24<>"Remove",CONCATENATE("INSERT INTO tbFinanceItemSeq(Report,ItemSeqID,ItemSN,ItemID) VALUES('",B24,"',",C24,",",E24,",",G24,")"),"")
A25: Exist | B25: PNLS | C25: =D25+1 -> 21 | D25: 20 | E25: =F25+1 -> 21 | F25: 20 | G25: 1125 | H25: (PNL)Dividend Income | I25: =IF(A25<>"Remove",CONCATENATE("INSERT INTO tbFinanceItemSeq(Report,ItemSeqID,ItemSN,ItemID) VALUES('",B25,"',",C25,",",E25,",",G25,")"),"") -> INSERT INTO tbFinanceItemSeq(Report,ItemSeqID,ItemSN,ItemID) VALUES('PNLS',21,21,1125)
A26: Remove | B26: PNLS | C26: =D26+1 -> 22 | D26: 21 | E26: =F26+1 -> 22 | F26: 21 | G26: 1126 | H26: (PNL)Gain/(Loss) Disposal of FA | I26: =IF(A26<>"Remove",CONCATENATE("INSERT INTO tbFinanceItemSeq(Report,ItemSeqID,ItemSN,ItemID) VALUES('",B26,"',",C26,",",E26,",",G26,")"),"")
A27: Exist | B27: PNLS | C27: =D27 -> 22 | D27: 22 | E27: =F27 -> 22 | F27: 22 | G27: 1127 | H27: (PNL)Other Non-Op Income/(Exp) | I27: =IF(A27<>"Remove",CONCATENATE("INSERT INTO tbFinanceItemSeq(Report,ItemSeqID,ItemSN,ItemID) VALUES('",B27,"',",C27,",",E27,",",G27,")"),"") -> INSERT INTO tbFinanceItemSeq(Report,ItemSeqID,ItemSN,ItemID) VALUES('PNLS',22,22,1127)
A28: Exist | B28: PNLS | C28: =D28 -> 23 | D28: 23 | E28: =F28 -> 23 | F28: 23 | G28: 1128 | H28: (PNL)Total Non-Op Income/(Exp) | I28: =IF(A28<>"Remove",CONCATENATE("INSERT INTO tbFinanceItemSeq(Report,ItemSeqID,ItemSN,ItemID) VALUES('",B28,"',",C28,",",E28,",",G28,")"),"") -> INSERT INTO tbFinanceItemSeq(Report,ItemSeqID,ItemSN,ItemID) VALUES('PNLS',23,23,1128)
A29: Exist | B29: PNLS | C29: =D29 -> 24 | D29: 24 | E29: =F29 -> 24 | F29: 24 | G29: 1129 | H29: (PNL)Profit Before Taxation | I29: =IF(A29<>"Remove",CONCATENATE("INSERT INTO tbFinanceItemSeq(Report,ItemSeqID,ItemSN,ItemID) VALUES('",B29,"',",C29,",",E29,",",G29,")"),"") -> INSERT INTO tbFinanceItemSeq(Report,ItemSeqID,ItemSN,ItemID) VALUES('PNLS',24,24,1129)
A30: Exist | B30: PNLS | C30: =D30 -> 25 | D30: 25 | E30: =F30 -> 25 | F30: 25 | G30: 1130 | H30: (PNL)Less: Taxation | I30: =IF(A30<>"Remove",CONCATENATE("INSERT INTO tbFinanceItemSeq(Report,ItemSeqID,ItemSN,ItemID) VALUES('",B30,"',",C30,",",E30,",",G30,")"),"") -> INSERT INTO tbFinanceItemSeq(Report,ItemSeqID,ItemSN,ItemID) VALUES('PNLS',25,25,1130)
A31: Remove | B31: PNLS | C31: =D31 -> 26 | D31: 26 | E31: =F31 -> 26 | F31: 26 | G31: 1131 | H31: (PNL)Profit After Taxation | I31: =IF(A31<>"Remove",CONCATENATE("INSERT INTO tbFinanceItemSeq(Report,ItemSeqID,ItemSN,ItemID) VALUES('",B31,"',",C31,",",E31,",",G31,")"),"")
A32: New | B32: PNLS | C32: =D32 -> 26 | D32: 26 | E32: =F32 -> 26 | F32: 26 | G32: 1131 | H32: (PNL)Profits After Taxation | I32: =IF(A32<>"Remove",CONCATENATE("INSERT INTO tbFinanceItemSeq(Report,ItemSeqID,ItemSN,ItemID) VALUES('",B32,"',",C32,",",E32,",",G32,")"),"") -> INSERT INTO tbFinanceItemSeq(Report,ItemSeqID,ItemSN,ItemID) VALUES('PNLS',26,26,1131)
A33: Exist | B33: PNLS | C33: =D33 -> 27 | D33: 27 | E33: =F33 -> 27 | F33: 27 | G33: 1474 | H33: (PNL)Dividend Expenses | I33: =IF(A33<>"Remove",CONCATENATE("INSERT INTO tbFinanceItemSeq(Report,ItemSeqID,ItemSN,ItemID) VALUES('",B33,"',",C33,",",E33,",",G33,")"),"") -> INSERT INTO tbFinanceItemSeq(Report,ItemSeqID,ItemSN,ItemID) VALUES('PNLS',27,27,1474)
A34: Exist | B34: PNLS | C34: =D34 -> 28 | D34: 28 | E34: =F34 -> 0 | F34: 0 | G34: 46 | H34: Performance Indicators | I34: =IF(A34<>"Remove",CONCATENATE("INSERT INTO tbFinanceItemSeq(Report,ItemSeqID,ItemSN,ItemID) VALUES('",B34,"',",C34,",",E34,",",G34,")"),"") -> INSERT INTO tbFinanceItemSeq(Report,ItemSeqID,ItemSN,ItemID) VALUES('PNLS',28,0,46)
A35: Exist | B35: PNLS | C35: =D35 -> 29 | D35: 29 | E35: =F35 -> 1 | F35: 1 | G35: 1135 | H35: Gross Profits Margin % | I35: =IF(A35<>"Remove",CONCATENATE("INSERT INTO tbFinanceItemSeq(Report,ItemSeqID,ItemSN,ItemID) VALUES('",B35,"',",C35,",",E35,",",G35,")"),"") -> INSERT INTO tbFinanceItemSeq(Report,ItemSeqID,ItemSN,ItemID) VALUES('PNLS',29,1,1135)
A36: Exist | B36: PNLS | C36: =D36 -> 30 | D36: 30 | E36: =F36 -> 2 | F36: 2 | G36: 1136 | H36: - External Sales GP % | I36: =IF(A36<>"Remove",CONCATENATE("INSERT INTO tbFinanceItemSeq(Report,ItemSeqID,ItemSN,ItemID) VALUES('",B36,"',",C36,",",E36,",",G36,")"),"") -> INSERT INTO tbFinanceItemSeq(Report,ItemSeqID,ItemSN,ItemID) VALUES('PNLS',30,2,1136)
A37: Exist | B37: PNLS | C37: =D37 -> 31 | D37: 31 | E37: =F37 -> 3 | F37: 3 | G37: 1137 | H37: - Interco Sales GP % | I37: =IF(A37<>"Remove",CONCATENATE("INSERT INTO tbFinanceItemSeq(Report,ItemSeqID,ItemSN,ItemID) VALUES('",B37,"',",C37,",",E37,",",G37,")"),"") -> INSERT INTO tbFinanceItemSeq(Report,ItemSeqID,ItemSN,ItemID) VALUES('PNLS',31,3,1137)
A38: Exist | B38: PNLS | C38: =D38 -> 32 | D38: 32 | E38: =F38 -> 4 | F38: 4 | G38: 50 | H38: Selling & Dist Margin % | I38: =IF(A38<>"Remove",CONCATENATE("INSERT INTO tbFinanceItemSeq(Report,ItemSeqID,ItemSN,ItemID) VALUES('",B38,"',",C38,",",E38,",",G38,")"),"") -> INSERT INTO tbFinanceItemSeq(Report,ItemSeqID,ItemSN,ItemID) VALUES('PNLS',32,4,50)
A39: Remove | B39: PNLS | C39: =D39 -> 33 | D39: 33 | E39: =F39 -> 5 | F39: 5 | G39: 1138 | H39: A&G Margin Direct % | I39: =IF(A39<>"Remove",CONCATENATE("INSERT INTO tbFinanceItemSeq(Report,ItemSeqID,ItemSN,ItemID) VALUES('",B39,"',",C39,",",E39,",",G39,")"),"")
A40: Exist | B40: PNLS | C40: 33 | D40: 34 | E40: 5 | F40: 6 | G40: 1139 | H40: A&G Margin Total % | I40: =IF(A40<>"Remove",CONCATENATE("INSERT INTO tbFinanceItemSeq(Report,ItemSeqID,ItemSN,ItemID) VALUES('",B40,"',",C40,",",E40,",",G40,")"),"") -> INSERT INTO tbFinanceItemSeq(Report,ItemSeqID,ItemSN,ItemID) VALUES('PNLS',33,5,1139)
A41: Exist | B41: PNLS | C41: 34 | D41: 35 | E41: 6 | F41: 7 | G41: 53 | H41: Operating Profit Margin % | I41: =IF(A41<>"Remove",CONCATENATE("INSERT INTO tbFinanceItemSeq(Report,ItemSeqID,ItemSN,ItemID) VALUES('",B41,"',",C41,",",E41,",",G41,")"),"") -> INSERT INTO tbFinanceItemSeq(Report,ItemSeqID,ItemSN,ItemID) VALUES('PNLS',34,6,53)
A42: Exist | B42: PNLS | C42: 35 | D42: 36 | E42: 7 | F42: 8 | G42: 52 | H42: Profit Before Taxation % | I42: =IF(A42<>"Remove",CONCATENATE("INSERT INTO tbFinanceItemSeq(Report,ItemSeqID,ItemSN,ItemID) VALUES('",B42,"',",C42,",",E42,",",G42,")"),"") -> INSERT INTO tbFinanceItemSeq(Report,ItemSeqID,ItemSN,ItemID) VALUES('PNLS',35,7,52)
A43: Exist | B43: PNLS | C43: 36 | D43: 37 | E43: 8 | F43: 9 | G43: 1140 | H43: Profit After Taxation % | I43: =IF(A43<>"Remove",CONCATENATE("INSERT INTO tbFinanceItemSeq(Report,ItemSeqID,ItemSN,ItemID) VALUES('",B43,"',",C43,",",E43,",",G43,")"),"") -> INSERT INTO tbFinanceItemSeq(Report,ItemSeqID,ItemSN,ItemID) VALUES('PNLS',36,8,1140)

Sheet F121 F24 Debug
A1: SELECT TOP 10 * FROM tbReport where ReportID = 433;
A2: --F121 Manufacturing Account.rpt
A3: --procReportFinanceMA
A4: --(BS)
A6: select s.* , i.ItemName from tbFinanceItemSeq s
A7: LEFT JOIN tbFinanceItem i on s.ItemID = i.ItemID
A8: where s.Report = 'MA'
A9: order by s.ItemSeqID
A12: DELETE FROM tbFinanceItemSeq where Report = 'MA'
A14: Update tbReport
A15: set FileName = 'F121 Manufacturing Account.rpt' ,
A16: Description = '[COA2016] F24 Manufacturing Account'
A17: where ReportID =433;

Sheet F121 F24 Origin
A1: Report | B1: ItemSeqID | C1: ItemSN | D1: ItemID | E1: ItemName
A2: MA | B2: 1 | C2: 1 | D2: 1280 | E2: (MA)Planned Production (M3 / KG)
A3: MA | B3: 2 | C3: 2 | D3: 1281 | E3: (MA)Actual Production (M3 / KG)
A4: MA | B4: 3 | C4: 3 | D4: 1282 | E4: (MA)Variance (M3 / KG)
A5: MA | B5: 4 | C5: 4 | D5: 1283 | E5: (MA)Manufacturing Costs
A6: MA | B6: 5 | C6: 5 | D6: 1284 | E6: (MA)DM-Raw Materials
A7: MA | B7: 6 | C7: 6 | D7: 1285 | E7: (MA)DM-Parts & Access
A8: MA | B8: 7 | C8: 7 | D8: 1286 | E8: (MA)DM-Packing & Label Materials
A9: MA | B9: 8 | C9: 8 | D9: 1287 | E9: (MA)DM-Others
A10: MA | B10: 9 | C10: 9 | D10: 1288 | E10: (MA)Direct Material
A11: MA | B11: 10 | C11: 10 | D11: 1289 | E11: (MA)DL-Salary & Leave
A12: MA | B12: 11 | C12: 11 | D12: 1290 | E12: (MA)DL-Bonus
A13: MA | B13: 12 | C13: 12 | D13: 1291 | E13: (MA)DL-Foreign Workers/Casual/Temp
... A65: MA | B65: 64 | C65: 9 | D65: 1342 | E65: (MA)Manufacturing Costs (m3/ Kg)

Sheet F121 F24 Dif
A1: Old | B1: New | C1: Diff | D1: Is Exist Name | E1: Is Exist | F1: Is New | G1: Is Remove | H1: Remark
A2: Planned Production (M3 / KG) | C2: =EXACT(A2,B2) -> FALSE | D2: =VLOOKUP(B2, A2:A336, 1, FALSE) -> #N/A | E2: =IF((AND(EXACT(C2,"TRUE"),_xlfn.IFNA(D2,"NA")<>"NA")),"Exist","") | F2: =IF((AND(EXACT(C2,"FALSE"),_xlfn.IFNA(D2,"NA")="NA")),"New","") -> New | G2: =IF((AND(ISBLANK(B2),EXACT(C2,"FALSE"))),"Remove","") -> Remove
A3: Actual Production (M3 / KG) | C3: =EXACT(A3,B3) -> FALSE | D3: =VLOOKUP(B3, A3:A337, 1, FALSE) -> #N/A | E3: =IF((AND(EXACT(C3,"TRUE"),_xlfn.IFNA(D3,"NA")<>"NA")),"Exist","") | F3: =IF((AND(EXACT(C3,"FALSE"),_xlfn.IFNA(D3,"NA")="NA")),"New","") -> New | G3: =IF((AND(ISBLANK(B3),EXACT(C3,"FALSE"))),"Remove","") -> Remove
A4: Variance (M3 / KG) | C4: =EXACT(A4,B4) -> FALSE | D4: =VLOOKUP(B4, A4:A338, 1, FALSE) -> #N/A | E4: =IF((AND(EXACT(C4,"TRUE"),_xlfn.IFNA(D4,"NA")<>"NA")),"Exist","") | F4: =IF((AND(EXACT(C4,"FALSE"),_xlfn.IFNA(D4,"NA")="NA")),"New","") -> New | G4: =IF((AND(ISBLANK(B4),EXACT(C4,"FALSE"))),"Remove","") -> Remove
A5: Manufacturing Costs | B5: Manufacturing Costs | C5: =EXACT(A5,B5) -> TRUE | D5: =VLOOKUP(B5, A5:A339, 1, FALSE) -> Manufacturing Costs | E5: =IF((AND(EXACT(C5,"TRUE"),_xlfn.IFNA(D5,"NA")<>"NA")),"Exist","") -> Exist | F5: =IF((AND(EXACT(C5,"FALSE"),_xlfn.IFNA(D5,"NA")="NA")),"New","") | G5: =IF((AND(ISBLANK(B5),EXACT(C5,"FALSE"))),"Remove","")
A6: DM-Raw Materials | B6: DM-Raw Materials | C6: =EXACT(A6,B6) -> TRUE | D6: =VLOOKUP(B6, A6:A340, 1, FALSE) -> DM-Raw Materials | E6: =IF((AND(EXACT(C6,"TRUE"),_xlfn.IFNA(D6,"NA")<>"NA")),"Exist","") -> Exist | F6: =IF((AND(EXACT(C6,"FALSE"),_xlfn.IFNA(D6,"NA")="NA")),"New","") | G6: =IF((AND(ISBLANK(B6),EXACT(C6,"FALSE"))),"Remove","")
A7: DM-Parts & Access | B7: DM-Parts & Access | C7: =EXACT(A7,B7) -> TRUE | D7: =VLOOKUP(B7, A7:A341, 1, FALSE) -> DM-Parts & Access | E7: =IF((AND(EXACT(C7,"TRUE"),_xlfn.IFNA(D7,"NA")<>"NA")),"Exist","") -> Exist | F7: =IF((AND(EXACT(C7,"FALSE"),_xlfn.IFNA(D7,"NA")="NA")),"New","") | G7: =IF((AND(ISBLANK(B7),EXACT(C7,"FALSE"))),"Remove","")
A8: DM-Packing & Label Materials | B8: DM-Packing & Label Materials | C8: =EXACT(A8,B8) -> TRUE | D8: =VLOOKUP(B8, A8:A342, 1, FALSE) -> DM-Packing & Label Materials | E8: =IF((AND(EXACT(C8,"TRUE"),_xlfn.IFNA(D8,"NA")<>"NA")),"Exist","") -> Exist | F8: =IF((AND(EXACT(C8,"FALSE"),_xlfn.IFNA(D8,"NA")="NA")),"New","") | G8: =IF((AND(ISBLANK(B8),EXACT(C8,"FALSE"))),"Remove","")
A9: DM-Others | B9: DM-Others | C9: =EXACT(A9,B9) -> TRUE | D9: =VLOOKUP(B9, A9:A343, 1, FALSE) -> DM-Others | E9: =IF((AND(EXACT(C9,"TRUE"),_xlfn.IFNA(D9,"NA")<>"NA")),"Exist","") -> Exist | F9: =IF((AND(EXACT(C9,"FALSE"),_xlfn.IFNA(D9,"NA")="NA")),"New","") | G9: =IF((AND(ISBLANK(B9),EXACT(C9,"FALSE"))),"Remove","")
A10: Direct Material | B10: Direct Material | C10: =EXACT(A10,B10) -> TRUE | D10: =VLOOKUP(B10, A10:A344, 1, FALSE) -> Direct Material | E10: =IF((AND(EXACT(C10,"TRUE"),_xlfn.IFNA(D10,"NA")<>"NA")),"Exist","") -> Exist | F10: =IF((AND(EXACT(C10,"FALSE"),_xlfn.IFNA(D10,"NA")="NA")),"New","") | G10: =IF((AND(ISBLANK(B10),EXACT(C10,"FALSE"))),"Remove","")
A11: Salary & Leave | B11: Salary & Leave | C11: =EXACT(A11,B11) -> TRUE | D11: =VLOOKUP(B11, A11:A345, 1, FALSE) -> Salary & Leave | E11: =IF((AND(EXACT(C11,"TRUE"),_xlfn.IFNA(D11,"NA")<>"NA")),"Exist","") -> Exist | F11: =IF((AND(EXACT(C11,"FALSE"),_xlfn.IFNA(D11,"NA")="NA")),"New","") | G11: =IF((AND(ISBLANK(B11),EXACT(C11,"FALSE"))),"Remove","")
A12: Bonus | B12: Bonus | C12: =EXACT(A12,B12) -> TRUE | D12: =VLOOKUP(B12, A12:A346, 1, FALSE) -> Bonus | E12: =IF((AND(EXACT(C12,"TRUE"),_xlfn.IFNA(D12,"NA")<>"NA")),"Exist","") -> Exist | F12: =IF((AND(EXACT(C12,"FALSE"),_xlfn.IFNA(D12,"NA")="NA")),"New","") | G12: =IF((AND(ISBLANK(B12),EXACT(C12,"FALSE"))),"Remove","")
A13: Foreign Workers/Casual/Temp | B13: Foreign Workers/Casual/Temp | C13: =EXACT(A13,B13) -> TRUE | D13: =VLOOKUP(B13, A13:A347, 1, FALSE) -> Foreign Workers/Casual/Temp | E13: =IF((AND(EXACT(C13,"TRUE"),_xlfn.IFNA(D13,"NA")<>"NA")),"Exist","") -> Exist | F13: =IF((AND(EXACT(C13,"FALSE"),_xlfn.IFNA(D13,"NA")="NA")),"New","") | G13: =IF((AND(ISBLANK(B13),EXACT(C13,"FALSE"))),"Remove","")
A14: Contractors | C14: =EXACT(A14,B14) -> FALSE | D14: =VLOOKUP(B14, A14:A348, 1, FALSE) -> #N/A | E14: =IF((AND(EXACT(C14,"TRUE"),_xlfn.IFNA(D14,"NA")<>"NA")),"Exist","") | F14: =IF((AND(EXACT(C14,"FALSE"),_xlfn.IFNA(D14,"NA")="NA")),"New","") -> New | G14: =IF((AND(ISBLANK(B14),EXACT(C14,"FALSE"))),"Remove","") -> Remove
A15: DL-Overtime | B15: DL-Overtime | C15: =EXACT(A15,B15) -> TRUE | D15: =VLOOKUP(B15, A15:A349, 1, FALSE) -> DL-Overtime | E15: =IF((AND(EXACT(C15,"TRUE"),_xlfn.IFNA(D15,"NA")<>"NA")),"Exist","") -> Exist | F15: =IF((AND(EXACT(C15,"FALSE"),_xlfn.IFNA(D15,"NA")="NA")),"New","") | G15: =IF((AND(ISBLANK(B15),EXACT(C15,"FALSE"))),"Remove","")
A16: DL-Shift Allowance & Incentive | B16: DL-Shift Allowance & Incentive | C16: =EXACT(A16,B16) -> TRUE | D16: =VLOOKUP(B16, A16:A350, 1, FALSE) -> DL-Shift Allowance & Incentive | E16: =IF((AND(EXACT(C16,"TRUE"),_xlfn.IFNA(D16,"NA")<>"NA")),"Exist","") -> Exist | F16: =IF((AND(EXACT(C16,"FALSE"),_xlfn.IFNA(D16,"NA")="NA")),"New","") | G16: =IF((AND(ISBLANK(B16),EXACT(C16,"FALSE"))),"Remove","")
A17: DL-Staff Transport/Vehicle Rental | B17: DL-Staff Transport/Vehicle Rental | C17: =EXACT(A17,B17) -> TRUE | D17: =VLOOKUP(B17, A17:A351, 1, FALSE) -> DL-Staff Transport/Vehicle Rental | E17: =IF((AND(EXACT(C17,"TRUE"),_xlfn.IFNA(D17,"NA")<>"NA")),"Exist","") -> Exist | F17: =IF((AND(EXACT(C17,"FALSE"),_xlfn.IFNA(D17,"NA")="NA")),"New","") | G17: =IF((AND(ISBLANK(B17),EXACT(C17,"FALSE"))),"Remove","")
A18: DL-Social Security Contribution | B18: DL-Social Security Contribution | C18: =EXACT(A18,B18) -> TRUE | D18: =VLOOKUP(B18, A18:A352, 1, FALSE) -> DL-Social Security Contribution | E18: =IF((AND(EXACT(C18,"TRUE"),_xlfn.IFNA(D18,"NA")<>"NA")),"Exist","") -> Exist | F18: =IF((AND(EXACT(C18,"FALSE"),_xlfn.IFNA(D18,"NA")="NA")),"New","") | G18: =IF((AND(ISBLANK(B18),EXACT(C18,"FALSE"))),"Remove","")
A19: DL-Workers` Levy | B19: DL-Workers` Levy | C19: =EXACT(A19,B19) -> TRUE | D19: =VLOOKUP(B19, A19:A353, 1, FALSE) -> DL-Workers` Levy | E19: =IF((AND(EXACT(C19,"TRUE"),_xlfn.IFNA(D19,"NA")<>"NA")),"Exist","") -> Exist | F19: =IF((AND(EXACT(C19,"FALSE"),_xlfn.IFNA(D19,"NA")="NA")),"New","") | G19: =IF((AND(ISBLANK(B19),EXACT(C19,"FALSE"))),"Remove","")
A20: DL-Others Direct Labor Costs | B20: DL-Others Direct Labor Costs | C20: =EXACT(A20,B20) -> TRUE | D20: =VLOOKUP(B20, A20:A354, 1, FALSE) -> DL-Others Direct Labor Costs | E20: =IF((AND(EXACT(C20,"TRUE"),_xlfn.IFNA(D20,"NA")<>"NA")),"Exist","") -> Exist | F20: =IF((AND(EXACT(C20,"FALSE"),_xlfn.IFNA(D20,"NA")="NA")),"New","") | G20: =IF((AND(ISBLANK(B20),EXACT(C20,"FALSE"))),"Remove","")
A21: Direct Labor | B21: Direct Labor | C21: =EXACT(A21,B21) -> TRUE | D21: =VLOOKUP(B21, A21:A355, 1, FALSE) -> Direct Labor | E21: =IF((AND(EXACT(C21,"TRUE"),_xlfn.IFNA(D21,"NA")<>"NA")),"Exist","") -> Exist | F21: =IF((AND(EXACT(C21,"FALSE"),_xlfn.IFNA(D21,"NA")="NA")),"New","") | G21: =IF((AND(ISBLANK(B21),EXACT(C21,"FALSE"))),"Remove","")
A22: Direct Expenses | B22: Direct Expenses | C22: =EXACT(A22,B22) -> TRUE | D22: =VLOOKUP(B22, A22:A356, 1, FALSE) -> Direct Expenses | E22: =IF((AND(EXACT(C22,"TRUE"),_xlfn.IFNA(D22,"NA")<>"NA")),"Exist","") -> Exist | F22: =IF((AND(EXACT(C22,"FALSE"),_xlfn.IFNA(D22,"NA")="NA")),"New","") | G22: =IF((AND(ISBLANK(B22),EXACT(C22,"FALSE"))),"Remove","")
A23: Prime Cost | B23: Prime Cost | C23: =EXACT(A23,B23) -> TRUE | D23: =VLOOKUP(B23, A23:A357, 1, FALSE) -> Prime Cost | E23: =IF((AND(EXACT(C23,"TRUE"),_xlfn.IFNA(D23,"NA")<>"NA")),"Exist","") -> Exist | F23: =IF((AND(EXACT(C23,"FALSE"),_xlfn.IFNA(D23,"NA")="NA")),"New","") | G23: =IF((AND(ISBLANK(B23),EXACT(C23,"FALSE"))),"Remove","")
A24: Indirect Material | B24: Indirect Material | C24: =EXACT(A24,B24) -> TRUE | D24: =VLOOKUP(B24, A24:A358, 1, FALSE) -> Indirect Material | E24: =IF((AND(EXACT(C24,"TRUE"),_xlfn.IFNA(D24,"NA")<>"NA")),"Exist","") -> Exist | F24: =IF((AND(EXACT(C24,"FALSE"),_xlfn.IFNA(D24,"NA")="NA")),"New","") | G24: =IF((AND(ISBLANK(B24),EXACT(C24,"FALSE"))),"Remove","")
A25: IL-Salary & Leave | B25: IL-Salary & Leave | C25: =EXACT(A25,B25) -> TRUE | D25: =VLOOKUP(B25, A25:A359, 1, FALSE) -> IL-Salary & Leave | E25: =IF((AND(EXACT(C25,"TRUE"),_xlfn.IFNA(D25,"NA")<>"NA")),"Exist","") -> Exist | F25: =IF((AND(EXACT(C25,"FALSE"),_xlfn.IFNA(D25,"NA")="NA")),"New","") | G25: =IF((AND(ISBLANK(B25),EXACT(C25,"FALSE"))),"Remove","")
A26: IL-Bonus | B26: IL-Bonus | C26: =EXACT(A26,B26) -> TRUE | D26: =VLOOKUP(B26, A26:A360, 1, FALSE) -> IL-Bonus | E26: =IF((AND(EXACT(C26,"TRUE"),_xlfn.IFNA(D26,"NA")<>"NA")),"Exist","") -> Exist | F26: =IF((AND(EXACT(C26,"FALSE"),_xlfn.IFNA(D26,"NA")="NA")),"New","") | G26: =IF((AND(ISBLANK(B26),EXACT(C26,"FALSE"))),"Remove","")
... A34: IL-Other Indirect Labor Costs | B34: IL-Other Indirect Labor Costs | C34: =EXACT(A34,B34) -> TRUE | D34: =VLOOKUP(B34, A34:A368, 1, FALSE) -> IL-Other Indirect Labor Costs | E34: =IF((AND(EXACT(C34,"TRUE"),_xlfn.IFNA(D34,"NA")<>"NA")),"Exist","") -> Exist | F34: =IF((AND(EXACT(C34,"FALSE"),_xlfn.IFNA(D34,"NA")="NA")),"New","") | G34: =IF((AND(ISBLANK(B34),EXACT(C34,"FALSE"))),"Remove","")
B35: QA Allocated Cost | C35: =EXACT(A35,B35) -> FALSE | D35: =VLOOKUP(B35, A35:A369, 1, FALSE) -> #N/A | E35: =IF((AND(EXACT(C35,"TRUE"),_xlfn.IFNA(D35,"NA")<>"NA")),"Exist","") | F35: =IF((AND(EXACT(C35,"FALSE"),_xlfn.IFNA(D35,"NA")="NA")),"New","") -> New | G35: =IF((AND(ISBLANK(B35),EXACT(C35,"FALSE"))),"Remove","")
B36: PM Allocated Cost | C36: =EXACT(A36,B36) -> FALSE | D36: =VLOOKUP(B36, A36:A370, 1, FALSE) -> #N/A | E36: =IF((AND(EXACT(C36,"TRUE"),_xlfn.IFNA(D36,"NA")<>"NA")),"Exist","") | F36: =IF((AND(EXACT(C36,"FALSE"),_xlfn.IFNA(D36,"NA")="NA")),"New","") -> New | G36: =IF((AND(ISBLANK(B36),EXACT(C36,"FALSE"))),"Remove","")
A37: Indirect Labor | B37: Indirect Labor | C37: =EXACT(A37,B37) -> TRUE | D37: =VLOOKUP(B37, A37:A371, 1, FALSE) -> Indirect Labor | E37: =IF((AND(EXACT(C37,"TRUE"),_xlfn.IFNA(D37,"NA")<>"NA")),"Exist","") -> Exist | F37: =IF((AND(EXACT(C37,"FALSE"),_xlfn.IFNA(D37,"NA")="NA")),"New","") | G37: =IF((AND(ISBLANK(B37),EXACT(C37,"FALSE"))),"Remove","")
A38: Utilities - Elec, Water, Gas | B38: Utilities - Elec, Water, Gas | C38: =EXACT(A38,B38) -> TRUE | D38: =VLOOKUP(B38, A38:A372, 1, FALSE) -> Utilities - Elec, Water, Gas | E38: =IF((AND(EXACT(C38,"TRUE"),_xlfn.IFNA(D38,"NA")<>"NA")),"Exist","") -> Exist | F38: =IF((AND(EXACT(C38,"FALSE"),_xlfn.IFNA(D38,"NA")="NA")),"New","") | G38: =IF((AND(ISBLANK(B38),EXACT(C38,"FALSE"))),"Remove","")
A39: Product Development/Testing | B39: Product Development/Testing | C39: =EXACT(A39,B39) -> TRUE | D39: =VLOOKUP(B39, A39:A373, 1, FALSE) -> Product Development/Testing | E39: =IF((AND(EXACT(C39,"TRUE"),_xlfn.IFNA(D39,"NA")<>"NA")),"Exist","") -> Exist | F39: =IF((AND(EXACT(C39,"FALSE"),_xlfn.IFNA(D39,"NA")="NA")),"New","") | G39: =IF((AND(ISBLANK(B39),EXACT(C39,"FALSE"))),"Remove","")
A40: Carriage/Transport | C40: =EXACT(A40,B40) -> FALSE | D40: =VLOOKUP(B40, A40:A374, 1, FALSE) -> #N/A | E40: =IF((AND(EXACT(C40,"TRUE"),_xlfn.IFNA(D40,"NA")<>"NA")),"Exist","") | F40: =IF((AND(EXACT(C40,"FALSE"),_xlfn.IFNA(D40,"NA")="NA")),"New","") -> New | G40: =IF((AND(ISBLANK(B40),EXACT(C40,"FALSE"))),"Remove","") -> Remove
B41: Carriage/Transport/Storage | C41: =EXACT(A41,B41) -> FALSE | D41: =VLOOKUP(B41, A41:A375, 1, FALSE) -> #N/A | E41: =IF((AND(EXACT(C41,"TRUE"),_xlfn.IFNA(D41,"NA")<>"NA")),"Exist","") | F41: =IF((AND(EXACT(C41,"FALSE"),_xlfn.IFNA(D41,"NA")="NA")),"New","") -> New | G41: =IF((AND(ISBLANK(B41),EXACT(C41,"FALSE"))),"Remove","")
A42: Manufacturing Loss/Wastage | B42: Manufacturing Loss/Wastage | C42: =EXACT(A42,B42) -> TRUE | D42: =VLOOKUP(B42, A42:A376, 1, FALSE) -> Manufacturing Loss/Wastage | E42: =IF((AND(EXACT(C42,"TRUE"),_xlfn.IFNA(D42,"NA")<>"NA")),"Exist","") -> Exist | F42: =IF((AND(EXACT(C42,"FALSE"),_xlfn.IFNA(D42,"NA")="NA")),"New","") | G42: =IF((AND(ISBLANK(B42),EXACT(C42,"FALSE"))),"Remove","")
A43: Rejects/Reworks/Scrap | B43: Rejects/Reworks/Scrap | C43: =EXACT(A43,B43) -> TRUE | D43: =VLOOKUP(B43, A43:A377, 1, FALSE) -> Rejects/Reworks/Scrap | E43: =IF((AND(EXACT(C43,"TRUE"),_xlfn.IFNA(D43,"NA")<>"NA")),"Exist","") -> Exist | F43: =IF((AND(EXACT(C43,"FALSE"),_xlfn.IFNA(D43,"NA")="NA")),"New","") | G43: =IF((AND(ISBLANK(B43),EXACT(C43,"FALSE"))),"Remove","")
A44: Sales of Scrap Production | C44: =EXACT(A44,B44) -> FALSE | D44: =VLOOKUP(B44, A44:A378, 1, FALSE) -> #N/A | E44: =IF((AND(EXACT(C44,"TRUE"),_xlfn.IFNA(D44,"NA")<>"NA")),"Exist","") | F44: =IF((AND(EXACT(C44,"FALSE"),_xlfn.IFNA(D44,"NA")="NA")),"New","") -> New | G44: =IF((AND(ISBLANK(B44),EXACT(C44,"FALSE"))),"Remove","") -> Remove
A45: Disposal of Slurge | C45: =EXACT(A45,B45) -> FALSE | D45: =VLOOKUP(B45, A45:A379, 1, FALSE) -> #N/A | E45: =IF((AND(EXACT(C45,"TRUE"),_xlfn.IFNA(D45,"NA")<>"NA")),"Exist","") | F45: =IF((AND(EXACT(C45,"FALSE"),_xlfn.IFNA(D45,"NA")="NA")),"New","") -> New | G45: =IF((AND(ISBLANK(B45),EXACT(C45,"FALSE"))),"Remove","") -> Remove
B46: Disposal of Sludge/Others | C46: =EXACT(A46,B46) -> FALSE | D46: =VLOOKUP(B46, A46:A380, 1, FALSE) -> #N/A | E46: =IF((AND(EXACT(C46,"TRUE"),_xlfn.IFNA(D46,"NA")<>"NA")),"Exist","") | F46: =IF((AND(EXACT(C46,"FALSE"),_xlfn.IFNA(D46,"NA")="NA")),"New","") -> New | G46: =IF((AND(ISBLANK(B46),EXACT(C46,"FALSE"))),"Remove","")
A47: Variable Overhead | C47: =EXACT(A47,B47) -> FALSE | D47: =VLOOKUP(B47, A47:A381, 1, FALSE) -> #N/A | E47: =IF((AND(EXACT(C47,"TRUE"),_xlfn.IFNA(D47,"NA")<>"NA")),"Exist","") | F47: =IF((AND(EXACT(C47,"FALSE"),_xlfn.IFNA(D47,"NA")="NA")),"New","") -> New | G47: =IF((AND(ISBLANK(B47),EXACT(C47,"FALSE"))),"Remove","") -> Remove
A48: Work in Progress | C48: =EXACT(A48,B48) -> FALSE | D48: =VLOOKUP(B48, A48:A382, 1, FALSE) -> #N/A | E48: =IF((AND(EXACT(C48,"TRUE"),_xlfn.IFNA(D48,"NA")<>"NA")),"Exist","") | F48: =IF((AND(EXACT(C48,"FALSE"),_xlfn.IFNA(D48,"NA")="NA")),"New","") -> New | G48: =IF((AND(ISBLANK(B48),EXACT(C48,"FALSE"))),"Remove","") -> Remove
B49: QA Allocated Cost | C49: =EXACT(A49,B49) -> FALSE | D49: =VLOOKUP(B49, A49:A383, 1, FALSE) -> #N/A | E49: =IF((AND(EXACT(C49,"TRUE"),_xlfn.IFNA(D49,"NA")<>"NA")),"Exist","") | F49: =IF((AND(EXACT(C49,"FALSE"),_xlfn.IFNA(D49,"NA")="NA")),"New","") -> New | G49: =IF((AND(ISBLANK(B49),EXACT(C49,"FALSE"))),"Remove","")
B50: PM Allocated Cost | C50: =EXACT(A50,B50) -> FALSE | D50: =VLOOKUP(B50, A50:A384, 1, FALSE) -> #N/A | E50: =IF((AND(EXACT(C50,"TRUE"),_xlfn.IFNA(D50,"NA")<>"NA")),"Exist","") | F50: =IF((AND(EXACT(C50,"FALSE"),_xlfn.IFNA(D50,"NA")="NA")),"New","") -> New | G50: =IF((AND(ISBLANK(B50),EXACT(C50,"FALSE"))),"Remove","")
A51: Total Variable Costs | C51: =EXACT(A51,B51) -> FALSE | D51: =VLOOKUP(B51, A51:A385, 1, FALSE) -> #N/A | E51: =IF((AND(EXACT(C51,"TRUE"),_xlfn.IFNA(D51,"NA")<>"NA")),"Exist","") | F51: =IF((AND(EXACT(C51,"FALSE"),_xlfn.IFNA(D51,"NA")="NA")),"New","") -> New | G51: =IF((AND(ISBLANK(B51),EXACT(C51,"FALSE"))),"Remove","") -> Remove
B52: Other Variable Overhead | C52: =EXACT(A52,B52) -> FALSE | D52: =VLOOKUP(B52, A52:A386, 1, FALSE) -> #N/A | E52: =IF((AND(EXACT(C52,"TRUE"),_xlfn.IFNA(D52,"NA")<>"NA")),"Exist","") | F52: =IF((AND(EXACT(C52,"FALSE"),_xlfn.IFNA(D52,"NA")="NA")),"New","") -> New | G52: =IF((AND(ISBLANK(B52),EXACT(C52,"FALSE"))),"Remove","")
B53: Total Variable Overhead | C53: =EXACT(A53,B53) -> FALSE | D53: =VLOOKUP(B53, A53:A387, 1, FALSE) -> #N/A | E53: =IF((AND(EXACT(C53,"TRUE"),_xlfn.IFNA(D53,"NA")<>"NA")),"Exist","") | F53: =IF((AND(EXACT(C53,"FALSE"),_xlfn.IFNA(D53,"NA")="NA")),"New","") -> New | G53: =IF((AND(ISBLANK(B53),EXACT(C53,"FALSE"))),"Remove","")
A54: Factory Rental/Upkeep | B54: Factory Rental/Upkeep | C54: =EXACT(A54,B54) -> TRUE | D54: =VLOOKUP(B54, A54:A388, 1, FALSE) -> Factory Rental/Upkeep | E54: =IF((AND(EXACT(C54,"TRUE"),_xlfn.IFNA(D54,"NA")<>"NA")),"Exist","") -> Exist | F54: =IF((AND(EXACT(C54,"FALSE"),_xlfn.IFNA(D54,"NA")="NA")),"New","") | G54: =IF((AND(ISBLANK(B54),EXACT(C54,"FALSE"))),"Remove","")
A55: Property Tax for Factory | B55: Property Tax for Factory | C55: =EXACT(A55,B55) -> TRUE | D55: =VLOOKUP(B55, A55:A389, 1, FALSE) -> Property Tax for Factory | E55: =IF((AND(EXACT(C55,"TRUE"),_xlfn.IFNA(D55,"NA")<>"NA")),"Exist","") -> Exist | F55: =IF((AND(EXACT(C55,"FALSE"),_xlfn.IFNA(D55,"NA")="NA")),"New","") | G55: =IF((AND(ISBLANK(B55),EXACT(C55,"FALSE"))),"Remove","")
A56: Repair & Maintainance | C56: =EXACT(A56,B56) -> FALSE | D56: =VLOOKUP(B56, A56:A390, 1, FALSE) -> #N/A | E56: =IF((AND(EXACT(C56,"TRUE"),_xlfn.IFNA(D56,"NA")<>"NA")),"Exist","") | F56: =IF((AND(EXACT(C56,"FALSE"),_xlfn.IFNA(D56,"NA")="NA")),"New","") -> New | G56: =IF((AND(ISBLANK(B56),EXACT(C56,"FALSE"))),"Remove","") -> Remove
B57: Repair & Maintainance/Upkeep | C57: =EXACT(A57,B57) -> FALSE | D57: =VLOOKUP(B57, A57:A391, 1, FALSE) -> #N/A | E57: =IF((AND(EXACT(C57,"TRUE"),_xlfn.IFNA(D57,"NA")<>"NA")),"Exist","") | F57: =IF((AND(EXACT(C57,"FALSE"),_xlfn.IFNA(D57,"NA")="NA")),"New","") -> New | G57: =IF((AND(ISBLANK(B57),EXACT(C57,"FALSE"))),"Remove","")
A58: Leasing of Mac & Equip/Vehicles | C58: =EXACT(A58,B58) -> FALSE | D58: =VLOOKUP(B58, A58:A392, 1, FALSE) -> #N/A | E58: =IF((AND(EXACT(C58,"TRUE"),_xlfn.IFNA(D58,"NA")<>"NA")),"Exist","") | F58: =IF((AND(EXACT(C58,"FALSE"),_xlfn.IFNA(D58,"NA")="NA")),"New","") -> New | G58: =IF((AND(ISBLANK(B58),EXACT(C58,"FALSE"))),"Remove","") -> Remove
B59: Leasing of Mac&Equip/Vehicles/Cyl | C59: =EXACT(A59,B59) -> FALSE | D59: =VLOOKUP(B59, A59:A393, 1, FALSE) -> #N/A | E59: =IF((AND(EXACT(C59,"TRUE"),_xlfn.IFNA(D59,"NA")<>"NA")),"Exist","") | F59: =IF((AND(EXACT(C59,"FALSE"),_xlfn.IFNA(D59,"NA")="NA")),"New","") -> New | G59: =IF((AND(ISBLANK(B59),EXACT(C59,"FALSE"))),"Remove","")
A60: Depreciation | B60: Depreciation | C60: =EXACT(A60,B60) -> TRUE | D60: =VLOOKUP(B60, A60:A394, 1, FALSE) -> Depreciation | E60: =IF((AND(EXACT(C60,"TRUE"),_xlfn.IFNA(D60,"NA")<>"NA")),"Exist","") -> Exist | F60: =IF((AND(EXACT(C60,"FALSE"),_xlfn.IFNA(D60,"NA")="NA")),"New","") | G60: =IF((AND(ISBLANK(B60),EXACT(C60,"FALSE"))),"Remove","")
A61: Licenses & Insurance | B61: Licenses & Insurance | C61: =EXACT(A61,B61) -> TRUE | D61: =VLOOKUP(B61, A61:A395, 1, FALSE) -> Licenses & Insurance | E61: =IF((AND(EXACT(C61,"TRUE"),_xlfn.IFNA(D61,"NA")<>"NA")),"Exist","") -> Exist | F61: =IF((AND(EXACT(C61,"FALSE"),_xlfn.IFNA(D61,"NA")="NA")),"New","") | G61: =IF((AND(ISBLANK(B61),EXACT(C61,"FALSE"))),"Remove","")
A62: Non Capitalised Purchases | B62: Non Capitalised Purchases | C62: =EXACT(A62,B62) -> TRUE | D62: =VLOOKUP(B62, A62:A396, 1, FALSE) -> Non Capitalised Purchases | E62: =IF((AND(EXACT(C62,"TRUE"),_xlfn.IFNA(D62,"NA")<>"NA")),"Exist","") -> Exist | F62: =IF((AND(EXACT(C62,"FALSE"),_xlfn.IFNA(D62,"NA")="NA")),"New","") | G62: =IF((AND(ISBLANK(B62),EXACT(C62,"FALSE"))),"Remove","")
A63: Others Fixed Overhead | B63: Others Fixed Overhead | C63: =EXACT(A63,B63) -> TRUE | D63: =VLOOKUP(B63, A63:A397, 1, FALSE) -> Others Fixed Overhead | E63: =IF((AND(EXACT(C63,"TRUE"),_xlfn.IFNA(D63,"NA")<>"NA")),"Exist","") -> Exist | F63: =IF((AND(EXACT(C63,"FALSE"),_xlfn.IFNA(D63,"NA")="NA")),"New","") | G63: =IF((AND(ISBLANK(B63),EXACT(C63,"FALSE"))),"Remove","")
B64: QA Allocated Cost | C64: =EXACT(A64,B64) -> FALSE | D64: =VLOOKUP(B64, A64:A398, 1, FALSE) -> #N/A | E64: =IF((AND(EXACT(C64,"TRUE"),_xlfn.IFNA(D64,"NA")<>"NA")),"Exist","") | F64: =IF((AND(EXACT(C64,"FALSE"),_xlfn.IFNA(D64,"NA")="NA")),"New","") -> New | G64: =IF((AND(ISBLANK(B64),EXACT(C64,"FALSE"))),"Remove","")
B65: PM Allocated Cost | C65: =EXACT(A65,B65) -> FALSE | D65: =VLOOKUP(B65, A65:A399, 1, FALSE) -> #N/A | E65: =IF((AND(EXACT(C65,"TRUE"),_xlfn.IFNA(D65,"NA")<>"NA")),"Exist","") | F65: =IF((AND(EXACT(C65,"FALSE"),_xlfn.IFNA(D65,"NA")="NA")),"New","") -> New | G65: =IF((AND(ISBLANK(B65),EXACT(C65,"FALSE"))),"Remove","")
A66: Fixed Overhead | B66: Fixed Overhead
A67: Cost of Goods Manufactured | B67: Cost of Goods Manufactured
A68: Performance Indicators
A69: Direct Material (m3 / Kg)
A70: Direct Labour (m3 / Kg)
A71: Direct Exps (m3 / Kg)
A72: Indirect Material (m3 / Kg)
A73: Indirect Labour (m3 / Kg)
A74: Variable Overhead (m3 / Kg)
A75: Total Variable (m3 / Kg)
A76: Fixed Overhead (m3 / Kg)
A77: Manufacturing Costs (m3/ Kg)

Sheet F121 F24 New
A1: Status | B1: Report | C1: New-ItemSeqID | D1: ItemSeqID | E1: New-ItemSN | F1: ItemSN | G1: ItemID | H1: ItemName | I1: COA Mapping | J1: Insert Script | K1: Finance Item
A2: Remove | B2: MA | C2: 1 | D2: 1 | E2: 1 | F2: 1 | G2: 1280 | H2: (MA)Planned Production (M3 / KG) | J2: =IF(A2<>"Remove",CONCATENATE("INSERT INTO tbFinanceItemSeq(Report,ItemSeqID,ItemSN,ItemID) VALUES('",B2,"',",C2,",",E2,",",G2,")"),"") | K2: =IF(A2<>"New","",CONCATENATE("INSERT INTO tbFinanceItem(ItemName) VALUES('",H2,"')"))
A3: Remove | B3: MA | C3: 2 | D3: 2 | E3: 2 | F3: 2 | G3: 1281 | H3: (MA)Actual Production (M3 / KG) | J3: =IF(A3<>"Remove",CONCATENATE("INSERT INTO tbFinanceItemSeq(Report,ItemSeqID,ItemSN,ItemID) VALUES('",B3,"',",C3,",",E3,",",G3,")"),"") | K3: =IF(A3<>"New","",CONCATENATE("INSERT INTO tbFinanceItem(ItemName) VALUES('",H3,"')"))
A4: Remove | B4: MA | C4: 3 | D4: 3 | E4: 3 | F4: 3 | G4: 1282 | H4: (MA)Variance (M3 / KG) | J4: =IF(A4<>"Remove",CONCATENATE("INSERT INTO tbFinanceItemSeq(Report,ItemSeqID,ItemSN,ItemID) VALUES('",B4,"',",C4,",",E4,",",G4,")"),"") | K4: =IF(A4<>"New","",CONCATENATE("INSERT INTO tbFinanceItem(ItemName) VALUES('",H4,"')"))
A5: Exist | B5: MA | C5: 1 | D5: 4 | E5: 1 | F5: 4 | G5: 1283 | H5: (MA)Manufacturing Costs | J5: =IF(A5<>"Remove",CONCATENATE("INSERT INTO tbFinanceItemSeq(Report,ItemSeqID,ItemSN,ItemID) VALUES('",B5,"',",C5,",",E5,",",G5,")"),"") -> INSERT INTO tbFinanceItemSeq(Report,ItemSeqID,ItemSN,ItemID) VALUES('MA',1,1,1283) | K5: =IF(A5<>"New","",CONCATENATE("INSERT INTO tbFinanceItem(ItemName) VALUES('",H5,"')"))
A6: Exist | B6: MA | C6: 2 | D6: 5 | E6: 2 | F6: 5 | G6: 1284 | H6: (MA)DM-Raw Materials | I6: 6101 | J6: =IF(A6<>"Remove",CONCATENATE("INSERT INTO tbFinanceItemSeq(Report,ItemSeqID,ItemSN,ItemID) VALUES('",B6,"',",C6,",",E6,",",G6,")"),"") -> INSERT INTO tbFinanceItemSeq(Report,ItemSeqID,ItemSN,ItemID) VALUES('MA',2,2,1284) | K6: =IF(A6<>"New","",CONCATENATE("INSERT INTO tbFinanceItem(ItemName) VALUES('",H6,"')"))
A7: Exist | B7: MA | C7: 3 | D7: 6 | E7: 3 | F7: 6 | G7: 1285 | H7: (MA)DM-Parts & Access | I7: 6102 | J7: =IF(A7<>"Remove",CONCATENATE("INSERT INTO tbFinanceItemSeq(Report,ItemSeqID,ItemSN,ItemID) VALUES('",B7,"',",C7,",",E7,",",G7,")"),"") -> INSERT INTO tbFinanceItemSeq(Report,ItemSeqID,ItemSN,ItemID) VALUES('MA',3,3,1285) | K7: =IF(A7<>"New","",CONCATENATE("INSERT INTO tbFinanceItem(ItemName) VALUES('",H7,"')"))
A8: Exist | B8: MA | C8: 4 | D8: 7 | E8: 4 | F8: 7 | G8: 1286 | H8: (MA)DM-Packing & Label Materials | I8: 6103 to 6104 | J8: =IF(A8<>"Remove",CONCATENATE("INSERT INTO tbFinanceItemSeq(Report,ItemSeqID,ItemSN,ItemID) VALUES('",B8,"',",C8,",",E8,",",G8,")"),"") -> INSERT INTO tbFinanceItemSeq(Report,ItemSeqID,ItemSN,ItemID) VALUES('MA',4,4,1286) | K8: =IF(A8<>"New","",CONCATENATE("INSERT INTO tbFinanceItem(ItemName) VALUES('",H8,"')"))
A9: Exist | B9: MA | C9: 5 | D9: 8 | E9: 5 | F9: 8 | G9: 1287 | H9: (MA)DM-Others | I9: 6105 to 6199 | J9: =IF(A9<>"Remove",CONCATENATE("INSERT INTO tbFinanceItemSeq(Report,ItemSeqID,ItemSN,ItemID) VALUES('",B9,"',",C9,",",E9,",",G9,")"),"") -> INSERT INTO tbFinanceItemSeq(Report,ItemSeqID,ItemSN,ItemID) VALUES('MA',5,5,1287) | K9: =IF(A9<>"New","",CONCATENATE("INSERT INTO tbFinanceItem(ItemName) VALUES('",H9,"')"))
A10: Exist | B10: MA | C10: 6 | D10: 9 | E10: 6 | F10: 9 | G10: 1288 | H10: (MA)Direct Material | I10: =SUM(C7:C10) | J10: =IF(A10<>"Remove",CONCATENATE("INSERT INTO tbFinanceItemSeq(Report,ItemSeqID,ItemSN,ItemID) VALUES('",B10,"',",C10,",",E10,",",G10,")"),"") -> INSERT INTO tbFinanceItemSeq(Report,ItemSeqID,ItemSN,ItemID) VALUES('MA',6,6,1288) | K10: =IF(A10<>"New","",CONCATENATE("INSERT INTO tbFinanceItem(ItemName) VALUES('",H10,"')"))
A11: Exist | B11: MA | C11: 7 | D11: 10 | E11: 7 | F11: 10 | G11: 1289 | H11: (MA)DL-Salary & Leave | I11: 6201 to 6202 | J11: =IF(A11<>"Remove",CONCATENATE("INSERT INTO tbFinanceItemSeq(Report,ItemSeqID,ItemSN,ItemID) VALUES('",B11,"',",C11,",",E11,",",G11,")"),"") -> INSERT INTO tbFinanceItemSeq(Report,ItemSeqID,ItemSN,ItemID) VALUES('MA',7,7,1289) | K11: =IF(A11<>"New","",CONCATENATE("INSERT INTO tbFinanceItem(ItemName) VALUES('",H11,"')"))
A12: Exist | B12: MA | C12: 8 | D12: 11 | E12: 8 | F12: 11 | G12: 1290 | H12: (MA)DL-Bonus | I12: 6203 to 6204 | J12: =IF(A12<>"Remove",CONCATENATE("INSERT INTO tbFinanceItemSeq(Report,ItemSeqID,ItemSN,ItemID) VALUES('",B12,"',",C12,",",E12,",",G12,")"),"") -> INSERT INTO tbFinanceItemSeq(Report,ItemSeqID,ItemSN,ItemID) VALUES('MA',8,8,1290) | K12: =IF(A12<>"New","",CONCATENATE("INSERT INTO tbFinanceItem(ItemName) VALUES('",H12,"')"))
A13: Exist | B13: MA | C13: 9 | D13: 12 | E13: 9 | F13: 12 | G13: 1291 | H13: (MA)DL-Foreign Workers/Casual/Temp | I13: 6206, 6208 | J13: =IF(A13<>"Remove",CONCATENATE("INSERT INTO tbFinanceItemSeq(Report,ItemSeqID,ItemSN,ItemID) VALUES('",B13,"',",C13,",",E13,",",G13,")"),"") -> INSERT INTO tbFinanceItemSeq(Report,ItemSeqID,ItemSN,ItemID) VALUES('MA',9,9,1291) | K13: =IF(A13<>"New","",CONCATENATE("INSERT INTO tbFinanceItem(ItemName) VALUES('",H13,"')"))
A14: Remove | B14: MA | C14: 10 | D14: 13 | E14: 10 | F14: 13 | G14: 1292 | H14: (MA)DL-Contractors | J14: =IF(A14<>"Remove",CONCATENATE("INSERT INTO tbFinanceItemSeq(Report,ItemSeqID,ItemSN,ItemID) VALUES('",B14,"',",C14,",",E14,",",G14,")"),"") | K14: =IF(A14<>"New","",CONCATENATE("INSERT INTO tbFinanceItem(ItemName) VALUES('",H14,"')"))
A15: Exist | B15: MA | C15: 10 | D15: 14 | E15: 10 | F15: 14 | G15: 1293 | H15: (MA)DL-Overtime | I15: 6209 to 6210 | J15: =IF(A15<>"Remove",CONCATENATE("INSERT INTO tbFinanceItemSeq(Report,ItemSeqID,ItemSN,ItemID) VALUES('",B15,"',",C15,",",E15,",",G15,")"),"") -> INSERT INTO tbFinanceItemSeq(Report,ItemSeqID,ItemSN,ItemID) VALUES('MA',10,10,1293) | K15: =IF(A15<>"New","",CONCATENATE("INSERT INTO tbFinanceItem(ItemName) VALUES('",H15,"')"))
A16: Exist | B16: MA | C16: 11 | D16: 15 | E16: 11 | F16: 15 | G16: 1294 | H16: (MA)DL-Shift Allowance & Incentive | I16: 6205, 6211 to 6212 | J16: =IF(A16<>"Remove",CONCATENATE("INSERT INTO tbFinanceItemSeq(Report,ItemSeqID,ItemSN,ItemID) VALUES('",B16,"',",C16,",",E16,",",G16,")"),"") -> INSERT INTO tbFinanceItemSeq(Report,ItemSeqID,ItemSN,ItemID) VALUES('MA',11,11,1294) | K16: =IF(A16<>"New","",CONCATENATE("INSERT INTO tbFinanceItem(ItemName) VALUES('",H16,"')"))
A17: Exist | B17: MA | C17: 12 | D17: 16 | E17: 12 | F17: 16 | G17: 1295 | H17: (MA)DL-Staff Transport/Vehicle Rental | I17: 6213 | J17: =IF(A17<>"Remove",CONCATENATE("INSERT INTO tbFinanceItemSeq(Report,ItemSeqID,ItemSN,ItemID) VALUES('",B17,"',",C17,",",E17,",",G17,")"),"") -> INSERT INTO tbFinanceItemSeq(Report,ItemSeqID,ItemSN,ItemID) VALUES('MA',12,12,1295) | K17: =IF(A17<>"New","",CONCATENATE("INSERT INTO tbFinanceItem(ItemName) VALUES('",H17,"')"))
A18: Exist | B18: MA | C18: 13 | D18: 17 | E18: 13 | F18: 17 | G18: 1296 | H18: (MA)DL-Social Security Contribution | I18: 6214 | J18: =IF(A18<>"Remove",CONCATENATE("INSERT INTO tbFinanceItemSeq(Report,ItemSeqID,ItemSN,ItemID) VALUES('",B18,"',",C18,",",E18,",",G18,")"),"") -> INSERT INTO tbFinanceItemSeq(Report,ItemSeqID,ItemSN,ItemID) VALUES('MA',13,13,1296) | K18: =IF(A18<>"New","",CONCATENATE("INSERT INTO tbFinanceItem(ItemName) VALUES('",H18,"')"))
A19: Exist | B19: MA | C19: 14 | D19: 18 | E19: 14 | F19: 18 | G19: 1297 | H19: (MA)DL-Workers` Levy | I19: 6215 | J19: =IF(A19<>"Remove",CONCATENATE("INSERT INTO tbFinanceItemSeq(Report,ItemSeqID,ItemSN,ItemID) VALUES('",B19,"',",C19,",",E19,",",G19,")"),"") -> INSERT INTO tbFinanceItemSeq(Report,ItemSeqID,ItemSN,ItemID) VALUES('MA',14,14,1297) | K19: =IF(A19<>"New","",CONCATENATE("INSERT INTO tbFinanceItem(ItemName) VALUES('",H19,"')"))
A20: Exist | B20: MA | C20: 15 | D20: 19 | E20: 15 | F20: 19 | G20: 1298 | H20: (MA)DL-Others Direct Labor Costs | I20: 6207, 6216 to 6229 | J20: =IF(A20<>"Remove",CONCATENATE("INSERT INTO tbFinanceItemSeq(Report,ItemSeqID,ItemSN,ItemID) VALUES('",B20,"',",C20,",",E20,",",G20,")"),"") -> INSERT INTO tbFinanceItemSeq(Report,ItemSeqID,ItemSN,ItemID) VALUES('MA',15,15,1298) | K20: =IF(A20<>"New","",CONCATENATE("INSERT INTO tbFinanceItem(ItemName) VALUES('",H20,"')"))
A21: Exist | B21: MA | C21: 16 | D21: 20 | E21: 16 | F21: 20 | G21: 1299 | H21: (MA)Direct Labor | I21: =SUM(C12:C20) | J21: =IF(A21<>"Remove",CONCATENATE("INSERT INTO tbFinanceItemSeq(Report,ItemSeqID,ItemSN,ItemID) VALUES('",B21,"',",C21,",",E21,",",G21,")"),"") -> INSERT INTO tbFinanceItemSeq(Report,ItemSeqID,ItemSN,ItemID) VALUES('MA',16,16,1299) | K21: =IF(A21<>"New","",CONCATENATE("INSERT INTO tbFinanceItem(ItemName) VALUES('",H21,"')"))
A22: Exist | B22: MA | C22: 17 | D22: 21 | E22: 17 | F22: 21 | G22: 1300 | H22: (MA)Direct Expenses | I22: 6251 to 6299 | J22: =IF(A22<>"Remove",CONCATENATE("INSERT INTO tbFinanceItemSeq(Report,ItemSeqID,ItemSN,ItemID) VALUES('",B22,"',",C22,",",E22,",",G22,")"),"") -> INSERT INTO tbFinanceItemSeq(Report,ItemSeqID,ItemSN,ItemID) VALUES('MA',17,17,1300) | K22: =IF(A22<>"New","",CONCATENATE("INSERT INTO tbFinanceItem(ItemName) VALUES('",H22,"')"))
A23: Exist | B23: MA | C23: 18 | D23: 22 | E23: 18 | F23: 22 | G23: 1301 | H23: (MA)Prime Cost | I23: =C11+C21+C22 | J23: =IF(A23<>"Remove",CONCATENATE("INSERT INTO tbFinanceItemSeq(Report,ItemSeqID,ItemSN,ItemID) VALUES('",B23,"',",C23,",",E23,",",G23,")"),"") -> INSERT INTO tbFinanceItemSeq(Report,ItemSeqID,ItemSN,ItemID) VALUES('MA',18,18,1301) | K23: =IF(A23<>"New","",CONCATENATE("INSERT INTO tbFinanceItem(ItemName) VALUES('",H23,"')"))
A24: Exist | B24: MA | C24: 19 | D24: 23 | E24: 19 | F24: 23 | G24: 1302 | H24: (MA)Indirect Material | I24: 6301 to 6310 | J24: =IF(A24<>"Remove",CONCATENATE("INSERT INTO tbFinanceItemSeq(Report,ItemSeqID,ItemSN,ItemID) VALUES('",B24,"',",C24,",",E24,",",G24,")"),"") -> INSERT INTO tbFinanceItemSeq(Report,ItemSeqID,ItemSN,ItemID) VALUES('MA',19,19,1302) | K24: =IF(A24<>"New","",CONCATENATE("INSERT INTO tbFinanceItem(ItemName) VALUES('",H24,"')"))
A25: Exist | B25: MA | C25: 20 | D25: 24 | E25: 20 | F25: 24 | G25: 1303 | H25: (MA)IL-Salary & Leave | I25: 6311 | J25: =IF(A25<>"Remove",CONCATENATE("INSERT INTO tbFinanceItemSeq(Report,ItemSeqID,ItemSN,ItemID) VALUES('",B25,"',",C25,",",E25,",",G25,")"),"") -> INSERT INTO tbFinanceItemSeq(Report,ItemSeqID,ItemSN,ItemID) VALUES('MA',20,20,1303) | K25: =IF(A25<>"New","",CONCATENATE("INSERT INTO tbFinanceItem(ItemName) VALUES('",H25,"')"))
A26: Exist | B26: MA | C26: 21 | D26: 25 | E26: 21 | F26: 25 | G26: 1304 | H26: (MA)IL-Bonus | I26: 6312 | J26: =IF(A26<>"Remove",CONCATENATE("INSERT INTO tbFinanceItemSeq(Report,ItemSeqID,ItemSN,ItemID) VALUES('",B26,"',",C26,",",E26,",",G26,")"),"") -> INSERT INTO tbFinanceItemSeq(Report,ItemSeqID,ItemSN,ItemID) VALUES('MA',21,21,1304) | K26: =IF(A26<>"New","",CONCATENATE("INSERT INTO tbFinanceItem(ItemName) VALUES('",H26,"')"))
... A34: Exist | B34: MA | C34: 29 | D34: 33 | E34: 29 | F34: 33 | G34: 1312 | H34: (MA)IL-Other Indirect Labor Costs | I34: 6315, 6323 to 6349 | J34: =IF(A34<>"Remove",CONCATENATE("INSERT INTO tbFinanceItemSeq(Report,ItemSeqID,ItemSN,ItemID) VALUES('",B34,"',",C34,",",E34,",",G34,")"),"") -> INSERT INTO tbFinanceItemSeq(Report,ItemSeqID,ItemSN,ItemID) VALUES('MA',29,29,1312) | K34: =IF(A34<>"New","",CONCATENATE("INSERT INTO tbFinanceItem(ItemName) VALUES('",H34,"')"))
A35: New | B35: MA | C35: 30 | E35: 30 | G35: =CONCATENATE("(SELECT ItemID FROM tbFinanceItem where ItemName = '",H35,"')") -> (SELECT ItemID FROM tbFinanceItem where ItemName = '(MA)IL-QA Allocated Cost') | H35: (MA)IL-QA Allocated Cost | J35: =IF(A35<>"Remove",CONCATENATE("INSERT INTO tbFinanceItemSeq(Report,ItemSeqID,ItemSN,ItemID) VALUES('",B35,"',",C35,",",E35,",",G35,")"),"") -> INSERT INTO tbFinanceItemSeq(Report,ItemSeqID,ItemSN,ItemID) VALUES('MA',30,30,(SELECT ItemID FROM tbFinanceItem where ItemName = '(MA)IL-QA Allocated Cost')) | K35: =IF(A35<>"New","",CONCATENATE("INSERT INTO tbFinanceItem(ItemName) VALUES('",H35,"')")) -> INSERT INTO tbFinanceItem(ItemName) VALUES('(MA)IL-QA Allocated Cost')
A36: New | B36: MA | C36: 31 | E36: 31 | G36: =CONCATENATE("(SELECT ItemID FROM tbFinanceItem where ItemName = '",H36,"')") -> (SELECT ItemID FROM tbFinanceItem where ItemName = '(MA)IL-PM Allocated Cost') | H36: (MA)IL-PM Allocated Cost | J36: =IF(A36<>"Remove",CONCATENATE("INSERT INTO tbFinanceItemSeq(Report,ItemSeqID,ItemSN,ItemID) VALUES('",B36,"',",C36,",",E36,",",G36,")"),"") -> INSERT INTO tbFinanceItemSeq(Report,ItemSeqID,ItemSN,ItemID) VALUES('MA',31,31,(SELECT ItemID FROM tbFinanceItem where ItemName = '(MA)IL-PM Allocated Cost')) | K36: =IF(A36<>"New","",CONCATENATE("INSERT INTO tbFinanceItem(ItemName) VALUES('",H36,"')")) -> INSERT INTO tbFinanceItem(ItemName) VALUES('(MA)IL-PM Allocated Cost')
A37: Exist | B37: MA | C37: 32 | D37: 34 | E37: 32 | F37: 34 | G37: 1313 | H37: (MA)Indirect Labor | I37: =SUM(C25:C36) | J37: =IF(A37<>"Remove",CONCATENATE("INSERT INTO tbFinanceItemSeq(Report,ItemSeqID,ItemSN,ItemID) VALUES('",B37,"',",C37,",",E37,",",G37,")"),"") -> INSERT INTO tbFinanceItemSeq(Report,ItemSeqID,ItemSN,ItemID) VALUES('MA',32,32,1313) | K37: =IF(A37<>"New","",CONCATENATE("INSERT INTO tbFinanceItem(ItemName) VALUES('",H37,"')"))
A38: Exist | B38: MA | C38: 33 | D38: 35 | E38: 33 | F38: 35 | G38: 1314 | H38: (MA)Utilities - Elec, Water, Gas | I38: 6401 to 6410 | J38: =IF(A38<>"Remove",CONCATENATE("INSERT INTO tbFinanceItemSeq(Report,ItemSeqID,ItemSN,ItemID) VALUES('",B38,"',",C38,",",E38,",",G38,")"),"") -> INSERT INTO tbFinanceItemSeq(Report,ItemSeqID,ItemSN,ItemID) VALUES('MA',33,33,1314) | K38: =IF(A38<>"New","",CONCATENATE("INSERT INTO tbFinanceItem(ItemName) VALUES('",H38,"')"))
A39: Exist | B39: MA | C39: 34 | D39: 36 | E39: 34 | F39: 36 | G39: 1315 | H39: (MA)Product Development/Testing | I39: 6421 to 6430 | J39: =IF(A39<>"Remove",CONCATENATE("INSERT INTO tbFinanceItemSeq(Report,ItemSeqID,ItemSN,ItemID) VALUES('",B39,"',",C39,",",E39,",",G39,")"),"") -> INSERT INTO tbFinanceItemSeq(Report,ItemSeqID,ItemSN,ItemID) VALUES('MA',34,34,1315) | K39: =IF(A39<>"New","",CONCATENATE("INSERT INTO tbFinanceItem(ItemName) VALUES('",H39,"')"))
A40: Remove | B40: MA | C40: 35 | D40: 37 | E40: 35 | F40: 37 | G40: 1316 | H40: (MA)Carriage/Transport | J40: =IF(A40<>"Remove",CONCATENATE("INSERT INTO tbFinanceItemSeq(Report,ItemSeqID,ItemSN,ItemID) VALUES('",B40,"',",C40,",",E40,",",G40,")"),"") | K40: =IF(A40<>"New","",CONCATENATE("INSERT INTO tbFinanceItem(ItemName) VALUES('",H40,"')"))
A41: New | B41: MA | C41: 35 | D41: 37 | E41: 35 | F41: 37 | G41: =CONCATENATE("(SELECT ItemID FROM tbFinanceItem where ItemName = '",H41,"')") -> (SELECT ItemID FROM tbFinanceItem where ItemName = '(MA)Carriage/Transport/Storage') | H41: (MA)Carriage/Transport/Storage | I41: 6411 to 6420 | J41: =IF(A41<>"Remove",CONCATENATE("INSERT INTO tbFinanceItemSeq(Report,ItemSeqID,ItemSN,ItemID) VALUES('",B41,"',",C41,",",E41,",",G41,")"),"") -> INSERT INTO tbFinanceItemSeq(Report,ItemSeqID,ItemSN,ItemID) VALUES('MA',35,35,(SELECT ItemID FROM tbFinanceItem where ItemName = '(MA)Carriage/Transport/Storage')) | K41: =IF(A41<>"New","",CONCATENATE("INSERT INTO tbFinanceItem(ItemName) VALUES('",H41,"')")) -> INSERT INTO tbFinanceItem(ItemName) VALUES('(MA)Carriage/Transport/Storage')
A42: Exist | B42: MA | C42: 36 | D42: 38 | E42: 36 | F42: 38 | G42: 1317 | H42: (MA)Manufacturing Loss/Wastage | I42: 6431, 6432 | J42: =IF(A42<>"Remove",CONCATENATE("INSERT INTO tbFinanceItemSeq(Report,ItemSeqID,ItemSN,ItemID) VALUES('",B42,"',",C42,",",E42,",",G42,")"),"") -> INSERT INTO tbFinanceItemSeq(Report,ItemSeqID,ItemSN,ItemID) VALUES('MA',36,36,1317) | K42: =IF(A42<>"New","",CONCATENATE("INSERT INTO tbFinanceItem(ItemName) VALUES('",H42,"')"))
A43: Exist | B43: MA | C43: 37 | D43: 39 | E43: 37 | F43: 39 | G43: 1318 | H43: (MA)Rejects/Reworks/Scrap | I43: 6433 to 6435 | J43: =IF(A43<>"Remove",CONCATENATE("INSERT INTO tbFinanceItemSeq(Report,ItemSeqID,ItemSN,ItemID) VALUES('",B43,"',",C43,",",E43,",",G43,")"),"") -> INSERT INTO tbFinanceItemSeq(Report,ItemSeqID,ItemSN,ItemID) VALUES('MA',37,37,1318) | K43: =IF(A43<>"New","",CONCATENATE("INSERT INTO tbFinanceItem(ItemName) VALUES('",H43,"')"))
A44: Remove | B44: MA | C44: 38 | D44: 40 | E44: 38 | F44: 40 | G44: 1319 | H44: (MA)Sales of Scrap Production | J44: =IF(A44<>"Remove",CONCATENATE("INSERT INTO tbFinanceItemSeq(Report,ItemSeqID,ItemSN,ItemID) VALUES('",B44,"',",C44,",",E44,",",G44,")"),"") | K44: =IF(A44<>"New","",CONCATENATE("INSERT INTO tbFinanceItem(ItemName) VALUES('",H44,"')"))
A45: Remove | B45: MA | C45: 39 | D45: 41 | E45: 39 | F45: 41 | G45: 1320 | H45: (MA)Disposal of Slurge | J45: =IF(A45<>"Remove",CONCATENATE("INSERT INTO tbFinanceItemSeq(Report,ItemSeqID,ItemSN,ItemID) VALUES('",B45,"',",C45,",",E45,",",G45,")"),"") | K45: =IF(A45<>"New","",CONCATENATE("INSERT INTO tbFinanceItem(ItemName) VALUES('",H45,"')"))
A46: New | B46: MA | C46: 38 | E46: 38 | G46: =CONCATENATE("(SELECT ItemID FROM tbFinanceItem where ItemName = '",H46,"')") -> (SELECT ItemID FROM tbFinanceItem where ItemName = '(MA)Disposal of Slurge/Others') | H46: (MA)Disposal of Slurge/Others | I46: 6436 to 6499 | J46: =IF(A46<>"Remove",CONCATENATE("INSERT INTO tbFinanceItemSeq(Report,ItemSeqID,ItemSN,ItemID) VALUES('",B46,"',",C46,",",E46,",",G46,")"),"") -> INSERT INTO tbFinanceItemSeq(Report,ItemSeqID,ItemSN,ItemID) VALUES('MA',38,38,(SELECT ItemID FROM tbFinanceItem where ItemName = '(MA)Disposal of Slurge/Others')) | K46: =IF(A46<>"New","",CONCATENATE("INSERT INTO tbFinanceItem(ItemName) VALUES('",H46,"')")) -> INSERT INTO tbFinanceItem(ItemName) VALUES('(MA)Disposal of Slurge/Others')
A47: Remove | B47: MA | C47: 39 | D47: 42 | E47: 39 | F47: 42 | G47: 1321 | H47: (MA)Variable Overhead | J47: =IF(A47<>"Remove",CONCATENATE("INSERT INTO tbFinanceItemSeq(Report,ItemSeqID,ItemSN,ItemID) VALUES('",B47,"',",C47,",",E47,",",G47,")"),"") | K47: =IF(A47<>"New","",CONCATENATE("INSERT INTO tbFinanceItem(ItemName) VALUES('",H47,"')"))
A48: Remove | B48: MA | C48: 40 | D48: 43 | E48: 40 | F48: 43 | G48: 1322 | H48: (MA)Work in Progress | J48: =IF(A48<>"Remove",CONCATENATE("INSERT INTO tbFinanceItemSeq(Report,ItemSeqID,ItemSN,ItemID) VALUES('",B48,"',",C48,",",E48,",",G48,")"),"") | K48: =IF(A48<>"New","",CONCATENATE("INSERT INTO tbFinanceItem(ItemName) VALUES('",H48,"')"))
A49: New | B49: MA | C49: 39 | E49: 39 | G49: =CONCATENATE("(SELECT ItemID FROM tbFinanceItem where ItemName = '",H49,"')") -> (SELECT ItemID FROM tbFinanceItem where ItemName = '(MA)VO-QA Allocated Cost') | H49: (MA)VO-QA Allocated Cost | J49: =IF(A49<>"Remove",CONCATENATE("INSERT INTO tbFinanceItemSeq(Report,ItemSeqID,ItemSN,ItemID) VALUES('",B49,"',",C49,",",E49,",",G49,")"),"") -> INSERT INTO tbFinanceItemSeq(Report,ItemSeqID,ItemSN,ItemID) VALUES('MA',39,39,(SELECT ItemID FROM tbFinanceItem where ItemName = '(MA)VO-QA Allocated Cost')) | K49: =IF(A49<>"New","",CONCATENATE("INSERT INTO tbFinanceItem(ItemName) VALUES('",H49,"')")) -> INSERT INTO tbFinanceItem(ItemName) VALUES('(MA)VO-QA Allocated Cost')
A50: New | B50: MA | C50: 40 | E50: 40 | G50: =CONCATENATE("(SELECT ItemID FROM tbFinanceItem where ItemName = '",H50,"')") -> (SELECT ItemID FROM tbFinanceItem where ItemName = '(MA)VO-PM Allocated Cost') | H50: (MA)VO-PM Allocated Cost | J50: =IF(A50<>"Remove",CONCATENATE("INSERT INTO tbFinanceItemSeq(Report,ItemSeqID,ItemSN,ItemID) VALUES('",B50,"',",C50,",",E50,",",G50,")"),"") -> INSERT INTO tbFinanceItemSeq(Report,ItemSeqID,ItemSN,ItemID) VALUES('MA',40,40,(SELECT ItemID FROM tbFinanceItem where ItemName = '(MA)VO-PM Allocated Cost')) | K50: =IF(A50<>"New","",CONCATENATE("INSERT INTO tbFinanceItem(ItemName) VALUES('",H50,"')")) -> INSERT INTO tbFinanceItem(ItemName) VALUES('(MA)VO-PM Allocated Cost')
A51: Remove | B51: MA | C51: 43 | D51: 44 | E51: 43 | F51: 44 | G51: 1323 | H51: (MA)Total Variable Costs | J51: =IF(A51<>"Remove",CONCATENATE("INSERT INTO tbFinanceItemSeq(Report,ItemSeqID,ItemSN,ItemID) VALUES('",B51,"',",C51,",",E51,",",G51,")"),"") | K51: =IF(A51<>"New","",CONCATENATE("INSERT INTO tbFinanceItem(ItemName) VALUES('",H51,"')"))
A52: New | B52: MA | C52: 41 | E52: 41 | G52: =CONCATENATE("(SELECT ItemID FROM tbFinanceItem where ItemName = '",H52,"')") -> (SELECT ItemID FROM tbFinanceItem where ItemName = '(MA)Other Variable Overhead') | H52: (MA)Other Variable Overhead | I52: =SUM(C38:C45) | J52: =IF(A52<>"Remove",CONCATENATE("INSERT INTO tbFinanceItemSeq(Report,ItemSeqID,ItemSN,ItemID) VALUES('",B52,"',",C52,",",E52,",",G52,")"),"") -> INSERT INTO tbFinanceItemSeq(Report,ItemSeqID,ItemSN,ItemID) VALUES('MA',41,41,(SELECT ItemID FROM tbFinanceItem where ItemName = '(MA)Other Variable Overhead')) | K52: =IF(A52<>"New","",CONCATENATE("INSERT INTO tbFinanceItem(ItemName) VALUES('",H52,"')")) -> INSERT INTO tbFinanceItem(ItemName) VALUES('(MA)Other Variable Overhead')
A53: New | B53: MA | C53: 42 | E53: 42 | G53: =CONCATENATE("(SELECT ItemID FROM tbFinanceItem where ItemName = '",H53,"')") -> (SELECT ItemID FROM tbFinanceItem where ItemName = '(MA)Total Variable Overhead') | H53: (MA)Total Variable Overhead | I53: =C24+C37+C46 | J53: =IF(A53<>"Remove",CONCATENATE("INSERT INTO tbFinanceItemSeq(Report,ItemSeqID,ItemSN,ItemID) VALUES('",B53,"',",C53,",",E53,",",G53,")"),"") -> INSERT INTO tbFinanceItemSeq(Report,ItemSeqID,ItemSN,ItemID) VALUES('MA',42,42,(SELECT ItemID FROM tbFinanceItem where ItemName = '(MA)Total Variable Overhead')) | K53: =IF(A53<>"New","",CONCATENATE("INSERT INTO tbFinanceItem(ItemName) VALUES('",H53,"')")) -> INSERT INTO tbFinanceItem(ItemName) VALUES('(MA)Total Variable Overhead')
A54: Exist | B54: MA | C54: 43 | D54: 45 | E54: 43 | F54: 45 | G54: 1324 | H54: (MA)Factory Rental/Upkeep | I54: 6501 to 6502, 6506 | J54: =IF(A54<>"Remove",CONCATENATE("INSERT INTO tbFinanceItemSeq(Report,ItemSeqID,ItemSN,ItemID) VALUES('",B54,"',",C54,",",E54,",",G54,")"),"") -> INSERT INTO tbFinanceItemSeq(Report,ItemSeqID,ItemSN,ItemID) VALUES('MA',43,43,1324) | K54: =IF(A54<>"New","",CONCATENATE("INSERT INTO tbFinanceItem(ItemName) VALUES('",H54,"')"))
A55: Exist | B55: MA | C55: 44 | D55: 46 | E55: 44 | F55: 46 | G55: 1325 | H55: (MA)Property Tax for Factory | I55: 6503 | J55: =IF(A55<>"Remove",CONCATENATE("INSERT INTO tbFinanceItemSeq(Report,ItemSeqID,ItemSN,ItemID) VALUES('",B55,"',",C55,",",E55,",",G55,")"),"") -> INSERT INTO tbFinanceItemSeq(Report,ItemSeqID,ItemSN,ItemID) VALUES('MA',44,44,1325) | K55: =IF(A55<>"New","",CONCATENATE("INSERT INTO tbFinanceItem(ItemName) VALUES('",H55,"')"))
A56: Remove | B56: MA | C56: 48 | D56: 47 | E56: 48 | F56: 47 | G56: 1326 | H56: (MA)Repair & Maintainance | J56: =IF(A56<>"Remove",CONCATENATE("INSERT INTO tbFinanceItemSeq(Report,ItemSeqID,ItemSN,ItemID) VALUES('",B56,"',",C56,",",E56,",",G56,")"),"") | K56: =IF(A56<>"New","",CONCATENATE("INSERT INTO tbFinanceItem(ItemName) VALUES('",H56,"')"))
A57: New | B57: MA | C57: 45 | E57: 45 | G57: =CONCATENATE("(SELECT ItemID FROM tbFinanceItem where ItemName = '",H57,"')") -> (SELECT ItemID FROM tbFinanceItem where ItemName = '(MA)Repair & Maintainance/Upkeep') | H57: (MA)Repair & Maintainance/Upkeep | I57: 6601 to 6620 | J57: =IF(A57<>"Remove",CONCATENATE("INSERT INTO tbFinanceItemSeq(Report,ItemSeqID,ItemSN,ItemID) VALUES('",B57,"',",C57,",",E57,",",G57,")"),"") -> INSERT INTO tbFinanceItemSeq(Report,ItemSeqID,ItemSN,ItemID) VALUES('MA',45,45,(SELECT ItemID FROM tbFinanceItem where ItemName = '(MA)Repair & Maintainance/Upkeep')) | K57: =IF(A57<>"New","",CONCATENATE("INSERT INTO tbFinanceItem(ItemName) VALUES('",H57,"')")) -> INSERT INTO tbFinanceItem(ItemName) VALUES('(MA)Repair & Maintainance/Upkeep')
A58: Remove | B58: MA | C58: 49 | D58: 48 | E58: 49 | F58: 48 | G58: 1327 | H58: (MA)Leasing of Mac & Equip/Vehicles | J58: =IF(A58<>"Remove",CONCATENATE("INSERT INTO tbFinanceItemSeq(Report,ItemSeqID,ItemSN,ItemID) VALUES('",B58,"',",C58,",",E58,",",G58,")"),"") | K58: =IF(A58<>"New","",CONCATENATE("INSERT INTO tbFinanceItem(ItemName) VALUES('",H58,"')"))
A59: New | B59: MA | C59: 46 | E59: 46 | G59: =CONCATENATE("(SELECT ItemID FROM tbFinanceItem where ItemName = '",H59,"')") -> (SELECT ItemID FROM tbFinanceItem where ItemName = '(MA)Leasing of Mac & Equip/Vehicles/Cyl') | H59: (MA)Leasing of Mac & Equip/Vehicles/Cyl | I59: 6621 to 6623 | J59: =IF(A59<>"Remove",CONCATENATE("INSERT INTO tbFinanceItemSeq(Report,ItemSeqID,ItemSN,ItemID) VALUES('",B59,"',",C59,",",E59,",",G59,")"),"") -> INSERT INTO tbFinanceItemSeq(Report,ItemSeqID,ItemSN,ItemID) VALUES('MA',46,46,(SELECT ItemID FROM tbFinanceItem where ItemName = '(MA)Leasing of Mac & Equip/Vehicles/Cyl')) | K59: =IF(A59<>"New","",CONCATENATE("INSERT INTO tbFinanceItem(ItemName) VALUES('",H59,"')")) -> INSERT INTO tbFinanceItem(ItemName) VALUES('(MA)Leasing of Mac & Equip/Vehicles/Cyl')
A60: Exist | B60: MA | C60: 47 | D60: 49 | E60: 47 | F60: 49 | G60: 1328 | H60: (MA)Depreciation | I60: 6701 to 6749 | J60: =IF(A60<>"Remove",CONCATENATE("INSERT INTO tbFinanceItemSeq(Report,ItemSeqID,ItemSN,ItemID) VALUES('",B60,"',",C60,",",E60,",",G60,")"),"") -> INSERT INTO tbFinanceItemSeq(Report,ItemSeqID,ItemSN,ItemID) VALUES('MA',47,47,1328) | K60: =IF(A60<>"New","",CONCATENATE("INSERT INTO tbFinanceItem(ItemName) VALUES('",H60,"')"))
A61: Exist | B61: MA | C61: 48 | D61: 50 | E61: 48 | F61: 50 | G61: 1329 | H61: (MA)Licenses & Insurance | I61: 6504, 6751 to 6759 | J61: =IF(A61<>"Remove",CONCATENATE("INSERT INTO tbFinanceItemSeq(Report,ItemSeqID,ItemSN,ItemID) VALUES('",B61,"',",C61,",",E61,",",G61,")"),"") -> INSERT INTO tbFinanceItemSeq(Report,ItemSeqID,ItemSN,ItemID) VALUES('MA',48,48,1329) | K61: =IF(A61<>"New","",CONCATENATE("INSERT INTO tbFinanceItem(ItemName) VALUES('",H61,"')"))
A62: Exist | B62: MA | C62: 49 | D62: 51 | E62: 49 | F62: 51 | G62: 1330 | H62: (MA)Non Capitalised Purchases | I62: 6761 to 6769 | J62: =IF(A62<>"Remove",CONCATENATE("INSERT INTO tbFinanceItemSeq(Report,ItemSeqID,ItemSN,ItemID) VALUES('",B62,"',",C62,",",E62,",",G62,")"),"") -> INSERT INTO tbFinanceItemSeq(Report,ItemSeqID,ItemSN,ItemID) VALUES('MA',49,49,1330) | K62: =IF(A62<>"New","",CONCATENATE("INSERT INTO tbFinanceItem(ItemName) VALUES('",H62,"')"))
A63: Exist | B63: MA | C63: 50 | D63: 52 | E63: 50 | F63: 52 | G63: 1331 | H63: (MA)Others Fixed Overhead | I63: 6505, 6771 to 6799 | J63: =IF(A63<>"Remove",CONCATENATE("INSERT INTO tbFinanceItemSeq(Report,ItemSeqID,ItemSN,ItemID) VALUES('",B63,"',",C63,",",E63,",",G63,")"),"") -> INSERT INTO tbFinanceItemSeq(Report,ItemSeqID,ItemSN,ItemID) VALUES('MA',50,50,1331) | K63: =IF(A63<>"New","",CONCATENATE("INSERT INTO tbFinanceItem(ItemName) VALUES('",H63,"')"))
A64: New | B64: MA | C64: 51 | E64: 51 | G64: =CONCATENATE("(SELECT ItemID FROM tbFinanceItem where ItemName = '",H64,"')") -> (SELECT ItemID FROM tbFinanceItem where ItemName = '(MA)QA Allocated Cost') | H64: (MA)QA Allocated Cost | J64: =IF(A64<>"Remove",CONCATENATE("INSERT INTO tbFinanceItemSeq(Report,ItemSeqID,ItemSN,ItemID) VALUES('",B64,"',",C64,",",E64,",",G64,")"),"") -> INSERT INTO tbFinanceItemSeq(Report,ItemSeqID,ItemSN,ItemID) VALUES('MA',51,51,(SELECT ItemID FROM tbFinanceItem where ItemName = '(MA)QA Allocated Cost')) | K64: =IF(A64<>"New","",CONCATENATE("INSERT INTO tbFinanceItem(ItemName) VALUES('",H64,"')")) -> INSERT INTO tbFinanceItem(ItemName) VALUES('(MA)QA Allocated Cost')
A65: New | B65: MA | C65: 52 | E65: 52 | G65: =CONCATENATE("(SELECT ItemID FROM tbFinanceItem where ItemName = '",H65,"')") -> (SELECT ItemID FROM tbFinanceItem where ItemName = '(MA)PM Allocated Cost') | H65: (MA)PM Allocated Cost | J65: =IF(A65<>"Remove",CONCATENATE("INSERT INTO tbFinanceItemSeq(Report,ItemSeqID,ItemSN,ItemID) VALUES('",B65,"',",C65,",",E65,",",G65,")"),"") -> INSERT INTO tbFinanceItemSeq(Report,ItemSeqID,ItemSN,ItemID) VALUES('MA',52,52,(SELECT ItemID FROM tbFinanceItem where ItemName = '(MA)PM Allocated Cost')) | K65: =IF(A65<>"New","",CONCATENATE("INSERT INTO tbFinanceItem(ItemName) VALUES('",H65,"')")) -> INSERT INTO tbFinanceItem(ItemName) VALUES('(MA)PM Allocated Cost')
A66: Exist | B66: MA | C66: 53 | D66: 53 | E66: 53 | F66: 53 | G66: 1332 | H66: (MA)Fixed Overhead | I66: =SUM(C48:C57) | J66: =IF(A66<>"Remove",CONCATENATE("INSERT INTO tbFinanceItemSeq(Report,ItemSeqID,ItemSN,ItemID) VALUES('",B66,"',",C66,",",E66,",",G66,")"),"") -> INSERT INTO tbFinanceItemSeq(Report,ItemSeqID,ItemSN,ItemID) VALUES('MA',53,53,1332) | K66: =IF(A66<>"New","",CONCATENATE("INSERT INTO tbFinanceItem(ItemName) VALUES('",H66,"')"))
A67: Exist | B67: MA | C67: 54 | D67: 54 | E67: 54 | F67: 54 | G67: 1333 | H67: (MA)Cost of Goods Manufactured | I67: =C23+C47+C58 | J67: =IF(A67<>"Remove",CONCATENATE("INSERT INTO tbFinanceItemSeq(Report,ItemSeqID,ItemSN,ItemID) VALUES('",B67,"',",C67,",",E67,",",G67,")"),"") -> INSERT INTO tbFinanceItemSeq(Report,ItemSeqID,ItemSN,ItemID) VALUES('MA',54,54,1333) | K67: =IF(A67<>"New","",CONCATENATE("INSERT INTO tbFinanceItem(ItemName) VALUES('",H67,"')"))
A68: Remove | B68: MA | C68: 58 | D68: 55 | E68: 58 | F68: 0 | G68: 46 | H68: Performance Indicators | J68: =IF(A68<>"Remove",CONCATENATE("INSERT INTO tbFinanceItemSeq(Report,ItemSeqID,ItemSN,ItemID) VALUES('",B68,"',",C68,",",E68,",",G68,")"),"") | K68: =IF(A68<>"New","",CONCATENATE("INSERT INTO tbFinanceItem(ItemName) VALUES('",H68,"')"))
A69: Remove | B69: MA | C69: 59 | D69: 56 | E69: 59 | F69: 1 | G69: 1334 | H69: (MA)Direct Material (m3 / Kg) | J69: =IF(A69<>"Remove",CONCATENATE("INSERT INTO tbFinanceItemSeq(Report,ItemSeqID,ItemSN,ItemID) VALUES('",B69,"',",C69,",",E69,",",G69,")"),"") | K69: =IF(A69<>"New","",CONCATENATE("INSERT INTO tbFinanceItem(ItemName) VALUES('",H69,"')"))
A70: Remove | B70: MA | C70: 60 | D70: 57 | E70: 60 | F70: 2 | G70: 1335 | H70: (MA)Direct Labour (m3 / Kg) | J70: =IF(A70<>"Remove",CONCATENATE("INSERT INTO tbFinanceItemSeq(Report,ItemSeqID,ItemSN,ItemID) VALUES('",B70,"',",C70,",",E70,",",G70,")"),"") | K70: =IF(A70<>"New","",CONCATENATE("INSERT INTO tbFinanceItem(ItemName) VALUES('",H70,"')"))
A71: Remove | B71: MA | C71: 61 | D71: 58 | E71: 61 | F71: 3 | G71: 1336 | H71: (MA)Direct Exps (m3 / Kg) | J71: =IF(A71<>"Remove",CONCATENATE("INSERT INTO tbFinanceItemSeq(Report,ItemSeqID,ItemSN,ItemID) VALUES('",B71,"',",C71,",",E71,",",G71,")"),"") | K71: =IF(A71<>"New","",CONCATENATE("INSERT INTO tbFinanceItem(ItemName) VALUES('",H71,"')"))
A72: Remove | B72: MA | C72: 62 | D72: 59 | E72: 62 | F72: 4 | G72: 1337 | H72: (MA)Indirect Material (m3 / Kg) | J72: =IF(A72<>"Remove",CONCATENATE("INSERT INTO tbFinanceItemSeq(Report,ItemSeqID,ItemSN,ItemID) VALUES('",B72,"',",C72,",",E72,",",G72,")"),"") | K72: =IF(A72<>"New","",CONCATENATE("INSERT INTO tbFinanceItem(ItemName) VALUES('",H72,"')"))
A73: Remove | B73: MA | C73: 63 | D73: 60 | E73: 63 | F73: 5 | G73: 1338 | H73: (MA)Indirect Labour (m3 / Kg) | J73: =IF(A73<>"Remove",CONCATENATE("INSERT INTO tbFinanceItemSeq(Report,ItemSeqID,ItemSN,ItemID) VALUES('",B73,"',",C73,",",E73,",",G73,")"),"") | K73: =IF(A73<>"New","",CONCATENATE("INSERT INTO tbFinanceItem(ItemName) VALUES('",H73,"')"))
A74: Remove | B74: MA | C74: 64 | D74: 61 | E74: 64 | F74: 6 | G74: 1339 | H74: (MA)Variable Overhead (m3 / Kg) | J74: =IF(A74<>"Remove",CONCATENATE("INSERT INTO tbFinanceItemSeq(Report,ItemSeqID,ItemSN,ItemID) VALUES('",B74,"',",C74,",",E74,",",G74,")"),"") | K74: =IF(A74<>"New","",CONCATENATE("INSERT INTO tbFinanceItem(ItemName) VALUES('",H74,"')"))
A75: Remove | B75: MA | C75: 65 | D75: 62 | E75: 65 | F75: 7 | G75: 1340 | H75: (MA)Total Variable (m3 / Kg) | J75: =IF(A75<>"Remove",CONCATENATE("INSERT INTO tbFinanceItemSeq(Report,ItemSeqID,ItemSN,ItemID) VALUES('",B75,"',",C75,",",E75,",",G75,")"),"") | K75: =IF(A75<>"New","",CONCATENATE("INSERT INTO tbFinanceItem(ItemName) VALUES('",H75,"')"))
A76: Remove | B76: MA | C76: 66 | D76: 63 | E76: 66 | F76: 8 | G76: 1341 | H76: (MA)Fixed Overhead (m3 / Kg) | J76: =IF(A76<>"Remove",CONCATENATE("INSERT INTO tbFinanceItemSeq(Report,ItemSeqID,ItemSN,ItemID) VALUES('",B76,"',",C76,",",E76,",",G76,")"),"") | K76: =IF(A76<>"New","",CONCATENATE("INSERT INTO tbFinanceItem(ItemName) VALUES('",H76,"')"))
A77: Remove | B77: MA | C77: 67 | D77: 64 | E77: 67 | F77: 9 | G77: 1342 | H77: (MA)Manufacturing Costs (m3/ Kg) | J77: =IF(A77<>"Remove",CONCATENATE("INSERT INTO tbFinanceItemSeq(Report,ItemSeqID,ItemSN,ItemID) VALUES('",B77,"',",C77,",",E77,",",G77,")"),"") | K77: =IF(A77<>"New","",CONCATENATE("INSERT INTO tbFinanceItem(ItemName) VALUES('",H77,"')"))

Sheet F131 F30 BS-Debug
A1: SELECT TOP 10 * FROM tbReport where ReportID = 431;
A2: --F131 Balance Sheet.rpt
A3: --procReportFinanceBS
A4: --(BS)
A6: select s.* , i.ItemName from tbFinanceItemSeq s
A7: LEFT JOIN tbFinanceItem i on s.ItemID = i.ItemID
A8: where s.Report = 'BS'
A9: order by s.ItemSeqID
A12: DELETE FROM tbFinanceItemSeq where Report = 'BS'
A15: Update tbReport
A16: set FileName = 'F131 Balance Sheet.rpt' ,
A17: Description = '[COA2016] F30 Balance Sheet'
A18: where ReportID =431;

Sheet F131 F30 BS-Origin
A1: Report | B1: ItemSeqID | C1: ItemSN | D1: ItemID | E1: ItemName | F1: Insert Script
A2: BS | B2: 1 | C2: 1 | D2: 501 | E2: (BS)Cash and Bank Balances | F2: =CONCATENATE("INSERT INTO tbFinanceItemSeq(Report,ItemSeqID,ItemSN,ItemID) VALUES('",A2,"',",B2,",",C2,",",D2,")") -> INSERT INTO tbFinanceItemSeq(Report,ItemSeqID,ItemSN,ItemID) VALUES('BS',1,1,501)
A3: BS | B3: 2 | C3: 2 | D3: 502 | E3: (BS)Fixed Deposits | F3: =CONCATENATE("INSERT INTO tbFinanceItemSeq(Report,ItemSeqID,ItemSN,ItemID) VALUES('",A3,"',",B3,",",C3,",",D3,")") -> INSERT INTO tbFinanceItemSeq(Report,ItemSeqID,ItemSN,ItemID) VALUES('BS',2,2,502)
A4: BS | B4: 3 | C4: 3 | D4: 503 | E4: (BS)Stocks | F4: =CONCATENATE("INSERT INTO tbFinanceItemSeq(Report,ItemSeqID,ItemSN,ItemID) VALUES('",A4,"',",B4,",",C4,",",D4,")") -> INSERT INTO tbFinanceItemSeq(Report,ItemSeqID,ItemSN,ItemID) VALUES('BS',3,3,503)
A5: BS | B5: 4 | C5: 4 | D5: 504 | E5: (BS)Trade Debtors | F5: =CONCATENATE("INSERT INTO tbFinanceItemSeq(Report,ItemSeqID,ItemSN,ItemID) VALUES('",A5,"',",B5,",",C5,",",D5,")") -> INSERT INTO tbFinanceItemSeq(Report,ItemSeqID,ItemSN,ItemID) VALUES('BS',4,4,504)
A6: BS | B6: 5 | C6: 5 | D6: 505 | E6: (BS)Due From Assoc/JV/Related - Current | F6: =CONCATENATE("INSERT INTO tbFinanceItemSeq(Report,ItemSeqID,ItemSN,ItemID) VALUES('",A6,"',",B6,",",C6,",",D6,")") -> INSERT INTO tbFinanceItemSeq(Report,ItemSeqID,ItemSN,ItemID) VALUES('BS',5,5,505)
A7: BS | B7: 6 | C7: 6 | D7: 506 | E7: (BS)Due From Interco - Current | F7: =CONCATENATE("INSERT INTO tbFinanceItemSeq(Report,ItemSeqID,ItemSN,ItemID) VALUES('",A7,"',",B7,",",C7,",",D7,")") -> INSERT INTO tbFinanceItemSeq(Report,ItemSeqID,ItemSN,ItemID) VALUES('BS',6,6,506)
A8: BS | B8: 7 | C8: 7 | D8: 507 | E8: (BS)Short-Term Investment | F8: =CONCATENATE("INSERT INTO tbFinanceItemSeq(Report,ItemSeqID,ItemSN,ItemID) VALUES('",A8,"',",B8,",",C8,",",D8,")") -> INSERT INTO tbFinanceItemSeq(Report,ItemSeqID,ItemSN,ItemID) VALUES('BS',7,7,507)
A9: BS | B9: 8 | C9: 8 | D9: 508 | E9: (BS)Other Debtors/Deposits/Prepayment | F9: =CONCATENATE("INSERT INTO tbFinanceItemSeq(Report,ItemSeqID,ItemSN,ItemID) VALUES('",A9,"',",B9,",",C9,",",D9,")") -> INSERT INTO tbFinanceItemSeq(Report,ItemSeqID,ItemSN,ItemID) VALUES('BS',8,8,508)
A10: BS | B10: 9 | C10: 9 | D10: 509 | E10: (BS)TOTAL CURRENT ASSETS | F10: =CONCATENATE("INSERT INTO tbFinanceItemSeq(Report,ItemSeqID,ItemSN,ItemID) VALUES('",A10,"',",B10,",",C10,",",D10,")") -> INSERT INTO tbFinanceItemSeq(Report,ItemSeqID,ItemSN,ItemID) VALUES('BS',9,9,509)
A11: BS | B11: 10 | C11: 10 | D11: 510 | E11: (BS)Freehold Land | F11: =CONCATENATE("INSERT INTO tbFinanceItemSeq(Report,ItemSeqID,ItemSN,ItemID) VALUES('",A11,"',",B11,",",C11,",",D11,")") -> INSERT INTO tbFinanceItemSeq(Report,ItemSeqID,ItemSN,ItemID) VALUES('BS',10,10,510)
A12: BS | B12: 11 | C12: 11 | D12: 512 | E12: (BS)Leasehold Properties | F12: =CONCATENATE("INSERT INTO tbFinanceItemSeq(Report,ItemSeqID,ItemSN,ItemID) VALUES('",A12,"',",B12,",",C12,",",D12,")") -> INSERT INTO tbFinanceItemSeq(Report,ItemSeqID,ItemSN,ItemID) VALUES('BS',11,11,512)
A13: BS | B13: 12 | C13: 12 | D13: 513 | E13: (BS)Construction in Progress | F13: =CONCATENATE("INSERT INTO tbFinanceItemSeq(Report,ItemSeqID,ItemSN,ItemID) VALUES('",A13,"',",B13,",",C13,",",D13,")") -> INSERT INTO tbFinanceItemSeq(Report,ItemSeqID,ItemSN,ItemID) VALUES('BS',12,12,513)
... A69: BS | B69: 68 | C69: 7 | D69: 1134 | E69: Provision for Plant Maintenance | F69: =CONCATENATE("INSERT INTO tbFinanceItemSeq(Report,ItemSeqID,ItemSN,ItemID) VALUES('",A69,"',",B69,",",C69,",",D69,")") -> INSERT INTO tbFinanceItemSeq(Report,ItemSeqID,ItemSN,ItemID) VALUES('BS',68,7,1134)

Sheet F131 F30 BS-DIFF
A1: Old | B1: F30 New | C1: F30 Different | D1: F30R New | E1: F32 Different
A2: Cash and Bank Balances | B2: Cash and Bank Balances | C2: =IF(A2=B2,TRUE,B2) -> TRUE | D2: Cash and Bank Balances | E2: =IF(A2=D2,TRUE,D2) -> TRUE
A3: Fixed Deposits | B3: Fixed Deposits | C3: =IF(A3=B3,TRUE,B3) -> TRUE | D3: Fixed Deposits | E3: =IF(A3=D3,TRUE,D3) -> TRUE
A4: Stocks | B4: Stocks | C4: =IF(A4=B4,TRUE,B4) -> TRUE | D4: Stocks | E4: =IF(A4=D4,TRUE,D4) -> TRUE
A5: Trade Debtors | B5: Trade Debtors | C5: =IF(A5=B5,TRUE,B5) -> TRUE | D5: Trade Debtors | E5: =IF(A5=D5,TRUE,D5) -> TRUE
A6: Due From Assoc/JV/Related - Current | B6: Due From Assoc/JV/Related | C6: =IF(A6=B6,TRUE,B6) -> Due From Assoc/JV/Related | D6: Due From Assoc/JV/Related | E6: =IF(A6=D6,TRUE,D6) -> Due From Assoc/JV/Related
A7: Due From Interco - Current | B7: Due From Interco | C7: =IF(A7=B7,TRUE,B7) -> Due From Interco | D7: Due From Interco | E7: =IF(A7=D7,TRUE,D7) -> Due From Interco
A8: Short-Term Investment | B8: Short-Term Investment | C8: =IF(A8=B8,TRUE,B8) -> TRUE | D8: Short-Term Investment | E8: =IF(A8=D8,TRUE,D8) -> TRUE
A9: Other Debtors/Deposits/Prepayment | B9: Other Debtors/Deposits/Prepayment | C9: =IF(A9=B9,TRUE,B9) -> TRUE | D9: Other Debtors/Deposits/Prepayment | E9: =IF(A9=D9,TRUE,D9) -> TRUE
A10: TOTAL CURRENT ASSETS | B10: TOTAL CURRENT ASSETS | C10: =IF(A10=B10,TRUE,B10) -> TRUE | D10: TOTAL CURRENT ASSETS | E10: =IF(A10=D10,TRUE,D10) -> TRUE
A11: Freehold Land | B11: Freehold Land | C11: =IF(A11=B11,TRUE,B11) -> Freehold Land | D11: Freehold Land | E11: =IF(A11=D11,TRUE,D11) -> Freehold Land
A12: Leasehold Properties | B12: Leasehold Properties | C12: =IF(A12=B12,TRUE,B12) -> TRUE | D12: Leasehold Properties | E12: =IF(A12=D12,TRUE,D12) -> TRUE
A13: Construction in Progress | B13: Construction in Progress | C13: =IF(A13=B13,TRUE,B13) -> TRUE | D13: Construction in Progress | E13: =IF(A13=D13,TRUE,D13) -> TRUE
... A64: Stocks Turnover (Days) | B64: Stocks Turnover (Days) | C64: =IF(A64=B64,TRUE,B64) -> TRUE | D64: Stocks Turnover (Days) | E64: =IF(A64=D64,TRUE,D64) -> TRUE
B65: Creditors Turnover (Days) | C65: =IF(A66=B65,TRUE,B65) -> Creditors Turnover (Days) | D65: Creditors Turnover (Days) | E65: =IF(A65=D65,TRUE,D65) -> Creditors Turnover (Days)
A66: Liabilities To Equity (Leverage) | B66: Liabilities to Equity (Leverage) | C66: =IF(A66=B66,TRUE,B66) -> TRUE | D66: Liabilities to Equity (Leverage) | E66: =IF(A66=D66,TRUE,D66) -> TRUE
A67: Debt To Equity | B67: Debt to Equity | C67: =IF(A67=B67,TRUE,B67) -> TRUE | D67: Debt to Equity | E67: =IF(A67=D67,TRUE,D67) -> TRUE
A68: Prov for Doubtful Debts | B68: Provision for Doubtful Debts | C68: =IF(A68=B68,TRUE,B68) -> Provision for Doubtful Debts | D68: Provision for Doubtful Debts | E68: =IF(A68=D68,TRUE,D68) -> Provision for Doubtful Debts
A69: Provision for Stock Obso/Pilferage | B69: Provision for Stock Obso/Pilferage | C69: =IF(A69=B69,TRUE,B69) -> TRUE | D69: Provision for Stock Obso/Pilferage | E69: =IF(A69=D69,TRUE,D69) -> TRUE
A70: Provision for Plant Maintenance | B70: Provision for Plant Maintenance | C70: =IF(A70=B70,TRUE,B70) -> TRUE | D70: Provision for Plant Maintenance | E70: =IF(A70=D70,TRUE,D70) -> TRUE

Sheet F131 F30 BS-NEW
A1: Status | B1: Report | D1: ItemSeqID | F1: ItemSN | G1: ItemID | H1: ItemName | J1: Insert Script | K1: Remark
A2: Exist | B2: BS | C2: 1 | D2: 1 | E2: 1 | F2: 1 | G2: 501 | H2: (BS)Cash and Bank Balances | I2: 1000 to 1099Debit, 3000 to 3099Debit | J2: =IF(A2<>"Remove",CONCATENATE("INSERT INTO tbFinanceItemSeq(Report,ItemSeqID,ItemSN,ItemID) VALUES('",B2,"',",C2,",",E2,",",G2,")"),"") -> INSERT INTO tbFinanceItemSeq(Report,ItemSeqID,ItemSN,ItemID) VALUES('BS',1,1,501)
A3: Exist | B3: BS | C3: 2 | D3: 2 | E3: 2 | F3: 2 | G3: 502 | H3: (BS)Fixed Deposits | I3: 1100 to 1199 | J3: =IF(A3<>"Remove",CONCATENATE("INSERT INTO tbFinanceItemSeq(Report,ItemSeqID,ItemSN,ItemID) VALUES('",B3,"',",C3,",",E3,",",G3,")"),"") -> INSERT INTO tbFinanceItemSeq(Report,ItemSeqID,ItemSN,ItemID) VALUES('BS',2,2,502)
A4: Exist | B4: BS | C4: 3 | D4: 3 | E4: 3 | F4: 3 | G4: 503 | H4: (BS)Stocks | I4: 1200 to 1299 | J4: =IF(A4<>"Remove",CONCATENATE("INSERT INTO tbFinanceItemSeq(Report,ItemSeqID,ItemSN,ItemID) VALUES('",B4,"',",C4,",",E4,",",G4,")"),"") -> INSERT INTO tbFinanceItemSeq(Report,ItemSeqID,ItemSN,ItemID) VALUES('BS',3,3,503)
A5: Exist | B5: BS | C5: 4 | D5: 4 | E5: 4 | F5: 4 | G5: 504 | H5: (BS)Trade Debtors | I5: 1300 to 1399, 1499 | J5: =IF(A5<>"Remove",CONCATENATE("INSERT INTO tbFinanceItemSeq(Report,ItemSeqID,ItemSN,ItemID) VALUES('",B5,"',",C5,",",E5,",",G5,")"),"") -> INSERT INTO tbFinanceItemSeq(Report,ItemSeqID,ItemSN,ItemID) VALUES('BS',4,4,504)
A6: Exist | B6: BS | C6: 5 | D6: 5 | E6: 5 | F6: 5 | G6: 505 | H6: (BS)Due From Assoc/JV/Related - Current | I6: 1411 to 1433 | J6: =IF(A6<>"Remove",CONCATENATE("INSERT INTO tbFinanceItemSeq(Report,ItemSeqID,ItemSN,ItemID) VALUES('",B6,"',",C6,",",E6,",",G6,")"),"") -> INSERT INTO tbFinanceItemSeq(Report,ItemSeqID,ItemSN,ItemID) VALUES('BS',5,5,505)
A7: Exist | B7: BS | C7: 6 | D7: 6 | E7: 6 | F7: 6 | G7: 506 | H7: (BS)Due From Interco - Current | I7: 1401 to 1404 | J7: =IF(A7<>"Remove",CONCATENATE("INSERT INTO tbFinanceItemSeq(Report,ItemSeqID,ItemSN,ItemID) VALUES('",B7,"',",C7,",",E7,",",G7,")"),"") -> INSERT INTO tbFinanceItemSeq(Report,ItemSeqID,ItemSN,ItemID) VALUES('BS',6,6,506)
A8: Exist | B8: BS | C8: 7 | D8: 7 | E8: 7 | F8: 7 | G8: 507 | H8: (BS)Short-Term Investment | I8: 1501 to 1699 Except 1502 | J8: =IF(A8<>"Remove",CONCATENATE("INSERT INTO tbFinanceItemSeq(Report,ItemSeqID,ItemSN,ItemID) VALUES('",B8,"',",C8,",",E8,",",G8,")"),"") -> INSERT INTO tbFinanceItemSeq(Report,ItemSeqID,ItemSN,ItemID) VALUES('BS',7,7,507)
A9: Exist | B9: BS | C9: 8 | D9: 8 | E9: 8 | F9: 8 | G9: 508 | H9: (BS)Other Debtors/Deposits/Prepayment | I9: 1700, 1800 to 1999 | J9: =IF(A9<>"Remove",CONCATENATE("INSERT INTO tbFinanceItemSeq(Report,ItemSeqID,ItemSN,ItemID) VALUES('",B9,"',",C9,",",E9,",",G9,")"),"") -> INSERT INTO tbFinanceItemSeq(Report,ItemSeqID,ItemSN,ItemID) VALUES('BS',8,8,508)
A10: Exist | B10: BS | C10: 9 | D10: 9 | E10: 9 | F10: 9 | G10: 509 | H10: (BS)TOTAL CURRENT ASSETS | I10: =SUM(C5:C12) | J10: =IF(A10<>"Remove",CONCATENATE("INSERT INTO tbFinanceItemSeq(Report,ItemSeqID,ItemSN,ItemID) VALUES('",B10,"',",C10,",",E10,",",G10,")"),"") -> INSERT INTO tbFinanceItemSeq(Report,ItemSeqID,ItemSN,ItemID) VALUES('BS',9,9,509)
A11: Exist | B11: BS | C11: 10 | D11: 10 | E11: 10 | F11: 10 | G11: 510 | H11: (BS)Freehold Land | I11: 2001 (Exclude A-Z) | J11: =IF(A11<>"Remove",CONCATENATE("INSERT INTO tbFinanceItemSeq(Report,ItemSeqID,ItemSN,ItemID) VALUES('",B11,"',",C11,",",E11,",",G11,")"),"") -> INSERT INTO tbFinanceItemSeq(Report,ItemSeqID,ItemSN,ItemID) VALUES('BS',10,10,510)
A12: Exist | B12: BS | C12: 11 | D12: 11 | E12: 11 | F12: 11 | G12: 512 | H12: (BS)Leasehold Properties | I12: 2002 to 2019 (Exclude A-Z) | J12: =IF(A12<>"Remove",CONCATENATE("INSERT INTO tbFinanceItemSeq(Report,ItemSeqID,ItemSN,ItemID) VALUES('",B12,"',",C12,",",E12,",",G12,")"),"") -> INSERT INTO tbFinanceItemSeq(Report,ItemSeqID,ItemSN,ItemID) VALUES('BS',11,11,512)
A13: Exist | B13: BS | C13: 12 | D13: 12 | E13: 12 | F13: 12 | G13: 513 | H13: (BS)Construction in Progress | I13: 2021 (Exclude A-Z) | J13: =IF(A13<>"Remove",CONCATENATE("INSERT INTO tbFinanceItemSeq(Report,ItemSeqID,ItemSN,ItemID) VALUES('",B13,"',",C13,",",E13,",",G13,")"),"") -> INSERT INTO tbFinanceItemSeq(Report,ItemSeqID,ItemSN,ItemID) VALUES('BS',12,12,513)
... A19: Exist | B19: BS | C19: 18 | D19: 18 | E19: 18 | F19: 18 | G19: 519 | H19: (BS)Motor Vehicles | I19: 2401 to 2499 (Exclude A-Z) | J19: =IF(A19<>"Remove",CONCATENATE("INSERT INTO tbFinanceItemSeq(Report,ItemSeqID,ItemSN,ItemID) VALUES('",B19,"',",C19,",",E19,",",G19,")"),"") -> INSERT INTO tbFinanceItemSeq(Report,ItemSeqID,ItemSN,ItemID) VALUES('BS',18,18,519)
A20: Remove | B20: BS | C20: 19 | D20: 19 | E20: 19 | F20: 19 | G20: 520 | H20: (BS)Less:Accumulated Depreciation | J20: =IF(A20<>"Remove",CONCATENATE("INSERT INTO tbFinanceItemSeq(Report,ItemSeqID,ItemSN,ItemID) VALUES('",B20,"',",C20,",",E20,",",G20,")"),"") | K20: Update Name
A21: New | B21: BS | C21: 19 | D21: 19 | E21: 19 | F21: 19 | G21: 520 | H21: (BS)Less:Accumulated Depreciation/Impairment | I21: 2001 to 2499 A-Z | J21: =IF(A21<>"Remove",CONCATENATE("INSERT INTO tbFinanceItemSeq(Report,ItemSeqID,ItemSN,ItemID) VALUES('",B21,"',",C21,",",E21,",",G21,")"),"") -> INSERT INTO tbFinanceItemSeq(Report,ItemSeqID,ItemSN,ItemID) VALUES('BS',19,19,520)
A22: Exist | B22: BS | C22: 20 | D22: 20 | E22: 20 | F22: 20 | G22: 521 | H22: (BS)NET FIXED ASSETS | I22: =SUM(C14:C23) | J22: =IF(A22<>"Remove",CONCATENATE("INSERT INTO tbFinanceItemSeq(Report,ItemSeqID,ItemSN,ItemID) VALUES('",B22,"',",C22,",",E22,",",G22,")"),"") -> INSERT INTO tbFinanceItemSeq(Report,ItemSeqID,ItemSN,ItemID) VALUES('BS',20,20,521)
A23: Exist | B23: BS | C23: 21 | D23: 21 | E23: 21 | F23: 21 | G23: 522 | H23: (BS)Investment in Subsidiaries | I23: 2501 (Exclude Z) | J23: =IF(A23<>"Remove",CONCATENATE("INSERT INTO tbFinanceItemSeq(Report,ItemSeqID,ItemSN,ItemID) VALUES('",B23,"',",C23,",",E23,",",G23,")"),"") -> INSERT INTO tbFinanceItemSeq(Report,ItemSeqID,ItemSN,ItemID) VALUES('BS',21,21,522)
A24: Exist | B24: BS | C24: 22 | D24: 22 | E24: 22 | F24: 22 | G24: 523 | H24: (BS)Investment in Assoc/JV/Related | I24: 2502 to 2699 (Exclude Z) | J24: =IF(A24<>"Remove",CONCATENATE("INSERT INTO tbFinanceItemSeq(Report,ItemSeqID,ItemSN,ItemID) VALUES('",B24,"',",C24,",",E24,",",G24,")"),"") -> INSERT INTO tbFinanceItemSeq(Report,ItemSeqID,ItemSN,ItemID) VALUES('BS',22,22,523)
A25: Exist | B25: BS | C25: 23 | D25: 23 | E25: 23 | F25: 23 | G25: 524 | H25: (BS)Intangible Assets | I25: 2701 to 2719 | J25: =IF(A25<>"Remove",CONCATENATE("INSERT INTO tbFinanceItemSeq(Report,ItemSeqID,ItemSN,ItemID) VALUES('",B25,"',",C25,",",E25,",",G25,")"),"") -> INSERT INTO tbFinanceItemSeq(Report,ItemSeqID,ItemSN,ItemID) VALUES('BS',23,23,524)
A26: Exist | B26: BS | C26: 24 | D26: 24 | E26: 24 | F26: 24 | G26: 525 | H26: (BS)Due From Interco - Non Current | I26: 2721 | J26: =IF(A26<>"Remove",CONCATENATE("INSERT INTO tbFinanceItemSeq(Report,ItemSeqID,ItemSN,ItemID) VALUES('",B26,"',",C26,",",E26,",",G26,")"),"") -> INSERT INTO tbFinanceItemSeq(Report,ItemSeqID,ItemSN,ItemID) VALUES('BS',24,24,525)
A27: Exist | B27: BS | C27: 25 | D27: 25 | E27: 25 | F27: 25 | G27: 526 | H27: (BS)Due From Assoc/JV/Related - Non Current | I27: 2722 to 2723 | J27: =IF(A27<>"Remove",CONCATENATE("INSERT INTO tbFinanceItemSeq(Report,ItemSeqID,ItemSN,ItemID) VALUES('",B27,"',",C27,",",E27,",",G27,")"),"") -> INSERT INTO tbFinanceItemSeq(Report,ItemSeqID,ItemSN,ItemID) VALUES('BS',25,25,526)
A28: Exist | B28: BS | C28: 26 | D28: 26 | E28: 26 | F28: 26 | G28: 527 | H28: (BS)Due From Shareholders | I28: 2724 to 2799 | J28: =IF(A28<>"Remove",CONCATENATE("INSERT INTO tbFinanceItemSeq(Report,ItemSeqID,ItemSN,ItemID) VALUES('",B28,"',",C28,",",E28,",",G28,")"),"") -> INSERT INTO tbFinanceItemSeq(Report,ItemSeqID,ItemSN,ItemID) VALUES('BS',26,26,527)
A29: Exist | B29: BS | C29: 27 | D29: 27 | E29: 27 | F29: 27 | G29: 528 | H29: (BS)Deferred Tax Assets | I29: 2811 to 2899 | J29: =IF(A29<>"Remove",CONCATENATE("INSERT INTO tbFinanceItemSeq(Report,ItemSeqID,ItemSN,ItemID) VALUES('",B29,"',",C29,",",E29,",",G29,")"),"") -> INSERT INTO tbFinanceItemSeq(Report,ItemSeqID,ItemSN,ItemID) VALUES('BS',27,27,528)
A30: Exist | B30: BS | C30: 28 | D30: 28 | E30: 28 | F30: 28 | G30: 529 | H30: (BS)Derivatives - Non Current | I30: 1502, 2801 to 2809 | J30: =IF(A30<>"Remove",CONCATENATE("INSERT INTO tbFinanceItemSeq(Report,ItemSeqID,ItemSN,ItemID) VALUES('",B30,"',",C30,",",E30,",",G30,")"),"") -> INSERT INTO tbFinanceItemSeq(Report,ItemSeqID,ItemSN,ItemID) VALUES('BS',28,28,529)
A31: Exist | B31: BS | C31: 29 | D31: 29 | E31: 29 | F31: 29 | G31: 530 | H31: (BS)Goodwill | I31: 2901 to 2999 | J31: =IF(A31<>"Remove",CONCATENATE("INSERT INTO tbFinanceItemSeq(Report,ItemSeqID,ItemSN,ItemID) VALUES('",B31,"',",C31,",",E31,",",G31,")"),"") -> INSERT INTO tbFinanceItemSeq(Report,ItemSeqID,ItemSN,ItemID) VALUES('BS',29,29,530)
A32: Exist | B32: BS | C32: 30 | D32: 30 | E32: 30 | F32: 30 | G32: 531 | H32: (BS)Less: Impairment/Amortization/Prov | I32: 2501 to 2601Z | J32: =IF(A32<>"Remove",CONCATENATE("INSERT INTO tbFinanceItemSeq(Report,ItemSeqID,ItemSN,ItemID) VALUES('",B32,"',",C32,",",E32,",",G32,")"),"") -> INSERT INTO tbFinanceItemSeq(Report,ItemSeqID,ItemSN,ItemID) VALUES('BS',30,30,531)
... A62: Exist | B62: BS | C62: 60 | D62: 60 | E62: 60 | F62: 60 | G62: 561 | H62: (BS)TOTAL LIAB & EQUITY | I62: =C56+C63 | J62: =IF(A62<>"Remove",CONCATENATE("INSERT INTO tbFinanceItemSeq(Report,ItemSeqID,ItemSN,ItemID) VALUES('",B62,"',",C62,",",E62,",",G62,")"),"") -> INSERT INTO tbFinanceItemSeq(Report,ItemSeqID,ItemSN,ItemID) VALUES('BS',60,60,561)
A63: Exist | B63: BS | C63: 61 | D63: 61 | E63: 0 | F63: 0 | G63: 46 | H63: Performance Indicators | J63: =IF(A63<>"Remove",CONCATENATE("INSERT INTO tbFinanceItemSeq(Report,ItemSeqID,ItemSN,ItemID) VALUES('",B63,"',",C63,",",E63,",",G63,")"),"") -> INSERT INTO tbFinanceItemSeq(Report,ItemSeqID,ItemSN,ItemID) VALUES('BS',61,0,46)
A64: Exist | B64: BS | C64: 62 | D64: 62 | E64: 1 | F64: 1 | G64: 226 | H64: Debtors Turnover (Days) | I64: (Trade debtors + provision for debts)/ (External sales + External sales other) x No. of days to date | J64: =IF(A64<>"Remove",CONCATENATE("INSERT INTO tbFinanceItemSeq(Report,ItemSeqID,ItemSN,ItemID) VALUES('",B64,"',",C64,",",E64,",",G64,")"),"") -> INSERT INTO tbFinanceItemSeq(Report,ItemSeqID,ItemSN,ItemID) VALUES('BS',62,1,226)
A65: Exist | B65: BS | C65: 63 | D65: 63 | E65: 2 | F65: 2 | G65: 227 | H65: Stocks Turnover (Days) | I65: (Stock + Provision for stock obsolescence)/ -(Total Cost of sales) x No. of days to date | J65: =IF(A65<>"Remove",CONCATENATE("INSERT INTO tbFinanceItemSeq(Report,ItemSeqID,ItemSN,ItemID) VALUES('",B65,"',",C65,",",E65,",",G65,")"),"") -> INSERT INTO tbFinanceItemSeq(Report,ItemSeqID,ItemSN,ItemID) VALUES('BS',63,2,227)
A66: New | B66: BS | C66: 64 | D66: 64 | E66: 3 | F66: 3 | G66: 228 | H66: Creditors Turnover (Days) | I66: Account Payable/Cost of Goods Sold x No. of days to date | J66: =IF(A66<>"Remove",CONCATENATE("INSERT INTO tbFinanceItemSeq(Report,ItemSeqID,ItemSN,ItemID) VALUES('",B66,"',",C66,",",E66,",",G66,")"),"") -> INSERT INTO tbFinanceItemSeq(Report,ItemSeqID,ItemSN,ItemID) VALUES('BS',64,3,228) | K66: Existing
A67: Exist | B67: BS | C67: =D67+1 -> 65 | D67: 64 | E67: =F67+1 -> 4 | F67: 3 | G67: 229 | H67: Liabilities To Equity (Leverage) | I67: Total Liabilities / Total Equity | J67: =IF(A67<>"Remove",CONCATENATE("INSERT INTO tbFinanceItemSeq(Report,ItemSeqID,ItemSN,ItemID) VALUES('",B67,"',",C67,",",E67,",",G67,")"),"") -> INSERT INTO tbFinanceItemSeq(Report,ItemSeqID,ItemSN,ItemID) VALUES('BS',65,4,229)
A68: Exist | B68: BS | C68: =D68+1 -> 66 | D68: 65 | E68: =F68+1 -> 5 | F68: 4 | G68: 230 | H68: Debt To Equity | I68: Total Borrowings / Total Equity. Total Borrowings refers to summation of OD or factoring or revolving credit, Trust receipts or ST loans, current portion of Term Loans, Current HP creditors, Long Term Loans and HP Creditors. | J68: =IF(A68<>"Remove",CONCATENATE("INSERT INTO tbFinanceItemSeq(Report,ItemSeqID,ItemSN,ItemID) VALUES('",B68,"',",C68,",",E68,",",G68,")"),"") -> INSERT INTO tbFinanceItemSeq(Report,ItemSeqID,ItemSN,ItemID) VALUES('BS',66,5,230)
A69: Remove | B69: BS | C69: =D69+1 -> 67 | D69: 66 | E69: =F69+1 -> 6 | F69: 5 | G69: 1409 | H69: Prov for Doubtful Debts | I69: 1301Z | J69: =IF(A69<>"Remove",CONCATENATE("INSERT INTO tbFinanceItemSeq(Report,ItemSeqID,ItemSN,ItemID) VALUES('",B69,"',",C69,",",E69,",",G69,")"),"") | K69: Update Name
A70: New | B70: BS | C70: =D70+1 -> 67 | D70: 66 | E70: =F70+1 -> 6 | F70: 5 | G70: 1409 | H70: Prov for Doubtful Debts | I70: 1301Z | J70: =IF(A70<>"Remove",CONCATENATE("INSERT INTO tbFinanceItemSeq(Report,ItemSeqID,ItemSN,ItemID) VALUES('",B70,"',",C70,",",E70,",",G70,")"),"") -> INSERT INTO tbFinanceItemSeq(Report,ItemSeqID,ItemSN,ItemID) VALUES('BS',67,6,1409)
A71: Exist | B71: BS | C71: =D71+1 -> 68 | D71: 67 | E71: =F71+1 -> 7 | F71: 6 | G71: 1133 | H71: Provision for Stock Obso/Pilferage | I71: 1201Z, 1221Z, 1241Z, 1242Z, 1241L | J71: =IF(A71<>"Remove",CONCATENATE("INSERT INTO tbFinanceItemSeq(Report,ItemSeqID,ItemSN,ItemID) VALUES('",B71,"',",C71,",",E71,",",G71,")"),"") -> INSERT INTO tbFinanceItemSeq(Report,ItemSeqID,ItemSN,ItemID) VALUES('BS',68,7,1133)
A72: Exist | B72: BS | C72: =D72+1 -> 69 | D72: 68 | E72: =F72+1 -> 8 | F72: 7 | G72: 1134 | H72: Provision for Plant Maintenance | I72: 3993 | J72: =IF(A72<>"Remove",CONCATENATE("INSERT INTO tbFinanceItemSeq(Report,ItemSeqID,ItemSN,ItemID) VALUES('",B72,"',",C72,",",E72,",",G72,")"),"") -> INSERT INTO tbFinanceItemSeq(Report,ItemSeqID,ItemSN,ItemID) VALUES('BS',69,8,1134)

Sheet F30R BSR - Script
A1: INSERT INTO
A2: tbReport
A3: (ReportCategoryID,Description,FileName,StoredProcName,CreatedBy,CreatedDate,ModifiedBy,ModifiedDate,IsActive,IsExternalReport)
A4: VALUES
A5: (1,'[COA2016] F30R Balance Sheet (Raw)','F30R Balance Sheet (Raw).rpt',null,1,CURRENT_TIMESTAMP,Null,Null,1,0);

Sheet F141 F31 PNLD-Debug
A3: SELECT TOP 10 * FROM tbReport where ReportID = 430;
A4: --F141 Detailed Profit & Loss Account.rpt
A5: --procReportFinancePNLDetailByMonth
A6: --(PNLD)
A8: select s.* , i.ItemName from tbFinanceItemSeq s
A9: LEFT JOIN tbFinanceItem i on s.ItemID = i.ItemID
A10: where s.Report = 'PNLD'
A11: order by s.ItemSeqID
A14: DELETE FROM tbFinanceItemSeq where Report = 'PNLD'
A16: Update tbReport
A17: set FileName = 'F141 Detailed Profit & Loss Account.rpt' ,
A18: Description = '[COA2016] F31 Detailed Profit & Loss Account'
A19: where ReportID =430;

Sheet F141 F31 PNLD-Origin
A1: Report | B1: ItemSeqID | C1: ItemSN | D1: ItemID | E1: ItemName | F1: Insert Script
A2: PNLD | B2: 1 | C2: 1 | D2: 775 | E2: (PNLD)External Sales-Goods | F2: =CONCATENATE("INSERT INTO tbFinanceItemSeq(Report,ItemSeqID,ItemSN,ItemID) VALUES('",A2,"',",B2,",",C2,",",D2,")") -> INSERT INTO tbFinanceItemSeq(Report,ItemSeqID,ItemSN,ItemID) VALUES('PNLD',1,1,775)
A3: PNLD | B3: 2 | C3: 2 | D3: 776 | E3: (PNLD)External Sales-Project Sales | F3: =CONCATENATE("INSERT INTO tbFinanceItemSeq(Report,ItemSeqID,ItemSN,ItemID) VALUES('",A3,"',",B3,",",C3,",",D3,")") -> INSERT INTO tbFinanceItemSeq(Report,ItemSeqID,ItemSN,ItemID) VALUES('PNLD',2,2,776)
A4: PNLD | B4: 3 | C4: 3 | D4: 777 | E4: (PNLD)External Sales-Cylinder Rental | F4: =CONCATENATE("INSERT INTO tbFinanceItemSeq(Report,ItemSeqID,ItemSN,ItemID) VALUES('",A4,"',",B4,",",C4,",",D4,")") -> INSERT INTO tbFinanceItemSeq(Report,ItemSeqID,ItemSN,ItemID) VALUES('PNLD',3,3,777)
A5: PNLD | B5: 4 | C5: 4 | D5: 778 | E5: (PNLD)External Sales-Equip Rental | F5: =CONCATENATE("INSERT INTO tbFinanceItemSeq(Report,ItemSeqID,ItemSN,ItemID) VALUES('",A5,"',",B5,",",C5,",",D5,")") -> INSERT INTO tbFinanceItemSeq(Report,ItemSeqID,ItemSN,ItemID) VALUES('PNLD',4,4,778)
A6: PNLD | B6: 5 | C6: 5 | D6: 779 | E6: (PNLD)External Sales-Repair & Service | F6: =CONCATENATE("INSERT INTO tbFinanceItemSeq(Report,ItemSeqID,ItemSN,ItemID) VALUES('",A6,"',",B6,",",C6,",",D6,")") -> INSERT INTO tbFinanceItemSeq(Report,ItemSeqID,ItemSN,ItemID) VALUES('PNLD',5,5,779)
A7: PNLD | B7: 6 | C7: 6 | D7: 780 | E7: (PNLD)External Sales-Delivery Charges | F7: =CONCATENATE("INSERT INTO tbFinanceItemSeq(Report,ItemSeqID,ItemSN,ItemID) VALUES('",A7,"',",B7,",",C7,",",D7,")") -> INSERT INTO tbFinanceItemSeq(Report,ItemSeqID,ItemSN,ItemID) VALUES('PNLD',6,6,780)
A8: PNLD | B8: 7 | C8: 7 | D8: 781 | E8: (PNLD)External Sales-Other Charges | F8: =CONCATENATE("INSERT INTO tbFinanceItemSeq(Report,ItemSeqID,ItemSN,ItemID) VALUES('",A8,"',",B8,",",C8,",",D8,")") -> INSERT INTO tbFinanceItemSeq(Report,ItemSeqID,ItemSN,ItemID) VALUES('PNLD',7,7,781)
A9: PNLD | B9: 8 | C9: 8 | D9: 782 | E9: (PNLD)External Sales-Mgmt Fee | F9: =CONCATENATE("INSERT INTO tbFinanceItemSeq(Report,ItemSeqID,ItemSN,ItemID) VALUES('",A9,"',",B9,",",C9,",",D9,")") -> INSERT INTO tbFinanceItemSeq(Report,ItemSeqID,ItemSN,ItemID) VALUES('PNLD',8,8,782)
A10: PNLD | B10: 9 | C10: 9 | D10: 783 | E10: (PNLD)Enternal Sales-Property Rental | F10: =CONCATENATE("INSERT INTO tbFinanceItemSeq(Report,ItemSeqID,ItemSN,ItemID) VALUES('",A10,"',",B10,",",C10,",",D10,")") -> INSERT INTO tbFinanceItemSeq(Report,ItemSeqID,ItemSN,ItemID) VALUES('PNLD',9,9,783)
A11: PNLD | B11: 10 | C11: 10 | D11: 1343 | E11: (PNLD)External Sales | F11: =CONCATENATE("INSERT INTO tbFinanceItemSeq(Report,ItemSeqID,ItemSN,ItemID) VALUES('",A11,"',",B11,",",C11,",",D11,")") -> INSERT INTO tbFinanceItemSeq(Report,ItemSeqID,ItemSN,ItemID) VALUES('PNLD',10,10,1343)
A12: PNLD | B12: 11 | C12: 11 | D12: 785 | E12: (PNLD)Interco Sales-Goods | F12: =CONCATENATE("INSERT INTO tbFinanceItemSeq(Report,ItemSeqID,ItemSN,ItemID) VALUES('",A12,"',",B12,",",C12,",",D12,")") -> INSERT INTO tbFinanceItemSeq(Report,ItemSeqID,ItemSN,ItemID) VALUES('PNLD',11,11,785)
A13: PNLD | B13: 12 | C13: 12 | D13: 786 | E13: (PNLD)Interco Sales-Cylinder Rental | F13: =CONCATENATE("INSERT INTO tbFinanceItemSeq(Report,ItemSeqID,ItemSN,ItemID) VALUES('",A13,"',",B13,",",C13,",",D13,")") -> INSERT INTO tbFinanceItemSeq(Report,ItemSeqID,ItemSN,ItemID) VALUES('PNLD',12,12,786)
... A338: PNLD | B338: 337 | C338: 334 | D338: 1080 | E338: (PNLD)Dividends Declared | F338: =CONCATENATE("INSERT INTO tbFinanceItemSeq(Report,ItemSeqID,ItemSN,ItemID) VALUES('",A338,"',",B338,",",C338,",",D338,")") -> INSERT INTO tbFinanceItemSeq(Report,ItemSeqID,ItemSN,ItemID) VALUES('PNLD',337,334,1080)

Sheet F31 PNLD-DIFF
A1: F141 Old | B1: F31 New | C1: F31 Diff
A2: External Sales-Goods | B2: External Sales-Goods | C2: =IF(A2=B2,TRUE,B2) -> TRUE
A3: External Sales-Project Sales | B3: External Sales-Project Sales | C3: =IF(A3=B3,TRUE,B3) -> TRUE
A4: External Sales-Cylinder Rental | B4: External Sales-Cylinder Rental | C4: =IF(A4=B4,TRUE,B4) -> TRUE
A5: External Sales-Equip Rental | B5: External Sales-Equip Rental | C5: =IF(A5=B5,TRUE,B5) -> TRUE
A6: External Sales-Repair & Service | B6: External Sales-Repair & Service | C6: =IF(A6=B6,TRUE,B6) -> TRUE
A7: External Sales-Delivery Charges | B7: External Sales-Delivery Charges | C7: =IF(A7=B7,TRUE,B7) -> TRUE
A8: External Sales-Other Charges | B8: External Sales-Other Charges | C8: =IF(A8=B8,TRUE,B8) -> TRUE
A9: External Sales-Mgmt Fee | B9: External Sales-Mgmt Fee | C9: =IF(A9=B9,TRUE,B9) -> TRUE
A10: Enternal Sales-Property Rental | B10: Enternal Sales-Property Rental | C10: =IF(A10=B10,TRUE,B10) -> TRUE
A11: External Sales | B11: External Sales | C11: =IF(A11=B11,TRUE,B11) -> TRUE
A12: Interco Sales-Goods | B12: Interco Sales-Goods | C12: =IF(A12=B12,TRUE,B12) -> TRUE
A13: Interco Sales-Cylinder Rental | B13: Interco Sales-Cylinder Rental | C13: =IF(A13=B13,TRUE,B13) -> TRUE
... A73: Admin/Management Income | B73: Admin/Management Income | C73: =IF(A73=B73,TRUE,B73) -> TRUE
B74: Gain/(Loss) Disposal of FA | C74: =IF(A75=B74,TRUE,B74) -> Gain/(Loss) Disposal of FA
A75: Income on Disposal of Scrap | B75: Income on Disposal of Scrap | C75: =IF(A75=B75,TRUE,B75) -> TRUE
A76: Insurance Claim - Op | B76: Insurance Claim | C76: =IF(A76=B76,TRUE,B76) -> Insurance Claim
A77: Logistic Service Income | B77: Logistic Service Income | C77: =IF(A77=B77,TRUE,B77) -> TRUE
A78: Other Misc Income | B78: Other Misc Income | C78: =IF(A78=B78,TRUE,B78) -> TRUE
B79: Government Grant | C79: =IF(A84=B79,TRUE,B79) -> Government Grant
B80: Insurance Claim | C80: =IF(A80=B80,TRUE,B80) -> Insurance Claim
B81: Share of Assoc/JV`s P&L | C81: =IF(A81=B81,TRUE,B81) -> Share of Assoc/JV`s P&L
B82: Gain on Disposal of Investment | C82: =IF(A82=B82,TRUE,B82) -> Gain on Disposal of Investment
B83: Gain on Asset Held for Sales | C83: =IF(A83=B83,TRUE,B83) -> Gain on Asset Held for Sales
A84: Other Operating Income | B84: Other Operating Income | C84: =IF(A84=B84,TRUE,B84) -> TRUE
A85: Title:Less Other Operating Expenses | B85: Less Other Operating Expenses | C85: =IF(A85=B85,TRUE,B85) -> Less Other Operating Expenses
B86: Other Misc Expenses | C86: =IF(A96=B86,TRUE,B86) -> Other Misc Expenses
B87: Other Non-Operating Exps | C87: =IF(A87=B87,TRUE,B87) -> Other Non-Operating Exps
B88: Share of Assoc/JV`s P&L | C88: =IF(A88=B88,TRUE,B88) -> Share of Assoc/JV`s P&L
B89: Loss on Disposal of Investment | C89: =IF(A89=B89,TRUE,B89) -> Loss on Disposal of Investment
B90: Loss on Asset Held for Sales | C90: =IF(A90=B90,TRUE,B90) -> Loss on Asset Held for Sales
B91: Impairm Loss on Subsidiaries | C91: =IF(A91=B91,TRUE,B91) -> Impairm Loss on Subsidiaries
B92: Impairm Loss on Assoc/JV/Rel Co | C92: =IF(A92=B92,TRUE,B92) -> Impairm Loss on Assoc/JV/Rel Co
B93: Impairm Loss-Property | C93: =IF(A93=B93,TRUE,B93) -> Impairm Loss-Property
B94: Impairm Loss-Plant & Equip | C94: =IF(A94=B94,TRUE,B94) -> Impairm Loss-Plant & Equip
B95: Impairm Loss-Investment | C95: =IF(A95=B95,TRUE,B95) -> Impairm Loss-Investment
A96: Amortisation-Trade Name | B96: Impairm Loss-Others | C96: =IF(A96=B96,TRUE,B96) -> Impairm Loss-Others
A97: Amortisation-Cust Relationship | B97: Real Property Gain Tax | C97: =IF(A97=B97,TRUE,B97) -> Real Property Gain Tax
A98: Amortisation-Trademark & Patent | B98: Foreign Withholding Tax | C98: =IF(A98=B98,TRUE,B98) -> Foreign Withholding Tax
A99: Amortisation-Product License | B99: Amortisation-Product License | C99: =IF(A99=B99,TRUE,B99) -> TRUE
A100: Amortisation-Club Membership | B100: Amortisation-Club Membership | C100: =IF(A100=B100,TRUE,B100) -> TRUE
A101: Written Off-Trade Name | B101: Amortisation-Trademark & Patent | C101: =IF(A101=B101,TRUE,B101) -> Amortisation-Trademark & Patent
A102: Written Off-Cust Relationship | C102: =IF(A102=B102,TRUE,B102) -> 0
A103: Written Off-Trademark & Patent | C103: =IF(A103=B103,TRUE,B103) -> 0
A104: Written Off-Product License | C104: =IF(A104=B104,TRUE,B104) -> 0
A105: Written Off-Club Membership | C105: =IF(A105=B105,TRUE,B105) -> 0
A106: Other Misc Expenses | C106: =IF(A106=B106,TRUE,B106) -> 0
A107: Other Operating Expenses | B107: Other Operating Expenses | C107: =IF(A107=B107,TRUE,B107) -> TRUE
A108: Total Other Op Income/(Exp) | B108: Total Other Op Income/(Exp) | C108: =IF(A108=B108,TRUE,B108) -> TRUE
A109: Salary & Leave | B109: Salary & Leave | C109: =IF(A109=B109,TRUE,B109) -> TRUE
A110: Provision for Bonus | B110: Provision for Bonus | C110: =IF(A110=B110,TRUE,B110) -> TRUE
A111: Comms & Incentives | B111: Comms & Incentives | C111: =IF(A111=B111,TRUE,B111) -> TRUE
A112: Foreign Workers | B112: Foreign Workers | C112: =IF(A112=B112,TRUE,B112) -> TRUE
A113: Casual/Temp Staff | B113: Casual/Temp Staff | C113: =IF(A113=B113,TRUE,B113) -> TRUE
A114: Overtime | B114: Overtime | C114: =IF(A114=B114,TRUE,B114) -> TRUE
A115: Staff Allow & Incentive | B115: Staff Allow & Incentive | C115: =IF(A115=B115,TRUE,B115) -> TRUE
A116: Shift Allowance | B116: Shift Allowance | C116: =IF(A116=B116,TRUE,B116) -> TRUE
A117: Staff Transport | B117: Staff Transport | C117: =IF(A117=B117,TRUE,B117) -> TRUE
A118: Staff Vehicle Expenses | B118: Staff Vehicle Expenses | C118: =IF(A118=B118,TRUE,B118) -> TRUE
... A163: Insurance of Vehicles | B163: Insurance of Vehicles | C163: =IF(A163=B163,TRUE,B163) -> TRUE
B164: Upkeep-Machinery | C164: =IF(A164=B164,TRUE,B164) -> Upkeep-Machinery
B165: Upkeep-Equipment | C165: =IF(A165=B165,TRUE,B165) -> Upkeep-Equipment
B166: Upkeep-Furniture & Fitting | C166: =IF(A166=B166,TRUE,B166) -> Upkeep-Furniture & Fitting
B167: Upkeep-Office Equip | C167: =IF(A167=B167,TRUE,B167) -> Upkeep-Office Equip
B168: Upkeep-Computers | C168: =IF(A168=B168,TRUE,B168) -> Upkeep-Computers
A169: Equipment Expenses | B169: S&D Equipment Expenses | C169: =IF(A169=B169,TRUE,B169) -> S&D Equipment Expenses
A170: Rental | B170: Rental | C170: =IF(A170=B170,TRUE,B170) -> TRUE
A171: Upkeep of Premises | B171: Upkeep of Premises | C171: =IF(A171=B171,TRUE,B171) -> TRUE
A172: Waste Disposal | B172: Waste Disposal | C172: =IF(A172=B172,TRUE,B172) -> TRUE
A173: Electricity Charges | B173: Electricity Charges | C173: =IF(A173=B173,TRUE,B173) -> TRUE
A174: Water Charges | B174: Water Charges | C174: =IF(A174=B174,TRUE,B174) -> TRUE
A175: Gas Charges | B175: Gas Charges | C175: =IF(A175=B175,TRUE,B175) -> TRUE
A176: Property Tax | B176: Property Tax | C176: =IF(A176=B176,TRUE,B176) -> TRUE
A177: Licenses Fees | B177: Licenses Fees | C177: =IF(A177=B177,TRUE,B177) -> TRUE
A178: Insurance-General | B178: Insurance-General | C178: =IF(A178=B178,TRUE,B178) -> TRUE
A179: Rental/Property Related | B179: S&D Rental/Property Related | C179: =IF(A179=B179,TRUE,B179) -> S&D Rental/Property Related
A180: Dep-Leasehold Land | B180: Dep-Leasehold Land | C180: =IF(A180=B180,TRUE,B180) -> TRUE
... A208: Head Office Costs/Alloc | B208: Head Office Costs/Alloc | C208: =IF(A208=B208,TRUE,B208) -> TRUE
A209: Other Expenses | C209: =IF(A209=B209,TRUE,B209) -> 0
A210: Total Expenses | B210: Total S&D Expenses | C210: =IF(A210=B210,TRUE,B210) -> Total S&D Expenses
A211: Salary & Leave | B211: Salary & Leave | C211: =IF(A211=B211,TRUE,B211) -> TRUE
A212: Provision for Bonus | B212: Provision for Bonus | C212: =IF(A212=B212,TRUE,B212) -> TRUE
A213: Comms & Incentives | B213: Comms & Incentives | C213: =IF(A213=B213,TRUE,B213) -> TRUE
A214: Foreign Workers | B214: Foreign Workers | C214: =IF(A214=B214,TRUE,B214) -> TRUE
A215: Casual/Temp Staff | B215: Casual/Temp Staff | C215: =IF(A215=B215,TRUE,B215) -> TRUE
A216: Overtime | B216: Overtime | C216: =IF(A216=B216,TRUE,B216) -> TRUE
A217: Staff Allow & Incentive | B217: Staff Allow & Incentive | C217: =IF(A217=B217,TRUE,B217) -> TRUE
A218: Shift Allowance | B218: Shift Allowance | C218: =IF(A218=B218,TRUE,B218) -> TRUE
A219: Staff Transport | B219: Staff Transport | C219: =IF(A219=B219,TRUE,B219) -> TRUE
A220: Staff Vehicle Expenses | B220: Staff Vehicle Expenses | C220: =IF(A220=B220,TRUE,B220) -> TRUE
A221: Staff Vehicle Rental | B221: Staff Vehicle Rental | C221: =IF(A221=B221,TRUE,B221) -> TRUE
... A247: Upkeep of Motor Vehicle | B247: Upkeep of Motor Vehicle | C247: =IF(A247=B247,TRUE,B247) -> TRUE
B248: A&G Travelling/Transportation | C248: =IF(A248=B248,TRUE,B248) -> A&G Travelling/Transportation
A249: Entertainment | B249: Entertainment | C249: =IF(A249=B249,TRUE,B249) -> TRUE
A250: Donations | B250: Donations | C250: =IF(A250=B250,TRUE,B250) -> TRUE
A251: Travelling/Entertainment | B251: A&G Entertainment/Donations | C251: =IF(A251=B251,TRUE,B251) -> A&G Entertainment/Donations
A252: Leasing of Machinery & Equip | B252: Leasing of Machinery & Equip | C252: =IF(A252=B252,TRUE,B252) -> TRUE
A253: Non-Capitalised Purchases | B253: Non-Capitalised Purchases | C253: =IF(A253=B253,TRUE,B253) -> TRUE
A254: R&M-Equipment | B254: R&M-Equipment | C254: =IF(A254=B254,TRUE,B254) -> TRUE
A255: R&M-Office Equip | B255: R&M-Office Equip | C255: =IF(A255=B255,TRUE,B255) -> TRUE
...

Sheet F141 F31 PNLD-NEW
A1: Status | B1: Report | C1: New - ItemSeqID | D1: ItemSeqID | E1: New -ItemSN | F1: ItemSN | G1: ItemID | H1: COAMapping | I1: ItemName | J1: Insert Script | K1: Finance Item
A2: Exist | B2: PNLD | C2: 1 | D2: 1 | E2: 1 | F2: 1 | G2: 775 | H2: 5001 | I2: (PNLD)External Sales-Goods | J2: =IF(A2<>"Remove",CONCATENATE("INSERT INTO tbFinanceItemSeq(Report,ItemSeqID,ItemSN,ItemID) VALUES('",B2,"',",C2,",",E2,",",G2,")"),"") -> INSERT INTO tbFinanceItemSeq(Report,ItemSeqID,ItemSN,ItemID) VALUES('PNLD',1,1,775) | K2: =IF(A2<>"New","",CONCATENATE("INSERT INTO tbFinanceItem(ItemName) VALUES('",I2,"')"))
A3: Exist | B3: PNLD | C3: 2 | D3: 2 | E3: 2 | F3: 2 | G3: 776 | H3: 5002 | I3: (PNLD)External Sales-Project Sales | J3: =IF(A3<>"Remove",CONCATENATE("INSERT INTO tbFinanceItemSeq(Report,ItemSeqID,ItemSN,ItemID) VALUES('",B3,"',",C3,",",E3,",",G3,")"),"") -> INSERT INTO tbFinanceItemSeq(Report,ItemSeqID,ItemSN,ItemID) VALUES('PNLD',2,2,776) | K3: =IF(A3<>"New","",CONCATENATE("INSERT INTO tbFinanceItem(ItemName) VALUES('",I3,"')"))
A4: Exist | B4: PNLD | C4: 3 | D4: 3 | E4: 3 | F4: 3 | G4: 777 | H4: 5003 | I4: (PNLD)External Sales-Cylinder Rental | J4: =IF(A4<>"Remove",CONCATENATE("INSERT INTO tbFinanceItemSeq(Report,ItemSeqID,ItemSN,ItemID) VALUES('",B4,"',",C4,",",E4,",",G4,")"),"") -> INSERT INTO tbFinanceItemSeq(Report,ItemSeqID,ItemSN,ItemID) VALUES('PNLD',3,3,777) | K4: =IF(A4<>"New","",CONCATENATE("INSERT INTO tbFinanceItem(ItemName) VALUES('",I4,"')"))
A5: Exist | B5: PNLD | C5: 4 | D5: 4 | E5: 4 | F5: 4 | G5: 778 | H5: 5004 | I5: (PNLD)External Sales-Equip Rental | J5: =IF(A5<>"Remove",CONCATENATE("INSERT INTO tbFinanceItemSeq(Report,ItemSeqID,ItemSN,ItemID) VALUES('",B5,"',",C5,",",E5,",",G5,")"),"") -> INSERT INTO tbFinanceItemSeq(Report,ItemSeqID,ItemSN,ItemID) VALUES('PNLD',4,4,778) | K5: =IF(A5<>"New","",CONCATENATE("INSERT INTO tbFinanceItem(ItemName) VALUES('",I5,"')"))
A6: Exist | B6: PNLD | C6: 5 | D6: 5 | E6: 5 | F6: 5 | G6: 779 | H6: 5005 | I6: (PNLD)External Sales-Repair & Service | J6: =IF(A6<>"Remove",CONCATENATE("INSERT INTO tbFinanceItemSeq(Report,ItemSeqID,ItemSN,ItemID) VALUES('",B6,"',",C6,",",E6,",",G6,")"),"") -> INSERT INTO tbFinanceItemSeq(Report,ItemSeqID,ItemSN,ItemID) VALUES('PNLD',5,5,779) | K6: =IF(A6<>"New","",CONCATENATE("INSERT INTO tbFinanceItem(ItemName) VALUES('",I6,"')"))
A7: Exist | B7: PNLD | C7: 6 | D7: 6 | E7: 6 | F7: 6 | G7: 780 | H7: 5006 | I7: (PNLD)External Sales-Delivery Charges | J7: =IF(A7<>"Remove",CONCATENATE("INSERT INTO tbFinanceItemSeq(Report,ItemSeqID,ItemSN,ItemID) VALUES('",B7,"',",C7,",",E7,",",G7,")"),"") -> INSERT INTO tbFinanceItemSeq(Report,ItemSeqID,ItemSN,ItemID) VALUES('PNLD',6,6,780) | K7: =IF(A7<>"New","",CONCATENATE("INSERT INTO tbFinanceItem(ItemName) VALUES('",I7,"')"))
A8: Exist | B8: PNLD | C8: 7 | D8: 7 | E8: 7 | F8: 7 | G8: 781 | H8: 5007 | I8: (PNLD)External Sales-Other Charges | J8: =IF(A8<>"Remove",CONCATENATE("INSERT INTO tbFinanceItemSeq(Report,ItemSeqID,ItemSN,ItemID) VALUES('",B8,"',",C8,",",E8,",",G8,")"),"") -> INSERT INTO tbFinanceItemSeq(Report,ItemSeqID,ItemSN,ItemID) VALUES('PNLD',7,7,781) | K8: =IF(A8<>"New","",CONCATENATE("INSERT INTO tbFinanceItem(ItemName) VALUES('",I8,"')"))
A9: Exist | B9: PNLD | C9: 8 | D9: 8 | E9: 8 | F9: 8 | G9: 782 | H9: 5021 | I9: (PNLD)External Sales-Mgmt Fee | J9: =IF(A9<>"Remove",CONCATENATE("INSERT INTO tbFinanceItemSeq(Report,ItemSeqID,ItemSN,ItemID) VALUES('",B9,"',",C9,",",E9,",",G9,")"),"") -> INSERT INTO tbFinanceItemSeq(Report,ItemSeqID,ItemSN,ItemID) VALUES('PNLD',8,8,782) | K9: =IF(A9<>"New","",CONCATENATE("INSERT INTO tbFinanceItem(ItemName) VALUES('",I9,"')"))
A10: Exist | B10: PNLD | C10: 9 | D10: 9 | E10: 9 | F10: 9 | G10: 783 | H10: 5022 | I10: (PNLD)Enternal Sales-Property Rental | J10: =IF(A10<>"Remove",CONCATENATE("INSERT INTO tbFinanceItemSeq(Report,ItemSeqID,ItemSN,ItemID) VALUES('",B10,"',",C10,",",E10,",",G10,")"),"") -> INSERT INTO tbFinanceItemSeq(Report,ItemSeqID,ItemSN,ItemID) VALUES('PNLD',9,9,783) | K10: =IF(A10<>"New","",CONCATENATE("INSERT INTO tbFinanceItem(ItemName) VALUES('",I10,"')"))
A11: Exist | B11: PNLD | C11: 10 | D11: 10 | E11: 10 | F11: 10 | G11: 1343 | H11: =SUM(C4:C12) | I11: (PNLD)External Sales | J11: =IF(A11<>"Remove",CONCATENATE("INSERT INTO tbFinanceItemSeq(Report,ItemSeqID,ItemSN,ItemID) VALUES('",B11,"',",C11,",",E11,",",G11,")"),"") -> INSERT INTO tbFinanceItemSeq(Report,ItemSeqID,ItemSN,ItemID) VALUES('PNLD',10,10,1343) | K11: =IF(A11<>"New","",CONCATENATE("INSERT INTO tbFinanceItem(ItemName) VALUES('",I11,"')"))
A12: Exist | B12: PNLD | C12: 11 | D12: 11 | E12: 11 | F12: 11 | G12: 785 | H12: 5031 | I12: (PNLD)Interco Sales-Goods | J12: =IF(A12<>"Remove",CONCATENATE("INSERT INTO tbFinanceItemSeq(Report,ItemSeqID,ItemSN,ItemID) VALUES('",B12,"',",C12,",",E12,",",G12,")"),"") -> INSERT INTO tbFinanceItemSeq(Report,ItemSeqID,ItemSN,ItemID) VALUES('PNLD',11,11,785) | K12: =IF(A12<>"New","",CONCATENATE("INSERT INTO tbFinanceItem(ItemName) VALUES('",I12,"')"))
A13: Exist | B13: PNLD | C13: 12 | D13: 12 | E13: 12 | F13: 12 | G13: 786 | H13: 5032 | I13: (PNLD)Interco Sales-Cylinder Rental | J13: =IF(A13<>"Remove",CONCATENATE("INSERT INTO tbFinanceItemSeq(Report,ItemSeqID,ItemSN,ItemID) VALUES('",B13,"',",C13,",",E13,",",G13,")"),"") -> INSERT INTO tbFinanceItemSeq(Report,ItemSeqID,ItemSN,ItemID) VALUES('PNLD',12,12,786) | K13: =IF(A13<>"New","",CONCATENATE("INSERT INTO tbFinanceItem(ItemName) VALUES('",I13,"')"))
... A69: Exist | B69: PNLD | C69: 68 | D69: 68 | E69: 68 | F69: 68 | G69: 838 | H69: =C34+C70 | I69: (PNLD)Gross Profit | J69: =IF(A69<>"Remove",CONCATENATE("INSERT INTO tbFinanceItemSeq(Report,ItemSeqID,ItemSN,ItemID) VALUES('",B69,"',",C69,",",E69,",",G69,")"),"") -> INSERT INTO tbFinanceItemSeq(Report,ItemSeqID,ItemSN,ItemID) VALUES('PNLD',68,68,838) | K69: =IF(A69<>"New","",CONCATENATE("INSERT INTO tbFinanceItem(ItemName) VALUES('",I69,"')"))
A70: Exist | B70: PNLD | C70: 69 | D70: 69 | E70: 69 | F70: 0 | G70: 839 | I70: (PNLD)Title:Add Other Operating Income | J70: =IF(A70<>"Remove",CONCATENATE("INSERT INTO tbFinanceItemSeq(Report,ItemSeqID,ItemSN,ItemID) VALUES('",B70,"',",C70,",",E70,",",G70,")"),"") -> INSERT INTO tbFinanceItemSeq(Report,ItemSeqID,ItemSN,ItemID) VALUES('PNLD',69,69,839) | K70: =IF(A70<>"New","",CONCATENATE("INSERT INTO tbFinanceItem(ItemName) VALUES('",I70,"')"))
A71: Exist | B71: PNLD | C71: 70 | D71: 70 | E71: 70 | F71: 69 | G71: 840 | H71: 5501 | I71: (PNLD)Commission Income | J71: =IF(A71<>"Remove",CONCATENATE("INSERT INTO tbFinanceItemSeq(Report,ItemSeqID,ItemSN,ItemID) VALUES('",B71,"',",C71,",",E71,",",G71,")"),"") -> INSERT INTO tbFinanceItemSeq(Report,ItemSeqID,ItemSN,ItemID) VALUES('PNLD',70,70,840) | K71: =IF(A71<>"New","",CONCATENATE("INSERT INTO tbFinanceItem(ItemName) VALUES('",I71,"')"))
A72: Remove | B72: PNLD | C72: 71 | D72: 71 | E72: 70 | F72: 70 | G72: 841 | I72: (PNLD)Property Rental | J72: =IF(A72<>"Remove",CONCATENATE("INSERT INTO tbFinanceItemSeq(Report,ItemSeqID,ItemSN,ItemID) VALUES('",B72,"',",C72,",",E72,",",G72,")"),"") | K72: UPDATE tbFinanceItem SET ItemName = '(PNLD)Property Rental Income' WHERE ItemName = '(PNLD)Property Rental';
A73: New | B73: PNLD | C73: 71 | D73: 71 | E73: 71 | F73: 70 | G73: 841 | H73: 5502 | I73: (PNLD)Property Rental Income | J73: =IF(A73<>"Remove",CONCATENATE("INSERT INTO tbFinanceItemSeq(Report,ItemSeqID,ItemSN,ItemID) VALUES('",B73,"',",C73,",",E73,",",G73,")"),"") -> INSERT INTO tbFinanceItemSeq(Report,ItemSeqID,ItemSN,ItemID) VALUES('PNLD',71,71,841)
A74: Exist | B74: PNLD | C74: 72 | D74: 72 | E74: 72 | F74: 71 | G74: 842 | H74: 5503 | I74: (PNLD)Admin/Management Income | J74: =IF(A74<>"Remove",CONCATENATE("INSERT INTO tbFinanceItemSeq(Report,ItemSeqID,ItemSN,ItemID) VALUES('",B74,"',",C74,",",E74,",",G74,")"),"") -> INSERT INTO tbFinanceItemSeq(Report,ItemSeqID,ItemSN,ItemID) VALUES('PNLD',72,72,842) | K74: =IF(A74<>"New","",CONCATENATE("INSERT INTO tbFinanceItem(ItemName) VALUES('",I74,"')"))
A75: New | B75: PNLD | C75: 73 | E75: 73 | G75: 1057 | H75: 9101 | I75: (PNLD)Gain/(Loss) on Disposal of FA | J75: =IF(A75<>"Remove",CONCATENATE("INSERT INTO tbFinanceItemSeq(Report,ItemSeqID,ItemSN,ItemID) VALUES('",B75,"',",C75,",",E75,",",G75,")"),"") -> INSERT INTO tbFinanceItemSeq(Report,ItemSeqID,ItemSN,ItemID) VALUES('PNLD',73,73,1057) | K75: =IF(A75<>"New","",CONCATENATE("INSERT INTO tbFinanceItem(ItemName) VALUES('",I75,"')")) -> INSERT INTO tbFinanceItem(ItemName) VALUES('(PNLD)Gain/(Loss) on Disposal of FA')
A76: Exist | B76: PNLD | C76: =D76+1 -> 74 | D76: 73 | E76: 74 | F76: 72 | G76: 843 | H76: 5511 | I76: (PNLD)Income on Disposal of Scrap | J76: =IF(A76<>"Remove",CONCATENATE("INSERT INTO tbFinanceItemSeq(Report,ItemSeqID,ItemSN,ItemID) VALUES('",B76,"',",C76,",",E76,",",G76,")"),"") -> INSERT INTO tbFinanceItemSeq(Report,ItemSeqID,ItemSN,ItemID) VALUES('PNLD',74,74,843) | K76: =IF(A76<>"New","",CONCATENATE("INSERT INTO tbFinanceItem(ItemName) VALUES('",I76,"')"))
A77: Remove | B77: PNLD | C77: =D77+1 -> 75 | D77: 74 | E77: =F77+1 -> 74 | F77: 73 | G77: 844 | I77: (PNLD)Insurance Claim - Op | J77: =IF(A77<>"Remove",CONCATENATE("INSERT INTO tbFinanceItemSeq(Report,ItemSeqID,ItemSN,ItemID) VALUES('",B77,"',",C77,",",E77,",",G77,")"),"") | K77: =IF(A77<>"New","",CONCATENATE("INSERT INTO tbFinanceItem(ItemName) VALUES('",I77,"')"))
A78: New | B78: PNLD | C78: 75 | D78: 74 | E78: 75 | F78: 73 | G78: 844 | H78: 5512, 9011 | I78: (PNLD)Insurance Claim | J78: =IF(A78<>"Remove",CONCATENATE("INSERT INTO tbFinanceItemSeq(Report,ItemSeqID,ItemSN,ItemID) VALUES('",B78,"',",C78,",",E78,",",G78,")"),"") -> INSERT INTO tbFinanceItemSeq(Report,ItemSeqID,ItemSN,ItemID) VALUES('PNLD',75,75,844) | K78: =IF(A78<>"New","",CONCATENATE("INSERT INTO tbFinanceItem(ItemName) VALUES('",I78,"')")) -> INSERT INTO tbFinanceItem(ItemName) VALUES('(PNLD)Insurance Claim')
A79: Exist | B79: PNLD | C79: =D79+1 -> 76 | D79: 75 | E79: 76 | F79: 74 | G79: 1388 | H79: 5513 | I79: (PNLD)Logistic Service Income | J79: =IF(A79<>"Remove",CONCATENATE("INSERT INTO tbFinanceItemSeq(Report,ItemSeqID,ItemSN,ItemID) VALUES('",B79,"',",C79,",",E79,",",G79,")"),"") -> INSERT INTO tbFinanceItemSeq(Report,ItemSeqID,ItemSN,ItemID) VALUES('PNLD',76,76,1388) | K79: =IF(A79<>"New","",CONCATENATE("INSERT INTO tbFinanceItem(ItemName) VALUES('",I79,"')"))
A80: Exist | B80: PNLD | C80: =D80+1 -> 77 | D80: 76 | E80: 77 | F80: 75 | G80: 845 | H80: 5519 | I80: (PNLD)Other Misc Income | J80: =IF(A80<>"Remove",CONCATENATE("INSERT INTO tbFinanceItemSeq(Report,ItemSeqID,ItemSN,ItemID) VALUES('",B80,"',",C80,",",E80,",",G80,")"),"") -> INSERT INTO tbFinanceItemSeq(Report,ItemSeqID,ItemSN,ItemID) VALUES('PNLD',77,77,845) | K80: =IF(A80<>"New","",CONCATENATE("INSERT INTO tbFinanceItem(ItemName) VALUES('",I80,"')"))
A81: Exist | B81: PNLD | C81: 78 | D81: 78 | E81: 78 | F81: 77 | G81: 1050 | H81: 9001 | I81: (PNLD)Government Grant | J81: =IF(A81<>"Remove",CONCATENATE("INSERT INTO tbFinanceItemSeq(Report,ItemSeqID,ItemSN,ItemID) VALUES('",B81,"',",C81,",",E81,",",G81,")"),"") -> INSERT INTO tbFinanceItemSeq(Report,ItemSeqID,ItemSN,ItemID) VALUES('PNLD',78,78,1050) | K81: =IF(A81<>"New","",CONCATENATE("INSERT INTO tbFinanceItem(ItemName) VALUES('",I81,"')"))
A82: Remove | B82: PNLD | C82: 79 | D82: 79 | E82: 79 | F82: 78 | G82: 1051 | I82: (PNLD)Insurance Claim - Non-Op | J82: =IF(A82<>"Remove",CONCATENATE("INSERT INTO tbFinanceItemSeq(Report,ItemSeqID,ItemSN,ItemID) VALUES('",B82,"',",C82,",",E82,",",G82,")"),"") | K82: =IF(A82<>"New","",CONCATENATE("INSERT INTO tbFinanceItem(ItemName) VALUES('",I82,"')"))
A83: New | B83: PNLD | C83: 79 | E83: 79 | G83: =CONCATENATE("(SELECT TOP 1 ItemID FROM tbFinanceItem where ItemName = '",I83,"')") -> (SELECT TOP 1 ItemID FROM tbFinanceItem where ItemName = '(PNLD)Share of Assoc/JV’s P&L Credit') | H83: 9041Credit | I83: (PNLD)Share of Assoc/JV’s P&L Credit | J83: =IF(A83<>"Remove",CONCATENATE("INSERT INTO tbFinanceItemSeq(Report,ItemSeqID,ItemSN,ItemID) VALUES('",B83,"',",C83,",",E83,",",G83,")"),"") -> INSERT INTO tbFinanceItemSeq(Report,ItemSeqID,ItemSN,ItemID) VALUES('PNLD',79,79,(SELECT TOP 1 ItemID FROM tbFinanceItem where ItemName = '(PNLD)Share of Assoc/JV’s P&L Credit')) | K83: =IF(A83<>"New","",CONCATENATE("INSERT INTO tbFinanceItem(ItemName) VALUES('",I83,"')")) -> INSERT INTO tbFinanceItem(ItemName) VALUES('(PNLD)Share of Assoc/JV’s P&L Credit')
A84: New | B84: PNLD | C84: 80 | E84: 80 | G84: =CONCATENATE("(SELECT TOP 1 ItemID FROM tbFinanceItem where ItemName = '",I84,"')") -> (SELECT TOP 1 ItemID FROM tbFinanceItem where ItemName = '(PNLD)Gain on Disposal of Investment') | H84: 9102Credit | I84: (PNLD)Gain on Disposal of Investment | J84: =IF(A84<>"Remove",CONCATENATE("INSERT INTO tbFinanceItemSeq(Report,ItemSeqID,ItemSN,ItemID) VALUES('",B84,"',",C84,",",E84,",",G84,")"),"") -> INSERT INTO tbFinanceItemSeq(Report,ItemSeqID,ItemSN,ItemID) VALUES('PNLD',80,80,(SELECT TOP 1 ItemID FROM tbFinanceItem where ItemName = '(PNLD)Gain on Disposal of Investment')) | K84: =IF(A84<>"New","",CONCATENATE("INSERT INTO tbFinanceItem(ItemName) VALUES('",I84,"')")) -> INSERT INTO tbFinanceItem(ItemName) VALUES('(PNLD)Gain on Disposal of Investment')
A85: New | B85: PNLD | C85: 81 | E85: 81 | G85: =CONCATENATE("(SELECT TOP 1 ItemID FROM tbFinanceItem where ItemName = '",I85,"')") -> (SELECT TOP 1 ItemID FROM tbFinanceItem where ItemName = '(PNLD)Gain on Asset Held for Sales') | H85: 9103Credit | I85: (PNLD)Gain on Asset Held for Sales | J85: =IF(A85<>"Remove",CONCATENATE("INSERT INTO tbFinanceItemSeq(Report,ItemSeqID,ItemSN,ItemID) VALUES('",B85,"',",C85,",",E85,",",G85,")"),"") -> INSERT INTO tbFinanceItemSeq(Report,ItemSeqID,ItemSN,ItemID) VALUES('PNLD',81,81,(SELECT TOP 1 ItemID FROM tbFinanceItem where ItemName = '(PNLD)Gain on Asset Held for Sales')) | K85: =IF(A85<>"New","",CONCATENATE("INSERT INTO tbFinanceItem(ItemName) VALUES('",I85,"')")) -> INSERT INTO tbFinanceItem(ItemName) VALUES('(PNLD)Gain on Asset Held for Sales')
A86: Exist | B86: PNLD | C86: 82 | D86: 77 | E86: 82 | F86: 76 | G86: 1349 | H86: =SUM(C73:C84) | I86: (PNLD)Other Operating Income | J86: =IF(A86<>"Remove",CONCATENATE("INSERT INTO tbFinanceItemSeq(Report,ItemSeqID,ItemSN,ItemID) VALUES('",B86,"',",C86,",",E86,",",G86,")"),"") -> INSERT INTO tbFinanceItemSeq(Report,ItemSeqID,ItemSN,ItemID) VALUES('PNLD',82,82,1349) | K86: =IF(A86<>"New","",CONCATENATE("INSERT INTO tbFinanceItem(ItemName) VALUES('",I86,"')"))
A87: Exist | B87: PNLD | C87: 83 | D87: 78 | E87: 83 | F87: 0 | G87: 846 | I87: (PNLD)Title:Less Other Operating Expenses | J87: =IF(A87<>"Remove",CONCATENATE("INSERT INTO tbFinanceItemSeq(Report,ItemSeqID,ItemSN,ItemID) VALUES('",B87,"',",C87,",",E87,",",G87,")"),"") -> INSERT INTO tbFinanceItemSeq(Report,ItemSeqID,ItemSN,ItemID) VALUES('PNLD',83,83,846) | K87: =IF(A87<>"New","",CONCATENATE("INSERT INTO tbFinanceItem(ItemName) VALUES('",I87,"')"))
A88: New | B88: PNLD | C88: 84 | E88: 84 | G88: 857 | H88: 5629 | I88: (PNLD)Other Misc Expenses | J88: =IF(A88<>"Remove",CONCATENATE("INSERT INTO tbFinanceItemSeq(Report,ItemSeqID,ItemSN,ItemID) VALUES('",B88,"',",C88,",",E88,",",G88,")"),"") -> INSERT INTO tbFinanceItemSeq(Report,ItemSeqID,ItemSN,ItemID) VALUES('PNLD',84,84,857) | K88: =IF(A88<>"New","",CONCATENATE("INSERT INTO tbFinanceItem(ItemName) VALUES('",I88,"')")) -> INSERT INTO tbFinanceItem(ItemName) VALUES('(PNLD)Other Misc Expenses')
A89: New | B89: PNLD | C89: 85 | D89: 323 | E89: 85 | F89: 321 | G89: 1067 | H89: 9199 | I89: (PNLD)Other Non-Operating Exps | J89: =IF(A89<>"Remove",CONCATENATE("INSERT INTO tbFinanceItemSeq(Report,ItemSeqID,ItemSN,ItemID) VALUES('",B89,"',",C89,",",E89,",",G89,")"),"") -> INSERT INTO tbFinanceItemSeq(Report,ItemSeqID,ItemSN,ItemID) VALUES('PNLD',85,85,1067) | K89: =IF(A89<>"New","",CONCATENATE("INSERT INTO tbFinanceItem(ItemName) VALUES('",I89,"')")) -> INSERT INTO tbFinanceItem(ItemName) VALUES('(PNLD)Other Non-Operating Exps')
A90: New | B90: PNLD | C90: 86 | D90: 312 | E90: 86 | F90: 310 | G90: =CONCATENATE("(SELECT TOP 1 ItemID FROM tbFinanceItem where ItemName = '",I90,"')") -> (SELECT TOP 1 ItemID FROM tbFinanceItem where ItemName = '(PNLD)Share of Assoc/JV’s P&L Debit') | H90: 9041Debit | I90: (PNLD)Share of Assoc/JV’s P&L Debit | J90: =IF(A90<>"Remove",CONCATENATE("INSERT INTO tbFinanceItemSeq(Report,ItemSeqID,ItemSN,ItemID) VALUES('",B90,"',",C90,",",E90,",",G90,")"),"") -> INSERT INTO tbFinanceItemSeq(Report,ItemSeqID,ItemSN,ItemID) VALUES('PNLD',86,86,(SELECT TOP 1 ItemID FROM tbFinanceItem where ItemName = '(PNLD)Share of Assoc/JV’s P&L Debit')) | K90: =IF(A90<>"New","",CONCATENATE("INSERT INTO tbFinanceItem(ItemName) VALUES('",I90,"')")) -> INSERT INTO tbFinanceItem(ItemName) VALUES('(PNLD)Share of Assoc/JV’s P&L Debit')
A91: New | B91: PNLD | C91: 87 | D91: 314 | E91: 87 | F91: 312 | G91: =CONCATENATE("(SELECT TOP 1 ItemID FROM tbFinanceItem where ItemName = '",I91,"')") -> (SELECT TOP 1 ItemID FROM tbFinanceItem where ItemName = '(PNLD)Loss on Disposal of Investment') | H91: 9102Debit | I91: (PNLD)Loss on Disposal of Investment | J91: =IF(A91<>"Remove",CONCATENATE("INSERT INTO tbFinanceItemSeq(Report,ItemSeqID,ItemSN,ItemID) VALUES('",B91,"',",C91,",",E91,",",G91,")"),"") -> INSERT INTO tbFinanceItemSeq(Report,ItemSeqID,ItemSN,ItemID) VALUES('PNLD',87,87,(SELECT TOP 1 ItemID FROM tbFinanceItem where ItemName = '(PNLD)Loss on Disposal of Investment')) | K91: =IF(A91<>"New","",CONCATENATE("INSERT INTO tbFinanceItem(ItemName) VALUES('",I91,"')")) -> INSERT INTO tbFinanceItem(ItemName) VALUES('(PNLD)Loss on Disposal of Investment')
A92: New | B92: PNLD | C92: 88 | D92: 315 | E92: 88 | F92: 313 | G92: =CONCATENATE("(SELECT TOP 1 ItemID FROM tbFinanceItem where ItemName = '",I92,"')") -> (SELECT TOP 1 ItemID FROM tbFinanceItem where ItemName = '(PNLD)Loss on Asset Held for Sales') | H92: 9103Debit | I92: (PNLD)Loss on Asset Held for Sales | J92: =IF(A92<>"Remove",CONCATENATE("INSERT INTO tbFinanceItemSeq(Report,ItemSeqID,ItemSN,ItemID) VALUES('",B92,"',",C92,",",E92,",",G92,")"),"") -> INSERT INTO tbFinanceItemSeq(Report,ItemSeqID,ItemSN,ItemID) VALUES('PNLD',88,88,(SELECT TOP 1 ItemID FROM tbFinanceItem where ItemName = '(PNLD)Loss on Asset Held for Sales')) | K92: =IF(A92<>"New","",CONCATENATE("INSERT INTO tbFinanceItem(ItemName) VALUES('",I92,"')")) -> INSERT INTO tbFinanceItem(ItemName) VALUES('(PNLD)Loss on Asset Held for Sales')
A93: New | B93: PNLD | C93: 89 | D93: 316 | E93: 89 | F93: 314 | G93: 1060 | H93: 9111 | I93: (PNLD)Impairm Loss on Subsidiaries | J93: =IF(A93<>"Remove",CONCATENATE("INSERT INTO tbFinanceItemSeq(Report,ItemSeqID,ItemSN,ItemID) VALUES('",B93,"',",C93,",",E93,",",G93,")"),"") -> INSERT INTO tbFinanceItemSeq(Report,ItemSeqID,ItemSN,ItemID) VALUES('PNLD',89,89,1060) | K93: =IF(A93<>"New","",CONCATENATE("INSERT INTO tbFinanceItem(ItemName) VALUES('",I93,"')")) -> INSERT INTO tbFinanceItem(ItemName) VALUES('(PNLD)Impairm Loss on Subsidiaries')
A94: New | B94: PNLD | C94: 90 | D94: 317 | E94: 90 | F94: 315 | G94: 1061 | H94: 9112 | I94: (PNLD)Impairm Loss on Assoc/JV/Rel Co | J94: =IF(A94<>"Remove",CONCATENATE("INSERT INTO tbFinanceItemSeq(Report,ItemSeqID,ItemSN,ItemID) VALUES('",B94,"',",C94,",",E94,",",G94,")"),"") -> INSERT INTO tbFinanceItemSeq(Report,ItemSeqID,ItemSN,ItemID) VALUES('PNLD',90,90,1061) | K94: =IF(A94<>"New","",CONCATENATE("INSERT INTO tbFinanceItem(ItemName) VALUES('",I94,"')")) -> INSERT INTO tbFinanceItem(ItemName) VALUES('(PNLD)Impairm Loss on Assoc/JV/Rel Co')
A95: New | B95: PNLD | C95: 91 | D95: 318 | E95: 91 | F95: 316 | G95: 1062 | H95: 9113 | I95: (PNLD)Impairm Loss-Property | J95: =IF(A95<>"Remove",CONCATENATE("INSERT INTO tbFinanceItemSeq(Report,ItemSeqID,ItemSN,ItemID) VALUES('",B95,"',",C95,",",E95,",",G95,")"),"") -> INSERT INTO tbFinanceItemSeq(Report,ItemSeqID,ItemSN,ItemID) VALUES('PNLD',91,91,1062) | K95: =IF(A95<>"New","",CONCATENATE("INSERT INTO tbFinanceItem(ItemName) VALUES('",I95,"')")) -> INSERT INTO tbFinanceItem(ItemName) VALUES('(PNLD)Impairm Loss-Property')
A96: New | B96: PNLD | C96: 92 | D96: 319 | E96: 92 | F96: 317 | G96: 1063 | H96: 9114 | I96: (PNLD)Impairm Loss-Plant & Equip | J96: =IF(A96<>"Remove",CONCATENATE("INSERT INTO tbFinanceItemSeq(Report,ItemSeqID,ItemSN,ItemID) VALUES('",B96,"',",C96,",",E96,",",G96,")"),"") -> INSERT INTO tbFinanceItemSeq(Report,ItemSeqID,ItemSN,ItemID) VALUES('PNLD',92,92,1063) | K96: =IF(A96<>"New","",CONCATENATE("INSERT INTO tbFinanceItem(ItemName) VALUES('",I96,"')")) -> INSERT INTO tbFinanceItem(ItemName) VALUES('(PNLD)Impairm Loss-Plant & Equip')
A97: New | B97: PNLD | C97: 93 | D97: 320 | E97: 93 | F97: 318 | G97: 1064 | H97: 9115 | I97: (PNLD)Impairm Loss-Investment | J97: =IF(A97<>"Remove",CONCATENATE("INSERT INTO tbFinanceItemSeq(Report,ItemSeqID,ItemSN,ItemID) VALUES('",B97,"',",C97,",",E97,",",G97,")"),"") -> INSERT INTO tbFinanceItemSeq(Report,ItemSeqID,ItemSN,ItemID) VALUES('PNLD',93,93,1064) | K97: =IF(A97<>"New","",CONCATENATE("INSERT INTO tbFinanceItem(ItemName) VALUES('",I97,"')")) -> INSERT INTO tbFinanceItem(ItemName) VALUES('(PNLD)Impairm Loss-Investment')
A98: New | B98: PNLD | C98: 94 | D98: 322 | E98: 94 | F98: 320 | G98: 1066 | H98: 9117 | I98: (PNLD)Impairm Loss-Others | J98: =IF(A98<>"Remove",CONCATENATE("INSERT INTO tbFinanceItemSeq(Report,ItemSeqID,ItemSN,ItemID) VALUES('",B98,"',",C98,",",E98,",",G98,")"),"") -> INSERT INTO tbFinanceItemSeq(Report,ItemSeqID,ItemSN,ItemID) VALUES('PNLD',94,94,1066) | K98: =IF(A98<>"New","",CONCATENATE("INSERT INTO tbFinanceItem(ItemName) VALUES('",I98,"')")) -> INSERT INTO tbFinanceItem(ItemName) VALUES('(PNLD)Impairm Loss-Others')
A99: New | B99: PNLD | C99: 95 | D99: 324 | E99: 95 | F99: 322 | G99: 1068 | H99: 9121 | I99: (PNLD)Real Property Gain Tax | J99: =IF(A99<>"Remove",CONCATENATE("INSERT INTO tbFinanceItemSeq(Report,ItemSeqID,ItemSN,ItemID) VALUES('",B99,"',",C99,",",E99,",",G99,")"),"") -> INSERT INTO tbFinanceItemSeq(Report,ItemSeqID,ItemSN,ItemID) VALUES('PNLD',95,95,1068) | K99: =IF(A99<>"New","",CONCATENATE("INSERT INTO tbFinanceItem(ItemName) VALUES('",I99,"')")) -> INSERT INTO tbFinanceItem(ItemName) VALUES('(PNLD)Real Property Gain Tax')
A100: New | B100: PNLD | C100: 96 | D100: 325 | E100: 96 | F100: 323 | G100: 1069 | H100: 9122 | I100: (PNLD)Foreign Withholding Tax | J100: =IF(A100<>"Remove",CONCATENATE("INSERT INTO tbFinanceItemSeq(Report,ItemSeqID,ItemSN,ItemID) VALUES('",B100,"',",C100,",",E100,",",G100,")"),"") -> INSERT INTO tbFinanceItemSeq(Report,ItemSeqID,ItemSN,ItemID) VALUES('PNLD',96,96,1069) | K100: =IF(A100<>"New","",CONCATENATE("INSERT INTO tbFinanceItem(ItemName) VALUES('",I100,"')")) -> INSERT INTO tbFinanceItem(ItemName) VALUES('(PNLD)Foreign Withholding Tax')
A101: Remove | B101: PNLD | C101: 85 | D101: 79 | E101: 85 | F101: 77 | G101: 847 | I101: (PNLD)Amortisation-Trade Name | J101: =IF(A101<>"Remove",CONCATENATE("INSERT INTO tbFinanceItemSeq(Report,ItemSeqID,ItemSN,ItemID) VALUES('",B101,"',",C101,",",E101,",",G101,")"),"") | K101: =IF(A101<>"New","",CONCATENATE("INSERT INTO tbFinanceItem(ItemName) VALUES('",I101,"')"))
A102: Remove | B102: PNLD | C102: 86 | D102: 80 | E102: 86 | F102: 78 | G102: 848 | I102: (PNLD)Amortisation-Cust Relationship | J102: =IF(A102<>"Remove",CONCATENATE("INSERT INTO tbFinanceItemSeq(Report,ItemSeqID,ItemSN,ItemID) VALUES('",B102,"',",C102,",",E102,",",G102,")"),"") | K102: =IF(A102<>"New","",CONCATENATE("INSERT INTO tbFinanceItem(ItemName) VALUES('",I102,"')"))
A103: Remove | B103: PNLD | C103: 87 | D103: 81 | E103: 87 | F103: 79 | G103: 849 | I103: (PNLD)Amortisation-Trademark & Patent | J103: =IF(A103<>"Remove",CONCATENATE("INSERT INTO tbFinanceItemSeq(Report,ItemSeqID,ItemSN,ItemID) VALUES('",B103,"',",C103,",",E103,",",G103,")"),"") | K103: =IF(A103<>"New","",CONCATENATE("INSERT INTO tbFinanceItem(ItemName) VALUES('",I103,"')"))
A104: Exist | B104: PNLD | C104: 97 | D104: 82 | E104: 97 | F104: 80 | G104: 850 | H104: 9131 | I104: (PNLD)Amortisation-Product License | J104: =IF(A104<>"Remove",CONCATENATE("INSERT INTO tbFinanceItemSeq(Report,ItemSeqID,ItemSN,ItemID) VALUES('",B104,"',",C104,",",E104,",",G104,")"),"") -> INSERT INTO tbFinanceItemSeq(Report,ItemSeqID,ItemSN,ItemID) VALUES('PNLD',97,97,850) | K104: =IF(A104<>"New","",CONCATENATE("INSERT INTO tbFinanceItem(ItemName) VALUES('",I104,"')"))
A105: Exist | B105: PNLD | C105: 98 | D105: 83 | E105: 98 | F105: 81 | G105: 851 | H105: 9132 | I105: (PNLD)Amortisation-Club Membership | J105: =IF(A105<>"Remove",CONCATENATE("INSERT INTO tbFinanceItemSeq(Report,ItemSeqID,ItemSN,ItemID) VALUES('",B105,"',",C105,",",E105,",",G105,")"),"") -> INSERT INTO tbFinanceItemSeq(Report,ItemSeqID,ItemSN,ItemID) VALUES('PNLD',98,98,851) | K105: =IF(A105<>"New","",CONCATENATE("INSERT INTO tbFinanceItem(ItemName) VALUES('",I105,"')"))
A106: Exist | B106: PNLD | C106: 99 | D106: 80 | E106: 99 | F106: 78 | G106: 849 | H106: 9133 | I106: (PNLD)Amortisation-Trademark & Patent | J106: =IF(A106<>"Remove",CONCATENATE("INSERT INTO tbFinanceItemSeq(Report,ItemSeqID,ItemSN,ItemID) VALUES('",B106,"',",C106,",",E106,",",G106,")"),"") -> INSERT INTO tbFinanceItemSeq(Report,ItemSeqID,ItemSN,ItemID) VALUES('PNLD',99,99,849) | K106: =IF(A106<>"New","",CONCATENATE("INSERT INTO tbFinanceItem(ItemName) VALUES('",I106,"')"))
A107: Remove | B107: PNLD | C107: 90 | D107: 84 | E107: 90 | F107: 82 | G107: 852 | I107: (PNLD)Written Off-Trade Name | J107: =IF(A107<>"Remove",CONCATENATE("INSERT INTO tbFinanceItemSeq(Report,ItemSeqID,ItemSN,ItemID) VALUES('",B107,"',",C107,",",E107,",",G107,")"),"") | K107: =IF(A107<>"New","",CONCATENATE("INSERT INTO tbFinanceItem(ItemName) VALUES('",I107,"')"))
A108: Remove | B108: PNLD | C108: 91 | D108: 85 | E108: 91 | F108: 83 | G108: 853 | I108: (PNLD)Written Off-Cust Relationship | J108: =IF(A108<>"Remove",CONCATENATE("INSERT INTO tbFinanceItemSeq(Report,ItemSeqID,ItemSN,ItemID) VALUES('",B108,"',",C108,",",E108,",",G108,")"),"") | K108: =IF(A108<>"New","",CONCATENATE("INSERT INTO tbFinanceItem(ItemName) VALUES('",I108,"')"))
A109: Remove | B109: PNLD | C109: 92 | D109: 86 | E109: 92 | F109: 84 | G109: 854 | I109: (PNLD)Written Off-Trademark & Patent | J109: =IF(A109<>"Remove",CONCATENATE("INSERT INTO tbFinanceItemSeq(Report,ItemSeqID,ItemSN,ItemID) VALUES('",B109,"',",C109,",",E109,",",G109,")"),"") | K109: =IF(A109<>"New","",CONCATENATE("INSERT INTO tbFinanceItem(ItemName) VALUES('",I109,"')"))
A110: Remove | B110: PNLD | C110: 93 | D110: 87 | E110: 93 | F110: 85 | G110: 855 | I110: (PNLD)Written Off-Product License | J110: =IF(A110<>"Remove",CONCATENATE("INSERT INTO tbFinanceItemSeq(Report,ItemSeqID,ItemSN,ItemID) VALUES('",B110,"',",C110,",",E110,",",G110,")"),"") | K110: =IF(A110<>"New","",CONCATENATE("INSERT INTO tbFinanceItem(ItemName) VALUES('",I110,"')"))
A111: Remove | B111: PNLD | C111: 94 | D111: 88 | E111: 94 | F111: 86 | G111: 856 | I111: (PNLD)Written Off-Club Membership | J111: =IF(A111<>"Remove",CONCATENATE("INSERT INTO tbFinanceItemSeq(Report,ItemSeqID,ItemSN,ItemID) VALUES('",B111,"',",C111,",",E111,",",G111,")"),"") | K111: =IF(A111<>"New","",CONCATENATE("INSERT INTO tbFinanceItem(ItemName) VALUES('",I111,"')"))
A112: Remove | B112: PNLD | C112: 95 | D112: 89 | E112: 95 | F112: 87 | G112: 857 | I112: (PNLD)Other Misc Expenses | J112: =IF(A112<>"Remove",CONCATENATE("INSERT INTO tbFinanceItemSeq(Report,ItemSeqID,ItemSN,ItemID) VALUES('",B112,"',",C112,",",E112,",",G112,")"),"") | K112: =IF(A112<>"New","",CONCATENATE("INSERT INTO tbFinanceItem(ItemName) VALUES('",I112,"')"))
A113: Exist | B113: PNLD | C113: 100 | D113: 90 | E113: 100 | F113: 88 | G113: 1350 | H113: =SUM(C87:C102) | I113: (PNLD)Other Operating Expenses | J113: =IF(A113<>"Remove",CONCATENATE("INSERT INTO tbFinanceItemSeq(Report,ItemSeqID,ItemSN,ItemID) VALUES('",B113,"',",C113,",",E113,",",G113,")"),"") -> INSERT INTO tbFinanceItemSeq(Report,ItemSeqID,ItemSN,ItemID) VALUES('PNLD',100,100,1350) | K113: =IF(A113<>"New","",CONCATENATE("INSERT INTO tbFinanceItem(ItemName) VALUES('",I113,"')"))
A114: Exist | B114: PNLD | C114: 101 | D114: 91 | E114: 101 | F114: 89 | G114: 858 | H114: =C85+C103 | I114: (PNLD)Total Other Op Income/(Exp) | J114: =IF(A114<>"Remove",CONCATENATE("INSERT INTO tbFinanceItemSeq(Report,ItemSeqID,ItemSN,ItemID) VALUES('",B114,"',",C114,",",E114,",",G114,")"),"") -> INSERT INTO tbFinanceItemSeq(Report,ItemSeqID,ItemSN,ItemID) VALUES('PNLD',101,101,858) | K114: =IF(A114<>"New","",CONCATENATE("INSERT INTO tbFinanceItem(ItemName) VALUES('",I114,"')"))
A115: Exist | B115: PNLD | C115: 102 | D115: 92 | E115: 102 | F115: 90 | G115: 860 | H115: 7001 | I115: (PNLD)S&D Salary & Leave | J115: =IF(A115<>"Remove",CONCATENATE("INSERT INTO tbFinanceItemSeq(Report,ItemSeqID,ItemSN,ItemID) VALUES('",B115,"',",C115,",",E115,",",G115,")"),"") -> INSERT INTO tbFinanceItemSeq(Report,ItemSeqID,ItemSN,ItemID) VALUES('PNLD',102,102,860) | K115: =IF(A115<>"New","",CONCATENATE("INSERT INTO tbFinanceItem(ItemName) VALUES('",I115,"')"))
A116: Exist | B116: PNLD | C116: 103 | D116: 93 | E116: 103 | F116: 91 | G116: 861 | H116: 7002 | I116: (PNLD)S&D Provision for Bonus | J116: =IF(A116<>"Remove",CONCATENATE("INSERT INTO tbFinanceItemSeq(Report,ItemSeqID,ItemSN,ItemID) VALUES('",B116,"',",C116,",",E116,",",G116,")"),"") -> INSERT INTO tbFinanceItemSeq(Report,ItemSeqID,ItemSN,ItemID) VALUES('PNLD',103,103,861) | K116: =IF(A116<>"New","",CONCATENATE("INSERT INTO tbFinanceItem(ItemName) VALUES('",I116,"')"))
A117: Exist | B117: PNLD | C117: 104 | D117: 94 | E117: 104 | F117: 92 | G117: 862 | H117: 7003 | I117: (PNLD)S&D Comms & Incentives | J117: =IF(A117<>"Remove",CONCATENATE("INSERT INTO tbFinanceItemSeq(Report,ItemSeqID,ItemSN,ItemID) VALUES('",B117,"',",C117,",",E117,",",G117,")"),"") -> INSERT INTO tbFinanceItemSeq(Report,ItemSeqID,ItemSN,ItemID) VALUES('PNLD',104,104,862) | K117: =IF(A117<>"New","",CONCATENATE("INSERT INTO tbFinanceItem(ItemName) VALUES('",I117,"')"))
A118: Exist | B118: PNLD | C118: 105 | D118: 95 | E118: 105 | F118: 93 | G118: 863 | H118: 7004 | I118: (PNLD)S&D Foreign Workers | J118: =IF(A118<>"Remove",CONCATENATE("INSERT INTO tbFinanceItemSeq(Report,ItemSeqID,ItemSN,ItemID) VALUES('",B118,"',",C118,",",E118,",",G118,")"),"") -> INSERT INTO tbFinanceItemSeq(Report,ItemSeqID,ItemSN,ItemID) VALUES('PNLD',105,105,863) | K118: =IF(A118<>"New","",CONCATENATE("INSERT INTO tbFinanceItem(ItemName) VALUES('",I118,"')"))
A119: Exist | B119: PNLD | C119: 106 | D119: 96 | E119: 106 | F119: 94 | G119: 864 | H119: 7005 | I119: (PNLD)S&D Casual/Temp Staff | J119: =IF(A119<>"Remove",CONCATENATE("INSERT INTO tbFinanceItemSeq(Report,ItemSeqID,ItemSN,ItemID) VALUES('",B119,"',",C119,",",E119,",",G119,")"),"") -> INSERT INTO tbFinanceItemSeq(Report,ItemSeqID,ItemSN,ItemID) VALUES('PNLD',106,106,864) | K119: =IF(A119<>"New","",CONCATENATE("INSERT INTO tbFinanceItem(ItemName) VALUES('",I119,"')"))
A120: Exist | B120: PNLD | C120: 107 | D120: 97 | E120: 107 | F120: 95 | G120: 865 | H120: 7006 | I120: (PNLD)S&D Overtime | J120: =IF(A120<>"Remove",CONCATENATE("INSERT INTO tbFinanceItemSeq(Report,ItemSeqID,ItemSN,ItemID) VALUES('",B120,"',",C120,",",E120,",",G120,")"),"") -> INSERT INTO tbFinanceItemSeq(Report,ItemSeqID,ItemSN,ItemID) VALUES('PNLD',107,107,865) | K120: =IF(A120<>"New","",CONCATENATE("INSERT INTO tbFinanceItem(ItemName) VALUES('",I120,"')"))
A121: Exist | B121: PNLD | C121: 108 | D121: 98 | E121: 108 | F121: 96 | G121: 866 | H121: 7007 | I121: (PNLD)S&D Staff Allow & Incentive | J121: =IF(A121<>"Remove",CONCATENATE("INSERT INTO tbFinanceItemSeq(Report,ItemSeqID,ItemSN,ItemID) VALUES('",B121,"',",C121,",",E121,",",G121,")"),"") -> INSERT INTO tbFinanceItemSeq(Report,ItemSeqID,ItemSN,ItemID) VALUES('PNLD',108,108,866) | K121: =IF(A121<>"New","",CONCATENATE("INSERT INTO tbFinanceItem(ItemName) VALUES('",I121,"')"))
A122: Exist | B122: PNLD | C122: 109 | D122: 99 | E122: 109 | F122: 97 | G122: 867 | H122: 7008 | I122: (PNLD)S&D Shift Allowance | J122: =IF(A122<>"Remove",CONCATENATE("INSERT INTO tbFinanceItemSeq(Report,ItemSeqID,ItemSN,ItemID) VALUES('",B122,"',",C122,",",E122,",",G122,")"),"") -> INSERT INTO tbFinanceItemSeq(Report,ItemSeqID,ItemSN,ItemID) VALUES('PNLD',109,109,867) | K122: =IF(A122<>"New","",CONCATENATE("INSERT INTO tbFinanceItem(ItemName) VALUES('",I122,"')"))
A123: Exist | B123: PNLD | C123: 110 | D123: 100 | E123: 110 | F123: 98 | G123: 868 | H123: 7009 | I123: (PNLD)S&D Staff Transport | J123: =IF(A123<>"Remove",CONCATENATE("INSERT INTO tbFinanceItemSeq(Report,ItemSeqID,ItemSN,ItemID) VALUES('",B123,"',",C123,",",E123,",",G123,")"),"") -> INSERT INTO tbFinanceItemSeq(Report,ItemSeqID,ItemSN,ItemID) VALUES('PNLD',110,110,868) | K123: =IF(A123<>"New","",CONCATENATE("INSERT INTO tbFinanceItem(ItemName) VALUES('",I123,"')"))
A124: Exist | B124: PNLD | C124: 111 | D124: 101 | E124: 111 | F124: 99 | G124: 869 | H124: 7010 | I124: (PNLD)S&D Staff Vehicle Expenses | J124: =IF(A124<>"Remove",CONCATENATE("INSERT INTO tbFinanceItemSeq(Report,ItemSeqID,ItemSN,ItemID) VALUES('",B124,"',",C124,",",E124,",",G124,")"),"") -> INSERT INTO tbFinanceItemSeq(Report,ItemSeqID,ItemSN,ItemID) VALUES('PNLD',111,111,869) | K124: =IF(A124<>"New","",CONCATENATE("INSERT INTO tbFinanceItem(ItemName) VALUES('",I124,"')"))
... A170: Exist | B170: PNLD | C170: 157 | D170: 146 | E170: 157 | F170: 144 | G170: 910 | H170: 7410 | I170: (PNLD)S&D Insurance of Vehicles | J170: =IF(A170<>"Remove",CONCATENATE("INSERT INTO tbFinanceItemSeq(Report,ItemSeqID,ItemSN,ItemID) VALUES('",B170,"',",C170,",",E170,",",G170,")"),"") -> INSERT INTO tbFinanceItemSeq(Report,ItemSeqID,ItemSN,ItemID) VALUES('PNLD',157,157,910) | K170: =IF(A170<>"New","",CONCATENATE("INSERT INTO tbFinanceItem(ItemName) VALUES('",I170,"')"))
A171: Exist | B171: PNLD | C171: 158 | E171: 158 | G171: =CONCATENATE("(SELECT ItemID FROM tbFinanceItem where ItemName = '",I171,"')") -> (SELECT ItemID FROM tbFinanceItem where ItemName = '(PNLD)S&D Upkeep-Machinery') | H171: 7411 | I171: (PNLD)S&D Upkeep-Machinery | J171: =IF(A171<>"Remove",CONCATENATE("INSERT INTO tbFinanceItemSeq(Report,ItemSeqID,ItemSN,ItemID) VALUES('",B171,"',",C171,",",E171,",",G171,")"),"") -> INSERT INTO tbFinanceItemSeq(Report,ItemSeqID,ItemSN,ItemID) VALUES('PNLD',158,158,(SELECT ItemID FROM tbFinanceItem where ItemName = '(PNLD)S&D Upkeep-Machinery')) | K171: =IF(A171<>"New","",CONCATENATE("INSERT INTO tbFinanceItem(ItemName) VALUES('",I171,"')"))
A172: Exist | B172: PNLD | C172: 159 | E172: 159 | G172: =CONCATENATE("(SELECT ItemID FROM tbFinanceItem where ItemName = '",I172,"')") -> (SELECT ItemID FROM tbFinanceItem where ItemName = '(PNLD)S&D Upkeep-Equipment') | H172: 7412 | I172: (PNLD)S&D Upkeep-Equipment | J172: =IF(A172<>"Remove",CONCATENATE("INSERT INTO tbFinanceItemSeq(Report,ItemSeqID,ItemSN,ItemID) VALUES('",B172,"',",C172,",",E172,",",G172,")"),"") -> INSERT INTO tbFinanceItemSeq(Report,ItemSeqID,ItemSN,ItemID) VALUES('PNLD',159,159,(SELECT ItemID FROM tbFinanceItem where ItemName = '(PNLD)S&D Upkeep-Equipment')) | K172: =IF(A172<>"New","",CONCATENATE("INSERT INTO tbFinanceItem(ItemName) VALUES('",I172,"')"))
A173: Exist | B173: PNLD | C173: 160 | E173: 160 | G173: =CONCATENATE("(SELECT ItemID FROM tbFinanceItem where ItemName = '",I173,"')") -> (SELECT ItemID FROM tbFinanceItem where ItemName = '(PNLD)S&D Upkeep-Furniture & Fitting') | H173: 7413 | I173: (PNLD)S&D Upkeep-Furniture & Fitting | J173: =IF(A173<>"Remove",CONCATENATE("INSERT INTO tbFinanceItemSeq(Report,ItemSeqID,ItemSN,ItemID) VALUES('",B173,"',",C173,",",E173,",",G173,")"),"") -> INSERT INTO tbFinanceItemSeq(Report,ItemSeqID,ItemSN,ItemID) VALUES('PNLD',160,160,(SELECT ItemID FROM tbFinanceItem where ItemName = '(PNLD)S&D Upkeep-Furniture & Fitting')) | K173: =IF(A173<>"New","",CONCATENATE("INSERT INTO tbFinanceItem(ItemName) VALUES('",I173,"')"))
A174: Exist | B174: PNLD | C174: 161 | E174: 161 | G174: =CONCATENATE("(SELECT ItemID FROM tbFinanceItem where ItemName = '",I174,"')") -> (SELECT ItemID FROM tbFinanceItem where ItemName = '(PNLD)S&D Upkeep-Office Equip') | H174: 7414 | I174: (PNLD)S&D Upkeep-Office Equip | J174: =IF(A174<>"Remove",CONCATENATE("INSERT INTO tbFinanceItemSeq(Report,ItemSeqID,ItemSN,ItemID) VALUES('",B174,"',",C174,",",E174,",",G174,")"),"") -> INSERT INTO tbFinanceItemSeq(Report,ItemSeqID,ItemSN,ItemID) VALUES('PNLD',161,161,(SELECT ItemID FROM tbFinanceItem where ItemName = '(PNLD)S&D Upkeep-Office Equip')) | K174: =IF(A174<>"New","",CONCATENATE("INSERT INTO tbFinanceItem(ItemName) VALUES('",I174,"')"))
A175: Exist | B175: PNLD | C175: 162 | E175: 162 | G175: =CONCATENATE("(SELECT ItemID FROM tbFinanceItem where ItemName = '",I175,"')") -> (SELECT ItemID FROM tbFinanceItem where ItemName = '(PNLD)S&D Upkeep-Computers') | H175: 7415 | I175: (PNLD)S&D Upkeep-Computers | J175: =IF(A175<>"Remove",CONCATENATE("INSERT INTO tbFinanceItemSeq(Report,ItemSeqID,ItemSN,ItemID) VALUES('",B175,"',",C175,",",E175,",",G175,")"),"") -> INSERT INTO tbFinanceItemSeq(Report,ItemSeqID,ItemSN,ItemID) VALUES('PNLD',162,162,(SELECT ItemID FROM tbFinanceItem where ItemName = '(PNLD)S&D Upkeep-Computers')) | K175: =IF(A175<>"New","",CONCATENATE("INSERT INTO tbFinanceItem(ItemName) VALUES('",I175,"')"))
A176: Exist | B176: PNLD | C176: 163 | D176: 147 | E176: 163 | F176: 145 | G176: 1354 | H176: =SUM(C151:C165) | I176: (PNLD)S&D Equipment Expenses | J176: =IF(A176<>"Remove",CONCATENATE("INSERT INTO tbFinanceItemSeq(Report,ItemSeqID,ItemSN,ItemID) VALUES('",B176,"',",C176,",",E176,",",G176,")"),"") -> INSERT INTO tbFinanceItemSeq(Report,ItemSeqID,ItemSN,ItemID) VALUES('PNLD',163,163,1354) | K176: =IF(A176<>"New","",CONCATENATE("INSERT INTO tbFinanceItem(ItemName) VALUES('",I176,"')"))
A177: Exist | B177: PNLD | C177: 164 | D177: 148 | E177: 164 | F177: 146 | G177: 911 | H177: 7501 | I177: (PNLD)S&D Rental | J177: =IF(A177<>"Remove",CONCATENATE("INSERT INTO tbFinanceItemSeq(Report,ItemSeqID,ItemSN,ItemID) VALUES('",B177,"',",C177,",",E177,",",G177,")"),"") -> INSERT INTO tbFinanceItemSeq(Report,ItemSeqID,ItemSN,ItemID) VALUES('PNLD',164,164,911) | K177: =IF(A177<>"New","",CONCATENATE("INSERT INTO tbFinanceItem(ItemName) VALUES('",I177,"')"))
A178: Exist | B178: PNLD | C178: 165 | D178: 149 | E178: 165 | F178: 147 | G178: 912 | H178: 7502 | I178: (PNLD)S&D Upkeep of Premises | J178: =IF(A178<>"Remove",CONCATENATE("INSERT INTO tbFinanceItemSeq(Report,ItemSeqID,ItemSN,ItemID) VALUES('",B178,"',",C178,",",E178,",",G178,")"),"") -> INSERT INTO tbFinanceItemSeq(Report,ItemSeqID,ItemSN,ItemID) VALUES('PNLD',165,165,912) | K178: =IF(A178<>"New","",CONCATENATE("INSERT INTO tbFinanceItem(ItemName) VALUES('",I178,"')"))
A179: Exist | B179: PNLD | C179: 166 | D179: 150 | E179: 166 | F179: 148 | G179: 913 | H179: 7503 | I179: (PNLD)S&D Waste Disposal | J179: =IF(A179<>"Remove",CONCATENATE("INSERT INTO tbFinanceItemSeq(Report,ItemSeqID,ItemSN,ItemID) VALUES('",B179,"',",C179,",",E179,",",G179,")"),"") -> INSERT INTO tbFinanceItemSeq(Report,ItemSeqID,ItemSN,ItemID) VALUES('PNLD',166,166,913) | K179: =IF(A179<>"New","",CONCATENATE("INSERT INTO tbFinanceItem(ItemName) VALUES('",I179,"')"))
A180: Exist | B180: PNLD | C180: 167 | D180: 151 | E180: 167 | F180: 149 | G180: 914 | H180: 7504 | I180: (PNLD)S&D Electricity Charges | J180: =IF(A180<>"Remove",CONCATENATE("INSERT INTO tbFinanceItemSeq(Report,ItemSeqID,ItemSN,ItemID) VALUES('",B180,"',",C180,",",E180,",",G180,")"),"") -> INSERT INTO tbFinanceItemSeq(Report,ItemSeqID,ItemSN,ItemID) VALUES('PNLD',167,167,914) | K180: =IF(A180<>"New","",CONCATENATE("INSERT INTO tbFinanceItem(ItemName) VALUES('",I180,"')"))
A181: Exist | B181: PNLD | C181: 168 | D181: 152 | E181: 168 | F181: 150 | G181: 915 | H181: 7505 | I181: (PNLD)S&D Water Charges | J181: =IF(A181<>"Remove",CONCATENATE("INSERT INTO tbFinanceItemSeq(Report,ItemSeqID,ItemSN,ItemID) VALUES('",B181,"',",C181,",",E181,",",G181,")"),"") -> INSERT INTO tbFinanceItemSeq(Report,ItemSeqID,ItemSN,ItemID) VALUES('PNLD',168,168,915) | K181: =IF(A181<>"New","",CONCATENATE("INSERT INTO tbFinanceItem(ItemName) VALUES('",I181,"')"))
A182: Exist | B182: PNLD | C182: 169 | D182: 153 | E182: 169 | F182: 151 | G182: 916 | H182: 7506 | I182: (PNLD)S&D Gas Charges | J182: =IF(A182<>"Remove",CONCATENATE("INSERT INTO tbFinanceItemSeq(Report,ItemSeqID,ItemSN,ItemID) VALUES('",B182,"',",C182,",",E182,",",G182,")"),"") -> INSERT INTO tbFinanceItemSeq(Report,ItemSeqID,ItemSN,ItemID) VALUES('PNLD',169,169,916) | K182: =IF(A182<>"New","",CONCATENATE("INSERT INTO tbFinanceItem(ItemName) VALUES('",I182,"')"))
A183: Exist | B183: PNLD | C183: 170 | D183: 154 | E183: 170 | F183: 152 | G183: 917 | H183: 7507 | I183: (PNLD)S&D Property Tax | J183: =IF(A183<>"Remove",CONCATENATE("INSERT INTO tbFinanceItemSeq(Report,ItemSeqID,ItemSN,ItemID) VALUES('",B183,"',",C183,",",E183,",",G183,")"),"") -> INSERT INTO tbFinanceItemSeq(Report,ItemSeqID,ItemSN,ItemID) VALUES('PNLD',170,170,917) | K183: =IF(A183<>"New","",CONCATENATE("INSERT INTO tbFinanceItem(ItemName) VALUES('",I183,"')"))
A184: Exist | B184: PNLD | C184: 171 | D184: 155 | E184: 171 | F184: 153 | G184: 918 | H184: 7508 | I184: (PNLD)S&D Licenses Fees | J184: =IF(A184<>"Remove",CONCATENATE("INSERT INTO tbFinanceItemSeq(Report,ItemSeqID,ItemSN,ItemID) VALUES('",B184,"',",C184,",",E184,",",G184,")"),"") -> INSERT INTO tbFinanceItemSeq(Report,ItemSeqID,ItemSN,ItemID) VALUES('PNLD',171,171,918) | K184: =IF(A184<>"New","",CONCATENATE("INSERT INTO tbFinanceItem(ItemName) VALUES('",I184,"')"))
A185: Exist | B185: PNLD | C185: 172 | D185: 156 | E185: 172 | F185: 154 | G185: 919 | H185: 7509 | I185: (PNLD)S&D Insurance-General | J185: =IF(A185<>"Remove",CONCATENATE("INSERT INTO tbFinanceItemSeq(Report,ItemSeqID,ItemSN,ItemID) VALUES('",B185,"',",C185,",",E185,",",G185,")"),"") -> INSERT INTO tbFinanceItemSeq(Report,ItemSeqID,ItemSN,ItemID) VALUES('PNLD',172,172,919) | K185: =IF(A185<>"New","",CONCATENATE("INSERT INTO tbFinanceItem(ItemName) VALUES('",I185,"')"))
A186: Exist | B186: PNLD | C186: 173 | D186: 157 | E186: 173 | F186: 155 | G186: 1355 | H186: =SUM(C167:C175) | I186: (PNLD)S&D Rental/Property Related | J186: =IF(A186<>"Remove",CONCATENATE("INSERT INTO tbFinanceItemSeq(Report,ItemSeqID,ItemSN,ItemID) VALUES('",B186,"',",C186,",",E186,",",G186,")"),"") -> INSERT INTO tbFinanceItemSeq(Report,ItemSeqID,ItemSN,ItemID) VALUES('PNLD',173,173,1355) | K186: =IF(A186<>"New","",CONCATENATE("INSERT INTO tbFinanceItem(ItemName) VALUES('",I186,"')"))
A187: Exist | B187: PNLD | C187: 174 | D187: 158 | E187: 174 | F187: 156 | G187: 920 | H187: 7601 | I187: (PNLD)S&D Dep-Leasehold Land | J187: =IF(A187<>"Remove",CONCATENATE("INSERT INTO tbFinanceItemSeq(Report,ItemSeqID,ItemSN,ItemID) VALUES('",B187,"',",C187,",",E187,",",G187,")"),"") -> INSERT INTO tbFinanceItemSeq(Report,ItemSeqID,ItemSN,ItemID) VALUES('PNLD',174,174,920) | K187: =IF(A187<>"New","",CONCATENATE("INSERT INTO tbFinanceItem(ItemName) VALUES('",I187,"')"))
... A209: Exist | B209: PNLD | C209: 196 | D209: 180 | E209: 196 | F209: 178 | G209: 940 | H209: 7708 | I209: (PNLD)S&D Other Misc Expenses | J209: =IF(A209<>"Remove",CONCATENATE("INSERT INTO tbFinanceItemSeq(Report,ItemSeqID,ItemSN,ItemID) VALUES('",B209,"',",C209,",",E209,",",G209,")"),"") -> INSERT INTO tbFinanceItemSeq(Report,ItemSeqID,ItemSN,ItemID) VALUES('PNLD',196,196,940) | K209: =IF(A209<>"New","",CONCATENATE("INSERT INTO tbFinanceItem(ItemName) VALUES('",I209,"')"))
A210: Remove | B210: PNLD | D210: 181 | F210: 179 | G210: 1369 | I210: (PNLD)S&D A&P Marcom Exps | J210: =IF(A210<>"Remove",CONCATENATE("INSERT INTO tbFinanceItemSeq(Report,ItemSeqID,ItemSN,ItemID) VALUES('",B210,"',",C210,",",E210,",",G210,")"),"") | K210: =IF(A210<>"New","",CONCATENATE("INSERT INTO tbFinanceItem(ItemName) VALUES('",I210,"')"))
A211: Exist | B211: PNLD | C211: 197 | D211: 182 | E211: 197 | F211: 180 | G211: 1370 | H211: 7903 | I211: (PNLD)S&D Warehouse & Logistic Exps | J211: =IF(A211<>"Remove",CONCATENATE("INSERT INTO tbFinanceItemSeq(Report,ItemSeqID,ItemSN,ItemID) VALUES('",B211,"',",C211,",",E211,",",G211,")"),"") -> INSERT INTO tbFinanceItemSeq(Report,ItemSeqID,ItemSN,ItemID) VALUES('PNLD',197,197,1370) | K211: =IF(A211<>"New","",CONCATENATE("INSERT INTO tbFinanceItem(ItemName) VALUES('",I211,"')"))
A212: Exist | B212: PNLD | C212: 198 | D212: 183 | E212: 198 | F212: 181 | G212: 1371 | H212: 7910 | I212: (PNLD)S&D Product Support Welding | J212: =IF(A212<>"Remove",CONCATENATE("INSERT INTO tbFinanceItemSeq(Report,ItemSeqID,ItemSN,ItemID) VALUES('",B212,"',",C212,",",E212,",",G212,")"),"") -> INSERT INTO tbFinanceItemSeq(Report,ItemSeqID,ItemSN,ItemID) VALUES('PNLD',198,198,1371) | K212: =IF(A212<>"New","",CONCATENATE("INSERT INTO tbFinanceItem(ItemName) VALUES('",I212,"')"))
A213: Exist | B213: PNLD | C213: 199 | D213: 184 | E213: 199 | F213: 182 | G213: 1372 | H213: 7920 | I213: (PNLD)S&D Product Support Safety | J213: =IF(A213<>"Remove",CONCATENATE("INSERT INTO tbFinanceItemSeq(Report,ItemSeqID,ItemSN,ItemID) VALUES('",B213,"',",C213,",",E213,",",G213,")"),"") -> INSERT INTO tbFinanceItemSeq(Report,ItemSeqID,ItemSN,ItemID) VALUES('PNLD',199,199,1372) | K213: =IF(A213<>"New","",CONCATENATE("INSERT INTO tbFinanceItem(ItemName) VALUES('",I213,"')"))
A214: Exist | B214: PNLD | C214: 200 | D214: 185 | E214: 200 | F214: 183 | G214: 941 | H214: 7998 | I214: (PNLD)S&D Recovery to/from Interco | J214: =IF(A214<>"Remove",CONCATENATE("INSERT INTO tbFinanceItemSeq(Report,ItemSeqID,ItemSN,ItemID) VALUES('",B214,"',",C214,",",E214,",",G214,")"),"") -> INSERT INTO tbFinanceItemSeq(Report,ItemSeqID,ItemSN,ItemID) VALUES('PNLD',200,200,941) | K214: =IF(A214<>"New","",CONCATENATE("INSERT INTO tbFinanceItem(ItemName) VALUES('",I214,"')"))
A215: Exist | B215: PNLD | C215: 201 | D215: 186 | E215: 201 | F215: 184 | G215: 942 | H215: 7999 | I215: (PNLD)S&D Head Office Costs/Alloc | J215: =IF(A215<>"Remove",CONCATENATE("INSERT INTO tbFinanceItemSeq(Report,ItemSeqID,ItemSN,ItemID) VALUES('",B215,"',",C215,",",E215,",",G215,")"),"") -> INSERT INTO tbFinanceItemSeq(Report,ItemSeqID,ItemSN,ItemID) VALUES('PNLD',201,201,942) | K215: =IF(A215<>"New","",CONCATENATE("INSERT INTO tbFinanceItem(ItemName) VALUES('",I215,"')"))
A216: Remove | B216: PNLD | C216: 203 | D216: 187 | E216: 203 | F216: 185 | G216: 1358 | I216: (PNLD)S&D Other Expenses | J216: =IF(A216<>"Remove",CONCATENATE("INSERT INTO tbFinanceItemSeq(Report,ItemSeqID,ItemSN,ItemID) VALUES('",B216,"',",C216,",",E216,",",G216,")"),"") | K216: =IF(A216<>"New","",CONCATENATE("INSERT INTO tbFinanceItem(ItemName) VALUES('",I216,"')"))
A217: Exist | B217: PNLD | C217: 202 | D217: 188 | E217: 202 | F217: 186 | G217: 943 | H217: =C132+C141+C147+C150+C166+C176+C190+C196+C197:C204 | I217: (PNLD)Total S&D Expenses | J217: =IF(A217<>"Remove",CONCATENATE("INSERT INTO tbFinanceItemSeq(Report,ItemSeqID,ItemSN,ItemID) VALUES('",B217,"',",C217,",",E217,",",G217,")"),"") -> INSERT INTO tbFinanceItemSeq(Report,ItemSeqID,ItemSN,ItemID) VALUES('PNLD',202,202,943) | K217: =IF(A217<>"New","",CONCATENATE("INSERT INTO tbFinanceItem(ItemName) VALUES('",I217,"')"))
A218: Exist | B218: PNLD | C218: 203 | D218: 189 | E218: 203 | F218: 187 | G218: 945 | H218: 8001 | I218: (PNLD)A&G Salary & Leave | J218: =IF(A218<>"Remove",CONCATENATE("INSERT INTO tbFinanceItemSeq(Report,ItemSeqID,ItemSN,ItemID) VALUES('",B218,"',",C218,",",E218,",",G218,")"),"") -> INSERT INTO tbFinanceItemSeq(Report,ItemSeqID,ItemSN,ItemID) VALUES('PNLD',203,203,945) | K218: =IF(A218<>"New","",CONCATENATE("INSERT INTO tbFinanceItem(ItemName) VALUES('",I218,"')"))
A219: Exist | B219: PNLD | C219: 204 | D219: 190 | E219: 204 | F219: 188 | G219: 946 | H219: 8002 | I219: (PNLD)A&G Provision for Bonus | J219: =IF(A219<>"Remove",CONCATENATE("INSERT INTO tbFinanceItemSeq(Report,ItemSeqID,ItemSN,ItemID) VALUES('",B219,"',",C219,",",E219,",",G219,")"),"") -> INSERT INTO tbFinanceItemSeq(Report,ItemSeqID,ItemSN,ItemID) VALUES('PNLD',204,204,946) | K219: =IF(A219<>"New","",CONCATENATE("INSERT INTO tbFinanceItem(ItemName) VALUES('",I219,"')"))
A220: Exist | B220: PNLD | C220: 205 | D220: 191 | E220: 205 | F220: 189 | G220: 947 | H220: 8003 | I220: (PNLD)A&G Comms & Incentives | J220: =IF(A220<>"Remove",CONCATENATE("INSERT INTO tbFinanceItemSeq(Report,ItemSeqID,ItemSN,ItemID) VALUES('",B220,"',",C220,",",E220,",",G220,")"),"") -> INSERT INTO tbFinanceItemSeq(Report,ItemSeqID,ItemSN,ItemID) VALUES('PNLD',205,205,947) | K220: =IF(A220<>"New","",CONCATENATE("INSERT INTO tbFinanceItem(ItemName) VALUES('",I220,"')"))
A221: Exist | B221: PNLD | C221: 206 | D221: 192 | E221: 206 | F221: 190 | G221: 948 | H221: 8004 | I221: (PNLD)A&G Foreign Workers | J221: =IF(A221<>"Remove",CONCATENATE("INSERT INTO tbFinanceItemSeq(Report,ItemSeqID,ItemSN,ItemID) VALUES('",B221,"',",C221,",",E221,",",G221,")"),"") -> INSERT INTO tbFinanceItemSeq(Report,ItemSeqID,ItemSN,ItemID) VALUES('PNLD',206,206,948) | K221: =IF(A221<>"New","",CONCATENATE("INSERT INTO tbFinanceItem(ItemName) VALUES('",I221,"')"))
...

Sheet F142 F32 MAD-Debug
A1: SELECT TOP 10 * FROM tbReport where ReportID = 434;
A2: --F142 Detailed Manufacturing Account.rpt
A3: --procReportFinanceMADetailByMonth
A4: --(MAD)
A6: select s.* , i.ItemName from tbFinanceItemSeq s
A7: LEFT JOIN tbFinanceItem i on s.ItemID = i.ItemID
A8: where s.Report = 'MAD'
A9: order by s.ItemSeqID
A12: DELETE FROM tbFinanceItemSeq where Report = 'MAD'
A14: Update tbReport
A15: set FileName = 'F142 Detailed Manufacturing Account.rpt' ,
A16: Description = '[COA2016] F32 Detailed Manufacturing Account'
A17: where ReportID =430;

Sheet F142 F32 MAD-Origin
A1: Report | B1: ItemSeqID | C1: ItemSN | D1: ItemID | E1: ItemName | F1: Insert Script
A2: MAD | B2: 1 | C2: 0 | D2: 1141 | E2: (MAD)Title:Direct Material | F2: =CONCATENATE("INSERT INTO tbFinanceItemSeq(Report,ItemSeqID,ItemSN,ItemID) VALUES('",A2,"',",B2,",",C2,",",D2,")") -> INSERT INTO tbFinanceItemSeq(Report,ItemSeqID,ItemSN,ItemID) VALUES('MAD',1,0,1141)
A3: MAD | B3: 2 | C3: 1 | D3: 1142 | E3: (MAD)DM-Raw Materials | F3: =CONCATENATE("INSERT INTO tbFinanceItemSeq(Report,ItemSeqID,ItemSN,ItemID) VALUES('",A3,"',",B3,",",C3,",",D3,")") -> INSERT INTO tbFinanceItemSeq(Report,ItemSeqID,ItemSN,ItemID) VALUES('MAD',2,1,1142)
A4: MAD | B4: 3 | C4: 2 | D4: 1143 | E4: (MAD)DM-Parts & Access | F4: =CONCATENATE("INSERT INTO tbFinanceItemSeq(Report,ItemSeqID,ItemSN,ItemID) VALUES('",A4,"',",B4,",",C4,",",D4,")") -> INSERT INTO tbFinanceItemSeq(Report,ItemSeqID,ItemSN,ItemID) VALUES('MAD',3,2,1143)
A5: MAD | B5: 4 | C5: 3 | D5: 1144 | E5: (MAD)DM-Packaging Materials | F5: =CONCATENATE("INSERT INTO tbFinanceItemSeq(Report,ItemSeqID,ItemSN,ItemID) VALUES('",A5,"',",B5,",",C5,",",D5,")") -> INSERT INTO tbFinanceItemSeq(Report,ItemSeqID,ItemSN,ItemID) VALUES('MAD',4,3,1144)
A6: MAD | B6: 5 | C6: 4 | D6: 1145 | E6: (MAD)DM-Labelling Materials | F6: =CONCATENATE("INSERT INTO tbFinanceItemSeq(Report,ItemSeqID,ItemSN,ItemID) VALUES('",A6,"',",B6,",",C6,",",D6,")") -> INSERT INTO tbFinanceItemSeq(Report,ItemSeqID,ItemSN,ItemID) VALUES('MAD',5,4,1145)
A7: MAD | B7: 6 | C7: 5 | D7: 1146 | E7: (MAD)DM-Refill Materials | F7: =CONCATENATE("INSERT INTO tbFinanceItemSeq(Report,ItemSeqID,ItemSN,ItemID) VALUES('",A7,"',",B7,",",C7,",",D7,")") -> INSERT INTO tbFinanceItemSeq(Report,ItemSeqID,ItemSN,ItemID) VALUES('MAD',6,5,1146)
